Workbook

Sheet Base extract
A1: Designation_Complémentaire | B1: Remise | C1: Total_Ligne_HT_Remisé | D1: V_Total_Ligne_TTC | E1: TVA | F1: N__DA | G1: N__Poste_DA | H1: Site_Stock | I1: Code_ss_famille | J1: Saisie_de_réception__ | K1: Code_Direction | L1: Code_complément | M1: SS_compte_anal | N1: Centre_d_Analyse | O1: Accord_Cadre | P1: RAL | Q1: V_Montant_RAL | R1: Code_Société | S1: Avenant | T1: Acheteur | U1: Tot_CA_HT | V1: Tot_CA_TTC | W1: Devise | X1: Etat_Financ_ | Y1: Date_creat | Z1: Date_de_Validation | AA1: Date_Période | AB1: Date_AR | AC1: Objet_CA | AD1: Ctr_Emetteur_entete | AE1: Ctr_Livraison_entete | AF1: Sect_Imputation_entete | AG1: Code_Complémentaire_entete | AH1: Sous_Compte_d_Analyse_entete | AI1: Type_document | AJ1: V_Expédition_soldée | AK1: Code_du_Modèle_de_Cde | AL1: V_Etat_commande_en_tête | AM1: V_Etat_commande_ligne | AN1: Nom_Acheteur | AO1: Raison_sociale_Fournisseur | AP1: Nom_demandeur | AQ1: V_Critère_de_saisie | AR1: Code_Article | AS1: Quantité_comm | AT1: Unité | AU1: Prix_Unitaire | AV1: Design__sommaire | AW1: Section_d_imput | AX1: Code_Fournis | AY1: N__de_Cde | AZ1: N_Poste | BA1: Date_de_livr__prev_
A2: SPOT - RECORD TV - suivant Facture N°TV000000282 | B2: 0 | C2: 549120 | D2: 658 944.00 | E2: 20 | F2: 139303 | G2: 1 | I2: MEDMEDI | J2: True | K2: DCG | L2: E110_MD_DCOM | M2: DCG-COM-MEDIA | N2: NA | P2: 1 | Q2: 549 120.00 | R2: YASMG | T2: FELANA13 | U2: 3 926 784.00 | V2: 4 712 140.80 | W2: MGA | X2: F | Y2: 46237 | Z2: 2026-08-03 | AA2: 46237 | AB2: 0000-00-00 | AC2: SPOT - RECORD TV | AD2: YASSIE | AE2: YASSIE | AF2: C100 | AG2: E110_MD_DCOM | AH2: DCG-COM-MEDIA | AI2: STD | AL2: E | AM2: E | AN2: Felana RARIVOSON | AO2: RTV RECORD | AP2: RAZAFINDRAHAGA Setra | AR2: 1265 | AS2: 1 | AT2: UN | AU2: 549120 | AV2: PUBLICITE ET ANNONCE | AW2: C100 | AX2: 973 | AY2: 136058 | AZ2: 1 | BA2: 2026-07-29
A3: SPOT - RECORD TV - suivant Facture N°RD000000250 | B3: 0 | C3: 403200 | D3: 483 840.00 | E3: 20 | F3: 139303 | G3: 2 | I3: MEDMEDI | J3: True | K3: DCG | L3: E110_MD_DCOM | M3: DCG-COM-MEDIA | N3: NA | P3: 1 | Q3: 403 200.00 | R3: YASMG | T3: FELANA13 | U3: 3 926 784.00 | V3: 4 712 140.80 | W3: MGA | X3: F | Y3: 46237 | Z3: 2026-08-03 | AA3: 46237 | AB3: 0000-00-00 | AC3: SPOT - RECORD TV | AD3: YASSIE | AE3: YASSIE | AF3: C100 | AG3: E110_MD_DCOM | AH3: DCG-COM-MEDIA | AI3: STD | AL3: E | AM3: E | AN3: Felana RARIVOSON | AO3: RTV RECORD | AP3: RAZAFINDRAHAGA Setra | AR3: 1265 | AS3: 1 | AT3: UN | AU3: 403200 | AV3: PUBLICITE ET ANNONCE | AW3: C100 | AX3: 973 | AY3: 136058 | AZ3: 2 | BA3: 2026-07-29
A4: SPOT - RECORD TV - suivant Facture N°RD000000270 | B4: 0 | C4: 82944 | D4: 99 532.80 | E4: 20 | F4: 139303 | G4: 3 | I4: MEDMEDI | J4: True | K4: DCG | L4: E110_MD_DCOM | M4: DCG-COM-MEDIA | N4: NA | P4: 1 | Q4: 82 944.00 | R4: YASMG | T4: FELANA13 | U4: 3 926 784.00 | V4: 4 712 140.80 | W4: MGA | X4: F | Y4: 46237 | Z4: 2026-08-03 | AA4: 46237 | AB4: 0000-00-00 | AC4: SPOT - RECORD TV | AD4: YASSIE | AE4: YASSIE | AF4: C100 | AG4: E110_MD_DCOM | AH4: DCG-COM-MEDIA | AI4: STD | AL4: E | AM4: E | AN4: Felana RARIVOSON | AO4: RTV RECORD | AP4: RAZAFINDRAHAGA Setra | AR4: 1265 | AS4: 1 | AT4: UN | AU4: 82944 | AV4: PUBLICITE ET ANNONCE | AW4: C100 | AX4: 973 | AY4: 136058 | AZ4: 3 | BA4: 2026-07-29
A5: SPOT - RECORD TV - suivant Facture N°RD000000280 | B5: 0 | C5: 403200 | D5: 483 840.00 | E5: 20 | F5: 139303 | G5: 4 | I5: MEDMEDI | J5: True | K5: DCG | L5: E110_MD_DCOM | M5: DCG-COM-MEDIA | N5: NA | P5: 1 | Q5: 403 200.00 | R5: YASMG | T5: FELANA13 | U5: 3 926 784.00 | V5: 4 712 140.80 | W5: MGA | X5: F | Y5: 46237 | Z5: 2026-08-03 | AA5: 46237 | AB5: 0000-00-00 | AC5: SPOT - RECORD TV | AD5: YASSIE | AE5: YASSIE | AF5: C100 | AG5: E110_MD_DCOM | AH5: DCG-COM-MEDIA | AI5: STD | AL5: E | AM5: E | AN5: Felana RARIVOSON | AO5: RTV RECORD | AP5: RAZAFINDRAHAGA Setra | AR5: 1265 | AS5: 1 | AT5: UN | AU5: 403200 | AV5: PUBLICITE ET ANNONCE | AW5: C100 | AX5: 973 | AY5: 136058 | AZ5: 4 | BA5: 2026-07-29
A6: SPOT - RECORD TV - suivant Facture N°RD000000296 | B6: 0 | C6: 829440 | D6: 995 328.00 | E6: 20 | F6: 139303 | G6: 5 | I6: MEDMEDI | J6: True | K6: DCG | L6: E110_MD_DCOM | M6: DCG-COM-MEDIA | N6: NA | P6: 1 | Q6: 829 440.00 | R6: YASMG | T6: FELANA13 | U6: 3 926 784.00 | V6: 4 712 140.80 | W6: MGA | X6: F | Y6: 46237 | Z6: 2026-08-03 | AA6: 46237 | AB6: 0000-00-00 | AC6: SPOT - RECORD TV | AD6: YASSIE | AE6: YASSIE | AF6: C100 | AG6: E110_MD_DCOM | AH6: DCG-COM-MEDIA | AI6: STD | AL6: E | AM6: E | AN6: Felana RARIVOSON | AO6: RTV RECORD | AP6: RAZAFINDRAHAGA Setra | AR6: 1265 | AS6: 1 | AT6: UN | AU6: 829440 | AV6: PUBLICITE ET ANNONCE | AW6: C100 | AX6: 973 | AY6: 136058 | AZ6: 5 | BA6: 2026-07-29
A7: SPOT - RECORD TV - suivant Facture N°RD000000297 | B7: 0 | C7: 829440 | D7: 995 328.00 | E7: 20 | F7: 139303 | G7: 6 | I7: MEDMEDI | J7: True | K7: DCG | L7: E110_MD_DCOM | M7: DCG-COM-MEDIA | N7: NA | P7: 1 | Q7: 829 440.00 | R7: YASMG | T7: FELANA13 | U7: 3 926 784.00 | V7: 4 712 140.80 | W7: MGA | X7: F | Y7: 46237 | Z7: 2026-08-03 | AA7: 46237 | AB7: 0000-00-00 | AC7: SPOT - RECORD TV | AD7: YASSIE | AE7: YASSIE | AF7: C100 | AG7: E110_MD_DCOM | AH7: DCG-COM-MEDIA | AI7: STD | AL7: E | AM7: E | AN7: Felana RARIVOSON | AO7: RTV RECORD | AP7: RAZAFINDRAHAGA Setra | AR7: 1265 | AS7: 1 | AT7: UN | AU7: 829440 | AV7: PUBLICITE ET ANNONCE | AW7: C100 | AX7: 973 | AY7: 136058 | AZ7: 6 | BA7: 2026-07-29
A8: SPOT - RECORD TV - suivant Facture N°RD000000288 | B8: 0 | C8: 829440 | D8: 995 328.00 | E8: 20 | F8: 139303 | G8: 7 | I8: MEDMEDI | J8: True | K8: DCG | L8: E110_MD_DCOM | M8: DCG-COM-MEDIA | N8: NA | P8: 1 | Q8: 829 440.00 | R8: YASMG | T8: FELANA13 | U8: 3 926 784.00 | V8: 4 712 140.80 | W8: MGA | X8: F | Y8: 46237 | Z8: 2026-08-03 | AA8: 46237 | AB8: 0000-00-00 | AC8: SPOT - RECORD TV | AD8: YASSIE | AE8: YASSIE | AF8: C100 | AG8: E110_MD_DCOM | AH8: DCG-COM-MEDIA | AI8: STD | AL8: E | AM8: E | AN8: Felana RARIVOSON | AO8: RTV RECORD | AP8: RAZAFINDRAHAGA Setra | AR8: 1265 | AS8: 1 | AT8: UN | AU8: 829440 | AV8: PUBLICITE ET ANNONCE | AW8: C100 | AX8: 973 | AY8: 136058 | AZ8: 7 | BA8: 2026-07-29
A9: Stickers Home Plus - 7,5 x 6 cm - suivant proforma N° FP05186 | B9: 0 | C9: 5124000 | D9: 6 148 800.00 | E9: 20 | F9: 139299 | G9: 1 | I9: GELACCS | J9: True | K9: DCG | L9: E110_TR_MBLK | M9: DCG-SHS | N9: NA | P9: 30500 | Q9: 5 124 000.00 | R9: YASMG | T9: FELANA13 | U9: 39 000 000.00 | V9: 46 800 000.00 | W9: MGA | Y9: 46237 | Z9: 2026-08-03 | AA9: 46237 | AB9: 0000-00-00 | AC9: STICKERS MBALIK | AD9: YASSIE | AE9: GALE | AF9: C100 | AG9: E110_TR_MBLK | AH9: DCG-SHS | AI9: STD | AL9: E | AM9: E | AN9: Felana RARIVOSON | AO9: SIGN | AP9: RAZAFINDRAHAGA Setra | AR9: 24694 | AS9: 30500 | AT9: UN | AU9: 168 | AV9: STICKERS AUTOCOLLANT - MBALIK - JUILLET 2025 | AW9: C100 | AX9: 1089 | AY9: 136059 | AZ9: 1 | BA9: 2026-07-29
A10: Stickers Home Plus - 13x19 cm (sticker facing) - suivant proforma N° FP05186 | B10: 0 | C10: 19764000 | D10: 23 716 800.00 | E10: 20 | F10: 139299 | G10: 2 | I10: GELACCS | J10: True | K10: DCG | L10: E110_TR_MBLK | M10: DCG-SHS | N10: NA | P10: 30500 | Q10: 19 764 000.00 | R10: YASMG | T10: FELANA13 | U10: 39 000 000.00 | V10: 46 800 000.00 | W10: MGA | Y10: 46237 | Z10: 2026-08-03 | AA10: 46237 | AB10: 0000-00-00 | AC10: STICKERS MBALIK | AD10: YASSIE | AE10: GALE | AF10: C100 | AG10: E110_TR_MBLK | AH10: DCG-SHS | AI10: STD | AL10: E | AM10: E | AN10: Felana RARIVOSON | AO10: SIGN | AP10: RAZAFINDRAHAGA Setra | AR10: 24694 | AS10: 30500 | AT10: UN | AU10: 648 | AV10: STICKERS AUTOCOLLANT - MBALIK - JUILLET 2025 | AW10: C100 | AX10: 1089 | AY10: 136059 | AZ10: 2 | BA10: 2026-07-29
A11: Stickers Home Plus - 2,8x2,8 cm (sticker rond) - suivant proforma N° FP05186 | B11: 0 | C11: 1098000 | D11: 1 317 600.00 | E11: 20 | F11: 139299 | G11: 3 | I11: GELACCS | J11: True | K11: DCG | L11: E110_TR_MBLK | M11: DCG-SHS | N11: NA | P11: 30500 | Q11: 1 098 000.00 | R11: YASMG | T11: FELANA13 | U11: 39 000 000.00 | V11: 46 800 000.00 | W11: MGA | Y11: 46237 | Z11: 2026-08-03 | AA11: 46237 | AB11: 0000-00-00 | AC11: STICKERS MBALIK | AD11: YASSIE | AE11: GALE | AF11: C100 | AG11: E110_TR_MBLK | AH11: DCG-SHS | AI11: STD | AL11: E | AM11: E | AN11: Felana RARIVOSON | AO11: SIGN | AP11: RAZAFINDRAHAGA Setra | AR11: 24694 | AS11: 30500 | AT11: UN | AU11: 36 | AV11: STICKERS AUTOCOLLANT - MBALIK - JUILLET 2025 | AW11: C100 | AX11: 1089 | AY11: 136059 | AZ11: 3 | BA11: 2026-07-29
A12: Stickers Home Plus - 3,5x2 cm (sticker pour cacher logo Sunking sur l'image du boîtier du facing) - suivant proforma N° FP05186 | B12: 0 | C12: 854000 | D12: 1 024 800.00 | E12: 20 | F12: 139299 | G12: 4 | I12: GELACCS | J12: True | K12: DCG | L12: E110_TR_MBLK | M12: DCG-SHS | N12: NA | P12: 30500 | Q12: 854 000.00 | R12: YASMG | T12: FELANA13 | U12: 39 000 000.00 | V12: 46 800 000.00 | W12: MGA | Y12: 46237 | Z12: 2026-08-03 | AA12: 46237 | AB12: 0000-00-00 | AC12: STICKERS MBALIK | AD12: YASSIE | AE12: GALE | AF12: C100 | AG12: E110_TR_MBLK | AH12: DCG-SHS | AI12: STD | AL12: E | AM12: E | AN12: Felana RARIVOSON | AO12: SIGN | AP12: RAZAFINDRAHAGA Setra | AR12: 24694 | AS12: 30500 | AT12: UN | AU12: 28 | AV12: STICKERS AUTOCOLLANT - MBALIK - JUILLET 2025 | AW12: C100 | AX12: 1089 | AY12: 136059 | AZ12: 4 | BA12: 2026-07-29
A13: Stickers Home Plus - 7x2 cm (sticker dos) - suivant proforma N° FP05186 | B13: 0 | C13: 1488400 | D13: 1 786 080.00 | E13: 20 | F13: 139299 | G13: 5 | I13: GELACCS | J13: True | K13: DCG | L13: E110_TR_MBLK | M13: DCG-SHS | N13: NA | P13: 30500 | Q13: 1 488 400.00 | R13: YASMG | T13: FELANA13 | U13: 39 000 000.00 | V13: 46 800 000.00 | W13: MGA | Y13: 46237 | Z13: 2026-08-03 | AA13: 46237 | AB13: 0000-00-00 | AC13: STICKERS MBALIK | AD13: YASSIE | AE13: GALE | AF13: C100 | AG13: E110_TR_MBLK | AH13: DCG-SHS | AI13: STD | AL13: E | AM13: E | AN13: Felana RARIVOSON | AO13: SIGN | AP13: RAZAFINDRAHAGA Setra | AR13: 24694 | AS13: 30500 | AT13: UN | AU13: 48.8 | AV13: STICKERS AUTOCOLLANT - MBALIK - JUILLET 2025 | AW13: C100 | AX13: 1089 | AY13: 136059 | AZ13: 5 | BA13: 2026-07-29
A14: Stickers Home Plus - 11x5,3 cm sticker côté jaune - suivant proforma N° FP05186 | B14: 0 | C14: 9333000 | D14: 11 199 600.00 | E14: 20 | F14: 139299 | G14: 6 | I14: GELACCS | J14: True | K14: DCG | L14: E110_TR_MBLK | M14: DCG-SHS | N14: NA | P14: 61000 | Q14: 9 333 000.00 | R14: YASMG | T14: FELANA13 | U14: 39 000 000.00 | V14: 46 800 000.00 | W14: MGA | Y14: 46237 | Z14: 2026-08-03 | AA14: 46237 | AB14: 0000-00-00 | AC14: STICKERS MBALIK | AD14: YASSIE | AE14: GALE | AF14: C100 | AG14: E110_TR_MBLK | AH14: DCG-SHS | AI14: STD | AL14: E | AM14: E | AN14: Felana RARIVOSON | AO14: SIGN | AP14: RAZAFINDRAHAGA Setra | AR14: 24694 | AS14: 61000 | AT14: UN | AU14: 153 | AV14: STICKERS AUTOCOLLANT - MBALIK - JUILLET 2025 | AW14: C100 | AX14: 1089 | AY14: 136059 | AZ14: 6 | BA14: 2026-07-29
A15: POSE A ANDRAHARO | B15: 0 | C15: 1338600 | D15: 1 606 320.00 | E15: 20 | F15: 139299 | G15: 7 | I15: ELEMCEL | J15: True | K15: DCG | L15: E110_TR_MBLK | M15: DCG-SHS | N15: NA | P15: 1 | Q15: 1 338 600.00 | R15: YASMG | T15: FELANA13 | U15: 39 000 000.00 | V15: 46 800 000.00 | W15: MGA | Y15: 46237 | Z15: 2026-08-03 | AA15: 46237 | AB15: 0000-00-00 | AC15: STICKERS MBALIK | AD15: YASSIE | AE15: GALE | AF15: C100 | AG15: E110_TR_MBLK | AH15: DCG-SHS | AI15: STD | AL15: E | AM15: E | AN15: Felana RARIVOSON | AO15: SIGN | AP15: RAZAFINDRAHAGA Setra | AR15: 2061 | AS15: 1 | AT15: UN | AU15: 1338600 | AV15: FRAIS DE POSE | AW15: C100 | AX15: 1089 | AY15: 136059 | AZ15: 7 | BA15: 2026-07-29
A16: TRAVAUX DE COULLAGE DALLE EN BETON YAS STORE AMBOHIPO - suivant Devis N° 206/2026 INDICE 0 | B16: 0 | C16: 782000 | D16: 782 000.00 | E16: 0 | F16: 139284 | G16: 1 | I16: INFPYLX | J16: True | K16: DCG | L16: E250_DRB | M16: DCG-DRB | N16: NA | P16: 1 | Q16: 782 000.00 | R16: YASMG | T16: FELANA13 | U16: 782 000.00 | V16: 782 000.00 | W16: MGA | X16: F | Y16: 46237 | Z16: 2026-08-03 | AA16: 46237 | AB16: 0000-00-00 | AC16: YS AMBOHIPO | AD16: YASSIE | AE16: YASSIE | AF16: C102 | AG16: E250_DRB | AH16: DCG-DRB | AI16: STD | AL16: E | AM16: E | AN16: Felana RARIVOSON | AO16: AVRA BTP | AP16: RAZAFINDRAHAGA Setra | AR16: 1526 | AS16: 1 | AT16: UN | AU16: 782000 | AV16: TRAVAUX SUPPLEMENTAIRES | AW16: C102 | AX16: 4038 | AY16: 136060 | AZ16: 1 | BA16: 2026-07-28
A17: TRAVAUX DE POSE CARREAUX MURAUX - suivant devis N° 205/2026 INDICE 0 | B17: 0 | C17: 824000 | D17: 824 000.00 | E17: 0 | F17: 139283 | G17: 1 | I17: INFPYLX | J17: True | K17: DCG | L17: E250_DRB | M17: DCG-DRB | N17: NA | P17: 1 | Q17: 824 000.00 | R17: YASMG | T17: FELANA13 | U17: 824 000.00 | V17: 824 000.00 | W17: MGA | Y17: 46237 | Z17: 2026-08-03 | AA17: 46237 | AB17: 0000-00-00 | AC17: YS ITAOSY | AD17: YASSIE | AE17: YASSIE | AF17: C102 | AG17: E250_DRB | AH17: DCG-DRB | AI17: STD | AL17: E | AM17: E | AN17: Felana RARIVOSON | AO17: AVRA BTP | AP17: RAZAFINDRAHAGA Setra | AR17: 1526 | AS17: 1 | AT17: UN | AU17: 824000 | AV17: TRAVAUX SUPPLEMENTAIRES | AW17: C102 | AX17: 4038 | AY17: 136061 | AZ17: 1 | BA17: 2026-07-28
A18: REMBOURSEMENT FRAIS BAC CDZ S14 - PROFORMA N°192-A/FP/TELMA/2026 | B18: 0 | C18: 1480000 | D18: 1 480 000.00 | E18: 0 | F18: 139333 | G18: 1 | I18: PRICTRL | J18: False | K18: DCG | L18: E214_DCG | M18: DCG-DVIR | N18: NA | P18: 0 | Q18: 0.00 | R18: YASMG | T18: FELANA13 | U18: 11 417 000.00 | V18: 11 417 000.00 | W18: MGA | X18: F | Y18: 46237 | Z18: 2026-08-03 | AA18: 46237 | AB18: 0000-00-00 | AC18: REMBOURSEMENT FRAIS BAC CDZ | AD18: YASSIE | AE18: YASSIE | AF18: C104 | AG18: E214_DCG | AH18: DCG-DVIR | AI18: STD | AL18: S | AM18: S | AN18: Felana RARIVOSON | AO18: LCS CONSULTING | AP18: RAZAFINDRAHAGA Setra | AR18: 11533 | AS18: 1 | AT18: PIE | AU18: 1480000 | AV18: PRESTATION DIVERS | AW18: C104 | AX18: 2490 | AY18: 136062 | AZ18: 1 | BA18: 2026-07-30
A19: REMBOURSEMENT FRAIS BAC CDZ S15 - PROFORMA N°194-A/FP/TELMA/2026 | B19: 0 | C19: 1483000 | D19: 1 483 000.00 | E19: 0 | F19: 139333 | G19: 2 | I19: PRICTRL | J19: False | K19: DCG | L19: E214_DCG | M19: DCG-DVIR | N19: NA | P19: 0 | Q19: 0.00 | R19: YASMG | T19: FELANA13 | U19: 11 417 000.00 | V19: 11 417 000.00 | W19: MGA | X19: F | Y19: 46237 | Z19: 2026-08-03 | AA19: 46237 | AB19: 0000-00-00 | AC19: REMBOURSEMENT FRAIS BAC CDZ | AD19: YASSIE | AE19: YASSIE | AF19: C104 | AG19: E214_DCG | AH19: DCG-DVIR | AI19: STD | AL19: S | AM19: S | AN19: Felana RARIVOSON | AO19: LCS CONSULTING | AP19: RAZAFINDRAHAGA Setra | AR19: 11533 | AS19: 1 | AT19: PIE | AU19: 1483000 | AV19: PRESTATION DIVERS | AW19: C104 | AX19: 2490 | AY19: 136062 | AZ19: 2 | BA19: 2026-07-30
A20: REMBOURSEMENT FRAIS BAC CDZ S16 - PROFORMA N°212-A/FP/TELMA/2026 | B20: 0 | C20: 1717000 | D20: 1 717 000.00 | E20: 0 | F20: 139333 | G20: 3 | I20: PRICTRL | J20: False | K20: DCG | L20: E214_DCG | M20: DCG-DVIR | N20: NA | P20: 0 | Q20: 0.00 | R20: YASMG | T20: FELANA13 | U20: 11 417 000.00 | V20: 11 417 000.00 | W20: MGA | X20: F | Y20: 46237 | Z20: 2026-08-03 | AA20: 46237 | AB20: 0000-00-00 | AC20: REMBOURSEMENT FRAIS BAC CDZ | AD20: YASSIE | AE20: YASSIE | AF20: C104 | AG20: E214_DCG | AH20: DCG-DVIR | AI20: STD | AL20: S | AM20: S | AN20: Felana RARIVOSON | AO20: LCS CONSULTING | AP20: RAZAFINDRAHAGA Setra | AR20: 11533 | AS20: 1 | AT20: PIE | AU20: 1717000 | AV20: PRESTATION DIVERS | AW20: C104 | AX20: 2490 | AY20: 136062 | AZ20: 3 | BA20: 2026-07-30
A21: REMBOURSEMENT FRAIS BAC CDZ S17 - PROFORMA N°214-A/FP/TELMA/2026 | B21: 0 | C21: 1593000 | D21: 1 593 000.00 | E21: 0 | F21: 139333 | G21: 4 | I21: PRICTRL | J21: False | K21: DCG | L21: E214_DCG | M21: DCG-DVIR | N21: NA | P21: 0 | Q21: 0.00 | R21: YASMG | T21: FELANA13 | U21: 11 417 000.00 | V21: 11 417 000.00 | W21: MGA | X21: F | Y21: 46237 | Z21: 2026-08-03 | AA21: 46237 | AB21: 0000-00-00 | AC21: REMBOURSEMENT FRAIS BAC CDZ | AD21: YASSIE | AE21: YASSIE | AF21: C104 | AG21: E214_DCG | AH21: DCG-DVIR | AI21: STD | AL21: S | AM21: S | AN21: Felana RARIVOSON | AO21: LCS CONSULTING | AP21: RAZAFINDRAHAGA Setra | AR21: 11533 | AS21: 1 | AT21: PIE | AU21: 1593000 | AV21: PRESTATION DIVERS | AW21: C104 | AX21: 2490 | AY21: 136062 | AZ21: 4 | BA21: 2026-07-30
A22: REMBOURSEMENT FRAIS BAC CDZ S20 - PROFORMA N°243-A/FP/TELMA/2026 | B22: 0 | C22: 1247000 | D22: 1 247 000.00 | E22: 0 | F22: 139333 | G22: 5 | I22: PRICTRL | J22: False | K22: DCG | L22: E214_DCG | M22: DCG-DVIR | N22: NA | P22: 0 | Q22: 0.00 | R22: YASMG | T22: FELANA13 | U22: 11 417 000.00 | V22: 11 417 000.00 | W22: MGA | X22: F | Y22: 46237 | Z22: 2026-08-03 | AA22: 46237 | AB22: 0000-00-00 | AC22: REMBOURSEMENT FRAIS BAC CDZ | AD22: YASSIE | AE22: YASSIE | AF22: C104 | AG22: E214_DCG | AH22: DCG-DVIR | AI22: STD | AL22: S | AM22: S | AN22: Felana RARIVOSON | AO22: LCS CONSULTING | AP22: RAZAFINDRAHAGA Setra | AR22: 11533 | AS22: 1 | AT22: PIE | AU22: 1247000 | AV22: PRESTATION DIVERS | AW22: C104 | AX22: 2490 | AY22: 136062 | AZ22: 5 | BA22: 2026-07-30
A23: REMBOURSEMENT FRAIS BAC CDZ S22 - PROFORMA N°283-A/FP/TELMA/2026 | B23: 0 | C23: 2046000 | D23: 2 046 000.00 | E23: 0 | F23: 139333 | G23: 6 | I23: PRICTRL | J23: False | K23: DCG | L23: E214_DCG | M23: DCG-DVIR | N23: NA | P23: 0 | Q23: 0.00 | R23: YASMG | T23: FELANA13 | U23: 11 417 000.00 | V23: 11 417 000.00 | W23: MGA | X23: F | Y23: 46237 | Z23: 2026-08-03 | AA23: 46237 | AB23: 0000-00-00 | AC23: REMBOURSEMENT FRAIS BAC CDZ | AD23: YASSIE | AE23: YASSIE | AF23: C104 | AG23: E214_DCG | AH23: DCG-DVIR | AI23: STD | AL23: S | AM23: S | AN23: Felana RARIVOSON | AO23: LCS CONSULTING | AP23: RAZAFINDRAHAGA Setra | AR23: 11533 | AS23: 1 | AT23: PIE | AU23: 2046000 | AV23: PRESTATION DIVERS | AW23: C104 | AX23: 2490 | AY23: 136062 | AZ23: 6 | BA23: 2026-07-30
A24: REMBOURSEMENT FRAIS BAC CDZ S21 - PROFORMA N°285-A/FP/TELMA/2026 | B24: 0 | C24: 1851000 | D24: 1 851 000.00 | E24: 0 | F24: 139333 | G24: 7 | I24: PRICTRL | J24: False | K24: DCG | L24: E214_DCG | M24: DCG-DVIR | N24: NA | P24: 0 | Q24: 0.00 | R24: YASMG | T24: FELANA13 | U24: 11 417 000.00 | V24: 11 417 000.00 | W24: MGA | X24: F | Y24: 46237 | Z24: 2026-08-03 | AA24: 46237 | AB24: 0000-00-00 | AC24: REMBOURSEMENT FRAIS BAC CDZ | AD24: YASSIE | AE24: YASSIE | AF24: C104 | AG24: E214_DCG | AH24: DCG-DVIR | AI24: STD | AL24: S | AM24: S | AN24: Felana RARIVOSON | AO24: LCS CONSULTING | AP24: RAZAFINDRAHAGA Setra | AR24: 11533 | AS24: 1 | AT24: PIE | AU24: 1851000 | AV24: PRESTATION DIVERS | AW24: C104 | AX24: 2490 | AY24: 136062 | AZ24: 7 | BA24: 2026-07-30
A25: Rajout de 150 ARS dans la région du Grand Axe Nord pour une durée de 5 mois - août 2026 à décembre 2026 - suivant proforma N° 402-A/FP/TELMA /2026 | B25: 0 | C25: 302775000 | D25: 363 330 000.00 | E25: 20 | F25: 139331 | G25: 1 | I25: PRICTRL | J25: True | K25: DCG | L25: E214_DCG | M25: DCG-DVIR | N25: NA | P25: 1 | Q25: 302 775 000.00 | R25: YASMG | T25: FELANA13 | U25: 302 775 000.00 | V25: 363 330 000.00 | W25: MGA | Y25: 46237 | Z25: 2026-08-03 | AA25: 46237 | AB25: 0000-00-00 | AC25: RAJOUT ARS DANS LA ZONE NORD | AD25: YASSIE | AE25: YASSIE | AF25: C104 | AG25: E214_DCG | AH25: DCG-DVIR | AI25: STD | AL25: E | AM25: E | AN25: Felana RARIVOSON | AO25: LCS CONSULTING | AP25: RAZAFINDRAHAGA Setra | AR25: 1264 | AS25: 1 | AT25: UN | AU25: 302775000 | AV25: PRESTATION EXTERNE | AW25: C104 | AX25: 2490 | AY25: 136063 | AZ25: 1 | BA25: 2026-07-30
A26: Prestation intérimaire Telma 265 VAD dont 166 Tàna et 99 Région mois d'août 2026 - suivant proforma N°400-A/FP/TELMA/2026 | B26: 0 | C26: 119162000 | D26: 142 994 400.00 | E26: 20 | F26: 139328 | G26: 1 | I26: PRICTRL | J26: True | K26: DCG | L26: E214_DCG | M26: DCG-DRB | N26: NA | P26: 1 | Q26: 119 162 000.00 | R26: YASMG | T26: FELANA13 | U26: 238 324 000.00 | V26: 285 988 800.00 | W26: MGA | X26: F | Y26: 46237 | Z26: 2026-08-03 | AA26: 46237 | AB26: 0000-00-00 | AC26: Salaire VAD AOUT et SEPTEMBRE 2026 | AD26: YASSIE | AE26: YASSIE | AF26: C102 | AG26: E214_DCG | AH26: DCG-DRB | AI26: STD | AL26: E | AM26: E | AN26: Felana RARIVOSON | AO26: LCS CONSULTING | AP26: RAZAFINDRAHAGA Setra | AR26: 1264 | AS26: 1 | AT26: UN | AU26: 119162000 | AV26: PRESTATION EXTERNE | AW26: C102 | AX26: 2490 | AY26: 136064 | AZ26: 1 | BA26: 2026-07-30
A27: Prestation intérimaire Telma 265 VAD dont 166 Tàna et 99 Région mois de septembre 2026 - suivant proforma N°401-A/FP/TELMA/2026 | B27: 0 | C27: 119162000 | D27: 142 994 400.00 | E27: 20 | F27: 139328 | G27: 2 | I27: PRICTRL | J27: True | K27: DCG | L27: E214_DCG | M27: DCG-DRB | N27: NA | P27: 1 | Q27: 119 162 000.00 | R27: YASMG | T27: FELANA13 | U27: 238 324 000.00 | V27: 285 988 800.00 | W27: MGA | X27: F | Y27: 46237 | Z27: 2026-08-03 | AA27: 46237 | AB27: 0000-00-00 | AC27: Salaire VAD AOUT et SEPTEMBRE 2026 | AD27: YASSIE | AE27: YASSIE | AF27: C102 | AG27: E214_DCG | AH27: DCG-DRB | AI27: STD | AL27: E | AM27: E | AN27: Felana RARIVOSON | AO27: LCS CONSULTING | AP27: RAZAFINDRAHAGA Setra | AR27: 1264 | AS27: 1 | AT27: UN | AU27: 119162000 | AV27: PRESTATION EXTERNE | AW27: C102 | AX27: 2490 | AY27: 136064 | AZ27: 2 | BA27: 2026-07-30
A28: Prestation de défilé africain ( Danse africaine / DJ ambiance africaine /Maquillage / Transport) # PROFORMA NO 001 | B28: 0 | C28: 7000000 | D28: 7 000 000.00 | E28: 0 | F28: 139315 | G28: 1 | I28: PRICTRL | J28: False | K28: DCG | L28: E110_AP_DCOM | M28: DCG-COM | N28: NA | P28: 1 | Q28: 7 000 000.00 | R28: YASMG | T28: FELANA13 | U28: 7 000 000.00 | V28: 7 000 000.00 | W28: MGA | Y28: 46237 | Z28: 2026-08-03 | AA28: 46237 | AB28: 0000-00-00 | AC28: AFRICA DAY | AD28: YASSIE | AE28: YASSIE | AF28: C100 | AG28: E110_AP_DCOM | AH28: DCG-COM | AI28: STD | AL28: E | AM28: E | AN28: Felana RARIVOSON | AO28: ROOTS CONSEILS | AP28: RAZAFINDRAHAGA Setra | AR28: 11533 | AS28: 1 | AT28: PIE | AU28: 7000000 | AV28: PRESTATION DIVERS | AW28: C100 | AX28: 7090 | AY28: 136065 | AZ28: 1 | BA28: 2026-07-29
A29: ENTRETIEN MOTO - 15556WWT - MORONDAVA - PROFORMA N°111 | B29: 0 | C29: 817000 | D29: 817 000.00 | E29: 0 | F29: 139310 | G29: 1 | I29: PRMVEHI | J29: True | K29: DCG | L29: E222_DCG | M29: DCG-SHS | N29: NA | P29: 1 | Q29: 817 000.00 | R29: YASMG | T29: FELANA13 | U29: 817 000.00 | V29: 817 000.00 | W29: MGA | Y29: 46237 | Z29: 2026-08-03 | AA29: 46237 | AB29: 0000-00-00 | AC29: ENTRETIEN MOTO - MORONDAVA | AD29: YASSIE | AE29: YASSIE | AF29: C100 | AG29: E222_DCG | AH29: DCG-SHS | AI29: STD | AL29: E | AM29: E | AN29: Felana RARIVOSON | AO29: RAMANAMBONONA LALANIRIANA HANITRINIAINA | AP29: RAZAFINDRAHAGA Setra | AR29: 1185 | AS29: 1 | AT29: UN | AU29: 817000 | AV29: ENTRETIEN ET REPARATION VEHICULE Y COMPRIS PIECES DE RECHAN | AW29: C100 | AX29: 6740 | AY29: 136066 | AZ29: 1 | BA29: 2026-07-29
A30: ENTRETIEN MOTO - 46608WWT - TANA - devis 1de2478442 du 13/07/2026 | B30: 0 | C30: 90500 | D30: 108 600.00 | E30: 20 | F30: 139309 | G30: 1 | I30: PRMVEHI | J30: True | K30: DCG | L30: E222_DCG | M30: DCG-SHS | N30: NA | P30: 1 | Q30: 90 500.00 | R30: YASMG | T30: FELANA13 | U30: 90 500.00 | V30: 108 600.00 | W30: MGA | Y30: 46237 | Z30: 2026-08-03 | AA30: 46237 | AB30: 0000-00-00 | AC30: ENTRETIEN MOTO - MBALIK | AD30: YASSIE | AE30: YASSIE | AF30: C100 | AG30: E222_DCG | AH30: DCG-SHS | AI30: STD | AL30: E | AM30: E | AN30: Felana RARIVOSON | AO30: MADAGASCAR AUTOMOBILE | AP30: RAZAFINDRAHAGA Setra | AR30: 1185 | AS30: 1 | AT30: UN | AU30: 90500 | AV30: ENTRETIEN ET REPARATION VEHICULE Y COMPRIS PIECES DE RECHAN | AW30: C100 | AX30: 1184 | AY30: 136067 | AZ30: 1 | BA30: 2026-07-29
A31: Apport Numéraire FESTIVAL DONA BE - FACTURE N°12 | B31: 0 | C31: 40000000 | D31: 40 000 000.00 | E31: 0 | F31: 139337 | G31: 1 | I31: MECSPDC | J31: True | K31: DCG | L31: E110_AC_DCOM | M31: DCG-COM-PART | N31: NA | P31: 1 | Q31: 40 000 000.00 | R31: YASMG | T31: FELANA13 | U31: 40 000 000.00 | V31: 40 000 000.00 | W31: MGA | X31: F | Y31: 46237 | Z31: 2026-08-12 | AA31: 46237 | AB31: 0000-00-00 | AC31: FESTIVAL DONA BE | AD31: YASSIE | AE31: YASSIE | AF31: C100 | AG31: E110_AC_DCOM | AH31: DCG-COM-PART | AI31: STD | AL31: E | AM31: E | AN31: Felana RARIVOSON | AO31: JUMELLES PRODUCTION | AP31: RAZAFINDRAHAGA Setra | AR31: 1267 | AS31: 1 | AT31: UN | AU31: 40000000 | AV31: SPONSORING | AW31: C100 | AX31: 4323 | AY31: 136068 | AZ31: 1 | BA31: 2026-07-30
A32: Gazetiko 1/8 page Quadrichromie - FA N° FAC/2026/2997 | B32: 0 | C32: 6234785.4 | D32: 7 481 742.48 | E32: 20 | F32: 139307 | G32: 1 | I32: MEDMEDI | J32: True | K32: DCG | L32: E110_MD_DCOM | M32: DCG-COM-MEDIA | N32: NA | P32: 1 | Q32: 6 234 785.40 | R32: YASMG | T32: FELANA13 | U32: 29 855 556.88 | V32: 35 826 668.26 | W32: MGA | X32: F | Y32: 46237 | Z32: 2026-08-03 | AA32: 46237 | AB32: 0000-00-00 | AC32: ANNULE ET REMPLACE DA 139119 | AD32: YASSIE | AE32: YASSIE | AF32: C100 | AG32: E110_MD_DCOM | AH32: DCG-COM-MEDIA | AI32: STD | AL32: E | AM32: E | AN32: Felana RARIVOSON | AO32: MIDI PUBLICITE | AP32: RAZAFINDRAHAGA Setra | AR32: 1265 | AS32: 1 | AT32: UN | AU32: 6234785.4 | AV32: PUBLICITE ET ANNONCE | AW32: C100 | AX32: 2566 | AY32: 136069 | AZ32: 1 | BA32: 2026-07-29
A33: Midi 1/8 page Quadrichromie - FA N° FAC/2026/2996 | B33: 0 | C33: 8314553.6 | D33: 9 977 464.32 | E33: 20 | F33: 139307 | G33: 2 | I33: MEDMEDI | J33: True | K33: DCG | L33: E110_MD_DCOM | M33: DCG-COM-MEDIA | N33: NA | P33: 1 | Q33: 8 314 553.60 | R33: YASMG | T33: FELANA13 | U33: 29 855 556.88 | V33: 35 826 668.26 | W33: MGA | X33: F | Y33: 46237 | Z33: 2026-08-03 | AA33: 46237 | AB33: 0000-00-00 | AC33: ANNULE ET REMPLACE DA 139119 | AD33: YASSIE | AE33: YASSIE | AF33: C100 | AG33: E110_MD_DCOM | AH33: DCG-COM-MEDIA | AI33: STD | AL33: E | AM33: E | AN33: Felana RARIVOSON | AO33: MIDI PUBLICITE | AP33: RAZAFINDRAHAGA Setra | AR33: 1265 | AS33: 1 | AT33: UN | AU33: 8314553.6 | AV33: PUBLICITE ET ANNONCE | AW33: C100 | AX33: 2566 | AY33: 136069 | AZ33: 2 | BA33: 2026-07-29
A34: Gazetiko 1/8 page Quadrichromie - FA N° FAC/2026/3004 | B34: 0 | C34: 6607983 | D34: 7 929 579.60 | E34: 20 | F34: 139307 | G34: 3 | I34: MEDMEDI | J34: True | K34: DCG | L34: E110_MD_DCOM | M34: DCG-COM-MEDIA | N34: NA | P34: 1 | Q34: 6 607 983.00 | R34: YASMG | T34: FELANA13 | U34: 29 855 556.88 | V34: 35 826 668.26 | W34: MGA | X34: F | Y34: 46237 | Z34: 2026-08-03 | AA34: 46237 | AB34: 0000-00-00 | AC34: ANNULE ET REMPLACE DA 139119 | AD34: YASSIE | AE34: YASSIE | AF34: C100 | AG34: E110_MD_DCOM | AH34: DCG-COM-MEDIA | AI34: STD | AL34: E | AM34: E | AN34: Felana RARIVOSON | AO34: MIDI PUBLICITE | AP34: RAZAFINDRAHAGA Setra | AR34: 1265 | AS34: 1 | AT34: UN | AU34: 6607983 | AV34: PUBLICITE ET ANNONCE | AW34: C100 | AX34: 2566 | AY34: 136069 | AZ34: 3 | BA34: 2026-07-29
A35: Midi 1/8 page Quadrichromie - FA N° FAC/2026/3003 | B35: 0 | C35: 8698234.9 | D35: 10 437 881.86 | E35: 20 | F35: 139307 | G35: 4 | I35: MEDMEDI | J35: True | K35: DCG | L35: E110_MD_DCOM | M35: DCG-COM-MEDIA | N35: NA | P35: 1 | Q35: 8 698 234.88 | R35: YASMG | T35: FELANA13 | U35: 29 855 556.88 | V35: 35 826 668.26 | W35: MGA | X35: F | Y35: 46237 | Z35: 2026-08-03 | AA35: 46237 | AB35: 0000-00-00 | AC35: ANNULE ET REMPLACE DA 139119 | AD35: YASSIE | AE35: YASSIE | AF35: C100 | AG35: E110_MD_DCOM | AH35: DCG-COM-MEDIA | AI35: STD | AL35: E | AM35: E | AN35: Felana RARIVOSON | AO35: MIDI PUBLICITE | AP35: RAZAFINDRAHAGA Setra | AR35: 1265 | AS35: 1 | AT35: UN | AU35: 8698234.9 | AV35: PUBLICITE ET ANNONCE | AW35: C100 | AX35: 2566 | AY35: 136069 | AZ35: 4 | BA35: 2026-07-29
A36: Gazetiko 1/8 page Quadrichromie - FA N° FAC/2026/2332 | B36: 0 | C36: 3109980 | D36: 3 731 976.00 | E36: 20 | F36: 139305 | G36: 1 | I36: MEDMEDI | J36: True | K36: DCG | L36: E110_MD_DCOM | M36: DCG-COM-MEDIA | N36: NA | P36: 1 | Q36: 3 109 980.00 | R36: YASMG | T36: FELANA13 | U36: 20 941 238.56 | V36: 25 129 486.28 | W36: MGA | X36: F | Y36: 46237 | Z36: 2026-08-03 | AA36: 46237 | AB36: 0000-00-00 | AC36: ANNULE ET REMPLACE DA 139119 | AD36: YASSIE | AE36: YASSIE | AF36: C100 | AG36: E110_MD_DCOM | AH36: DCG-COM-MEDIA | AI36: STD | AL36: E | AM36: E | AN36: Felana RARIVOSON | AO36: MIDI PUBLICITE | AP36: RAZAFINDRAHAGA Setra | AR36: 1265 | AS36: 1 | AT36: UN | AU36: 3109980 | AV36: PUBLICITE ET ANNONCE | AW36: C100 | AX36: 2566 | AY36: 136070 | AZ36: 1 | BA36: 2026-07-29
A37: Midi 1/8 page Quadrichromie - FA N° FAC/2026/1810 | B37: 0 | C37: 4136906.9 | D37: 4 964 288.26 | E37: 20 | F37: 139305 | G37: 2 | I37: MEDMEDI | J37: True | K37: DCG | L37: E110_MD_DCOM | M37: DCG-COM-MEDIA | N37: NA | P37: 1 | Q37: 4 136 906.88 | R37: YASMG | T37: FELANA13 | U37: 20 941 238.56 | V37: 25 129 486.28 | W37: MGA | X37: F | Y37: 46237 | Z37: 2026-08-03 | AA37: 46237 | AB37: 0000-00-00 | AC37: ANNULE ET REMPLACE DA 139119 | AD37: YASSIE | AE37: YASSIE | AF37: C100 | AG37: E110_MD_DCOM | AH37: DCG-COM-MEDIA | AI37: STD | AL37: E | AM37: E | AN37: Felana RARIVOSON | AO37: MIDI PUBLICITE | AP37: RAZAFINDRAHAGA Setra | AR37: 1265 | AS37: 1 | AT37: UN | AU37: 4136906.9 | AV37: PUBLICITE ET ANNONCE | AW37: C100 | AX37: 2566 | AY37: 136070 | AZ37: 2 | BA37: 2026-07-29
A38: Midi 1/8 page Quadrichromie - FA N° FAC/2026/2993 | B38: 0 | C38: 7785969.3 | D38: 9 343 163.14 | E38: 20 | F38: 139305 | G38: 3 | I38: MEDMEDI | J38: True | K38: DCG | L38: E110_MD_DCOM | M38: DCG-COM-MEDIA | N38: NA | P38: 1 | Q38: 7 785 969.28 | R38: YASMG | T38: FELANA13 | U38: 20 941 238.56 | V38: 25 129 486.28 | W38: MGA | X38: F | Y38: 46237 | Z38: 2026-08-03 | AA38: 46237 | AB38: 0000-00-00 | AC38: ANNULE ET REMPLACE DA 139119 | AD38: YASSIE | AE38: YASSIE | AF38: C100 | AG38: E110_MD_DCOM | AH38: DCG-COM-MEDIA | AI38: STD | AL38: E | AM38: E | AN38: Felana RARIVOSON | AO38: MIDI PUBLICITE | AP38: RAZAFINDRAHAGA Setra | AR38: 1265 | AS38: 1 | AT38: UN | AU38: 7785969.3 | AV38: PUBLICITE ET ANNONCE | AW38: C100 | AX38: 2566 | AY38: 136070 | AZ38: 3 | BA38: 2026-07-29
A39: Gazetiko 1/8 page Quadrichromie - FA N° FAC/2026/2994 | B39: 0 | C39: 5908382.4 | D39: 7 090 058.88 | E39: 20 | F39: 139305 | G39: 4 | I39: MEDMEDI | J39: True | K39: DCG | L39: E110_MD_DCOM | M39: DCG-COM-MEDIA | N39: NA | P39: 1 | Q39: 5 908 382.40 | R39: YASMG | T39: FELANA13 | U39: 20 941 238.56 | V39: 25 129 486.28 | W39: MGA | X39: F | Y39: 46237 | Z39: 2026-08-03 | AA39: 46237 | AB39: 0000-00-00 | AC39: ANNULE ET REMPLACE DA 139119 | AD39: YASSIE | AE39: YASSIE | AF39: C100 | AG39: E110_MD_DCOM | AH39: DCG-COM-MEDIA | AI39: STD | AL39: E | AM39: E | AN39: Felana RARIVOSON | AO39: MIDI PUBLICITE | AP39: RAZAFINDRAHAGA Setra | AR39: 1265 | AS39: 1 | AT39: UN | AU39: 5908382.4 | AV39: PUBLICITE ET ANNONCE | AW39: C100 | AX39: 2566 | AY39: 136070 | AZ39: 4 | BA39: 2026-07-29
A40: Gazetiko 1/8 page Quadrichromie - FA N° FAC/2026/2333 | B40: 0 | C40: 5084382.6 | D40: 6 101 259.12 | E40: 20 | F40: 139304 | G40: 1 | I40: MEDMEDI | J40: True | K40: DCG | L40: E110_MD_DCOM | M40: DCG-COM-MEDIA | N40: NA | P40: 1 | Q40: 5 084 382.60 | R40: YASMG | T40: FELANA13 | U40: 21 710 626.88 | V40: 26 052 752.26 | W40: MGA | X40: F | Y40: 46237 | Z40: 2026-08-03 | AA40: 46237 | AB40: 0000-00-00 | AC40: ANNULE ET REMPLACE DA 139119 | AD40: YASSIE | AE40: YASSIE | AF40: C100 | AG40: E110_MD_DCOM | AH40: DCG-COM-MEDIA | AI40: STD | AL40: E | AM40: E | AN40: Felana RARIVOSON | AO40: MIDI PUBLICITE | AP40: RAZAFINDRAHAGA Setra | AR40: 1265 | AS40: 1 | AT40: UN | AU40: 5084382.6 | AV40: PUBLICITE ET ANNONCE | AW40: C100 | AX40: 2566 | AY40: 136071 | AZ40: 1 | BA40: 2026-07-29
A41: Gazetiko 1/8 page Quadrichromie - FA N° FAC/2026/2335 | B41: 0 | C41: 3809580.6 | D41: 4 571 496.72 | E41: 20 | F41: 139304 | G41: 2 | I41: MEDMEDI | J41: True | K41: DCG | L41: E110_MD_DCOM | M41: DCG-COM-MEDIA | N41: NA | P41: 1 | Q41: 3 809 580.60 | R41: YASMG | T41: FELANA13 | U41: 21 710 626.88 | V41: 26 052 752.26 | W41: MGA | X41: F | Y41: 46237 | Z41: 2026-08-03 | AA41: 46237 | AB41: 0000-00-00 | AC41: ANNULE ET REMPLACE DA 139119 | AD41: YASSIE | AE41: YASSIE | AF41: C100 | AG41: E110_MD_DCOM | AH41: DCG-COM-MEDIA | AI41: STD | AL41: E | AM41: E | AN41: Felana RARIVOSON | AO41: MIDI PUBLICITE | AP41: RAZAFINDRAHAGA Setra | AR41: 1265 | AS41: 1 | AT41: UN | AU41: 3809580.6 | AV41: PUBLICITE ET ANNONCE | AW41: C100 | AX41: 2566 | AY41: 136071 | AZ41: 2 | BA41: 2026-07-29
A42: Midi 1/8 page Quadrichromie - FA N° FAC/2026/2336 | B42: 0 | C42: 5149494.4 | D42: 6 179 393.28 | E42: 20 | F42: 139304 | G42: 3 | I42: MEDMEDI | J42: True | K42: DCG | L42: E110_MD_DCOM | M42: DCG-COM-MEDIA | N42: NA | P42: 1 | Q42: 5 149 494.40 | R42: YASMG | T42: FELANA13 | U42: 21 710 626.88 | V42: 26 052 752.26 | W42: MGA | X42: F | Y42: 46237 | Z42: 2026-08-03 | AA42: 46237 | AB42: 0000-00-00 | AC42: ANNULE ET REMPLACE DA 139119 | AD42: YASSIE | AE42: YASSIE | AF42: C100 | AG42: E110_MD_DCOM | AH42: DCG-COM-MEDIA | AI42: STD | AL42: E | AM42: E | AN42: Felana RARIVOSON | AO42: MIDI PUBLICITE | AP42: RAZAFINDRAHAGA Setra | AR42: 1265 | AS42: 1 | AT42: UN | AU42: 5149494.4 | AV42: PUBLICITE ET ANNONCE | AW42: C100 | AX42: 2566 | AY42: 136071 | AZ42: 3 | BA42: 2026-07-29
... A50: Transport PLV YAS : Estrade + Panneau - PROFORMA N°190-07/LC/2026 | B50: 0 | C50: 600000 | D50: 600 000.00 | E50: 0 | F50: 139225 | G50: 1 | I50: TRNTERM | J50: True | K50: DCG | L50: E110_SP_DCOM | M50: DCG-COM-PART | N50: NA | P50: 0 | Q50: 0.00 | R50: YASMG | T50: FELANA13 | U50: 600 000.00 | V50: 600 000.00 | W50: MGA | X50: F | Y50: 46237 | Z50: 2026-08-03 | AA50: 46237 | AB50: 0000-00-00 | AC50: FINALE YAS COUPE DE MADA 2026 | AD50: YASSIE | AE50: YASSIE | AF50: C100 | AG50: E110_SP_DCOM | AH50: DCG-COM-PART | AI50: STD | AL50: S | AM50: S | AN50: Felana RARIVOSON | AO50: LUCKKY COMPANY | AP50: RAZAFINDRAHAGA Setra | AR50: 4276 | AS50: 2 | AT50: UN | AU50: 300000 | AV50: TRANSPORT | AW50: C100 | AX50: 3726 | AY50: 136077 | AZ50: 1 | BA50: 0000-00-00
A51: Location du 05/08 au 12/08# FACTURE PROFORMA-J498 DU 31/07/2026 | B51: 0 | C51: 2000000 | D51: 2 400 000.00 | E51: 20 | F51: 139362 | G51: 1 | I51: LOCLOCT | J51: True | K51: DSI | L51: E215_DSI | M51: DSI | N51: NA | P51: 8 | Q51: 2 000 000.00 | R51: YASMG | T51: NADIA7 | U51: 2 440 000.00 | V51: 2 928 000.00 | W51: MGA | Y51: 46237 | Z51: 2026-08-03 | AA51: 46237 | AB51: 0000-00-00 | AC51: Location LCD-Mission Tafita à Mahanoro 05 au 12 Août 2026 | AD51: YASSIE | AE51: YASSIE | AF51: C800 | AG51: E215_DSI | AH51: DSI | AI51: STD | AL51: E | AM51: E | AN51: RAVONINJATOVO Nadia | AO51: LOXEA MADAGASCAR | AP51: NJIVA Mbolatiana | AR51: 10626 | AS51: 8 | AT51: PIE | AU51: 250000 | AV51: LOCATION DE VOITURE COURTE DUREE | AW51: C800 | AX51: 629 | AY51: 136078 | AZ51: 1 | BA51: 2026-07-31
A52: Service chauffeur hors ville | B52: 0 | C52: 540000 | D52: 648 000.00 | E52: 20 | F52: 139362 | G52: 2 | I52: PRICTRL | J52: True | K52: DSI | L52: E215_DSI | M52: DSI | N52: NA | P52: 8 | Q52: 540 000.00 | R52: YASMG | T52: NADIA7 | U52: 2 440 000.00 | V52: 2 928 000.00 | W52: MGA | Y52: 46237 | Z52: 2026-08-03 | AA52: 46237 | AB52: 0000-00-00 | AC52: Location LCD-Mission Tafita à Mahanoro 05 au 12 Août 2026 | AD52: YASSIE | AE52: YASSIE | AF52: C800 | AG52: E215_DSI | AH52: DSI | AI52: STD | AL52: E | AM52: E | AN52: RAVONINJATOVO Nadia | AO52: LOXEA MADAGASCAR | AP52: NJIVA Mbolatiana | AR52: 6965 | AS52: 8 | AT52: UN | AU52: 67500 | AV52: PRESTATION DE SERVICES EXTERNE | AW52: C800 | AX52: 629 | AY52: 136078 | AZ52: 2 | BA52: 2026-07-31
A53: Remise | B53: 0 | C53: -100000 | D53: -120 000.00 | E53: 20 | F53: 139362 | G53: 3 | I53: GELACCS | J53: True | K53: DSI | L53: E215_DSI | M53: DSI | N53: NA | P53: 1 | Q53: -100 000.00 | R53: YASMG | T53: NADIA7 | U53: 2 440 000.00 | V53: 2 928 000.00 | W53: MGA | Y53: 46237 | Z53: 2026-08-03 | AA53: 46237 | AB53: 0000-00-00 | AC53: Location LCD-Mission Tafita à Mahanoro 05 au 12 Août 2026 | AD53: YASSIE | AE53: YASSIE | AF53: C800 | AG53: E215_DSI | AH53: DSI | AI53: STD | AL53: E | AM53: E | AN53: RAVONINJATOVO Nadia | AO53: LOXEA MADAGASCAR | AP53: NJIVA Mbolatiana | AR53: 2057 | AS53: 1 | AT53: UN | AU53: -100000 | AV53: REMISE | AW53: C800 | AX53: 629 | AY53: 136078 | AZ53: 3 | BA53: 2026-07-31
A54: Réf 06080/A026 En tête facture DSI, ft A4, imp quadri recto sur offset 90g, 1 visuel * 15000 ex# DEVIS DU 24/07/2026 | B54: 0 | C54: 1835294.1 | D54: 2 202 352.92 | E54: 20 | F54: 139295 | G54: 1 | I54: FRNPAPF | J54: True | K54: DSI | L54: E218_DSI | M54: DSI | N54: NA | P54: 15000 | Q54: 1 835 294.10 | R54: YASMG | T54: NADIA7 | U54: 1 530 000.00 | V54: 1 836 000.00 | W54: MGA | Y54: 46237 | Z54: 2026-08-03 | AA54: 46237 | AB54: 0000-00-00 | AC54: Achat 15000 Enveloppes GM En tête pour facturation | AD54: YASSIE | AE54: GALE | AF54: C800 | AG54: E218_DSI | AH54: DSI | AI54: STD | AL54: E | AM54: E | AN54: RAVONINJATOVO Nadia | AO54: MEGAPRINT | AP54: NJIVA Mbolatiana | AR54: 9753 | AS54: 15000 | AT54: UN | AU54: 122.35294 | AV54: ENTETE FACTURE | AW54: C800 | AX54: 88 | AY54: 136079 | AZ54: 1 | BA54: 2026-07-31
A55: Remise | B55: 0 | C55: -305294.1 | D55: -366 352.92 | E55: 20 | F55: 139295 | G55: 2 | I55: GELACCS | J55: True | K55: DSI | L55: E218_DSI | M55: DSI | N55: NA | P55: 1 | Q55: -305 294.10 | R55: YASMG | T55: NADIA7 | U55: 1 530 000.00 | V55: 1 836 000.00 | W55: MGA | Y55: 46237 | Z55: 2026-08-03 | AA55: 46237 | AB55: 0000-00-00 | AC55: Achat 15000 Enveloppes GM En tête pour facturation | AD55: YASSIE | AE55: GALE | AF55: C800 | AG55: E218_DSI | AH55: DSI | AI55: STD | AL55: E | AM55: E | AN55: RAVONINJATOVO Nadia | AO55: MEGAPRINT | AP55: NJIVA Mbolatiana | AR55: 2057 | AS55: 1 | AT55: UN | AU55: -305294.1 | AV55: REMISE | AW55: C800 | AX55: 88 | AY55: 136079 | AZ55: 2 | BA55: 2026-07-31
A56: Prestation intérimaire: 01 Technicien Drive Test et Performance Radio pour 2 mois# DEVIS N°3914 DU 03/07/2026 | B56: 0 | C56: 1504400 | D56: 1 805 280.00 | E56: 20 | F56: 139266 | G56: 1 | I56: PRICTRL | J56: True | K56: DTG | L56: E214_DTG | M56: DRH-ADMIN | N56: NA | P56: 1 | Q56: 1 504 400.00 | R56: YASMG | T56: NADIA7 | U56: 1 504 400.00 | V56: 1 805 280.00 | W56: MGA | X56: F | Y56: 46237 | Z56: 2026-08-03 | AA56: 46237 | AB56: 0000-00-00 | AD56: YASSIE | AE56: YASSIE | AF56: C500 | AG56: E214_DTG | AH56: DRH-ADMIN | AI56: STD | AL56: E | AM56: E | AN56: RAVONINJATOVO Nadia | AO56: MADAJOB | AP56: ANDRIANINA Rebecca | AR56: 14862 | AS56: 1 | AT56: UN | AU56: 1504400 | AV56: PRESTATION DE SERVICE | AW56: C500 | AX56: 723 | AY56: 136080 | AZ56: 1 | BA56: 2026-07-28
A57: Prestation intérimaire: 582 AR Terrain en Axe Régions pour 2 mois# FACTURE PROFORMA N°356-A/FP/TELMA /2026 DU 17/07/2026 | B57: 0 | C57: 469906800 | D57: 563 888 160.00 | E57: 20 | F57: 139174 | G57: 1 | I57: PRICTRL | J57: True | K57: DCG | L57: E214_DVI | M57: DRH-ADMIN | N57: NA | P57: 582 | Q57: 469 906 800.00 | R57: YASMG | T57: NADIA7 | U57: 469 906 800.00 | V57: 563 888 160.00 | W57: MGA | Y57: 46237 | Z57: 2026-08-03 | AA57: 46237 | AB57: 0000-00-00 | AD57: YASSIE | AE57: YASSIE | AF57: C104 | AG57: E214_DVI | AH57: DRH-ADMIN | AI57: STD | AL57: E | AM57: E | AN57: RAVONINJATOVO Nadia | AO57: LCS CONSULTING | AP57: ANDRIANINA Rebecca | AR57: 14862 | AS57: 582 | AT57: UN | AU57: 807400 | AV57: PRESTATION DE SERVICE | AW57: C104 | AX57: 2490 | AY57: 136081 | AZ57: 1 | BA57: 2026-07-22
A58: Remboursement IM AR MBALIK mois de Juin 2026 - suivant proforma N°338-A/FP/TELMA/2026 | B58: 0 | C58: 3660775 | D58: 3 660 775.00 | E58: 0 | F58: 139206 | G58: 1 | I58: PRICTRL | J58: True | K58: DCG | L58: E214_DCG | M58: DCG-SHS | N58: NA | P58: 1 | Q58: 3 660 775.00 | R58: YASMG | T58: FELANA13 | U58: 9 325 575.00 | V58: 9 325 575.00 | W58: MGA | X58: F | Y58: 46237 | Z58: 2026-08-03 | AA58: 46237 | AB58: 0000-00-00 | AC58: REMBOURSEMENT IM AR & FRAIS COLIS & IM ADV | AD58: YASSIE | AE58: YASSIE | AF58: C100 | AG58: E214_DCG | AH58: DCG-SHS | AI58: STD | AL58: E | AM58: E | AN58: Felana RARIVOSON | AO58: LCS CONSULTING | AP58: RAZAFINDRAHAGA Setra | AR58: 1264 | AS58: 1 | AT58: UN | AU58: 3660775 | AV58: PRESTATION EXTERNE | AW58: C100 | AX58: 2490 | AY58: 136082 | AZ58: 1 | BA58: 2026-07-22
A59: Remboursement frais colis AR MBALIK mois de Juin 2026 - suivant proforma N°339-A/FP/TELMA/2026 | B59: 0 | C59: 2214900 | D59: 2 214 900.00 | E59: 0 | F59: 139206 | G59: 2 | I59: PRICTRL | J59: True | K59: DCG | L59: E214_DCG | M59: DCG-SHS | N59: NA | P59: 1 | Q59: 2 214 900.00 | R59: YASMG | T59: FELANA13 | U59: 9 325 575.00 | V59: 9 325 575.00 | W59: MGA | X59: F | Y59: 46237 | Z59: 2026-08-03 | AA59: 46237 | AB59: 0000-00-00 | AC59: REMBOURSEMENT IM AR & FRAIS COLIS & IM ADV | AD59: YASSIE | AE59: YASSIE | AF59: C100 | AG59: E214_DCG | AH59: DCG-SHS | AI59: STD | AL59: E | AM59: E | AN59: Felana RARIVOSON | AO59: LCS CONSULTING | AP59: RAZAFINDRAHAGA Setra | AR59: 1264 | AS59: 1 | AT59: UN | AU59: 2214900 | AV59: PRESTATION EXTERNE | AW59: C100 | AX59: 2490 | AY59: 136082 | AZ59: 2 | BA59: 2026-07-22
A60: Remboursement IM CDV MBALIK mois de mai 2026 - suivant proforma N°329-A/FP/TELMA/2026 | B60: 0 | C60: 3449900 | D60: 3 449 900.00 | E60: 0 | F60: 139206 | G60: 3 | I60: PRICTRL | J60: True | K60: DCG | L60: E214_DCG | M60: DCG-SHS | N60: NA | P60: 1 | Q60: 3 449 900.00 | R60: YASMG | T60: FELANA13 | U60: 9 325 575.00 | V60: 9 325 575.00 | W60: MGA | X60: F | Y60: 46237 | Z60: 2026-08-03 | AA60: 46237 | AB60: 0000-00-00 | AC60: REMBOURSEMENT IM AR & FRAIS COLIS & IM ADV | AD60: YASSIE | AE60: YASSIE | AF60: C100 | AG60: E214_DCG | AH60: DCG-SHS | AI60: STD | AL60: E | AM60: E | AN60: Felana RARIVOSON | AO60: LCS CONSULTING | AP60: RAZAFINDRAHAGA Setra | AR60: 1264 | AS60: 1 | AT60: UN | AU60: 3449900 | AV60: PRESTATION EXTERNE | AW60: C100 | AX60: 2490 | AY60: 136082 | AZ60: 3 | BA60: 2026-07-22
A61: Prestation intérimaire: 01 Analyste Fonctionnel VE pour 2 mois# FACTURE PROFORMA N°366-A/FP/TELMA/2026 DU 17/07/2026 | B61: 0 | C61: 2247800 | D61: 2 697 360.00 | E61: 20 | F61: 139190 | G61: 1 | I61: PRICTRL | J61: True | K61: DCG | L61: E214_DVE | M61: DRH-ADMIN | N61: NA | P61: 1 | Q61: 2 247 800.00 | R61: YASMG | T61: NADIA7 | U61: 2 247 800.00 | V61: 2 697 360.00 | W61: MGA | Y61: 46237 | Z61: 2026-08-03 | AA61: 46237 | AB61: 0000-00-00 | AD61: YASSIE | AE61: YASSIE | AF61: C103 | AG61: E214_DVE | AH61: DRH-ADMIN | AI61: STD | AL61: E | AM61: E | AN61: RAVONINJATOVO Nadia | AO61: LCS CONSULTING | AP61: ANDRIANINA Rebecca | AR61: 14862 | AS61: 1 | AT61: UN | AU61: 2247800 | AV61: PRESTATION DE SERVICE | AW61: C103 | AX61: 2490 | AY61: 136083 | AZ61: 1 | BA61: 2026-07-22
A62: Prestation intérimaire: 75 AR Roadshow pour 2 mois# FACTURE PROFORMA N°355-A/FP/TELMA /2026 DU 17/07/2026 | B62: 0 | C62: 60555000 | D62: 72 666 000.00 | E62: 20 | F62: 139173 | G62: 1 | I62: PRICTRL | J62: True | K62: DCG | L62: E214_DVI | M62: DRH-ADMIN | N62: NA | P62: 75 | Q62: 60 555 000.00 | R62: YASMG | T62: NADIA7 | U62: 60 555 000.00 | V62: 72 666 000.00 | W62: MGA | Y62: 46237 | Z62: 2026-08-03 | AA62: 46237 | AB62: 0000-00-00 | AD62: YASSIE | AE62: YASSIE | AF62: C104 | AG62: E214_DVI | AH62: DRH-ADMIN | AI62: STD | AL62: E | AM62: E | AN62: RAVONINJATOVO Nadia | AO62: LCS CONSULTING | AP62: ANDRIANINA Rebecca | AR62: 14862 | AS62: 75 | AT62: UN | AU62: 807400 | AV62: PRESTATION DE SERVICE | AW62: C104 | AX62: 2490 | AY62: 136084 | AZ62: 1 | BA62: 2026-07-22
A63: COLLATION NOUVELLE RECRUE LE 24 JUILLET 2026 : Gâteaux entier - PROFORMA/EVENT/PRKL/2026 DU 21/07/26 | B63: 0 | C63: 120000 | D63: 144 000.00 | E63: 20 | F63: 139200 | G63: 1 | I63: VDPPERD | J63: True | K63: DCG | L63: E219_DCG | M63: DCG-BEF | N63: NA | P63: 12 | Q63: 120 000.00 | R63: YASMG | T63: FELANA13 | U63: 120 000.00 | V63: 144 000.00 | W63: MGA | X63: F | Y63: 46237 | Z63: 2026-08-03 | AA63: 46237 | AB63: 0000-00-00 | AC63: COLLATION LE 24/07/2026 | AD63: YASSIE | AE63: YASSIE | AF63: C100 | AG63: E219_DCG | AH63: DCG-BEF | AI63: STD | AL63: E | AM63: E | AN63: Felana RARIVOSON | AO63: SOCIETE DE GESTION ET EXPLOITATION DE M/CAR | AP63: RAZAFINDRAHAGA Setra | AR63: 12682 | AS63: 12 | AT63: UN | AU63: 10000 | AV63: COLLATION | AW63: C100 | AX63: 119 | AY63: 136085 | AZ63: 1 | BA63: 2026-07-22
A64: Prestation intérimaire: PERDIEM Mission - Rina juillet 26# FACTURE PROFORMA N°398-A/FP/TELMA/2026 du 28/07/2026 | B64: 0 | C64: 162300 | D64: 162 300.00 | E64: 0 | F64: 139294 | G64: 1 | I64: PRICTRL | J64: True | K64: DRH | L64: E214_DRH | M64: DRH-ADMIN | N64: NA | P64: 1 | Q64: 162 300.00 | R64: YASMG | T64: NADIA7 | U64: 162 300.00 | V64: 162 300.00 | W64: MGA | X64: F | Y64: 46237 | Z64: 2026-08-03 | AA64: 46237 | AB64: 0000-00-00 | AD64: YASSIE | AE64: YASSIE | AF64: C600 | AG64: E214_DRH | AH64: DRH-ADMIN | AI64: STD | AL64: E | AM64: E | AN64: RAVONINJATOVO Nadia | AO64: LCS CONSULTING | AP64: ANDRIANINA Rebecca | AR64: 14862 | AS64: 1 | AT64: UN | AU64: 162300 | AV64: PRESTATION DE SERVICE | AW64: C600 | AX64: 2490 | AY64: 136086 | AZ64: 1 | BA64: 2026-07-28
A65: Soutien de lévènement Festival Sorogno - FACTURE DU 14/07/2026 | B65: 0 | C65: 20000000 | D65: 20 000 000.00 | E65: 0 | F65: 139363 | G65: 1 | I65: MECSPDC | J65: True | K65: DCG | L65: E110_AC_DCOM | M65: DCG-COM-PART | N65: NA | P65: 0 | Q65: 0.00 | R65: YASMG | T65: FELANA13 | U65: 40 000 000.00 | V65: 40 000 000.00 | W65: MGA | X65: F | Y65: 46237 | Z65: 2026-08-03 | AA65: 46237 | AB65: 0000-00-00 | AC65: FESTIVAL SOROGNO 2026 | AD65: YASSIE | AE65: YASSIE | AF65: C100 | AG65: E110_AC_DCOM | AH65: DCG-COM-PART | AI65: STD | AL65: S | AM65: S | AN65: Felana RARIVOSON | AO65: ONG SOROGNO | AP65: RAZAFINDRAHAGA Setra | AR65: 1267 | AS65: 1 | AT65: UN | AU65: 20000000 | AV65: SPONSORING | AW65: C100 | AX65: 4331 | AY65: 136087 | AZ65: 1 | BA65: 0000-00-00
A66: Cachet Ambassadeur YAS MADADASCAR | B66: 0 | C66: 20000000 | D66: 20 000 000.00 | E66: 0 | F66: 139363 | G66: 2 | I66: FRNPAPF | J66: True | K66: DCG | L66: E110_AC_DCOM | M66: DCG-COM-PART | N66: NA | P66: 0 | Q66: 0.00 | R66: YASMG | T66: FELANA13 | U66: 40 000 000.00 | V66: 40 000 000.00 | W66: MGA | X66: F | Y66: 46237 | Z66: 2026-08-03 | AA66: 46237 | AB66: 0000-00-00 | AC66: FESTIVAL SOROGNO 2026 | AD66: YASSIE | AE66: YASSIE | AF66: C100 | AG66: E110_AC_DCOM | AH66: DCG-COM-PART | AI66: STD | AL66: S | AM66: S | AN66: Felana RARIVOSON | AO66: ONG SOROGNO | AP66: RAZAFINDRAHAGA Setra | AR66: 3307 | AS66: 5 | AT66: PIE | AU66: 4000000 | AV66: CACHET | AW66: C100 | AX66: 4331 | AY66: 136087 | AZ66: 2 | BA66: 0000-00-00
A67: Prestation intérimaire: Frais d'installation 01 Tech Pol en juillet 2026# FACTURE PROFORMA N°395-A/FP/TELMA/2026 du 28/07/2026 | B67: 0 | C67: 1027700 | D67: 1 027 700.00 | E67: 0 | F67: 139281 | G67: 1 | I67: PRICTRL | J67: True | K67: DTG | L67: E214_DTG | M67: DRH-ADMIN | N67: NA | P67: 1 | Q67: 1 027 700.00 | R67: YASMG | T67: NADIA7 | U67: 1 027 700.00 | V67: 1 027 700.00 | W67: MGA | X67: F | Y67: 46237 | Z67: 2026-08-03 | AA67: 46237 | AB67: 0000-00-00 | AD67: YASSIE | AE67: YASSIE | AF67: C500 | AG67: E214_DTG | AH67: DRH-ADMIN | AI67: STD | AL67: E | AM67: E | AN67: RAVONINJATOVO Nadia | AO67: LCS CONSULTING | AP67: ANDRIANINA Rebecca | AR67: 14862 | AS67: 1 | AT67: UN | AU67: 1027700 | AV67: PRESTATION DE SERVICE | AW67: C500 | AX67: 2490 | AY67: 136088 | AZ67: 1 | BA67: 2026-07-28
A68: HOUSSE CHAPITEAU - DRB - JUILLET 2026 - DEVIS B-PR0726-0131 DU 30/07/2026 | B68: 2 | C68: 7945350 | D68: 9 534 420.00 | E68: 20 | F68: 139357 | G68: 1 | I68: PLVPLES | J68: True | K68: DCG | L68: E110_TR_DRB | M68: DCG-DRB | N68: NA | P68: 15 | Q68: 7 945 350.00 | R68: YASMG | T68: FELANA13 | U68: 7 945 350.00 | V68: 9 534 420.00 | W68: MGA | X68: F | Y68: 46237 | Z68: 2026-08-03 | AA68: 46237 | AB68: 0000-00-00 | AC68: HOUSSE CHAPITEAU | AD68: YASSIE | AE68: GALE | AF68: C102 | AG68: E110_TR_DRB | AH68: DCG-DRB | AI68: STD | AL68: E | AM68: E | AN68: Felana RARIVOSON | AO68: MORA MARKET | AP68: RAZAFINDRAHAGA Setra | AR68: 31274 | AS68: 15 | AT68: UN | AU68: 540500 | AV68: HOUSSE CHAPITEAU - DRB - JUILLET 2026 | AW68: C102 | AX68: 4245 | AY68: 136089 | AZ68: 1 | BA68: 2026-07-31
A69: Prestation intérimaire: PERDIEM Suivi routier - Steve juillet 26# FACTURE PROFORMA N°397-A/FP/TELMA/2026 du 28/07/2026 | B69: 0 | C69: 1603000 | D69: 1 603 000.00 | E69: 0 | F69: 139286 | G69: 1 | I69: PRICTRL | J69: True | K69: DTG | L69: E214_DTG | M69: DRH-ADMIN | N69: NA | P69: 1 | Q69: 1 603 000.00 | R69: YASMG | T69: NADIA7 | U69: 1 603 000.00 | V69: 1 603 000.00 | W69: MGA | X69: F | Y69: 46237 | Z69: 2026-08-03 | AA69: 46237 | AB69: 0000-00-00 | AD69: YASSIE | AE69: YASSIE | AF69: C500 | AG69: E214_DTG | AH69: DRH-ADMIN | AI69: STD | AL69: E | AM69: E | AN69: RAVONINJATOVO Nadia | AO69: LCS CONSULTING | AP69: ANDRIANINA Rebecca | AR69: 14862 | AS69: 1 | AT69: UN | AU69: 1603000 | AV69: PRESTATION DE SERVICE | AW69: C500 | AX69: 2490 | AY69: 136090 | AZ69: 1 | BA69: 2026-07-28
A70: Prestation intérimaire: PERDIEM Suivi routier - Tsiry, Nirintsoa, Thierry, Tahiry août 26# FACTURE PROFORMA N°396-A/FP/TELMA/2026 du 28/07/2026 | B70: 0 | C70: 6412000 | D70: 6 412 000.00 | E70: 0 | F70: 139288 | G70: 1 | I70: PRICTRL | J70: True | K70: DTG | L70: E214_DTG | M70: DRH-ADMIN | N70: NA | P70: 1 | Q70: 6 412 000.00 | R70: YASMG | T70: NADIA7 | U70: 6 412 000.00 | V70: 6 412 000.00 | W70: MGA | X70: F | Y70: 46237 | Z70: 2026-08-03 | AA70: 46237 | AB70: 0000-00-00 | AD70: YASSIE | AE70: YASSIE | AF70: C500 | AG70: E214_DTG | AH70: DRH-ADMIN | AI70: STD | AL70: E | AM70: E | AN70: RAVONINJATOVO Nadia | AO70: LCS CONSULTING | AP70: ANDRIANINA Rebecca | AR70: 14862 | AS70: 1 | AT70: UN | AU70: 6412000 | AV70: PRESTATION DE SERVICE | AW70: C500 | AX70: 2490 | AY70: 136091 | AZ70: 1 | BA70: 2026-07-28
A71: Prestation intérimaire: 02 AR Micro Tanà pour 2 mois# DEVIS N° 002880 DU 20/07/2026 | B71: 0 | C71: 1494800 | D71: 1 793 760.00 | E71: 20 | F71: 139277 | G71: 1 | I71: PRICTRL | J71: True | K71: DCG | L71: E214_DVI | M71: DRH-ADMIN | N71: NA | P71: 1 | Q71: 1 494 800.00 | R71: YASMG | T71: NADIA7 | U71: 1 494 800.00 | V71: 1 793 760.00 | W71: MGA | X71: F | Y71: 46237 | Z71: 2026-08-03 | AA71: 46237 | AB71: 0000-00-00 | AD71: YASSIE | AE71: YASSIE | AF71: C104 | AG71: E214_DVI | AH71: DRH-ADMIN | AI71: STD | AL71: E | AM71: E | AN71: RAVONINJATOVO Nadia | AO71: MADAJOB | AP71: ANDRIANINA Rebecca | AR71: 14862 | AS71: 1 | AT71: UN | AU71: 1494800 | AV71: PRESTATION DE SERVICE | AW71: C104 | AX71: 723 | AY71: 136092 | AZ71: 1 | BA71: 2026-07-28
A72: Prestation intérimaire: IM 02 AR Micro Tanà pour 2 mois# DEVIS N° 002882 DU 20/07/2026 | B72: 0 | C72: 1458000 | D72: 1 458 000.00 | E72: 0 | F72: 139279 | G72: 1 | I72: PRICTRL | J72: True | K72: DCG | L72: E214_DVI | M72: DRH-ADMIN | N72: NA | P72: 1 | Q72: 1 458 000.00 | R72: YASMG | T72: NADIA7 | U72: 1 458 000.00 | V72: 1 458 000.00 | W72: MGA | X72: F | Y72: 46237 | Z72: 2026-08-03 | AA72: 46237 | AB72: 0000-00-00 | AD72: YASSIE | AE72: YASSIE | AF72: C104 | AG72: E214_DVI | AH72: DRH-ADMIN | AI72: STD | AL72: E | AM72: E | AN72: RAVONINJATOVO Nadia | AO72: MADAJOB | AP72: ANDRIANINA Rebecca | AR72: 14862 | AS72: 1 | AT72: UN | AU72: 1458000 | AV72: PRESTATION DE SERVICE | AW72: C104 | AX72: 723 | AY72: 136093 | AZ72: 1 | BA72: 2026-07-28
A73: ACHAT MOTO HONDA ACE 125 SHH 6DK - DEVIS DU 5/6/2026 | B73: 0 | C73: 7100000 | D73: 8 520 000.00 | E73: 20 | F73: 139356 | G73: 1 | I73: PRMVEHI | J73: True | K73: DCG | L73: 2026-CO-000001 | M73: DCG-DVI | N73: NA | P73: 1 | Q73: 7 100 000.00 | R73: YASMG | T73: FELANA13 | U73: 7 100 000.00 | V73: 8 520 000.00 | W73: MGA | X73: F | Y73: 46237 | Z73: 2026-08-03 | AA73: 46237 | AB73: 0000-00-00 | AC73: ACHAT MOTO | AD73: YASSIE | AE73: GALE | AF73: C104 | AG73: 2026-CO-000001 | AH73: DCG-DVI | AI73: STD | AL73: E | AM73: E | AN73: Felana RARIVOSON | AO73: MADAGASCAR AUTOMOBILE | AP73: RAZAFINDRAHAGA Setra | AR73: 4155 | AS73: 1 | AT73: UN | AU73: 7100000 | AV73: MOTO | AW73: C104 | AX73: 1184 | AY73: 136094 | AZ73: 1 | BA73: 2026-07-31
A74: ACHAT MOTO PEUGEOT KIBSEE 49.9CC - Modèle 2 temps - DEVIS DU 5/6/2026 | B74: 0 | C74: 12100000 | D74: 14 520 000.00 | E74: 20 | F74: 139355 | G74: 1 | I74: PRMVEHI | J74: True | K74: DCG | L74: 2026-CO-000001 | M74: DCG-DVE | N74: NA | P74: 2 | Q74: 12 100 000.00 | R74: YASMG | T74: FELANA13 | U74: 12 100 000.00 | V74: 14 520 000.00 | W74: MGA | X74: F | Y74: 46237 | Z74: 2026-08-03 | AA74: 46237 | AB74: 0000-00-00 | AC74: ACHAT MOTO | AD74: YASSIE | AE74: GALE | AF74: C103 | AG74: 2026-CO-000001 | AH74: DCG-DVE | AI74: STD | AL74: E | AM74: E | AN74: Felana RARIVOSON | AO74: MADAGASCAR AUTOMOBILE | AP74: RAZAFINDRAHAGA Setra | AR74: 4155 | AS74: 2 | AT74: UN | AU74: 6050000 | AV74: MOTO | AW74: C103 | AX74: 1184 | AY74: 136095 | AZ74: 1 | BA74: 2026-07-31
A75: ACHAT MOTO HONDA ACE 125 -SHH 6DK - DEVIS DU 27/7/2026 | B75: 0 | C75: 390500000 | D75: 468 600 000.00 | E75: 20 | F75: 139349 | G75: 1 | I75: PRMVEHI | J75: True | K75: DCG | L75: 2026-CO-000001 | M75: DCG-DVIR | N75: NA | P75: 55 | Q75: 390 500 000.00 | R75: YASMG | T75: FELANA13 | U75: 390 500 000.00 | V75: 468 600 000.00 | W75: MGA | X75: F | Y75: 46237 | Z75: 2026-08-03 | AA75: 46237 | AB75: 0000-00-00 | AC75: ACHAT MOTO | AD75: YASSIE | AE75: GALE | AF75: C104 | AG75: 2026-CO-000001 | AH75: DCG-DVIR | AI75: STD | AL75: E | AM75: E | AN75: Felana RARIVOSON | AO75: MADAGASCAR AUTOMOBILE | AP75: RAZAFINDRAHAGA Setra | AR75: 4155 | AS75: 55 | AT75: UN | AU75: 7100000 | AV75: MOTO | AW75: C104 | AX75: 1184 | AY75: 136096 | AZ75: 1 | BA75: 2026-07-30
A76: Prestation intérimaire: IM 30 AR Roadshow Tanà pour 2 mois# DEVIS N° 002881 DU 20/07/2026 | B76: 0 | C76: 21870000 | D76: 21 870 000.00 | E76: 0 | F76: 139278 | G76: 1 | I76: PRICTRL | J76: True | K76: DCG | L76: E214_DVI | M76: DRH-ADMIN | N76: NA | P76: 1 | Q76: 21 870 000.00 | R76: YASMG | T76: NADIA7 | U76: 21 870 000.00 | V76: 21 870 000.00 | W76: MGA | Y76: 46237 | Z76: 2026-08-03 | AA76: 46237 | AB76: 0000-00-00 | AD76: YASSIE | AE76: YASSIE | AF76: C104 | AG76: E214_DVI | AH76: DRH-ADMIN | AI76: STD | AL76: E | AM76: E | AN76: RAVONINJATOVO Nadia | AO76: MADAJOB | AP76: ANDRIANINA Rebecca | AR76: 14862 | AS76: 1 | AT76: UN | AU76: 21870000 | AV76: PRESTATION DE SERVICE | AW76: C104 | AX76: 723 | AY76: 136097 | AZ76: 1 | BA76: 2026-07-28
A77: Couverture 1/8 page en une du 23 et 30/01/2026 dans LA VERITE HEBDO - FACTURE N°11FI2321 DU 10/02/26 | B77: 0 | C77: 117000 | D77: 140 400.00 | E77: 20 | F77: 139346 | G77: 1 | I77: MEDMEDI | J77: True | K77: DCG | L77: E110_MD_DCOM | M77: DCG-COM-MEDIA | N77: NA | P77: 1 | Q77: 117 000.00 | R77: YASMG | T77: FELANA13 | U77: 117 000.00 | V77: 140 400.00 | W77: MGA | X77: F | Y77: 46237 | Z77: 2026-08-03 | AA77: 46237 | AB77: 0000-00-00 | AC77: REGUL LA VERITE | AD77: YASSIE | AE77: YASSIE | AF77: C100 | AG77: E110_MD_DCOM | AH77: DCG-COM-MEDIA | AI77: STD | AL77: E | AM77: E | AN77: Felana RARIVOSON | AO77: STE MALGACHE DE COMMUNICATION ET DE PRESSE | AP77: RAZAFINDRAHAGA Setra | AR77: 1265 | AS77: 1 | AT77: UN | AU77: 117000 | AV77: PUBLICITE ET ANNONCE | AW77: C100 | AX77: 2487 | AY77: 136098 | AZ77: 1 | BA77: 2026-07-30
A78: Prestation intérimaire: 30 AR Roadshow Tanà pour 2 mois# DEVIS N° 002879 DU 20/07/2026 | B78: 0 | C78: 22422000 | D78: 26 906 400.00 | E78: 20 | F78: 139276 | G78: 1 | I78: PRICTRL | J78: True | K78: DCG | L78: E214_DVI | M78: DRH-ADMIN | N78: NA | P78: 1 | Q78: 22 422 000.00 | R78: YASMG | T78: NADIA7 | U78: 22 422 000.00 | V78: 26 906 400.00 | W78: MGA | Y78: 46237 | Z78: 2026-08-03 | AA78: 46237 | AB78: 0000-00-00 | AD78: YASSIE | AE78: YASSIE | AF78: C104 | AG78: E214_DVI | AH78: DRH-ADMIN | AI78: STD | AL78: E | AM78: E | AN78: RAVONINJATOVO Nadia | AO78: MADAJOB | AP78: ANDRIANINA Rebecca | AR78: 14862 | AS78: 1 | AT78: UN | AU78: 22422000 | AV78: PRESTATION DE SERVICE | AW78: C104 | AX78: 723 | AY78: 136099 | AZ78: 1 | BA78: 2026-07-28
A79: Prestation intérimaire: 13 BO Tanà pour 2 mois# DEVIS N°002878 DU 20/07/2026 | B79: 0 | C79: 9716200 | D79: 11 659 440.00 | E79: 20 | F79: 139274 | G79: 1 | I79: PRICTRL | J79: True | K79: DCG | L79: E214_DVI | M79: DRH-ADMIN | N79: NA | P79: 1 | Q79: 9 716 200.00 | R79: YASMG | T79: NADIA7 | U79: 9 716 200.00 | V79: 11 659 440.00 | W79: MGA | Y79: 46237 | Z79: 2026-08-03 | AA79: 46237 | AB79: 0000-00-00 | AD79: YASSIE | AE79: YASSIE | AF79: C104 | AG79: E214_DVI | AH79: DRH-ADMIN | AI79: STD | AL79: E | AM79: E | AN79: RAVONINJATOVO Nadia | AO79: MADAJOB | AP79: ANDRIANINA Rebecca | AR79: 14862 | AS79: 1 | AT79: UN | AU79: 9716200 | AV79: PRESTATION DE SERVICE | AW79: C104 | AX79: 723 | AY79: 136100 | AZ79: 1 | BA79: 2026-07-28
A80: Sponsoring YAS x NAS PRODUCTION - FACTURE N°F-2026-32 | B80: 0 | C80: 60000000 | D80: 60 000 000.00 | E80: 0 | F80: 139345 | G80: 1 | I80: MECSPDC | J80: True | K80: DCG | L80: E110_AC_DCOM | M80: DCG-COM-PART | N80: NA | P80: 1 | Q80: 60 000 000.00 | R80: YASMG | T80: FELANA13 | U80: 60 000 000.00 | V80: 60 000 000.00 | W80: MGA | X80: F | Y80: 46237 | Z80: 2026-08-04 | AA80: 46237 | AB80: 0000-00-00 | AC80: SPONSORING | AD80: YASSIE | AE80: YASSIE | AF80: C100 | AG80: E110_AC_DCOM | AH80: DCG-COM-PART | AI80: STD | AL80: E | AM80: E | AN80: Felana RARIVOSON | AO80: EATIFA HOLDING SRL U | AP80: RAZAFINDRAHAGA Setra | AR80: 1267 | AS80: 1 | AT80: UN | AU80: 60000000 | AV80: SPONSORING | AW80: C100 | AX80: 7080 | AY80: 136101 | AZ80: 1 | BA80: 2026-07-30
A81: ATL RESOURCES - N°86071 #2026/05/04 | B81: 0 | C81: 55182.38 | D81: 49 664.14 | E81: -10 | F81: 139343 | G81: 1 | I81: PRICTRL | J81: False | K81: DCG | L81: E110_DG_DCOM | M81: DCG-COM | N81: NA | P81: 0 | Q81: 0.00 | R81: YASMG | T81: FELANA13 | U81: 135 766.00 | V81: 122 189.40 | W81: USD | X81: F | Y81: 46237 | Z81: 2026-08-04 | AA81: 46237 | AB81: 0000-00-00 | AC81: ATL & DIGITAL RESSOURCES | AD81: YASSIE | AE81: YASSIE | AF81: C100 | AG81: E110_DG_DCOM | AH81: DCG-COM | AI81: IMPORT | AL81: S | AM81: S | AN81: Felana RARIVOSON | AO81: Ogilvy South Africa - Johannesburg | AP81: RAZAFINDRAHAGA Setra | AR81: 11533 | AS81: 1 | AT81: PIE | AU81: 55182.38 | AV81: PRESTATION DIVERS | AW81: C100 | AX81: 7154 | AY81: 136102 | AZ81: 1 | BA81: 2026-07-30
A82: DIGITAL RESOURCES - N°86071 | B82: 0 | C82: 80583.62 | D82: 72 525.26 | E82: -10 | F82: 139343 | G82: 2 | I82: PRICTRL | J82: False | K82: DCG | L82: E110_DG_DCOM | M82: DCG-COM | N82: NA | P82: 0 | Q82: 0.00 | R82: YASMG | T82: FELANA13 | U82: 135 766.00 | V82: 122 189.40 | W82: USD | X82: F | Y82: 46237 | Z82: 2026-08-04 | AA82: 46237 | AB82: 0000-00-00 | AC82: ATL & DIGITAL RESSOURCES | AD82: YASSIE | AE82: YASSIE | AF82: C100 | AG82: E110_DG_DCOM | AH82: DCG-COM | AI82: IMPORT | AL82: S | AM82: S | AN82: Felana RARIVOSON | AO82: Ogilvy South Africa - Johannesburg | AP82: RAZAFINDRAHAGA Setra | AR82: 11533 | AS82: 1 | AT82: PIE | AU82: 80583.62 | AV82: PRESTATION DIVERS | AW82: C100 | AX82: 7154 | AY82: 136102 | AZ82: 2 | BA82: 2026-07-30
A83: Prestation intérimaire: 20 AR en Poste Fixe pour 2 mois# DEVIS N° 002877 DU 20/07/2026 | B83: 0 | C83: 14948000 | D83: 17 937 600.00 | E83: 20 | F83: 139273 | G83: 1 | I83: PRICTRL | J83: True | K83: DCG | L83: E214_DRB | M83: DRH-ADMIN | N83: NA | P83: 1 | Q83: 14 948 000.00 | R83: YASMG | T83: NADIA7 | U83: 14 948 000.00 | V83: 17 937 600.00 | W83: MGA | Y83: 46237 | Z83: 2026-08-03 | AA83: 46237 | AB83: 0000-00-00 | AD83: YASSIE | AE83: YASSIE | AF83: C102 | AG83: E214_DRB | AH83: DRH-ADMIN | AI83: STD | AL83: E | AM83: E | AN83: RAVONINJATOVO Nadia | AO83: MADAJOB | AP83: ANDRIANINA Rebecca | AR83: 14862 | AS83: 1 | AT83: UN | AU83: 14948000 | AV83: PRESTATION DE SERVICE | AW83: C102 | AX83: 723 | AY83: 136103 | AZ83: 1 | BA83: 2026-07-28
A84: Prestation intérimaire: 02 Tech Superv Filaire pour 2 mois# DEVIS N°3915 DU 03/07/2026 | B84: 0 | C84: 1248400 | D84: 1 498 080.00 | E84: 20 | F84: 139267 | G84: 1 | I84: PRICTRL | J84: True | K84: DTG | L84: E214_DTG | M84: DRH-ADMIN | N84: NA | P84: 1 | Q84: 1 248 400.00 | R84: YASMG | T84: NADIA7 | U84: 1 248 400.00 | V84: 1 498 080.00 | W84: MGA | Y84: 46237 | Z84: 2026-08-03 | AA84: 46237 | AB84: 0000-00-00 | AD84: YASSIE | AE84: YASSIE | AF84: C500 | AG84: E214_DTG | AH84: DRH-ADMIN | AI84: STD | AL84: E | AM84: E | AN84: RAVONINJATOVO Nadia | AO84: MADAJOB | AP84: ANDRIANINA Rebecca | AR84: 14862 | AS84: 1 | AT84: UN | AU84: 1248400 | AV84: PRESTATION DE SERVICE | AW84: C500 | AX84: 723 | AY84: 136104 | AZ84: 1 | BA84: 2026-07-28
A85: Prestation intérimaire: 44 AR en Kioska pour 2 mois# DEVIS N° 002876 DU 20/07/2026 | B85: 0 | C85: 32885600 | D85: 39 462 720.00 | E85: 20 | F85: 139271 | G85: 1 | I85: PRICTRL | J85: True | K85: DCG | L85: E214_DRB | M85: DRH-ADMIN | N85: NA | P85: 1 | Q85: 32 885 600.00 | R85: YASMG | T85: NADIA7 | U85: 32 885 600.00 | V85: 39 462 720.00 | W85: MGA | Y85: 46237 | Z85: 2026-08-04 | AA85: 46237 | AB85: 0000-00-00 | AD85: YASSIE | AE85: YASSIE | AF85: C102 | AG85: E214_DRB | AH85: DRH-ADMIN | AI85: STD | AL85: E | AM85: E | AN85: RAVONINJATOVO Nadia | AO85: MADAJOB | AP85: ANDRIANINA Rebecca | AR85: 14862 | AS85: 1 | AT85: UN | AU85: 32885600 | AV85: PRESTATION DE SERVICE | AW85: C102 | AX85: 723 | AY85: 136105 | AZ85: 1 | BA85: 2026-07-28
A86: Prestation intérimaire: 19 AR en Shop pour 2 mois# DEVIS N° 002875 DU 20/07/2026 | B86: 0 | C86: 14200600 | D86: 17 040 720.00 | E86: 20 | F86: 139270 | G86: 1 | I86: PRICTRL | J86: True | K86: DCG | L86: E214_DRB | M86: DRH-ADMIN | N86: NA | P86: 1 | Q86: 14 200 600.00 | R86: YASMG | T86: NADIA7 | U86: 14 200 600.00 | V86: 17 040 720.00 | W86: MGA | Y86: 46237 | Z86: 2026-08-03 | AA86: 46237 | AB86: 0000-00-00 | AD86: YASSIE | AE86: YASSIE | AF86: C102 | AG86: E214_DRB | AH86: DRH-ADMIN | AI86: STD | AL86: E | AM86: E | AN86: RAVONINJATOVO Nadia | AO86: MADAJOB | AP86: ANDRIANINA Rebecca | AR86: 14862 | AS86: 1 | AT86: UN | AU86: 14200600 | AV86: PRESTATION DE SERVICE | AW86: C102 | AX86: 723 | AY86: 136106 | AZ86: 1 | BA86: 2026-07-28
A87: IM- Un (07) VAD - TAMATAVE -STE MARIE -TAMATAVE du 10/07 au 20/07/2026 - suivant proforma N°331-A/FP/TELMA/2026 | B87: 0 | C87: 6230000 | D87: 6 230 000.00 | E87: 0 | F87: 139341 | G87: 1 | I87: PRICTRL | J87: True | K87: DCG | L87: E214_DCG | M87: DCG-DRB | N87: NA | P87: 1 | Q87: 6 230 000.00 | R87: YASMG | T87: FELANA13 | U87: 6 230 000.00 | V87: 6 230 000.00 | W87: MGA | X87: F | Y87: 46237 | Z87: 2026-08-03 | AA87: 46237 | AB87: 0000-00-00 | AC87: IM VAD JUILLET 2026 | AD87: YASSIE | AE87: YASSIE | AF87: C102 | AG87: E214_DCG | AH87: DCG-DRB | AI87: STD | AL87: E | AM87: E | AN87: Felana RARIVOSON | AO87: LCS CONSULTING | AP87: RAZAFINDRAHAGA Setra | AR87: 21266 | AS87: 1 | AT87: UN | AU87: 6230000 | AV87: INDEMNITE | AW87: C102 | AX87: 2490 | AY87: 136107 | AZ87: 1 | BA87: 2026-07-30
A88: JBL PORTABLE PARTY SPEAKER JBLPBSTAGE320UK - suivant proforma N°SQ26-0005528 | B88: 0 | C88: 87085961 | D88: 104 503 153.72 | E88: 20 | F88: 139314 | G88: 1 | I88: EEEELEC | J88: True | K88: DCG | L88: 2026-CO-000001 | M88: DCG-SHS | N88: NA | P88: 38 | Q88: 87 085 961.43 | R88: YASMG | T88: FELANA13 | U88: 115 585 960.97 | V88: 138 703 153.16 | W88: MGA | Y88: 46237 | Z88: 2026-08-03 | AA88: 46237 | AB88: 0000-00-00 | AC88: SONO | AD88: YASSIE | AE88: GALE | AF88: C100 | AG88: 2026-CO-000001 | AH88: DCG-SHS | AI88: STD | AL88: E | AM88: E | AN88: Felana RARIVOSON | AO88: UNITE DE DISTRIBUTION TECHNOLOGIQUE - UDITEC | AP88: RAZAFINDRAHAGA Setra | AR88: 23072 | AS88: 38 | AT88: UN | AU88: 2291735.8 | AV88: JBL PORTABLE PARTY SPEAKER JBLPBSTAGE320UK | AW88: C100 | AX88: 717 | AY88: 136108 | AZ88: 1 | BA88: 2026-07-29
A89: PLATINUM MIC B20 WIRELESS PKPWM200 - suivant proforma N°SQ26-0005528 | B89: 0 | C89: 28500000 | D89: 34 199 999.44 | E89: 20 | F89: 139314 | G89: 2 | I89: TCORADI | J89: True | K89: DCG | L89: 2026-CO-000001 | M89: DCG-SHS | N89: NA | P89: 76 | Q89: 28 499 999.54 | R89: YASMG | T89: FELANA13 | U89: 115 585 960.97 | V89: 138 703 153.16 | W89: MGA | Y89: 46237 | Z89: 2026-08-03 | AA89: 46237 | AB89: 0000-00-00 | AC89: SONO | AD89: YASSIE | AE89: GALE | AF89: C100 | AG89: 2026-CO-000001 | AH89: DCG-SHS | AI89: STD | AL89: E | AM89: E | AN89: Felana RARIVOSON | AO89: UNITE DE DISTRIBUTION TECHNOLOGIQUE - UDITEC | AP89: RAZAFINDRAHAGA Setra | AR89: 17182 | AS89: 76 | AT89: UN | AU89: 374999.99 | AV89: JBL MICROPHONE JBLWIRELESSMIC | AW89: C100 | AX89: 717 | AY89: 136108 | AZ89: 2 | BA89: 2026-07-29
A90: Prestation intérimaire: 01 Tech Testeur Service Perf pour 2 mois# DEVIS N°3916 DU 03/07/2026 | B90: 0 | C90: 1504400 | D90: 1 805 280.00 | E90: 20 | F90: 139268 | G90: 1 | I90: PRICTRL | J90: True | K90: DTG | L90: E214_DTG | M90: DRH-ADMIN | N90: NA | P90: 1 | Q90: 1 504 400.00 | R90: YASMG | T90: NADIA7 | U90: 1 504 400.00 | V90: 1 805 280.00 | W90: MGA | X90: F | Y90: 46237 | Z90: 2026-08-03 | AA90: 46237 | AB90: 0000-00-00 | AD90: YASSIE | AE90: YASSIE | AF90: C500 | AG90: E214_DTG | AH90: DRH-ADMIN | AI90: STD | AL90: E | AM90: E | AN90: RAVONINJATOVO Nadia | AO90: MADAJOB | AP90: ANDRIANINA Rebecca | AR90: 14862 | AS90: 1 | AT90: UN | AU90: 1504400 | AV90: PRESTATION DE SERVICE | AW90: C500 | AX90: 723 | AY90: 136109 | AZ90: 1 | BA90: 2026-07-28
A91: Prestation intérimaire: 01 Support BI pour 2 mois# DEVIS N°3913 DU 03/07/2026 | B91: 0 | C91: 1566350 | D91: 1 879 620.00 | E91: 20 | F91: 139265 | G91: 1 | I91: PRICTRL | J91: True | K91: DFG | L91: E214_DAF | M91: DRH-ADMIN | N91: NA | P91: 1 | Q91: 1 566 350.00 | R91: YASMG | T91: NADIA7 | U91: 1 566 350.00 | V91: 1 879 620.00 | W91: MGA | Y91: 46237 | Z91: 2026-08-03 | AA91: 46237 | AB91: 0000-00-00 | AD91: YASSIE | AE91: YASSIE | AF91: C700 | AG91: E214_DAF | AH91: DRH-ADMIN | AI91: STD | AL91: E | AM91: E | AN91: RAVONINJATOVO Nadia | AO91: MADAJOB | AP91: ANDRIANINA Rebecca | AR91: 14862 | AS91: 1 | AT91: UN | AU91: 1566350 | AV91: PRESTATION DE SERVICE | AW91: C700 | AX91: 723 | AY91: 136110 | AZ91: 1 | BA91: 2026-07-28
A92: Prestation intérimaire: 01 PHD pour 2 mois# DEVIS N°3912 DU 03/07/2026 | B92: 0 | C92: 1628300 | D92: 1 953 960.00 | E92: 20 | F92: 139264 | G92: 1 | I92: PRICTRL | J92: True | K92: DFG | L92: E214_DAF | M92: DRH-ADMIN | N92: NA | P92: 1 | Q92: 1 628 300.00 | R92: YASMG | T92: NADIA7 | U92: 1 628 300.00 | V92: 1 953 960.00 | W92: MGA | X92: F | Y92: 46237 | Z92: 2026-08-03 | AA92: 46237 | AB92: 0000-00-00 | AD92: YASSIE | AE92: YASSIE | AF92: C700 | AG92: E214_DAF | AH92: DRH-ADMIN | AI92: STD | AL92: E | AM92: E | AN92: RAVONINJATOVO Nadia | AO92: MADAJOB | AP92: ANDRIANINA Rebecca | AR92: 14862 | AS92: 1 | AT92: UN | AU92: 1628300 | AV92: PRESTATION DE SERVICE | AW92: C700 | AX92: 723 | AY92: 136111 | AZ92: 1 | BA92: 2026-07-28
A93: Prestation intérimaire: 01 Gest de Stock Xts vendables TITAN3 pour 2 mois# DEVIS N°3910 DU 03/07/2026 | B93: 0 | C93: 1504400 | D93: 1 805 280.00 | E93: 20 | F93: 139262 | G93: 1 | I93: PRICTRL | J93: True | K93: DFG | L93: E214_DAF | M93: DRH-ADMIN | N93: NA | P93: 1 | Q93: 1 504 400.00 | R93: YASMG | T93: NADIA7 | U93: 1 504 400.00 | V93: 1 805 280.00 | W93: MGA | X93: F | Y93: 46237 | Z93: 2026-08-03 | AA93: 46237 | AB93: 0000-00-00 | AD93: YASSIE | AE93: YASSIE | AF93: C700 | AG93: E214_DAF | AH93: DRH-ADMIN | AI93: STD | AL93: E | AM93: E | AN93: RAVONINJATOVO Nadia | AO93: MADAJOB | AP93: ANDRIANINA Rebecca | AR93: 14862 | AS93: 1 | AT93: UN | AU93: 1504400 | AV93: PRESTATION DE SERVICE | AW93: C700 | AX93: 723 | AY93: 136112 | AZ93: 1 | BA93: 2026-07-28
A94: Prestation intérimaire: 02 Juriste pour 2 mois# DEVIS N° 3911 DU 03/07/2026 | B94: 0 | C94: 4000000 | D94: 4 800 000.00 | E94: 20 | F94: 139263 | G94: 1 | I94: PRICTRL | J94: True | K94: DG | L94: E214_DJU | M94: DRH-ADMIN | N94: NA | P94: 1 | Q94: 4 000 000.00 | R94: YASMG | T94: NADIA7 | U94: 4 000 000.00 | V94: 4 800 000.00 | W94: MGA | Y94: 46237 | Z94: 2026-08-03 | AA94: 46237 | AB94: 0000-00-00 | AD94: YASSIE | AE94: YASSIE | AF94: C400 | AG94: E214_DJU | AH94: DRH-ADMIN | AI94: STD | AL94: E | AM94: E | AN94: RAVONINJATOVO Nadia | AO94: MADAJOB | AP94: ANDRIANINA Rebecca | AR94: 14862 | AS94: 1 | AT94: UN | AU94: 4000000 | AV94: PRESTATION DE SERVICE | AW94: C400 | AX94: 723 | AY94: 136113 | AZ94: 1 | BA94: 2026-07-28
A95: Prestation intérimaire: 01 Gest de Stock Xts vendables pour 2 mois# DEVIS N° 3909 DU 03/07/2026 | B95: 0 | C95: 1439972 | D95: 1 727 966.40 | E95: 20 | F95: 139261 | G95: 1 | I95: PRICTRL | J95: True | K95: DFG | L95: E214_DAF | M95: DRH-ADMIN | N95: NA | P95: 1 | Q95: 1 439 972.00 | R95: YASMG | T95: NADIA7 | U95: 1 439 972.00 | V95: 1 727 966.40 | W95: MGA | Y95: 46237 | Z95: 2026-08-03 | AA95: 46237 | AB95: 0000-00-00 | AD95: YASSIE | AE95: YASSIE | AF95: C700 | AG95: E214_DAF | AH95: DRH-ADMIN | AI95: STD | AL95: E | AM95: E | AN95: RAVONINJATOVO Nadia | AO95: MADAJOB | AP95: ANDRIANINA Rebecca | AR95: 14862 | AS95: 1 | AT95: UN | AU95: 1439972 | AV95: PRESTATION DE SERVICE | AW95: C700 | AX95: 723 | AY95: 136114 | AZ95: 1 | BA95: 2026-07-28
A96: Prestation intérimaire: 01 Chargé QVT/DEI pour 2 mois# DEVIS N° 3906 DU 03/07/2026 | B96: 0 | C96: 1628300 | D96: 1 953 960.00 | E96: 20 | F96: 139258 | G96: 1 | I96: PRICTRL | J96: True | K96: DRH | L96: E214_DRH | M96: DRH-ADMIN | N96: NA | P96: 1 | Q96: 1 628 300.00 | R96: YASMG | T96: NADIA7 | U96: 1 628 300.00 | V96: 1 953 960.00 | W96: MGA | Y96: 46237 | Z96: 2026-08-03 | AA96: 46237 | AB96: 0000-00-00 | AD96: YASSIE | AE96: YASSIE | AF96: C600 | AG96: E214_DRH | AH96: DRH-ADMIN | AI96: STD | AL96: E | AM96: E | AN96: RAVONINJATOVO Nadia | AO96: MADAJOB | AP96: ANDRIANINA Rebecca | AR96: 14862 | AS96: 1 | AT96: UN | AU96: 1628300 | AV96: PRESTATION DE SERVICE | AW96: C600 | AX96: 723 | AY96: 136115 | AZ96: 1 | BA96: 2026-07-28
A97: Prestation intérimaire: 10 Coordinateur Sales Outsourcing Tanà et Région pour 2 mois# DEVIS N° 3908 DU 03/07/2026 | B97: 0 | C97: 13310000 | D97: 15 972 000.00 | E97: 20 | F97: 139260 | G97: 1 | I97: PRICTRL | J97: True | K97: DCG | L97: E214_DRB | M97: DRH-ADMIN | N97: NA | P97: 1 | Q97: 13 310 000.00 | R97: YASMG | T97: NADIA7 | U97: 13 310 000.00 | V97: 15 972 000.00 | W97: MGA | Y97: 46237 | Z97: 2026-08-03 | AA97: 46237 | AB97: 0000-00-00 | AD97: YASSIE | AE97: YASSIE | AF97: C102 | AG97: E214_DRB | AH97: DRH-ADMIN | AI97: STD | AL97: E | AM97: E | AN97: RAVONINJATOVO Nadia | AO97: MADAJOB | AP97: ANDRIANINA Rebecca | AR97: 14862 | AS97: 1 | AT97: UN | AU97: 13310000 | AV97: PRESTATION DE SERVICE | AW97: C102 | AX97: 723 | AY97: 136116 | AZ97: 1 | BA97: 2026-07-28
A98: Prestation intérimaire: 01 Comptable pour 2 mois# DEVIS N° 3907 DU 03/07/2026 | B98: 0 | C98: 1504400 | D98: 1 805 280.00 | E98: 20 | F98: 139259 | G98: 1 | I98: PRICTRL | J98: True | K98: DFG | L98: E214_DAF | M98: DRH-ADMIN | N98: NA | P98: 1 | Q98: 1 504 400.00 | R98: YASMG | T98: NADIA7 | U98: 1 504 400.00 | V98: 1 805 280.00 | W98: MGA | Y98: 46237 | Z98: 2026-08-03 | AA98: 46237 | AB98: 0000-00-00 | AD98: YASSIE | AE98: YASSIE | AF98: C700 | AG98: E214_DAF | AH98: DRH-ADMIN | AI98: STD | AL98: E | AM98: E | AN98: RAVONINJATOVO Nadia | AO98: MADAJOB | AP98: ANDRIANINA Rebecca | AR98: 14862 | AS98: 1 | AT98: UN | AU98: 1504400 | AV98: PRESTATION DE SERVICE | AW98: C700 | AX98: 723 | AY98: 136117 | AZ98: 1 | BA98: 2026-07-28
A99: Prestation intérimaire: 01 Gestionnaire Recouvrement pour 2 mois# DEVIS N° 3905 DU 03/07/2026 | B99: 0 | C99: 1439972 | D99: 1 727 966.40 | E99: 20 | F99: 139257 | G99: 1 | I99: PRICTRL | J99: True | K99: DFG | L99: E214_DAF | M99: DRH-ADMIN | N99: NA | P99: 1 | Q99: 1 439 972.00 | R99: YASMG | T99: NADIA7 | U99: 1 439 972.00 | V99: 1 727 966.40 | W99: MGA | Y99: 46237 | Z99: 2026-08-03 | AA99: 46237 | AB99: 0000-00-00 | AD99: YASSIE | AE99: YASSIE | AF99: C700 | AG99: E214_DAF | AH99: DRH-ADMIN | AI99: STD | AL99: E | AM99: E | AN99: RAVONINJATOVO Nadia | AO99: MADAJOB | AP99: ANDRIANINA Rebecca | AR99: 14862 | AS99: 1 | AT99: UN | AU99: 1439972 | AV99: PRESTATION DE SERVICE | AW99: C700 | AX99: 723 | AY99: 136118 | AZ99: 1 | BA99: 2026-07-28
A100: Prestation intérimaire: 01 BO Admin et Orga pour 2 mois# DEVIS N° 3904 DU 03/07/2026 | B100: 0 | C100: 1566350 | D100: 1 879 620.00 | E100: 20 | F100: 139256 | G100: 1 | I100: PRICTRL | J100: True | K100: DFG | L100: E214_DAF | M100: DRH-ADMIN | N100: NA | P100: 1 | Q100: 1 566 350.00 | R100: YASMG | T100: NADIA7 | U100: 1 566 350.00 | V100: 1 879 620.00 | W100: MGA | Y100: 46237 | Z100: 2026-08-03 | AA100: 46237 | AB100: 0000-00-00 | AD100: YASSIE | AE100: YASSIE | AF100: C700 | AG100: E214_DAF | AH100: DRH-ADMIN | AI100: STD | AL100: E | AM100: E | AN100: RAVONINJATOVO Nadia | AO100: MADAJOB | AP100: ANDRIANINA Rebecca | AR100: 14862 | AS100: 1 | AT100: UN | AU100: 1566350 | AV100: PRESTATION DE SERVICE | AW100: C700 | AX100: 723 | AY100: 136119 | AZ100: 1 | BA100: 2026-07-28
A101: Prestation intérimaire: 01 Assistants RH pour 2 mois# DEVIS N° 3903 DU 03/07/2026 | B101: 0 | C101: 1628300 | D101: 1 953 960.00 | E101: 20 | F101: 139255 | G101: 1 | I101: PRICTRL | J101: True | K101: DRH | L101: E214_DRH | M101: DRH-ADMIN | N101: NA | P101: 1 | Q101: 1 628 300.00 | R101: YASMG | T101: NADIA7 | U101: 1 628 300.00 | V101: 1 953 960.00 | W101: MGA | X101: F | Y101: 46237 | Z101: 2026-08-03 | AA101: 46237 | AB101: 0000-00-00 | AD101: YASSIE | AE101: YASSIE | AF101: C600 | AG101: E214_DRH | AH101: DRH-ADMIN | AI101: STD | AL101: E | AM101: E | AN101: RAVONINJATOVO Nadia | AO101: MADAJOB | AP101: ANDRIANINA Rebecca | AR101: 14862 | AS101: 1 | AT101: UN | AU101: 1628300 | AV101: PRESTATION DE SERVICE | AW101: C600 | AX101: 723 | AY101: 136120 | AZ101: 1 | BA101: 2026-07-28
A102: CABLE 5to12V - suivant devis N°V/26/15226 | B102: 0 | C102: 13650000 | D102: 16 380 000.00 | E102: 20 | F102: 139252 | G102: 1 | I102: FRNPAPF | J102: True | K102: DCG | L102: CM_MBL_DCG | M102: DCG-SHS | N102: NA | P102: 525 | Q102: 13 650 000.00 | R102: YASMG | T102: FELANA13 | U102: 13 650 000.00 | V102: 16 380 000.00 | W102: MGA | X102: F | Y102: 46237 | Z102: 2026-08-03 | AA102: 46237 | AB102: 0000-00-00 | AC102: CABLE | AD102: YASSIE | AE102: GALE | AF102: C100 | AG102: CM_MBL_DCG | AH102: DCG-SHS | AI102: STD | AL102: E | AM102: E | AN102: Felana RARIVOSON | AO102: PRICE | AP102: RAZAFINDRAHAGA Setra | AR102: 10011 | AS102: 525 | AT102: PIE | AU102: 26000 | AV102: FLAT CABLE | AW102: C100 | AX102: 2632 | AY102: 136121 | AZ102: 1 | BA102: 2026-07-28
A103: INSTALLATION BORNE TICKETING - YAS STORE AMBATOBE LP - AMBATOBE 1 - AMBOHIPO - AMPASAMPITO - ITAOSY - TSARALALANA - DEVIS n° MNJ2605-072 | B103: 0 | C103: 1950000 | D103: 1 950 000.00 | E103: 0 | F103: 139214 | G103: 1 | I103: PRICTRL | J103: True | K103: DCG | L103: E250_DRB | M103: DCG-DRB | N103: NA | P103: 1 | Q103: 1 950 000.00 | R103: YASMG | T103: FELANA13 | U103: 6 450 000.00 | V103: 6 450 000.00 | W103: MGA | Y103: 46237 | Z103: 2026-08-03 | AA103: 46237 | AB103: 0000-00-00 | AC103: INSTALLATION BORNE TICKETING TANA & EST & MAJUNGA | AD103: YASSIE | AE103: YASSIE | AF103: C102 | AG103: E250_DRB | AH103: DCG-DRB | AI103: STD | AL103: E | AM103: E | AN103: Felana RARIVOSON | AO103: MANAJ SARL | AP103: RAZAFINDRAHAGA Setra | AR103: 14862 | AS103: 1 | AT103: UN | AU103: 1950000 | AV103: PRESTATION DE SERVICE | AW103: C102 | AX103: 2536 | AY103: 136122 | AZ103: 1 | BA103: 2026-07-23
A104: INSTALLATION BORNE TICKETING - YAS STORE FENERIVE EST - TAMATAVE : AVENUE - STREAMLINER - JOFFRE - GARE | B104: 0 | C104: 2200000 | D104: 2 200 000.00 | E104: 0 | F104: 139214 | G104: 2 | I104: PRICTRL | J104: True | K104: DCG | L104: E250_DRB | M104: DCG-DRB | N104: NA | P104: 1 | Q104: 2 200 000.00 | R104: YASMG | T104: FELANA13 | U104: 6 450 000.00 | V104: 6 450 000.00 | W104: MGA | Y104: 46237 | Z104: 2026-08-03 | AA104: 46237 | AB104: 0000-00-00 | AC104: INSTALLATION BORNE TICKETING TANA & EST & MAJUNGA | AD104: YASSIE | AE104: YASSIE | AF104: C102 | AG104: E250_DRB | AH104: DCG-DRB | AI104: STD | AL104: E | AM104: E | AN104: Felana RARIVOSON | AO104: MANAJ SARL | AP104: RAZAFINDRAHAGA Setra | AR104: 14862 | AS104: 1 | AT104: UN | AU104: 2200000 | AV104: PRESTATION DE SERVICE | AW104: C102 | AX104: 2536 | AY104: 136122 | AZ104: 2 | BA104: 2026-07-23
A105: INSTALLATION BORNE TICKETING - YAS STORE MAJUNGA CATHEDRALE - WELLO - AMPASIKA - ANTANIMASAJA - BAOBAB CITY - AKASYA | B105: 0 | C105: 2300000 | D105: 2 300 000.00 | E105: 0 | F105: 139214 | G105: 3 | I105: PRICTRL | J105: True | K105: DCG | L105: E250_DRB | M105: DCG-DRB | N105: NA | P105: 1 | Q105: 2 300 000.00 | R105: YASMG | T105: FELANA13 | U105: 6 450 000.00 | V105: 6 450 000.00 | W105: MGA | Y105: 46237 | Z105: 2026-08-03 | AA105: 46237 | AB105: 0000-00-00 | AC105: INSTALLATION BORNE TICKETING TANA & EST & MAJUNGA | AD105: YASSIE | AE105: YASSIE | AF105: C102 | AG105: E250_DRB | AH105: DCG-DRB | AI105: STD | AL105: E | AM105: E | AN105: Felana RARIVOSON | AO105: MANAJ SARL | AP105: RAZAFINDRAHAGA Setra | AR105: 14862 | AS105: 1 | AT105: UN | AU105: 2300000 | AV105: PRESTATION DE SERVICE | AW105: C102 | AX105: 2536 | AY105: 136122 | AZ105: 3 | BA105: 2026-07-23
A106: Prestation intérimaire: 02 Agent de mis sous pli pour 2 mois# devis N° 3902 du 03/07/2026 | B106: 0 | C106: 122400.12 | D106: 146 880.14 | E106: 20 | F106: 139254 | G106: 1 | I106: PRICTRL | J106: True | K106: DSI | L106: E214_DSI | M106: DRH-ADMIN | N106: NA | P106: 1 | Q106: 122 400.12 | R106: YASMG | T106: NADIA7 | U106: 122 400.12 | V106: 146 880.14 | W106: MGA | Y106: 46237 | Z106: 2026-08-03 | AA106: 46237 | AB106: 0000-00-00 | AD106: YASSIE | AE106: YASSIE | AF106: C800 | AG106: E214_DSI | AH106: DRH-ADMIN | AI106: STD | AL106: E | AM106: E | AN106: RAVONINJATOVO Nadia | AO106: MADAJOB | AP106: ANDRIANINA Rebecca | AR106: 14862 | AS106: 1 | AT106: UN | AU106: 122400.12 | AV106: PRESTATION DE SERVICE | AW106: C800 | AX106: 723 | AY106: 136123 | AZ106: 1 | BA106: 2026-07-28
A107: Prestation intérimaire: 08 ADV Tanà et Région pour 2 mois# DEVIS N° 3901 DU 03/07/2026 | B107: 0 | C107: 6707900 | D107: 8 049 480.00 | E107: 20 | F107: 139253 | G107: 1 | I107: PRICTRL | J107: True | K107: DFG | L107: E214_DAF | M107: DRH-ADMIN | N107: NA | P107: 1 | Q107: 6 707 900.00 | R107: YASMG | T107: NADIA7 | U107: 6 707 900.00 | V107: 8 049 480.00 | W107: MGA | Y107: 46237 | Z107: 2026-08-03 | AA107: 46237 | AB107: 0000-00-00 | AD107: YASSIE | AE107: YASSIE | AF107: C700 | AG107: E214_DAF | AH107: DRH-ADMIN | AI107: STD | AL107: E | AM107: E | AN107: RAVONINJATOVO Nadia | AO107: MADAJOB | AP107: ANDRIANINA Rebecca | AR107: 14862 | AS107: 1 | AT107: UN | AU107: 6707900 | AV107: PRESTATION DE SERVICE | AW107: C700 | AX107: 723 | AY107: 136124 | AZ107: 1 | BA107: 2026-07-28
...

Sheet Base Traitement
A1: N__de_Cde | B1: Raison_sociale_Fournisseur | C1: Design__sommaire | D1: Designation_Complémentaire | E1: Quantité_comm | F1: Unité | G1: Prix_Unitaire | H1: PU USD | I1: Total HT | J1: Total HT USD | K1: Devise | L1: Remise | M1: Date_creat | N1: Date_de_Validation | O1: N__DA | P1: Date_creat | Q1: Date_de_Validation | R1: V_Total_Ligne_TTC | S1: TVA | T1: N__Poste_DA | U1: Site_Stock | V1: Code_ss_famille | W1: Saisie_de_réception__ | X1: Code_Direction | Y1: Code_complément | Z1: SS_compte_anal | AA1: Centre_d_Analyse | AB1: Accord_Cadre | AC1: RAL | AD1: V_Montant_RAL | AE1: Code_Société | AF1: Avenant | AG1: Acheteur | AH1: Tot_CA_HT | AI1: Tot_CA_TTC | AJ1: Etat_Financ_ | AK1: Date_Période | AL1: Date_AR | AM1: Objet_CA | AN1: Ctr_Emetteur_entete | AO1: Ctr_Livraison_entete | AP1: Sect_Imputation_entete | AQ1: Code_Complémentaire_entete | AR1: Sous_Compte_d_Analyse_entete | AS1: Type_document | AT1: V_Expédition_soldée | AU1: Code_du_Modèle_de_Cde | AV1: V_Etat_commande_en_tête | AW1: V_Etat_commande_ligne | AX1: Nom_Acheteur | AY1: Nom_demandeur | AZ1: V_Critère_de_saisie | BA1: Code_Article | BB1: Section_d_imput | BC1: Code_Fournis | BD1: N_Poste | BE1: Date_de_livr__prev_
A2: 136058 | B2: RTV RECORD | C2: PUBLICITE ET ANNONCE | D2: SPOT - RECORD TV - suivant Facture N°TV000000282 | E2: 1 | F2: UN | G2: 549120 | I2: =E2*G2 -> 549120 | K2: MGA | L2: 0 | M2: 46237 | N2: 2026-08-03 | O2: 139303 | R2: 658 944.00 | S2: 20 | T2: 1 | V2: MEDMEDI | W2: True | X2: DCG | Y2: E110_MD_DCOM | Z2: DCG-COM-MEDIA | AA2: NA | AC2: 1 | AD2: 549 120.00 | AE2: YASMG | AG2: FELANA13 | AH2: 3 926 784.00 | AI2: 4 712 140.80 | AJ2: F | AK2: 46237 | AL2: 0000-00-00 | AM2: SPOT - RECORD TV | AN2: YASSIE | AO2: YASSIE | AP2: C100 | AQ2: E110_MD_DCOM | AR2: DCG-COM-MEDIA | AS2: STD | AV2: E | AW2: E | AX2: Felana RARIVOSON | AY2: RAZAFINDRAHAGA Setra | BA2: 1265 | BB2: C100 | BC2: 973 | BD2: 1 | BE2: 2026-07-29
A3: 136058 | B3: RTV RECORD | C3: PUBLICITE ET ANNONCE | D3: SPOT - RECORD TV - suivant Facture N°RD000000250 | E3: 1 | F3: UN | G3: 403200 | I3: =E3*G3 -> 403200 | K3: MGA | L3: 0 | M3: 46237 | N3: 2026-08-03 | O3: 139303 | R3: 483 840.00 | S3: 20 | T3: 2 | V3: MEDMEDI | W3: True | X3: DCG | Y3: E110_MD_DCOM | Z3: DCG-COM-MEDIA | AA3: NA | AC3: 1 | AD3: 403 200.00 | AE3: YASMG | AG3: FELANA13 | AH3: 3 926 784.00 | AI3: 4 712 140.80 | AJ3: F | AK3: 46237 | AL3: 0000-00-00 | AM3: SPOT - RECORD TV | AN3: YASSIE | AO3: YASSIE | AP3: C100 | AQ3: E110_MD_DCOM | AR3: DCG-COM-MEDIA | AS3: STD | AV3: E | AW3: E | AX3: Felana RARIVOSON | AY3: RAZAFINDRAHAGA Setra | BA3: 1265 | BB3: C100 | BC3: 973 | BD3: 2 | BE3: 2026-07-29
A4: 136058 | B4: RTV RECORD | C4: PUBLICITE ET ANNONCE | D4: SPOT - RECORD TV - suivant Facture N°RD000000270 | E4: 1 | F4: UN | G4: 82944 | I4: =E4*G4 -> 82944 | K4: MGA | L4: 0 | M4: 46237 | N4: 2026-08-03 | O4: 139303 | R4: 99 532.80 | S4: 20 | T4: 3 | V4: MEDMEDI | W4: True | X4: DCG | Y4: E110_MD_DCOM | Z4: DCG-COM-MEDIA | AA4: NA | AC4: 1 | AD4: 82 944.00 | AE4: YASMG | AG4: FELANA13 | AH4: 3 926 784.00 | AI4: 4 712 140.80 | AJ4: F | AK4: 46237 | AL4: 0000-00-00 | AM4: SPOT - RECORD TV | AN4: YASSIE | AO4: YASSIE | AP4: C100 | AQ4: E110_MD_DCOM | AR4: DCG-COM-MEDIA | AS4: STD | AV4: E | AW4: E | AX4: Felana RARIVOSON | AY4: RAZAFINDRAHAGA Setra | BA4: 1265 | BB4: C100 | BC4: 973 | BD4: 3 | BE4: 2026-07-29
A5: 136058 | B5: RTV RECORD | C5: PUBLICITE ET ANNONCE | D5: SPOT - RECORD TV - suivant Facture N°RD000000280 | E5: 1 | F5: UN | G5: 403200 | I5: =E5*G5 -> 403200 | K5: MGA | L5: 0 | M5: 46237 | N5: 2026-08-03 | O5: 139303 | R5: 483 840.00 | S5: 20 | T5: 4 | V5: MEDMEDI | W5: True | X5: DCG | Y5: E110_MD_DCOM | Z5: DCG-COM-MEDIA | AA5: NA | AC5: 1 | AD5: 403 200.00 | AE5: YASMG | AG5: FELANA13 | AH5: 3 926 784.00 | AI5: 4 712 140.80 | AJ5: F | AK5: 46237 | AL5: 0000-00-00 | AM5: SPOT - RECORD TV | AN5: YASSIE | AO5: YASSIE | AP5: C100 | AQ5: E110_MD_DCOM | AR5: DCG-COM-MEDIA | AS5: STD | AV5: E | AW5: E | AX5: Felana RARIVOSON | AY5: RAZAFINDRAHAGA Setra | BA5: 1265 | BB5: C100 | BC5: 973 | BD5: 4 | BE5: 2026-07-29
A6: 136058 | B6: RTV RECORD | C6: PUBLICITE ET ANNONCE | D6: SPOT - RECORD TV - suivant Facture N°RD000000296 | E6: 1 | F6: UN | G6: 829440 | I6: =E6*G6 -> 829440 | K6: MGA | L6: 0 | M6: 46237 | N6: 2026-08-03 | O6: 139303 | R6: 995 328.00 | S6: 20 | T6: 5 | V6: MEDMEDI | W6: True | X6: DCG | Y6: E110_MD_DCOM | Z6: DCG-COM-MEDIA | AA6: NA | AC6: 1 | AD6: 829 440.00 | AE6: YASMG | AG6: FELANA13 | AH6: 3 926 784.00 | AI6: 4 712 140.80 | AJ6: F | AK6: 46237 | AL6: 0000-00-00 | AM6: SPOT - RECORD TV | AN6: YASSIE | AO6: YASSIE | AP6: C100 | AQ6: E110_MD_DCOM | AR6: DCG-COM-MEDIA | AS6: STD | AV6: E | AW6: E | AX6: Felana RARIVOSON | AY6: RAZAFINDRAHAGA Setra | BA6: 1265 | BB6: C100 | BC6: 973 | BD6: 5 | BE6: 2026-07-29
A7: 136058 | B7: RTV RECORD | C7: PUBLICITE ET ANNONCE | D7: SPOT - RECORD TV - suivant Facture N°RD000000297 | E7: 1 | F7: UN | G7: 829440 | I7: =E7*G7 -> 829440 | K7: MGA | L7: 0 | M7: 46237 | N7: 2026-08-03 | O7: 139303 | R7: 995 328.00 | S7: 20 | T7: 6 | V7: MEDMEDI | W7: True | X7: DCG | Y7: E110_MD_DCOM | Z7: DCG-COM-MEDIA | AA7: NA | AC7: 1 | AD7: 829 440.00 | AE7: YASMG | AG7: FELANA13 | AH7: 3 926 784.00 | AI7: 4 712 140.80 | AJ7: F | AK7: 46237 | AL7: 0000-00-00 | AM7: SPOT - RECORD TV | AN7: YASSIE | AO7: YASSIE | AP7: C100 | AQ7: E110_MD_DCOM | AR7: DCG-COM-MEDIA | AS7: STD | AV7: E | AW7: E | AX7: Felana RARIVOSON | AY7: RAZAFINDRAHAGA Setra | BA7: 1265 | BB7: C100 | BC7: 973 | BD7: 6 | BE7: 2026-07-29
A8: 136058 | B8: RTV RECORD | C8: PUBLICITE ET ANNONCE | D8: SPOT - RECORD TV - suivant Facture N°RD000000288 | E8: 1 | F8: UN | G8: 829440 | I8: =E8*G8 -> 829440 | K8: MGA | L8: 0 | M8: 46237 | N8: 2026-08-03 | O8: 139303 | R8: 995 328.00 | S8: 20 | T8: 7 | V8: MEDMEDI | W8: True | X8: DCG | Y8: E110_MD_DCOM | Z8: DCG-COM-MEDIA | AA8: NA | AC8: 1 | AD8: 829 440.00 | AE8: YASMG | AG8: FELANA13 | AH8: 3 926 784.00 | AI8: 4 712 140.80 | AJ8: F | AK8: 46237 | AL8: 0000-00-00 | AM8: SPOT - RECORD TV | AN8: YASSIE | AO8: YASSIE | AP8: C100 | AQ8: E110_MD_DCOM | AR8: DCG-COM-MEDIA | AS8: STD | AV8: E | AW8: E | AX8: Felana RARIVOSON | AY8: RAZAFINDRAHAGA Setra | BA8: 1265 | BB8: C100 | BC8: 973 | BD8: 7 | BE8: 2026-07-29
A9: 136059 | B9: SIGN | C9: STICKERS AUTOCOLLANT - MBALIK - JUILLET 2025 | D9: Stickers Home Plus - 7,5 x 6 cm - suivant proforma N° FP05186 | E9: 30500 | F9: UN | G9: 168 | I9: =E9*G9 -> 5124000 | K9: MGA | L9: 0 | M9: 46237 | N9: 2026-08-03 | O9: 139299 | R9: 6 148 800.00 | S9: 20 | T9: 1 | V9: GELACCS | W9: True | X9: DCG | Y9: E110_TR_MBLK | Z9: DCG-SHS | AA9: NA | AC9: 30500 | AD9: 5 124 000.00 | AE9: YASMG | AG9: FELANA13 | AH9: 39 000 000.00 | AI9: 46 800 000.00 | AK9: 46237 | AL9: 0000-00-00 | AM9: STICKERS MBALIK | AN9: YASSIE | AO9: GALE | AP9: C100 | AQ9: E110_TR_MBLK | AR9: DCG-SHS | AS9: STD | AV9: E | AW9: E | AX9: Felana RARIVOSON | AY9: RAZAFINDRAHAGA Setra | BA9: 24694 | BB9: C100 | BC9: 1089 | BD9: 1 | BE9: 2026-07-29
A10: 136059 | B10: SIGN | C10: STICKERS AUTOCOLLANT - MBALIK - JUILLET 2025 | D10: Stickers Home Plus - 13x19 cm (sticker facing) - suivant proforma N° FP05186 | E10: 30500 | F10: UN | G10: 648 | I10: =E10*G10 -> 19764000 | K10: MGA | L10: 0 | M10: 46237 | N10: 2026-08-03 | O10: 139299 | R10: 23 716 800.00 | S10: 20 | T10: 2 | V10: GELACCS | W10: True | X10: DCG | Y10: E110_TR_MBLK | Z10: DCG-SHS | AA10: NA | AC10: 30500 | AD10: 19 764 000.00 | AE10: YASMG | AG10: FELANA13 | AH10: 39 000 000.00 | AI10: 46 800 000.00 | AK10: 46237 | AL10: 0000-00-00 | AM10: STICKERS MBALIK | AN10: YASSIE | AO10: GALE | AP10: C100 | AQ10: E110_TR_MBLK | AR10: DCG-SHS | AS10: STD | AV10: E | AW10: E | AX10: Felana RARIVOSON | AY10: RAZAFINDRAHAGA Setra | BA10: 24694 | BB10: C100 | BC10: 1089 | BD10: 2 | BE10: 2026-07-29
A11: 136059 | B11: SIGN | C11: STICKERS AUTOCOLLANT - MBALIK - JUILLET 2025 | D11: Stickers Home Plus - 2,8x2,8 cm (sticker rond) - suivant proforma N° FP05186 | E11: 30500 | F11: UN | G11: 36 | I11: =E11*G11 -> 1098000 | K11: MGA | L11: 0 | M11: 46237 | N11: 2026-08-03 | O11: 139299 | R11: 1 317 600.00 | S11: 20 | T11: 3 | V11: GELACCS | W11: True | X11: DCG | Y11: E110_TR_MBLK | Z11: DCG-SHS | AA11: NA | AC11: 30500 | AD11: 1 098 000.00 | AE11: YASMG | AG11: FELANA13 | AH11: 39 000 000.00 | AI11: 46 800 000.00 | AK11: 46237 | AL11: 0000-00-00 | AM11: STICKERS MBALIK | AN11: YASSIE | AO11: GALE | AP11: C100 | AQ11: E110_TR_MBLK | AR11: DCG-SHS | AS11: STD | AV11: E | AW11: E | AX11: Felana RARIVOSON | AY11: RAZAFINDRAHAGA Setra | BA11: 24694 | BB11: C100 | BC11: 1089 | BD11: 3 | BE11: 2026-07-29
A12: 136059 | B12: SIGN | C12: STICKERS AUTOCOLLANT - MBALIK - JUILLET 2025 | D12: Stickers Home Plus - 3,5x2 cm (sticker pour cacher logo Sunking sur l'image du boîtier du facing) - suivant proforma N° FP05186 | E12: 30500 | F12: UN | G12: 28 | I12: =E12*G12 -> 854000 | K12: MGA | L12: 0 | M12: 46237 | N12: 2026-08-03 | O12: 139299 | R12: 1 024 800.00 | S12: 20 | T12: 4 | V12: GELACCS | W12: True | X12: DCG | Y12: E110_TR_MBLK | Z12: DCG-SHS | AA12: NA | AC12: 30500 | AD12: 854 000.00 | AE12: YASMG | AG12: FELANA13 | AH12: 39 000 000.00 | AI12: 46 800 000.00 | AK12: 46237 | AL12: 0000-00-00 | AM12: STICKERS MBALIK | AN12: YASSIE | AO12: GALE | AP12: C100 | AQ12: E110_TR_MBLK | AR12: DCG-SHS | AS12: STD | AV12: E | AW12: E | AX12: Felana RARIVOSON | AY12: RAZAFINDRAHAGA Setra | BA12: 24694 | BB12: C100 | BC12: 1089 | BD12: 4 | BE12: 2026-07-29
A13: 136059 | B13: SIGN | C13: STICKERS AUTOCOLLANT - MBALIK - JUILLET 2025 | D13: Stickers Home Plus - 7x2 cm (sticker dos) - suivant proforma N° FP05186 | E13: 30500 | F13: UN | G13: 48.8 | I13: =E13*G13 -> 1488400 | K13: MGA | L13: 0 | M13: 46237 | N13: 2026-08-03 | O13: 139299 | R13: 1 786 080.00 | S13: 20 | T13: 5 | V13: GELACCS | W13: True | X13: DCG | Y13: E110_TR_MBLK | Z13: DCG-SHS | AA13: NA | AC13: 30500 | AD13: 1 488 400.00 | AE13: YASMG | AG13: FELANA13 | AH13: 39 000 000.00 | AI13: 46 800 000.00 | AK13: 46237 | AL13: 0000-00-00 | AM13: STICKERS MBALIK | AN13: YASSIE | AO13: GALE | AP13: C100 | AQ13: E110_TR_MBLK | AR13: DCG-SHS | AS13: STD | AV13: E | AW13: E | AX13: Felana RARIVOSON | AY13: RAZAFINDRAHAGA Setra | BA13: 24694 | BB13: C100 | BC13: 1089 | BD13: 5 | BE13: 2026-07-29
A14: 136059 | B14: SIGN | C14: STICKERS AUTOCOLLANT - MBALIK - JUILLET 2025 | D14: Stickers Home Plus - 11x5,3 cm sticker côté jaune - suivant proforma N° FP05186 | E14: 61000 | F14: UN | G14: 153 | I14: =E14*G14 -> 9333000 | K14: MGA | L14: 0 | M14: 46237 | N14: 2026-08-03 | O14: 139299 | R14: 11 199 600.00 | S14: 20 | T14: 6 | V14: GELACCS | W14: True | X14: DCG | Y14: E110_TR_MBLK | Z14: DCG-SHS | AA14: NA | AC14: 61000 | AD14: 9 333 000.00 | AE14: YASMG | AG14: FELANA13 | AH14: 39 000 000.00 | AI14: 46 800 000.00 | AK14: 46237 | AL14: 0000-00-00 | AM14: STICKERS MBALIK | AN14: YASSIE | AO14: GALE | AP14: C100 | AQ14: E110_TR_MBLK | AR14: DCG-SHS | AS14: STD | AV14: E | AW14: E | AX14: Felana RARIVOSON | AY14: RAZAFINDRAHAGA Setra | BA14: 24694 | BB14: C100 | BC14: 1089 | BD14: 6 | BE14: 2026-07-29
A15: 136059 | B15: SIGN | C15: FRAIS DE POSE | D15: POSE A ANDRAHARO | E15: 1 | F15: UN | G15: 1338600 | I15: =E15*G15 -> 1338600 | K15: MGA | L15: 0 | M15: 46237 | N15: 2026-08-03 | O15: 139299 | R15: 1 606 320.00 | S15: 20 | T15: 7 | V15: ELEMCEL | W15: True | X15: DCG | Y15: E110_TR_MBLK | Z15: DCG-SHS | AA15: NA | AC15: 1 | AD15: 1 338 600.00 | AE15: YASMG | AG15: FELANA13 | AH15: 39 000 000.00 | AI15: 46 800 000.00 | AK15: 46237 | AL15: 0000-00-00 | AM15: STICKERS MBALIK | AN15: YASSIE | AO15: GALE | AP15: C100 | AQ15: E110_TR_MBLK | AR15: DCG-SHS | AS15: STD | AV15: E | AW15: E | AX15: Felana RARIVOSON | AY15: RAZAFINDRAHAGA Setra | BA15: 2061 | BB15: C100 | BC15: 1089 | BD15: 7 | BE15: 2026-07-29
A16: 136060 | B16: AVRA BTP | C16: TRAVAUX SUPPLEMENTAIRES | D16: TRAVAUX DE COULLAGE DALLE EN BETON YAS STORE AMBOHIPO - suivant Devis N° 206/2026 INDICE 0 | E16: 1 | F16: UN | G16: 782000 | I16: =E16*G16 -> 782000 | K16: MGA | L16: 0 | M16: 46237 | N16: 2026-08-03 | O16: 139284 | R16: 782 000.00 | S16: 0 | T16: 1 | V16: INFPYLX | W16: True | X16: DCG | Y16: E250_DRB | Z16: DCG-DRB | AA16: NA | AC16: 1 | AD16: 782 000.00 | AE16: YASMG | AG16: FELANA13 | AH16: 782 000.00 | AI16: 782 000.00 | AJ16: F | AK16: 46237 | AL16: 0000-00-00 | AM16: YS AMBOHIPO | AN16: YASSIE | AO16: YASSIE | AP16: C102 | AQ16: E250_DRB | AR16: DCG-DRB | AS16: STD | AV16: E | AW16: E | AX16: Felana RARIVOSON | AY16: RAZAFINDRAHAGA Setra | BA16: 1526 | BB16: C102 | BC16: 4038 | BD16: 1 | BE16: 2026-07-28
A17: 136061 | B17: AVRA BTP | C17: TRAVAUX SUPPLEMENTAIRES | D17: TRAVAUX DE POSE CARREAUX MURAUX - suivant devis N° 205/2026 INDICE 0 | E17: 1 | F17: UN | G17: 824000 | I17: =E17*G17 -> 824000 | K17: MGA | L17: 0 | M17: 46237 | N17: 2026-08-03 | O17: 139283 | R17: 824 000.00 | S17: 0 | T17: 1 | V17: INFPYLX | W17: True | X17: DCG | Y17: E250_DRB | Z17: DCG-DRB | AA17: NA | AC17: 1 | AD17: 824 000.00 | AE17: YASMG | AG17: FELANA13 | AH17: 824 000.00 | AI17: 824 000.00 | AK17: 46237 | AL17: 0000-00-00 | AM17: YS ITAOSY | AN17: YASSIE | AO17: YASSIE | AP17: C102 | AQ17: E250_DRB | AR17: DCG-DRB | AS17: STD | AV17: E | AW17: E | AX17: Felana RARIVOSON | AY17: RAZAFINDRAHAGA Setra | BA17: 1526 | BB17: C102 | BC17: 4038 | BD17: 1 | BE17: 2026-07-28
A18: 136062 | B18: LCS CONSULTING | C18: PRESTATION DIVERS | D18: REMBOURSEMENT FRAIS BAC CDZ S14 - PROFORMA N°192-A/FP/TELMA/2026 | E18: 1 | F18: PIE | G18: 1480000 | I18: =E18*G18 -> 1480000 | K18: MGA | L18: 0 | M18: 46237 | N18: 2026-08-03 | O18: 139333 | R18: 1 480 000.00 | S18: 0 | T18: 1 | V18: PRICTRL | W18: False | X18: DCG | Y18: E214_DCG | Z18: DCG-DVIR | AA18: NA | AC18: 0 | AD18: 0.00 | AE18: YASMG | AG18: FELANA13 | AH18: 11 417 000.00 | AI18: 11 417 000.00 | AJ18: F | AK18: 46237 | AL18: 0000-00-00 | AM18: REMBOURSEMENT FRAIS BAC CDZ | AN18: YASSIE | AO18: YASSIE | AP18: C104 | AQ18: E214_DCG | AR18: DCG-DVIR | AS18: STD | AV18: S | AW18: S | AX18: Felana RARIVOSON | AY18: RAZAFINDRAHAGA Setra | BA18: 11533 | BB18: C104 | BC18: 2490 | BD18: 1 | BE18: 2026-07-30
A19: 136062 | B19: LCS CONSULTING | C19: PRESTATION DIVERS | D19: REMBOURSEMENT FRAIS BAC CDZ S15 - PROFORMA N°194-A/FP/TELMA/2026 | E19: 1 | F19: PIE | G19: 1483000 | I19: =E19*G19 -> 1483000 | K19: MGA | L19: 0 | M19: 46237 | N19: 2026-08-03 | O19: 139333 | R19: 1 483 000.00 | S19: 0 | T19: 2 | V19: PRICTRL | W19: False | X19: DCG | Y19: E214_DCG | Z19: DCG-DVIR | AA19: NA | AC19: 0 | AD19: 0.00 | AE19: YASMG | AG19: FELANA13 | AH19: 11 417 000.00 | AI19: 11 417 000.00 | AJ19: F | AK19: 46237 | AL19: 0000-00-00 | AM19: REMBOURSEMENT FRAIS BAC CDZ | AN19: YASSIE | AO19: YASSIE | AP19: C104 | AQ19: E214_DCG | AR19: DCG-DVIR | AS19: STD | AV19: S | AW19: S | AX19: Felana RARIVOSON | AY19: RAZAFINDRAHAGA Setra | BA19: 11533 | BB19: C104 | BC19: 2490 | BD19: 2 | BE19: 2026-07-30
A20: 136062 | B20: LCS CONSULTING | C20: PRESTATION DIVERS | D20: REMBOURSEMENT FRAIS BAC CDZ S16 - PROFORMA N°212-A/FP/TELMA/2026 | E20: 1 | F20: PIE | G20: 1717000 | I20: =E20*G20 -> 1717000 | K20: MGA | L20: 0 | M20: 46237 | N20: 2026-08-03 | O20: 139333 | R20: 1 717 000.00 | S20: 0 | T20: 3 | V20: PRICTRL | W20: False | X20: DCG | Y20: E214_DCG | Z20: DCG-DVIR | AA20: NA | AC20: 0 | AD20: 0.00 | AE20: YASMG | AG20: FELANA13 | AH20: 11 417 000.00 | AI20: 11 417 000.00 | AJ20: F | AK20: 46237 | AL20: 0000-00-00 | AM20: REMBOURSEMENT FRAIS BAC CDZ | AN20: YASSIE | AO20: YASSIE | AP20: C104 | AQ20: E214_DCG | AR20: DCG-DVIR | AS20: STD | AV20: S | AW20: S | AX20: Felana RARIVOSON | AY20: RAZAFINDRAHAGA Setra | BA20: 11533 | BB20: C104 | BC20: 2490 | BD20: 3 | BE20: 2026-07-30
A21: 136062 | B21: LCS CONSULTING | C21: PRESTATION DIVERS | D21: REMBOURSEMENT FRAIS BAC CDZ S17 - PROFORMA N°214-A/FP/TELMA/2026 | E21: 1 | F21: PIE | G21: 1593000 | I21: =E21*G21 -> 1593000 | K21: MGA | L21: 0 | M21: 46237 | N21: 2026-08-03 | O21: 139333 | R21: 1 593 000.00 | S21: 0 | T21: 4 | V21: PRICTRL | W21: False | X21: DCG | Y21: E214_DCG | Z21: DCG-DVIR | AA21: NA | AC21: 0 | AD21: 0.00 | AE21: YASMG | AG21: FELANA13 | AH21: 11 417 000.00 | AI21: 11 417 000.00 | AJ21: F | AK21: 46237 | AL21: 0000-00-00 | AM21: REMBOURSEMENT FRAIS BAC CDZ | AN21: YASSIE | AO21: YASSIE | AP21: C104 | AQ21: E214_DCG | AR21: DCG-DVIR | AS21: STD | AV21: S | AW21: S | AX21: Felana RARIVOSON | AY21: RAZAFINDRAHAGA Setra | BA21: 11533 | BB21: C104 | BC21: 2490 | BD21: 4 | BE21: 2026-07-30
A22: 136062 | B22: LCS CONSULTING | C22: PRESTATION DIVERS | D22: REMBOURSEMENT FRAIS BAC CDZ S20 - PROFORMA N°243-A/FP/TELMA/2026 | E22: 1 | F22: PIE | G22: 1247000 | I22: =E22*G22 -> 1247000 | K22: MGA | L22: 0 | M22: 46237 | N22: 2026-08-03 | O22: 139333 | R22: 1 247 000.00 | S22: 0 | T22: 5 | V22: PRICTRL | W22: False | X22: DCG | Y22: E214_DCG | Z22: DCG-DVIR | AA22: NA | AC22: 0 | AD22: 0.00 | AE22: YASMG | AG22: FELANA13 | AH22: 11 417 000.00 | AI22: 11 417 000.00 | AJ22: F | AK22: 46237 | AL22: 0000-00-00 | AM22: REMBOURSEMENT FRAIS BAC CDZ | AN22: YASSIE | AO22: YASSIE | AP22: C104 | AQ22: E214_DCG | AR22: DCG-DVIR | AS22: STD | AV22: S | AW22: S | AX22: Felana RARIVOSON | AY22: RAZAFINDRAHAGA Setra | BA22: 11533 | BB22: C104 | BC22: 2490 | BD22: 5 | BE22: 2026-07-30
A23: 136062 | B23: LCS CONSULTING | C23: PRESTATION DIVERS | D23: REMBOURSEMENT FRAIS BAC CDZ S22 - PROFORMA N°283-A/FP/TELMA/2026 | E23: 1 | F23: PIE | G23: 2046000 | I23: =E23*G23 -> 2046000 | K23: MGA | L23: 0 | M23: 46237 | N23: 2026-08-03 | O23: 139333 | R23: 2 046 000.00 | S23: 0 | T23: 6 | V23: PRICTRL | W23: False | X23: DCG | Y23: E214_DCG | Z23: DCG-DVIR | AA23: NA | AC23: 0 | AD23: 0.00 | AE23: YASMG | AG23: FELANA13 | AH23: 11 417 000.00 | AI23: 11 417 000.00 | AJ23: F | AK23: 46237 | AL23: 0000-00-00 | AM23: REMBOURSEMENT FRAIS BAC CDZ | AN23: YASSIE | AO23: YASSIE | AP23: C104 | AQ23: E214_DCG | AR23: DCG-DVIR | AS23: STD | AV23: S | AW23: S | AX23: Felana RARIVOSON | AY23: RAZAFINDRAHAGA Setra | BA23: 11533 | BB23: C104 | BC23: 2490 | BD23: 6 | BE23: 2026-07-30
A24: 136062 | B24: LCS CONSULTING | C24: PRESTATION DIVERS | D24: REMBOURSEMENT FRAIS BAC CDZ S21 - PROFORMA N°285-A/FP/TELMA/2026 | E24: 1 | F24: PIE | G24: 1851000 | I24: =E24*G24 -> 1851000 | K24: MGA | L24: 0 | M24: 46237 | N24: 2026-08-03 | O24: 139333 | R24: 1 851 000.00 | S24: 0 | T24: 7 | V24: PRICTRL | W24: False | X24: DCG | Y24: E214_DCG | Z24: DCG-DVIR | AA24: NA | AC24: 0 | AD24: 0.00 | AE24: YASMG | AG24: FELANA13 | AH24: 11 417 000.00 | AI24: 11 417 000.00 | AJ24: F | AK24: 46237 | AL24: 0000-00-00 | AM24: REMBOURSEMENT FRAIS BAC CDZ | AN24: YASSIE | AO24: YASSIE | AP24: C104 | AQ24: E214_DCG | AR24: DCG-DVIR | AS24: STD | AV24: S | AW24: S | AX24: Felana RARIVOSON | AY24: RAZAFINDRAHAGA Setra | BA24: 11533 | BB24: C104 | BC24: 2490 | BD24: 7 | BE24: 2026-07-30
A25: 136063 | B25: LCS CONSULTING | C25: PRESTATION EXTERNE | D25: Rajout de 150 ARS dans la région du Grand Axe Nord pour une durée de 5 mois - août 2026 à décembre 2026 - suivant proforma N° 402-A/FP/TELMA /2026 | E25: 1 | F25: UN | G25: 302775000 | I25: =E25*G25 -> 302775000 | K25: MGA | L25: 0 | M25: 46237 | N25: 2026-08-03 | O25: 139331 | R25: 363 330 000.00 | S25: 20 | T25: 1 | V25: PRICTRL | W25: True | X25: DCG | Y25: E214_DCG | Z25: DCG-DVIR | AA25: NA | AC25: 1 | AD25: 302 775 000.00 | AE25: YASMG | AG25: FELANA13 | AH25: 302 775 000.00 | AI25: 363 330 000.00 | AK25: 46237 | AL25: 0000-00-00 | AM25: RAJOUT ARS DANS LA ZONE NORD | AN25: YASSIE | AO25: YASSIE | AP25: C104 | AQ25: E214_DCG | AR25: DCG-DVIR | AS25: STD | AV25: E | AW25: E | AX25: Felana RARIVOSON | AY25: RAZAFINDRAHAGA Setra | BA25: 1264 | BB25: C104 | BC25: 2490 | BD25: 1 | BE25: 2026-07-30
A26: 136064 | B26: LCS CONSULTING | C26: PRESTATION EXTERNE | D26: Prestation intérimaire Telma 265 VAD dont 166 Tàna et 99 Région mois d'août 2026 - suivant proforma N°400-A/FP/TELMA/2026 | E26: 1 | F26: UN | G26: 119162000 | I26: =E26*G26 -> 119162000 | K26: MGA | L26: 0 | M26: 46237 | N26: 2026-08-03 | O26: 139328 | R26: 142 994 400.00 | S26: 20 | T26: 1 | V26: PRICTRL | W26: True | X26: DCG | Y26: E214_DCG | Z26: DCG-DRB | AA26: NA | AC26: 1 | AD26: 119 162 000.00 | AE26: YASMG | AG26: FELANA13 | AH26: 238 324 000.00 | AI26: 285 988 800.00 | AJ26: F | AK26: 46237 | AL26: 0000-00-00 | AM26: Salaire VAD AOUT et SEPTEMBRE 2026 | AN26: YASSIE | AO26: YASSIE | AP26: C102 | AQ26: E214_DCG | AR26: DCG-DRB | AS26: STD | AV26: E | AW26: E | AX26: Felana RARIVOSON | AY26: RAZAFINDRAHAGA Setra | BA26: 1264 | BB26: C102 | BC26: 2490 | BD26: 1 | BE26: 2026-07-30
A27: 136064 | B27: LCS CONSULTING | C27: PRESTATION EXTERNE | D27: Prestation intérimaire Telma 265 VAD dont 166 Tàna et 99 Région mois de septembre 2026 - suivant proforma N°401-A/FP/TELMA/2026 | E27: 1 | F27: UN | G27: 119162000 | I27: =E27*G27 -> 119162000 | K27: MGA | L27: 0 | M27: 46237 | N27: 2026-08-03 | O27: 139328 | R27: 142 994 400.00 | S27: 20 | T27: 2 | V27: PRICTRL | W27: True | X27: DCG | Y27: E214_DCG | Z27: DCG-DRB | AA27: NA | AC27: 1 | AD27: 119 162 000.00 | AE27: YASMG | AG27: FELANA13 | AH27: 238 324 000.00 | AI27: 285 988 800.00 | AJ27: F | AK27: 46237 | AL27: 0000-00-00 | AM27: Salaire VAD AOUT et SEPTEMBRE 2026 | AN27: YASSIE | AO27: YASSIE | AP27: C102 | AQ27: E214_DCG | AR27: DCG-DRB | AS27: STD | AV27: E | AW27: E | AX27: Felana RARIVOSON | AY27: RAZAFINDRAHAGA Setra | BA27: 1264 | BB27: C102 | BC27: 2490 | BD27: 2 | BE27: 2026-07-30
A28: 136065 | B28: ROOTS CONSEILS | C28: PRESTATION DIVERS | D28: Prestation de défilé africain ( Danse africaine / DJ ambiance africaine /Maquillage / Transport) # PROFORMA NO 001 | E28: 1 | F28: PIE | G28: 7000000 | I28: =E28*G28 -> 7000000 | K28: MGA | L28: 0 | M28: 46237 | N28: 2026-08-03 | O28: 139315 | R28: 7 000 000.00 | S28: 0 | T28: 1 | V28: PRICTRL | W28: False | X28: DCG | Y28: E110_AP_DCOM | Z28: DCG-COM | AA28: NA | AC28: 1 | AD28: 7 000 000.00 | AE28: YASMG | AG28: FELANA13 | AH28: 7 000 000.00 | AI28: 7 000 000.00 | AK28: 46237 | AL28: 0000-00-00 | AM28: AFRICA DAY | AN28: YASSIE | AO28: YASSIE | AP28: C100 | AQ28: E110_AP_DCOM | AR28: DCG-COM | AS28: STD | AV28: E | AW28: E | AX28: Felana RARIVOSON | AY28: RAZAFINDRAHAGA Setra | BA28: 11533 | BB28: C100 | BC28: 7090 | BD28: 1 | BE28: 2026-07-29
A29: 136066 | B29: RAMANAMBONONA LALANIRIANA HANITRINIAINA | C29: ENTRETIEN ET REPARATION VEHICULE Y COMPRIS PIECES DE RECHAN | D29: ENTRETIEN MOTO - 15556WWT - MORONDAVA - PROFORMA N°111 | E29: 1 | F29: UN | G29: 817000 | I29: =E29*G29 -> 817000 | K29: MGA | L29: 0 | M29: 46237 | N29: 2026-08-03 | O29: 139310 | R29: 817 000.00 | S29: 0 | T29: 1 | V29: PRMVEHI | W29: True | X29: DCG | Y29: E222_DCG | Z29: DCG-SHS | AA29: NA | AC29: 1 | AD29: 817 000.00 | AE29: YASMG | AG29: FELANA13 | AH29: 817 000.00 | AI29: 817 000.00 | AK29: 46237 | AL29: 0000-00-00 | AM29: ENTRETIEN MOTO - MORONDAVA | AN29: YASSIE | AO29: YASSIE | AP29: C100 | AQ29: E222_DCG | AR29: DCG-SHS | AS29: STD | AV29: E | AW29: E | AX29: Felana RARIVOSON | AY29: RAZAFINDRAHAGA Setra | BA29: 1185 | BB29: C100 | BC29: 6740 | BD29: 1 | BE29: 2026-07-29
A30: 136067 | B30: MADAGASCAR AUTOMOBILE | C30: ENTRETIEN ET REPARATION VEHICULE Y COMPRIS PIECES DE RECHAN | D30: ENTRETIEN MOTO - 46608WWT - TANA - devis 1de2478442 du 13/07/2026 | E30: 1 | F30: UN | G30: 90500 | I30: =E30*G30 -> 90500 | K30: MGA | L30: 0 | M30: 46237 | N30: 2026-08-03 | O30: 139309 | R30: 108 600.00 | S30: 20 | T30: 1 | V30: PRMVEHI | W30: True | X30: DCG | Y30: E222_DCG | Z30: DCG-SHS | AA30: NA | AC30: 1 | AD30: 90 500.00 | AE30: YASMG | AG30: FELANA13 | AH30: 90 500.00 | AI30: 108 600.00 | AK30: 46237 | AL30: 0000-00-00 | AM30: ENTRETIEN MOTO - MBALIK | AN30: YASSIE | AO30: YASSIE | AP30: C100 | AQ30: E222_DCG | AR30: DCG-SHS | AS30: STD | AV30: E | AW30: E | AX30: Felana RARIVOSON | AY30: RAZAFINDRAHAGA Setra | BA30: 1185 | BB30: C100 | BC30: 1184 | BD30: 1 | BE30: 2026-07-29
A31: 136068 | B31: JUMELLES PRODUCTION | C31: SPONSORING | D31: Apport Numéraire FESTIVAL DONA BE - FACTURE N°12 | E31: 1 | F31: UN | G31: 40000000 | I31: =E31*G31 -> 40000000 | K31: MGA | L31: 0 | M31: 46237 | N31: 2026-08-12 | O31: 139337 | R31: 40 000 000.00 | S31: 0 | T31: 1 | V31: MECSPDC | W31: True | X31: DCG | Y31: E110_AC_DCOM | Z31: DCG-COM-PART | AA31: NA | AC31: 1 | AD31: 40 000 000.00 | AE31: YASMG | AG31: FELANA13 | AH31: 40 000 000.00 | AI31: 40 000 000.00 | AJ31: F | AK31: 46237 | AL31: 0000-00-00 | AM31: FESTIVAL DONA BE | AN31: YASSIE | AO31: YASSIE | AP31: C100 | AQ31: E110_AC_DCOM | AR31: DCG-COM-PART | AS31: STD | AV31: E | AW31: E | AX31: Felana RARIVOSON | AY31: RAZAFINDRAHAGA Setra | BA31: 1267 | BB31: C100 | BC31: 4323 | BD31: 1 | BE31: 2026-07-30
A32: 136069 | B32: MIDI PUBLICITE | C32: PUBLICITE ET ANNONCE | D32: Gazetiko 1/8 page Quadrichromie - FA N° FAC/2026/2997 | E32: 1 | F32: UN | G32: 6234785.4 | I32: =E32*G32 -> 6234785.4 | K32: MGA | L32: 0 | M32: 46237 | N32: 2026-08-03 | O32: 139307 | R32: 7 481 742.48 | S32: 20 | T32: 1 | V32: MEDMEDI | W32: True | X32: DCG | Y32: E110_MD_DCOM | Z32: DCG-COM-MEDIA | AA32: NA | AC32: 1 | AD32: 6 234 785.40 | AE32: YASMG | AG32: FELANA13 | AH32: 29 855 556.88 | AI32: 35 826 668.26 | AJ32: F | AK32: 46237 | AL32: 0000-00-00 | AM32: ANNULE ET REMPLACE DA 139119 | AN32: YASSIE | AO32: YASSIE | AP32: C100 | AQ32: E110_MD_DCOM | AR32: DCG-COM-MEDIA | AS32: STD | AV32: E | AW32: E | AX32: Felana RARIVOSON | AY32: RAZAFINDRAHAGA Setra | BA32: 1265 | BB32: C100 | BC32: 2566 | BD32: 1 | BE32: 2026-07-29
A33: 136069 | B33: MIDI PUBLICITE | C33: PUBLICITE ET ANNONCE | D33: Midi 1/8 page Quadrichromie - FA N° FAC/2026/2996 | E33: 1 | F33: UN | G33: 8314553.6 | I33: =E33*G33 -> 8314553.6 | K33: MGA | L33: 0 | M33: 46237 | N33: 2026-08-03 | O33: 139307 | R33: 9 977 464.32 | S33: 20 | T33: 2 | V33: MEDMEDI | W33: True | X33: DCG | Y33: E110_MD_DCOM | Z33: DCG-COM-MEDIA | AA33: NA | AC33: 1 | AD33: 8 314 553.60 | AE33: YASMG | AG33: FELANA13 | AH33: 29 855 556.88 | AI33: 35 826 668.26 | AJ33: F | AK33: 46237 | AL33: 0000-00-00 | AM33: ANNULE ET REMPLACE DA 139119 | AN33: YASSIE | AO33: YASSIE | AP33: C100 | AQ33: E110_MD_DCOM | AR33: DCG-COM-MEDIA | AS33: STD | AV33: E | AW33: E | AX33: Felana RARIVOSON | AY33: RAZAFINDRAHAGA Setra | BA33: 1265 | BB33: C100 | BC33: 2566 | BD33: 2 | BE33: 2026-07-29
A34: 136069 | B34: MIDI PUBLICITE | C34: PUBLICITE ET ANNONCE | D34: Gazetiko 1/8 page Quadrichromie - FA N° FAC/2026/3004 | E34: 1 | F34: UN | G34: 6607983 | I34: =E34*G34 -> 6607983 | K34: MGA | L34: 0 | M34: 46237 | N34: 2026-08-03 | O34: 139307 | R34: 7 929 579.60 | S34: 20 | T34: 3 | V34: MEDMEDI | W34: True | X34: DCG | Y34: E110_MD_DCOM | Z34: DCG-COM-MEDIA | AA34: NA | AC34: 1 | AD34: 6 607 983.00 | AE34: YASMG | AG34: FELANA13 | AH34: 29 855 556.88 | AI34: 35 826 668.26 | AJ34: F | AK34: 46237 | AL34: 0000-00-00 | AM34: ANNULE ET REMPLACE DA 139119 | AN34: YASSIE | AO34: YASSIE | AP34: C100 | AQ34: E110_MD_DCOM | AR34: DCG-COM-MEDIA | AS34: STD | AV34: E | AW34: E | AX34: Felana RARIVOSON | AY34: RAZAFINDRAHAGA Setra | BA34: 1265 | BB34: C100 | BC34: 2566 | BD34: 3 | BE34: 2026-07-29
A35: 136069 | B35: MIDI PUBLICITE | C35: PUBLICITE ET ANNONCE | D35: Midi 1/8 page Quadrichromie - FA N° FAC/2026/3003 | E35: 1 | F35: UN | G35: 8698234.9 | I35: =E35*G35 -> 8698234.9 | K35: MGA | L35: 0 | M35: 46237 | N35: 2026-08-03 | O35: 139307 | R35: 10 437 881.86 | S35: 20 | T35: 4 | V35: MEDMEDI | W35: True | X35: DCG | Y35: E110_MD_DCOM | Z35: DCG-COM-MEDIA | AA35: NA | AC35: 1 | AD35: 8 698 234.88 | AE35: YASMG | AG35: FELANA13 | AH35: 29 855 556.88 | AI35: 35 826 668.26 | AJ35: F | AK35: 46237 | AL35: 0000-00-00 | AM35: ANNULE ET REMPLACE DA 139119 | AN35: YASSIE | AO35: YASSIE | AP35: C100 | AQ35: E110_MD_DCOM | AR35: DCG-COM-MEDIA | AS35: STD | AV35: E | AW35: E | AX35: Felana RARIVOSON | AY35: RAZAFINDRAHAGA Setra | BA35: 1265 | BB35: C100 | BC35: 2566 | BD35: 4 | BE35: 2026-07-29
A36: 136070 | B36: MIDI PUBLICITE | C36: PUBLICITE ET ANNONCE | D36: Gazetiko 1/8 page Quadrichromie - FA N° FAC/2026/2332 | E36: 1 | F36: UN | G36: 3109980 | I36: =E36*G36 -> 3109980 | K36: MGA | L36: 0 | M36: 46237 | N36: 2026-08-03 | O36: 139305 | R36: 3 731 976.00 | S36: 20 | T36: 1 | V36: MEDMEDI | W36: True | X36: DCG | Y36: E110_MD_DCOM | Z36: DCG-COM-MEDIA | AA36: NA | AC36: 1 | AD36: 3 109 980.00 | AE36: YASMG | AG36: FELANA13 | AH36: 20 941 238.56 | AI36: 25 129 486.28 | AJ36: F | AK36: 46237 | AL36: 0000-00-00 | AM36: ANNULE ET REMPLACE DA 139119 | AN36: YASSIE | AO36: YASSIE | AP36: C100 | AQ36: E110_MD_DCOM | AR36: DCG-COM-MEDIA | AS36: STD | AV36: E | AW36: E | AX36: Felana RARIVOSON | AY36: RAZAFINDRAHAGA Setra | BA36: 1265 | BB36: C100 | BC36: 2566 | BD36: 1 | BE36: 2026-07-29
A37: 136070 | B37: MIDI PUBLICITE | C37: PUBLICITE ET ANNONCE | D37: Midi 1/8 page Quadrichromie - FA N° FAC/2026/1810 | E37: 1 | F37: UN | G37: 4136906.9 | I37: =E37*G37 -> 4136906.9 | K37: MGA | L37: 0 | M37: 46237 | N37: 2026-08-03 | O37: 139305 | R37: 4 964 288.26 | S37: 20 | T37: 2 | V37: MEDMEDI | W37: True | X37: DCG | Y37: E110_MD_DCOM | Z37: DCG-COM-MEDIA | AA37: NA | AC37: 1 | AD37: 4 136 906.88 | AE37: YASMG | AG37: FELANA13 | AH37: 20 941 238.56 | AI37: 25 129 486.28 | AJ37: F | AK37: 46237 | AL37: 0000-00-00 | AM37: ANNULE ET REMPLACE DA 139119 | AN37: YASSIE | AO37: YASSIE | AP37: C100 | AQ37: E110_MD_DCOM | AR37: DCG-COM-MEDIA | AS37: STD | AV37: E | AW37: E | AX37: Felana RARIVOSON | AY37: RAZAFINDRAHAGA Setra | BA37: 1265 | BB37: C100 | BC37: 2566 | BD37: 2 | BE37: 2026-07-29
A38: 136070 | B38: MIDI PUBLICITE | C38: PUBLICITE ET ANNONCE | D38: Midi 1/8 page Quadrichromie - FA N° FAC/2026/2993 | E38: 1 | F38: UN | G38: 7785969.3 | I38: =E38*G38 -> 7785969.3 | K38: MGA | L38: 0 | M38: 46237 | N38: 2026-08-03 | O38: 139305 | R38: 9 343 163.14 | S38: 20 | T38: 3 | V38: MEDMEDI | W38: True | X38: DCG | Y38: E110_MD_DCOM | Z38: DCG-COM-MEDIA | AA38: NA | AC38: 1 | AD38: 7 785 969.28 | AE38: YASMG | AG38: FELANA13 | AH38: 20 941 238.56 | AI38: 25 129 486.28 | AJ38: F | AK38: 46237 | AL38: 0000-00-00 | AM38: ANNULE ET REMPLACE DA 139119 | AN38: YASSIE | AO38: YASSIE | AP38: C100 | AQ38: E110_MD_DCOM | AR38: DCG-COM-MEDIA | AS38: STD | AV38: E | AW38: E | AX38: Felana RARIVOSON | AY38: RAZAFINDRAHAGA Setra | BA38: 1265 | BB38: C100 | BC38: 2566 | BD38: 3 | BE38: 2026-07-29
A39: 136070 | B39: MIDI PUBLICITE | C39: PUBLICITE ET ANNONCE | D39: Gazetiko 1/8 page Quadrichromie - FA N° FAC/2026/2994 | E39: 1 | F39: UN | G39: 5908382.4 | I39: =E39*G39 -> 5908382.4 | K39: MGA | L39: 0 | M39: 46237 | N39: 2026-08-03 | O39: 139305 | R39: 7 090 058.88 | S39: 20 | T39: 4 | V39: MEDMEDI | W39: True | X39: DCG | Y39: E110_MD_DCOM | Z39: DCG-COM-MEDIA | AA39: NA | AC39: 1 | AD39: 5 908 382.40 | AE39: YASMG | AG39: FELANA13 | AH39: 20 941 238.56 | AI39: 25 129 486.28 | AJ39: F | AK39: 46237 | AL39: 0000-00-00 | AM39: ANNULE ET REMPLACE DA 139119 | AN39: YASSIE | AO39: YASSIE | AP39: C100 | AQ39: E110_MD_DCOM | AR39: DCG-COM-MEDIA | AS39: STD | AV39: E | AW39: E | AX39: Felana RARIVOSON | AY39: RAZAFINDRAHAGA Setra | BA39: 1265 | BB39: C100 | BC39: 2566 | BD39: 4 | BE39: 2026-07-29
A40: 136071 | B40: MIDI PUBLICITE | C40: PUBLICITE ET ANNONCE | D40: Gazetiko 1/8 page Quadrichromie - FA N° FAC/2026/2333 | E40: 1 | F40: UN | G40: 5084382.6 | I40: =E40*G40 -> 5084382.6 | K40: MGA | L40: 0 | M40: 46237 | N40: 2026-08-03 | O40: 139304 | R40: 6 101 259.12 | S40: 20 | T40: 1 | V40: MEDMEDI | W40: True | X40: DCG | Y40: E110_MD_DCOM | Z40: DCG-COM-MEDIA | AA40: NA | AC40: 1 | AD40: 5 084 382.60 | AE40: YASMG | AG40: FELANA13 | AH40: 21 710 626.88 | AI40: 26 052 752.26 | AJ40: F | AK40: 46237 | AL40: 0000-00-00 | AM40: ANNULE ET REMPLACE DA 139119 | AN40: YASSIE | AO40: YASSIE | AP40: C100 | AQ40: E110_MD_DCOM | AR40: DCG-COM-MEDIA | AS40: STD | AV40: E | AW40: E | AX40: Felana RARIVOSON | AY40: RAZAFINDRAHAGA Setra | BA40: 1265 | BB40: C100 | BC40: 2566 | BD40: 1 | BE40: 2026-07-29
A41: 136071 | B41: MIDI PUBLICITE | C41: PUBLICITE ET ANNONCE | D41: Gazetiko 1/8 page Quadrichromie - FA N° FAC/2026/2335 | E41: 1 | F41: UN | G41: 3809580.6 | I41: =E41*G41 -> 3809580.6 | K41: MGA | L41: 0 | M41: 46237 | N41: 2026-08-03 | O41: 139304 | R41: 4 571 496.72 | S41: 20 | T41: 2 | V41: MEDMEDI | W41: True | X41: DCG | Y41: E110_MD_DCOM | Z41: DCG-COM-MEDIA | AA41: NA | AC41: 1 | AD41: 3 809 580.60 | AE41: YASMG | AG41: FELANA13 | AH41: 21 710 626.88 | AI41: 26 052 752.26 | AJ41: F | AK41: 46237 | AL41: 0000-00-00 | AM41: ANNULE ET REMPLACE DA 139119 | AN41: YASSIE | AO41: YASSIE | AP41: C100 | AQ41: E110_MD_DCOM | AR41: DCG-COM-MEDIA | AS41: STD | AV41: E | AW41: E | AX41: Felana RARIVOSON | AY41: RAZAFINDRAHAGA Setra | BA41: 1265 | BB41: C100 | BC41: 2566 | BD41: 2 | BE41: 2026-07-29
A42: 136071 | B42: MIDI PUBLICITE | C42: PUBLICITE ET ANNONCE | D42: Midi 1/8 page Quadrichromie - FA N° FAC/2026/2336 | E42: 1 | F42: UN | G42: 5149494.4 | I42: =E42*G42 -> 5149494.4 | K42: MGA | L42: 0 | M42: 46237 | N42: 2026-08-03 | O42: 139304 | R42: 6 179 393.28 | S42: 20 | T42: 3 | V42: MEDMEDI | W42: True | X42: DCG | Y42: E110_MD_DCOM | Z42: DCG-COM-MEDIA | AA42: NA | AC42: 1 | AD42: 5 149 494.40 | AE42: YASMG | AG42: FELANA13 | AH42: 21 710 626.88 | AI42: 26 052 752.26 | AJ42: F | AK42: 46237 | AL42: 0000-00-00 | AM42: ANNULE ET REMPLACE DA 139119 | AN42: YASSIE | AO42: YASSIE | AP42: C100 | AQ42: E110_MD_DCOM | AR42: DCG-COM-MEDIA | AS42: STD | AV42: E | AW42: E | AX42: Felana RARIVOSON | AY42: RAZAFINDRAHAGA Setra | BA42: 1265 | BB42: C100 | BC42: 2566 | BD42: 3 | BE42: 2026-07-29
... A50: 136077 | B50: LUCKKY COMPANY | C50: TRANSPORT | D50: Transport PLV YAS : Estrade + Panneau - PROFORMA N°190-07/LC/2026 | E50: 2 | F50: UN | G50: 300000 | I50: =E50*G50 -> 600000 | K50: MGA | L50: 0 | M50: 46237 | N50: 2026-08-03 | O50: 139225 | R50: 600 000.00 | S50: 0 | T50: 1 | V50: TRNTERM | W50: True | X50: DCG | Y50: E110_SP_DCOM | Z50: DCG-COM-PART | AA50: NA | AC50: 0 | AD50: 0.00 | AE50: YASMG | AG50: FELANA13 | AH50: 600 000.00 | AI50: 600 000.00 | AJ50: F | AK50: 46237 | AL50: 0000-00-00 | AM50: FINALE YAS COUPE DE MADA 2026 | AN50: YASSIE | AO50: YASSIE | AP50: C100 | AQ50: E110_SP_DCOM | AR50: DCG-COM-PART | AS50: STD | AV50: S | AW50: S | AX50: Felana RARIVOSON | AY50: RAZAFINDRAHAGA Setra | BA50: 4276 | BB50: C100 | BC50: 3726 | BD50: 1 | BE50: 0000-00-00
A51: 136078 | B51: LOXEA MADAGASCAR | C51: LOCATION DE VOITURE COURTE DUREE | D51: Location du 05/08 au 12/08# FACTURE PROFORMA-J498 DU 31/07/2026 | E51: 8 | F51: PIE | G51: 250000 | I51: =E51*G51 -> 2000000 | K51: MGA | L51: 0 | M51: 46237 | N51: 2026-08-03 | O51: 139362 | R51: 2 400 000.00 | S51: 20 | T51: 1 | V51: LOCLOCT | W51: True | X51: DSI | Y51: E215_DSI | Z51: DSI | AA51: NA | AC51: 8 | AD51: 2 000 000.00 | AE51: YASMG | AG51: NADIA7 | AH51: 2 440 000.00 | AI51: 2 928 000.00 | AK51: 46237 | AL51: 0000-00-00 | AM51: Location LCD-Mission Tafita à Mahanoro 05 au 12 Août 2026 | AN51: YASSIE | AO51: YASSIE | AP51: C800 | AQ51: E215_DSI | AR51: DSI | AS51: STD | AV51: E | AW51: E | AX51: RAVONINJATOVO Nadia | AY51: NJIVA Mbolatiana | BA51: 10626 | BB51: C800 | BC51: 629 | BD51: 1 | BE51: 2026-07-31
A52: 136078 | B52: LOXEA MADAGASCAR | C52: PRESTATION DE SERVICES EXTERNE | D52: Service chauffeur hors ville | E52: 8 | F52: UN | G52: 67500 | I52: =E52*G52 -> 540000 | K52: MGA | L52: 0 | M52: 46237 | N52: 2026-08-03 | O52: 139362 | R52: 648 000.00 | S52: 20 | T52: 2 | V52: PRICTRL | W52: True | X52: DSI | Y52: E215_DSI | Z52: DSI | AA52: NA | AC52: 8 | AD52: 540 000.00 | AE52: YASMG | AG52: NADIA7 | AH52: 2 440 000.00 | AI52: 2 928 000.00 | AK52: 46237 | AL52: 0000-00-00 | AM52: Location LCD-Mission Tafita à Mahanoro 05 au 12 Août 2026 | AN52: YASSIE | AO52: YASSIE | AP52: C800 | AQ52: E215_DSI | AR52: DSI | AS52: STD | AV52: E | AW52: E | AX52: RAVONINJATOVO Nadia | AY52: NJIVA Mbolatiana | BA52: 6965 | BB52: C800 | BC52: 629 | BD52: 2 | BE52: 2026-07-31
A53: 136078 | B53: LOXEA MADAGASCAR | C53: REMISE | D53: Remise | E53: 1 | F53: UN | G53: -100000 | I53: =E53*G53 -> -100000 | K53: MGA | L53: 0 | M53: 46237 | N53: 2026-08-03 | O53: 139362 | R53: -120 000.00 | S53: 20 | T53: 3 | V53: GELACCS | W53: True | X53: DSI | Y53: E215_DSI | Z53: DSI | AA53: NA | AC53: 1 | AD53: -100 000.00 | AE53: YASMG | AG53: NADIA7 | AH53: 2 440 000.00 | AI53: 2 928 000.00 | AK53: 46237 | AL53: 0000-00-00 | AM53: Location LCD-Mission Tafita à Mahanoro 05 au 12 Août 2026 | AN53: YASSIE | AO53: YASSIE | AP53: C800 | AQ53: E215_DSI | AR53: DSI | AS53: STD | AV53: E | AW53: E | AX53: RAVONINJATOVO Nadia | AY53: NJIVA Mbolatiana | BA53: 2057 | BB53: C800 | BC53: 629 | BD53: 3 | BE53: 2026-07-31
A54: 136079 | B54: MEGAPRINT | C54: ENTETE FACTURE | D54: Réf 06080/A026 En tête facture DSI, ft A4, imp quadri recto sur offset 90g, 1 visuel * 15000 ex# DEVIS DU 24/07/2026 | E54: 15000 | F54: UN | G54: 122.35294 | I54: =E54*G54 -> 1835294.1 | K54: MGA | L54: 0 | M54: 46237 | N54: 2026-08-03 | O54: 139295 | R54: 2 202 352.92 | S54: 20 | T54: 1 | V54: FRNPAPF | W54: True | X54: DSI | Y54: E218_DSI | Z54: DSI | AA54: NA | AC54: 15000 | AD54: 1 835 294.10 | AE54: YASMG | AG54: NADIA7 | AH54: 1 530 000.00 | AI54: 1 836 000.00 | AK54: 46237 | AL54: 0000-00-00 | AM54: Achat 15000 Enveloppes GM En tête pour facturation | AN54: YASSIE | AO54: GALE | AP54: C800 | AQ54: E218_DSI | AR54: DSI | AS54: STD | AV54: E | AW54: E | AX54: RAVONINJATOVO Nadia | AY54: NJIVA Mbolatiana | BA54: 9753 | BB54: C800 | BC54: 88 | BD54: 1 | BE54: 2026-07-31
A55: 136079 | B55: MEGAPRINT | C55: REMISE | D55: Remise | E55: 1 | F55: UN | G55: -305294.1 | I55: =E55*G55 -> -305294.1 | K55: MGA | L55: 0 | M55: 46237 | N55: 2026-08-03 | O55: 139295 | R55: -366 352.92 | S55: 20 | T55: 2 | V55: GELACCS | W55: True | X55: DSI | Y55: E218_DSI | Z55: DSI | AA55: NA | AC55: 1 | AD55: -305 294.10 | AE55: YASMG | AG55: NADIA7 | AH55: 1 530 000.00 | AI55: 1 836 000.00 | AK55: 46237 | AL55: 0000-00-00 | AM55: Achat 15000 Enveloppes GM En tête pour facturation | AN55: YASSIE | AO55: GALE | AP55: C800 | AQ55: E218_DSI | AR55: DSI | AS55: STD | AV55: E | AW55: E | AX55: RAVONINJATOVO Nadia | AY55: NJIVA Mbolatiana | BA55: 2057 | BB55: C800 | BC55: 88 | BD55: 2 | BE55: 2026-07-31
A56: 136080 | B56: MADAJOB | C56: PRESTATION DE SERVICE | D56: Prestation intérimaire: 01 Technicien Drive Test et Performance Radio pour 2 mois# DEVIS N°3914 DU 03/07/2026 | E56: 1 | F56: UN | G56: 1504400 | I56: =E56*G56 -> 1504400 | K56: MGA | L56: 0 | M56: 46237 | N56: 2026-08-03 | O56: 139266 | R56: 1 805 280.00 | S56: 20 | T56: 1 | V56: PRICTRL | W56: True | X56: DTG | Y56: E214_DTG | Z56: DRH-ADMIN | AA56: NA | AC56: 1 | AD56: 1 504 400.00 | AE56: YASMG | AG56: NADIA7 | AH56: 1 504 400.00 | AI56: 1 805 280.00 | AJ56: F | AK56: 46237 | AL56: 0000-00-00 | AN56: YASSIE | AO56: YASSIE | AP56: C500 | AQ56: E214_DTG | AR56: DRH-ADMIN | AS56: STD | AV56: E | AW56: E | AX56: RAVONINJATOVO Nadia | AY56: ANDRIANINA Rebecca | BA56: 14862 | BB56: C500 | BC56: 723 | BD56: 1 | BE56: 2026-07-28
A57: 136081 | B57: LCS CONSULTING | C57: PRESTATION DE SERVICE | D57: Prestation intérimaire: 582 AR Terrain en Axe Régions pour 2 mois# FACTURE PROFORMA N°356-A/FP/TELMA /2026 DU 17/07/2026 | E57: 582 | F57: UN | G57: 807400 | I57: =E57*G57 -> 469906800 | K57: MGA | L57: 0 | M57: 46237 | N57: 2026-08-03 | O57: 139174 | R57: 563 888 160.00 | S57: 20 | T57: 1 | V57: PRICTRL | W57: True | X57: DCG | Y57: E214_DVI | Z57: DRH-ADMIN | AA57: NA | AC57: 582 | AD57: 469 906 800.00 | AE57: YASMG | AG57: NADIA7 | AH57: 469 906 800.00 | AI57: 563 888 160.00 | AK57: 46237 | AL57: 0000-00-00 | AN57: YASSIE | AO57: YASSIE | AP57: C104 | AQ57: E214_DVI | AR57: DRH-ADMIN | AS57: STD | AV57: E | AW57: E | AX57: RAVONINJATOVO Nadia | AY57: ANDRIANINA Rebecca | BA57: 14862 | BB57: C104 | BC57: 2490 | BD57: 1 | BE57: 2026-07-22
A58: 136082 | B58: LCS CONSULTING | C58: PRESTATION EXTERNE | D58: Remboursement IM AR MBALIK mois de Juin 2026 - suivant proforma N°338-A/FP/TELMA/2026 | E58: 1 | F58: UN | G58: 3660775 | I58: =E58*G58 -> 3660775 | K58: MGA | L58: 0 | M58: 46237 | N58: 2026-08-03 | O58: 139206 | R58: 3 660 775.00 | S58: 0 | T58: 1 | V58: PRICTRL | W58: True | X58: DCG | Y58: E214_DCG | Z58: DCG-SHS | AA58: NA | AC58: 1 | AD58: 3 660 775.00 | AE58: YASMG | AG58: FELANA13 | AH58: 9 325 575.00 | AI58: 9 325 575.00 | AJ58: F | AK58: 46237 | AL58: 0000-00-00 | AM58: REMBOURSEMENT IM AR & FRAIS COLIS & IM ADV | AN58: YASSIE | AO58: YASSIE | AP58: C100 | AQ58: E214_DCG | AR58: DCG-SHS | AS58: STD | AV58: E | AW58: E | AX58: Felana RARIVOSON | AY58: RAZAFINDRAHAGA Setra | BA58: 1264 | BB58: C100 | BC58: 2490 | BD58: 1 | BE58: 2026-07-22
A59: 136082 | B59: LCS CONSULTING | C59: PRESTATION EXTERNE | D59: Remboursement frais colis AR MBALIK mois de Juin 2026 - suivant proforma N°339-A/FP/TELMA/2026 | E59: 1 | F59: UN | G59: 2214900 | I59: =E59*G59 -> 2214900 | K59: MGA | L59: 0 | M59: 46237 | N59: 2026-08-03 | O59: 139206 | R59: 2 214 900.00 | S59: 0 | T59: 2 | V59: PRICTRL | W59: True | X59: DCG | Y59: E214_DCG | Z59: DCG-SHS | AA59: NA | AC59: 1 | AD59: 2 214 900.00 | AE59: YASMG | AG59: FELANA13 | AH59: 9 325 575.00 | AI59: 9 325 575.00 | AJ59: F | AK59: 46237 | AL59: 0000-00-00 | AM59: REMBOURSEMENT IM AR & FRAIS COLIS & IM ADV | AN59: YASSIE | AO59: YASSIE | AP59: C100 | AQ59: E214_DCG | AR59: DCG-SHS | AS59: STD | AV59: E | AW59: E | AX59: Felana RARIVOSON | AY59: RAZAFINDRAHAGA Setra | BA59: 1264 | BB59: C100 | BC59: 2490 | BD59: 2 | BE59: 2026-07-22
A60: 136082 | B60: LCS CONSULTING | C60: PRESTATION EXTERNE | D60: Remboursement IM CDV MBALIK mois de mai 2026 - suivant proforma N°329-A/FP/TELMA/2026 | E60: 1 | F60: UN | G60: 3449900 | I60: =E60*G60 -> 3449900 | K60: MGA | L60: 0 | M60: 46237 | N60: 2026-08-03 | O60: 139206 | R60: 3 449 900.00 | S60: 0 | T60: 3 | V60: PRICTRL | W60: True | X60: DCG | Y60: E214_DCG | Z60: DCG-SHS | AA60: NA | AC60: 1 | AD60: 3 449 900.00 | AE60: YASMG | AG60: FELANA13 | AH60: 9 325 575.00 | AI60: 9 325 575.00 | AJ60: F | AK60: 46237 | AL60: 0000-00-00 | AM60: REMBOURSEMENT IM AR & FRAIS COLIS & IM ADV | AN60: YASSIE | AO60: YASSIE | AP60: C100 | AQ60: E214_DCG | AR60: DCG-SHS | AS60: STD | AV60: E | AW60: E | AX60: Felana RARIVOSON | AY60: RAZAFINDRAHAGA Setra | BA60: 1264 | BB60: C100 | BC60: 2490 | BD60: 3 | BE60: 2026-07-22
A61: 136083 | B61: LCS CONSULTING | C61: PRESTATION DE SERVICE | D61: Prestation intérimaire: 01 Analyste Fonctionnel VE pour 2 mois# FACTURE PROFORMA N°366-A/FP/TELMA/2026 DU 17/07/2026 | E61: 1 | F61: UN | G61: 2247800 | I61: =E61*G61 -> 2247800 | K61: MGA | L61: 0 | M61: 46237 | N61: 2026-08-03 | O61: 139190 | R61: 2 697 360.00 | S61: 20 | T61: 1 | V61: PRICTRL | W61: True | X61: DCG | Y61: E214_DVE | Z61: DRH-ADMIN | AA61: NA | AC61: 1 | AD61: 2 247 800.00 | AE61: YASMG | AG61: NADIA7 | AH61: 2 247 800.00 | AI61: 2 697 360.00 | AK61: 46237 | AL61: 0000-00-00 | AN61: YASSIE | AO61: YASSIE | AP61: C103 | AQ61: E214_DVE | AR61: DRH-ADMIN | AS61: STD | AV61: E | AW61: E | AX61: RAVONINJATOVO Nadia | AY61: ANDRIANINA Rebecca | BA61: 14862 | BB61: C103 | BC61: 2490 | BD61: 1 | BE61: 2026-07-22
A62: 136084 | B62: LCS CONSULTING | C62: PRESTATION DE SERVICE | D62: Prestation intérimaire: 75 AR Roadshow pour 2 mois# FACTURE PROFORMA N°355-A/FP/TELMA /2026 DU 17/07/2026 | E62: 75 | F62: UN | G62: 807400 | I62: =E62*G62 -> 60555000 | K62: MGA | L62: 0 | M62: 46237 | N62: 2026-08-03 | O62: 139173 | R62: 72 666 000.00 | S62: 20 | T62: 1 | V62: PRICTRL | W62: True | X62: DCG | Y62: E214_DVI | Z62: DRH-ADMIN | AA62: NA | AC62: 75 | AD62: 60 555 000.00 | AE62: YASMG | AG62: NADIA7 | AH62: 60 555 000.00 | AI62: 72 666 000.00 | AK62: 46237 | AL62: 0000-00-00 | AN62: YASSIE | AO62: YASSIE | AP62: C104 | AQ62: E214_DVI | AR62: DRH-ADMIN | AS62: STD | AV62: E | AW62: E | AX62: RAVONINJATOVO Nadia | AY62: ANDRIANINA Rebecca | BA62: 14862 | BB62: C104 | BC62: 2490 | BD62: 1 | BE62: 2026-07-22
A63: 136085 | B63: SOCIETE DE GESTION ET EXPLOITATION DE M/CAR | C63: COLLATION | D63: COLLATION NOUVELLE RECRUE LE 24 JUILLET 2026 : Gâteaux entier - PROFORMA/EVENT/PRKL/2026 DU 21/07/26 | E63: 12 | F63: UN | G63: 10000 | I63: =E63*G63 -> 120000 | K63: MGA | L63: 0 | M63: 46237 | N63: 2026-08-03 | O63: 139200 | R63: 144 000.00 | S63: 20 | T63: 1 | V63: VDPPERD | W63: True | X63: DCG | Y63: E219_DCG | Z63: DCG-BEF | AA63: NA | AC63: 12 | AD63: 120 000.00 | AE63: YASMG | AG63: FELANA13 | AH63: 120 000.00 | AI63: 144 000.00 | AJ63: F | AK63: 46237 | AL63: 0000-00-00 | AM63: COLLATION LE 24/07/2026 | AN63: YASSIE | AO63: YASSIE | AP63: C100 | AQ63: E219_DCG | AR63: DCG-BEF | AS63: STD | AV63: E | AW63: E | AX63: Felana RARIVOSON | AY63: RAZAFINDRAHAGA Setra | BA63: 12682 | BB63: C100 | BC63: 119 | BD63: 1 | BE63: 2026-07-22
A64: 136086 | B64: LCS CONSULTING | C64: PRESTATION DE SERVICE | D64: Prestation intérimaire: PERDIEM Mission - Rina juillet 26# FACTURE PROFORMA N°398-A/FP/TELMA/2026 du 28/07/2026 | E64: 1 | F64: UN | G64: 162300 | I64: =E64*G64 -> 162300 | K64: MGA | L64: 0 | M64: 46237 | N64: 2026-08-03 | O64: 139294 | R64: 162 300.00 | S64: 0 | T64: 1 | V64: PRICTRL | W64: True | X64: DRH | Y64: E214_DRH | Z64: DRH-ADMIN | AA64: NA | AC64: 1 | AD64: 162 300.00 | AE64: YASMG | AG64: NADIA7 | AH64: 162 300.00 | AI64: 162 300.00 | AJ64: F | AK64: 46237 | AL64: 0000-00-00 | AN64: YASSIE | AO64: YASSIE | AP64: C600 | AQ64: E214_DRH | AR64: DRH-ADMIN | AS64: STD | AV64: E | AW64: E | AX64: RAVONINJATOVO Nadia | AY64: ANDRIANINA Rebecca | BA64: 14862 | BB64: C600 | BC64: 2490 | BD64: 1 | BE64: 2026-07-28
A65: 136087 | B65: ONG SOROGNO | C65: SPONSORING | D65: Soutien de lévènement Festival Sorogno - FACTURE DU 14/07/2026 | E65: 1 | F65: UN | G65: 20000000 | I65: =E65*G65 -> 20000000 | K65: MGA | L65: 0 | M65: 46237 | N65: 2026-08-03 | O65: 139363 | R65: 20 000 000.00 | S65: 0 | T65: 1 | V65: MECSPDC | W65: True | X65: DCG | Y65: E110_AC_DCOM | Z65: DCG-COM-PART | AA65: NA | AC65: 0 | AD65: 0.00 | AE65: YASMG | AG65: FELANA13 | AH65: 40 000 000.00 | AI65: 40 000 000.00 | AJ65: F | AK65: 46237 | AL65: 0000-00-00 | AM65: FESTIVAL SOROGNO 2026 | AN65: YASSIE | AO65: YASSIE | AP65: C100 | AQ65: E110_AC_DCOM | AR65: DCG-COM-PART | AS65: STD | AV65: S | AW65: S | AX65: Felana RARIVOSON | AY65: RAZAFINDRAHAGA Setra | BA65: 1267 | BB65: C100 | BC65: 4331 | BD65: 1 | BE65: 0000-00-00
A66: 136087 | B66: ONG SOROGNO | C66: CACHET | D66: Cachet Ambassadeur YAS MADADASCAR | E66: 5 | F66: PIE | G66: 4000000 | I66: =E66*G66 -> 20000000 | K66: MGA | L66: 0 | M66: 46237 | N66: 2026-08-03 | O66: 139363 | R66: 20 000 000.00 | S66: 0 | T66: 2 | V66: FRNPAPF | W66: True | X66: DCG | Y66: E110_AC_DCOM | Z66: DCG-COM-PART | AA66: NA | AC66: 0 | AD66: 0.00 | AE66: YASMG | AG66: FELANA13 | AH66: 40 000 000.00 | AI66: 40 000 000.00 | AJ66: F | AK66: 46237 | AL66: 0000-00-00 | AM66: FESTIVAL SOROGNO 2026 | AN66: YASSIE | AO66: YASSIE | AP66: C100 | AQ66: E110_AC_DCOM | AR66: DCG-COM-PART | AS66: STD | AV66: S | AW66: S | AX66: Felana RARIVOSON | AY66: RAZAFINDRAHAGA Setra | BA66: 3307 | BB66: C100 | BC66: 4331 | BD66: 2 | BE66: 0000-00-00
A67: 136088 | B67: LCS CONSULTING | C67: PRESTATION DE SERVICE | D67: Prestation intérimaire: Frais d'installation 01 Tech Pol en juillet 2026# FACTURE PROFORMA N°395-A/FP/TELMA/2026 du 28/07/2026 | E67: 1 | F67: UN | G67: 1027700 | I67: =E67*G67 -> 1027700 | K67: MGA | L67: 0 | M67: 46237 | N67: 2026-08-03 | O67: 139281 | R67: 1 027 700.00 | S67: 0 | T67: 1 | V67: PRICTRL | W67: True | X67: DTG | Y67: E214_DTG | Z67: DRH-ADMIN | AA67: NA | AC67: 1 | AD67: 1 027 700.00 | AE67: YASMG | AG67: NADIA7 | AH67: 1 027 700.00 | AI67: 1 027 700.00 | AJ67: F | AK67: 46237 | AL67: 0000-00-00 | AN67: YASSIE | AO67: YASSIE | AP67: C500 | AQ67: E214_DTG | AR67: DRH-ADMIN | AS67: STD | AV67: E | AW67: E | AX67: RAVONINJATOVO Nadia | AY67: ANDRIANINA Rebecca | BA67: 14862 | BB67: C500 | BC67: 2490 | BD67: 1 | BE67: 2026-07-28
A68: 136089 | B68: MORA MARKET | C68: HOUSSE CHAPITEAU - DRB - JUILLET 2026 | D68: HOUSSE CHAPITEAU - DRB - JUILLET 2026 - DEVIS B-PR0726-0131 DU 30/07/2026 | E68: 15 | F68: UN | G68: 540500 | I68: =E68*G68 -> 8107500 | K68: MGA | L68: 2 | M68: 46237 | N68: 2026-08-03 | O68: 139357 | R68: 9 534 420.00 | S68: 20 | T68: 1 | V68: PLVPLES | W68: True | X68: DCG | Y68: E110_TR_DRB | Z68: DCG-DRB | AA68: NA | AC68: 15 | AD68: 7 945 350.00 | AE68: YASMG | AG68: FELANA13 | AH68: 7 945 350.00 | AI68: 9 534 420.00 | AJ68: F | AK68: 46237 | AL68: 0000-00-00 | AM68: HOUSSE CHAPITEAU | AN68: YASSIE | AO68: GALE | AP68: C102 | AQ68: E110_TR_DRB | AR68: DCG-DRB | AS68: STD | AV68: E | AW68: E | AX68: Felana RARIVOSON | AY68: RAZAFINDRAHAGA Setra | BA68: 31274 | BB68: C102 | BC68: 4245 | BD68: 1 | BE68: 2026-07-31
A69: 136090 | B69: LCS CONSULTING | C69: PRESTATION DE SERVICE | D69: Prestation intérimaire: PERDIEM Suivi routier - Steve juillet 26# FACTURE PROFORMA N°397-A/FP/TELMA/2026 du 28/07/2026 | E69: 1 | F69: UN | G69: 1603000 | I69: =E69*G69 -> 1603000 | K69: MGA | L69: 0 | M69: 46237 | N69: 2026-08-03 | O69: 139286 | R69: 1 603 000.00 | S69: 0 | T69: 1 | V69: PRICTRL | W69: True | X69: DTG | Y69: E214_DTG | Z69: DRH-ADMIN | AA69: NA | AC69: 1 | AD69: 1 603 000.00 | AE69: YASMG | AG69: NADIA7 | AH69: 1 603 000.00 | AI69: 1 603 000.00 | AJ69: F | AK69: 46237 | AL69: 0000-00-00 | AN69: YASSIE | AO69: YASSIE | AP69: C500 | AQ69: E214_DTG | AR69: DRH-ADMIN | AS69: STD | AV69: E | AW69: E | AX69: RAVONINJATOVO Nadia | AY69: ANDRIANINA Rebecca | BA69: 14862 | BB69: C500 | BC69: 2490 | BD69: 1 | BE69: 2026-07-28
A70: 136091 | B70: LCS CONSULTING | C70: PRESTATION DE SERVICE | D70: Prestation intérimaire: PERDIEM Suivi routier - Tsiry, Nirintsoa, Thierry, Tahiry août 26# FACTURE PROFORMA N°396-A/FP/TELMA/2026 du 28/07/2026 | E70: 1 | F70: UN | G70: 6412000 | I70: =E70*G70 -> 6412000 | K70: MGA | L70: 0 | M70: 46237 | N70: 2026-08-03 | O70: 139288 | R70: 6 412 000.00 | S70: 0 | T70: 1 | V70: PRICTRL | W70: True | X70: DTG | Y70: E214_DTG | Z70: DRH-ADMIN | AA70: NA | AC70: 1 | AD70: 6 412 000.00 | AE70: YASMG | AG70: NADIA7 | AH70: 6 412 000.00 | AI70: 6 412 000.00 | AJ70: F | AK70: 46237 | AL70: 0000-00-00 | AN70: YASSIE | AO70: YASSIE | AP70: C500 | AQ70: E214_DTG | AR70: DRH-ADMIN | AS70: STD | AV70: E | AW70: E | AX70: RAVONINJATOVO Nadia | AY70: ANDRIANINA Rebecca | BA70: 14862 | BB70: C500 | BC70: 2490 | BD70: 1 | BE70: 2026-07-28
A71: 136092 | B71: MADAJOB | C71: PRESTATION DE SERVICE | D71: Prestation intérimaire: 02 AR Micro Tanà pour 2 mois# DEVIS N° 002880 DU 20/07/2026 | E71: 1 | F71: UN | G71: 1494800 | I71: =E71*G71 -> 1494800 | K71: MGA | L71: 0 | M71: 46237 | N71: 2026-08-03 | O71: 139277 | R71: 1 793 760.00 | S71: 20 | T71: 1 | V71: PRICTRL | W71: True | X71: DCG | Y71: E214_DVI | Z71: DRH-ADMIN | AA71: NA | AC71: 1 | AD71: 1 494 800.00 | AE71: YASMG | AG71: NADIA7 | AH71: 1 494 800.00 | AI71: 1 793 760.00 | AJ71: F | AK71: 46237 | AL71: 0000-00-00 | AN71: YASSIE | AO71: YASSIE | AP71: C104 | AQ71: E214_DVI | AR71: DRH-ADMIN | AS71: STD | AV71: E | AW71: E | AX71: RAVONINJATOVO Nadia | AY71: ANDRIANINA Rebecca | BA71: 14862 | BB71: C104 | BC71: 723 | BD71: 1 | BE71: 2026-07-28
A72: 136093 | B72: MADAJOB | C72: PRESTATION DE SERVICE | D72: Prestation intérimaire: IM 02 AR Micro Tanà pour 2 mois# DEVIS N° 002882 DU 20/07/2026 | E72: 1 | F72: UN | G72: 1458000 | I72: =E72*G72 -> 1458000 | K72: MGA | L72: 0 | M72: 46237 | N72: 2026-08-03 | O72: 139279 | R72: 1 458 000.00 | S72: 0 | T72: 1 | V72: PRICTRL | W72: True | X72: DCG | Y72: E214_DVI | Z72: DRH-ADMIN | AA72: NA | AC72: 1 | AD72: 1 458 000.00 | AE72: YASMG | AG72: NADIA7 | AH72: 1 458 000.00 | AI72: 1 458 000.00 | AJ72: F | AK72: 46237 | AL72: 0000-00-00 | AN72: YASSIE | AO72: YASSIE | AP72: C104 | AQ72: E214_DVI | AR72: DRH-ADMIN | AS72: STD | AV72: E | AW72: E | AX72: RAVONINJATOVO Nadia | AY72: ANDRIANINA Rebecca | BA72: 14862 | BB72: C104 | BC72: 723 | BD72: 1 | BE72: 2026-07-28
A73: 136094 | B73: MADAGASCAR AUTOMOBILE | C73: MOTO | D73: ACHAT MOTO HONDA ACE 125 SHH 6DK - DEVIS DU 5/6/2026 | E73: 1 | F73: UN | G73: 7100000 | I73: =E73*G73 -> 7100000 | K73: MGA | L73: 0 | M73: 46237 | N73: 2026-08-03 | O73: 139356 | R73: 8 520 000.00 | S73: 20 | T73: 1 | V73: PRMVEHI | W73: True | X73: DCG | Y73: 2026-CO-000001 | Z73: DCG-DVI | AA73: NA | AC73: 1 | AD73: 7 100 000.00 | AE73: YASMG | AG73: FELANA13 | AH73: 7 100 000.00 | AI73: 8 520 000.00 | AJ73: F | AK73: 46237 | AL73: 0000-00-00 | AM73: ACHAT MOTO | AN73: YASSIE | AO73: GALE | AP73: C104 | AQ73: 2026-CO-000001 | AR73: DCG-DVI | AS73: STD | AV73: E | AW73: E | AX73: Felana RARIVOSON | AY73: RAZAFINDRAHAGA Setra | BA73: 4155 | BB73: C104 | BC73: 1184 | BD73: 1 | BE73: 2026-07-31
A74: 136095 | B74: MADAGASCAR AUTOMOBILE | C74: MOTO | D74: ACHAT MOTO PEUGEOT KIBSEE 49.9CC - Modèle 2 temps - DEVIS DU 5/6/2026 | E74: 2 | F74: UN | G74: 6050000 | I74: =E74*G74 -> 12100000 | K74: MGA | L74: 0 | M74: 46237 | N74: 2026-08-03 | O74: 139355 | R74: 14 520 000.00 | S74: 20 | T74: 1 | V74: PRMVEHI | W74: True | X74: DCG | Y74: 2026-CO-000001 | Z74: DCG-DVE | AA74: NA | AC74: 2 | AD74: 12 100 000.00 | AE74: YASMG | AG74: FELANA13 | AH74: 12 100 000.00 | AI74: 14 520 000.00 | AJ74: F | AK74: 46237 | AL74: 0000-00-00 | AM74: ACHAT MOTO | AN74: YASSIE | AO74: GALE | AP74: C103 | AQ74: 2026-CO-000001 | AR74: DCG-DVE | AS74: STD | AV74: E | AW74: E | AX74: Felana RARIVOSON | AY74: RAZAFINDRAHAGA Setra | BA74: 4155 | BB74: C103 | BC74: 1184 | BD74: 1 | BE74: 2026-07-31
A75: 136096 | B75: MADAGASCAR AUTOMOBILE | C75: MOTO | D75: ACHAT MOTO HONDA ACE 125 -SHH 6DK - DEVIS DU 27/7/2026 | E75: 55 | F75: UN | G75: 7100000 | I75: =E75*G75 -> 390500000 | K75: MGA | L75: 0 | M75: 46237 | N75: 2026-08-03 | O75: 139349 | R75: 468 600 000.00 | S75: 20 | T75: 1 | V75: PRMVEHI | W75: True | X75: DCG | Y75: 2026-CO-000001 | Z75: DCG-DVIR | AA75: NA | AC75: 55 | AD75: 390 500 000.00 | AE75: YASMG | AG75: FELANA13 | AH75: 390 500 000.00 | AI75: 468 600 000.00 | AJ75: F | AK75: 46237 | AL75: 0000-00-00 | AM75: ACHAT MOTO | AN75: YASSIE | AO75: GALE | AP75: C104 | AQ75: 2026-CO-000001 | AR75: DCG-DVIR | AS75: STD | AV75: E | AW75: E | AX75: Felana RARIVOSON | AY75: RAZAFINDRAHAGA Setra | BA75: 4155 | BB75: C104 | BC75: 1184 | BD75: 1 | BE75: 2026-07-30
A76: 136097 | B76: MADAJOB | C76: PRESTATION DE SERVICE | D76: Prestation intérimaire: IM 30 AR Roadshow Tanà pour 2 mois# DEVIS N° 002881 DU 20/07/2026 | E76: 1 | F76: UN | G76: 21870000 | I76: =E76*G76 -> 21870000 | K76: MGA | L76: 0 | M76: 46237 | N76: 2026-08-03 | O76: 139278 | R76: 21 870 000.00 | S76: 0 | T76: 1 | V76: PRICTRL | W76: True | X76: DCG | Y76: E214_DVI | Z76: DRH-ADMIN | AA76: NA | AC76: 1 | AD76: 21 870 000.00 | AE76: YASMG | AG76: NADIA7 | AH76: 21 870 000.00 | AI76: 21 870 000.00 | AK76: 46237 | AL76: 0000-00-00 | AN76: YASSIE | AO76: YASSIE | AP76: C104 | AQ76: E214_DVI | AR76: DRH-ADMIN | AS76: STD | AV76: E | AW76: E | AX76: RAVONINJATOVO Nadia | AY76: ANDRIANINA Rebecca | BA76: 14862 | BB76: C104 | BC76: 723 | BD76: 1 | BE76: 2026-07-28
A77: 136098 | B77: STE MALGACHE DE COMMUNICATION ET DE PRESSE | C77: PUBLICITE ET ANNONCE | D77: Couverture 1/8 page en une du 23 et 30/01/2026 dans LA VERITE HEBDO - FACTURE N°11FI2321 DU 10/02/26 | E77: 1 | F77: UN | G77: 117000 | I77: =E77*G77 -> 117000 | K77: MGA | L77: 0 | M77: 46237 | N77: 2026-08-03 | O77: 139346 | R77: 140 400.00 | S77: 20 | T77: 1 | V77: MEDMEDI | W77: True | X77: DCG | Y77: E110_MD_DCOM | Z77: DCG-COM-MEDIA | AA77: NA | AC77: 1 | AD77: 117 000.00 | AE77: YASMG | AG77: FELANA13 | AH77: 117 000.00 | AI77: 140 400.00 | AJ77: F | AK77: 46237 | AL77: 0000-00-00 | AM77: REGUL LA VERITE | AN77: YASSIE | AO77: YASSIE | AP77: C100 | AQ77: E110_MD_DCOM | AR77: DCG-COM-MEDIA | AS77: STD | AV77: E | AW77: E | AX77: Felana RARIVOSON | AY77: RAZAFINDRAHAGA Setra | BA77: 1265 | BB77: C100 | BC77: 2487 | BD77: 1 | BE77: 2026-07-30
A78: 136099 | B78: MADAJOB | C78: PRESTATION DE SERVICE | D78: Prestation intérimaire: 30 AR Roadshow Tanà pour 2 mois# DEVIS N° 002879 DU 20/07/2026 | E78: 1 | F78: UN | G78: 22422000 | I78: =E78*G78 -> 22422000 | K78: MGA | L78: 0 | M78: 46237 | N78: 2026-08-03 | O78: 139276 | R78: 26 906 400.00 | S78: 20 | T78: 1 | V78: PRICTRL | W78: True | X78: DCG | Y78: E214_DVI | Z78: DRH-ADMIN | AA78: NA | AC78: 1 | AD78: 22 422 000.00 | AE78: YASMG | AG78: NADIA7 | AH78: 22 422 000.00 | AI78: 26 906 400.00 | AK78: 46237 | AL78: 0000-00-00 | AN78: YASSIE | AO78: YASSIE | AP78: C104 | AQ78: E214_DVI | AR78: DRH-ADMIN | AS78: STD | AV78: E | AW78: E | AX78: RAVONINJATOVO Nadia | AY78: ANDRIANINA Rebecca | BA78: 14862 | BB78: C104 | BC78: 723 | BD78: 1 | BE78: 2026-07-28
A79: 136100 | B79: MADAJOB | C79: PRESTATION DE SERVICE | D79: Prestation intérimaire: 13 BO Tanà pour 2 mois# DEVIS N°002878 DU 20/07/2026 | E79: 1 | F79: UN | G79: 9716200 | I79: =E79*G79 -> 9716200 | K79: MGA | L79: 0 | M79: 46237 | N79: 2026-08-03 | O79: 139274 | R79: 11 659 440.00 | S79: 20 | T79: 1 | V79: PRICTRL | W79: True | X79: DCG | Y79: E214_DVI | Z79: DRH-ADMIN | AA79: NA | AC79: 1 | AD79: 9 716 200.00 | AE79: YASMG | AG79: NADIA7 | AH79: 9 716 200.00 | AI79: 11 659 440.00 | AK79: 46237 | AL79: 0000-00-00 | AN79: YASSIE | AO79: YASSIE | AP79: C104 | AQ79: E214_DVI | AR79: DRH-ADMIN | AS79: STD | AV79: E | AW79: E | AX79: RAVONINJATOVO Nadia | AY79: ANDRIANINA Rebecca | BA79: 14862 | BB79: C104 | BC79: 723 | BD79: 1 | BE79: 2026-07-28
A80: 136101 | B80: EATIFA HOLDING SRL U | C80: SPONSORING | D80: Sponsoring YAS x NAS PRODUCTION - FACTURE N°F-2026-32 | E80: 1 | F80: UN | G80: 60000000 | I80: =E80*G80 -> 60000000 | K80: MGA | L80: 0 | M80: 46237 | N80: 2026-08-04 | O80: 139345 | R80: 60 000 000.00 | S80: 0 | T80: 1 | V80: MECSPDC | W80: True | X80: DCG | Y80: E110_AC_DCOM | Z80: DCG-COM-PART | AA80: NA | AC80: 1 | AD80: 60 000 000.00 | AE80: YASMG | AG80: FELANA13 | AH80: 60 000 000.00 | AI80: 60 000 000.00 | AJ80: F | AK80: 46237 | AL80: 0000-00-00 | AM80: SPONSORING | AN80: YASSIE | AO80: YASSIE | AP80: C100 | AQ80: E110_AC_DCOM | AR80: DCG-COM-PART | AS80: STD | AV80: E | AW80: E | AX80: Felana RARIVOSON | AY80: RAZAFINDRAHAGA Setra | BA80: 1267 | BB80: C100 | BC80: 7080 | BD80: 1 | BE80: 2026-07-30
A81: 136102 | B81: Ogilvy South Africa - Johannesburg | C81: PRESTATION DIVERS | D81: ATL RESOURCES - N°86071 #2026/05/04 | E81: 1 | F81: PIE | G81: 55182.38 | I81: =E81*G81 -> 55182.38 | K81: USD | L81: 0 | M81: 46237 | N81: 2026-08-04 | O81: 139343 | R81: 49 664.14 | S81: -10 | T81: 1 | V81: PRICTRL | W81: False | X81: DCG | Y81: E110_DG_DCOM | Z81: DCG-COM | AA81: NA | AC81: 0 | AD81: 0.00 | AE81: YASMG | AG81: FELANA13 | AH81: 135 766.00 | AI81: 122 189.40 | AJ81: F | AK81: 46237 | AL81: 0000-00-00 | AM81: ATL & DIGITAL RESSOURCES | AN81: YASSIE | AO81: YASSIE | AP81: C100 | AQ81: E110_DG_DCOM | AR81: DCG-COM | AS81: IMPORT | AV81: S | AW81: S | AX81: Felana RARIVOSON | AY81: RAZAFINDRAHAGA Setra | BA81: 11533 | BB81: C100 | BC81: 7154 | BD81: 1 | BE81: 2026-07-30
A82: 136102 | B82: Ogilvy South Africa - Johannesburg | C82: PRESTATION DIVERS | D82: DIGITAL RESOURCES - N°86071 | E82: 1 | F82: PIE | G82: 80583.62 | I82: =E82*G82 -> 80583.62 | K82: USD | L82: 0 | M82: 46237 | N82: 2026-08-04 | O82: 139343 | R82: 72 525.26 | S82: -10 | T82: 2 | V82: PRICTRL | W82: False | X82: DCG | Y82: E110_DG_DCOM | Z82: DCG-COM | AA82: NA | AC82: 0 | AD82: 0.00 | AE82: YASMG | AG82: FELANA13 | AH82: 135 766.00 | AI82: 122 189.40 | AJ82: F | AK82: 46237 | AL82: 0000-00-00 | AM82: ATL & DIGITAL RESSOURCES | AN82: YASSIE | AO82: YASSIE | AP82: C100 | AQ82: E110_DG_DCOM | AR82: DCG-COM | AS82: IMPORT | AV82: S | AW82: S | AX82: Felana RARIVOSON | AY82: RAZAFINDRAHAGA Setra | BA82: 11533 | BB82: C100 | BC82: 7154 | BD82: 2 | BE82: 2026-07-30
A83: 136103 | B83: MADAJOB | C83: PRESTATION DE SERVICE | D83: Prestation intérimaire: 20 AR en Poste Fixe pour 2 mois# DEVIS N° 002877 DU 20/07/2026 | E83: 1 | F83: UN | G83: 14948000 | I83: =E83*G83 -> 14948000 | K83: MGA | L83: 0 | M83: 46237 | N83: 2026-08-03 | O83: 139273 | R83: 17 937 600.00 | S83: 20 | T83: 1 | V83: PRICTRL | W83: True | X83: DCG | Y83: E214_DRB | Z83: DRH-ADMIN | AA83: NA | AC83: 1 | AD83: 14 948 000.00 | AE83: YASMG | AG83: NADIA7 | AH83: 14 948 000.00 | AI83: 17 937 600.00 | AK83: 46237 | AL83: 0000-00-00 | AN83: YASSIE | AO83: YASSIE | AP83: C102 | AQ83: E214_DRB | AR83: DRH-ADMIN | AS83: STD | AV83: E | AW83: E | AX83: RAVONINJATOVO Nadia | AY83: ANDRIANINA Rebecca | BA83: 14862 | BB83: C102 | BC83: 723 | BD83: 1 | BE83: 2026-07-28
A84: 136104 | B84: MADAJOB | C84: PRESTATION DE SERVICE | D84: Prestation intérimaire: 02 Tech Superv Filaire pour 2 mois# DEVIS N°3915 DU 03/07/2026 | E84: 1 | F84: UN | G84: 1248400 | I84: =E84*G84 -> 1248400 | K84: MGA | L84: 0 | M84: 46237 | N84: 2026-08-03 | O84: 139267 | R84: 1 498 080.00 | S84: 20 | T84: 1 | V84: PRICTRL | W84: True | X84: DTG | Y84: E214_DTG | Z84: DRH-ADMIN | AA84: NA | AC84: 1 | AD84: 1 248 400.00 | AE84: YASMG | AG84: NADIA7 | AH84: 1 248 400.00 | AI84: 1 498 080.00 | AK84: 46237 | AL84: 0000-00-00 | AN84: YASSIE | AO84: YASSIE | AP84: C500 | AQ84: E214_DTG | AR84: DRH-ADMIN | AS84: STD | AV84: E | AW84: E | AX84: RAVONINJATOVO Nadia | AY84: ANDRIANINA Rebecca | BA84: 14862 | BB84: C500 | BC84: 723 | BD84: 1 | BE84: 2026-07-28
A85: 136105 | B85: MADAJOB | C85: PRESTATION DE SERVICE | D85: Prestation intérimaire: 44 AR en Kioska pour 2 mois# DEVIS N° 002876 DU 20/07/2026 | E85: 1 | F85: UN | G85: 32885600 | I85: =E85*G85 -> 32885600 | K85: MGA | L85: 0 | M85: 46237 | N85: 2026-08-04 | O85: 139271 | R85: 39 462 720.00 | S85: 20 | T85: 1 | V85: PRICTRL | W85: True | X85: DCG | Y85: E214_DRB | Z85: DRH-ADMIN | AA85: NA | AC85: 1 | AD85: 32 885 600.00 | AE85: YASMG | AG85: NADIA7 | AH85: 32 885 600.00 | AI85: 39 462 720.00 | AK85: 46237 | AL85: 0000-00-00 | AN85: YASSIE | AO85: YASSIE | AP85: C102 | AQ85: E214_DRB | AR85: DRH-ADMIN | AS85: STD | AV85: E | AW85: E | AX85: RAVONINJATOVO Nadia | AY85: ANDRIANINA Rebecca | BA85: 14862 | BB85: C102 | BC85: 723 | BD85: 1 | BE85: 2026-07-28
A86: 136106 | B86: MADAJOB | C86: PRESTATION DE SERVICE | D86: Prestation intérimaire: 19 AR en Shop pour 2 mois# DEVIS N° 002875 DU 20/07/2026 | E86: 1 | F86: UN | G86: 14200600 | I86: =E86*G86 -> 14200600 | K86: MGA | L86: 0 | M86: 46237 | N86: 2026-08-03 | O86: 139270 | R86: 17 040 720.00 | S86: 20 | T86: 1 | V86: PRICTRL | W86: True | X86: DCG | Y86: E214_DRB | Z86: DRH-ADMIN | AA86: NA | AC86: 1 | AD86: 14 200 600.00 | AE86: YASMG | AG86: NADIA7 | AH86: 14 200 600.00 | AI86: 17 040 720.00 | AK86: 46237 | AL86: 0000-00-00 | AN86: YASSIE | AO86: YASSIE | AP86: C102 | AQ86: E214_DRB | AR86: DRH-ADMIN | AS86: STD | AV86: E | AW86: E | AX86: RAVONINJATOVO Nadia | AY86: ANDRIANINA Rebecca | BA86: 14862 | BB86: C102 | BC86: 723 | BD86: 1 | BE86: 2026-07-28
A87: 136107 | B87: LCS CONSULTING | C87: INDEMNITE | D87: IM- Un (07) VAD - TAMATAVE -STE MARIE -TAMATAVE du 10/07 au 20/07/2026 - suivant proforma N°331-A/FP/TELMA/2026 | E87: 1 | F87: UN | G87: 6230000 | I87: =E87*G87 -> 6230000 | K87: MGA | L87: 0 | M87: 46237 | N87: 2026-08-03 | O87: 139341 | R87: 6 230 000.00 | S87: 0 | T87: 1 | V87: PRICTRL | W87: True | X87: DCG | Y87: E214_DCG | Z87: DCG-DRB | AA87: NA | AC87: 1 | AD87: 6 230 000.00 | AE87: YASMG | AG87: FELANA13 | AH87: 6 230 000.00 | AI87: 6 230 000.00 | AJ87: F | AK87: 46237 | AL87: 0000-00-00 | AM87: IM VAD JUILLET 2026 | AN87: YASSIE | AO87: YASSIE | AP87: C102 | AQ87: E214_DCG | AR87: DCG-DRB | AS87: STD | AV87: E | AW87: E | AX87: Felana RARIVOSON | AY87: RAZAFINDRAHAGA Setra | BA87: 21266 | BB87: C102 | BC87: 2490 | BD87: 1 | BE87: 2026-07-30
A88: 136108 | B88: UNITE DE DISTRIBUTION TECHNOLOGIQUE - UDITEC | C88: JBL PORTABLE PARTY SPEAKER JBLPBSTAGE320UK | D88: JBL PORTABLE PARTY SPEAKER JBLPBSTAGE320UK - suivant proforma N°SQ26-0005528 | E88: 38 | F88: UN | G88: 2291735.8 | I88: =E88*G88 -> 87085961 | K88: MGA | L88: 0 | M88: 46237 | N88: 2026-08-03 | O88: 139314 | R88: 104 503 153.72 | S88: 20 | T88: 1 | V88: EEEELEC | W88: True | X88: DCG | Y88: 2026-CO-000001 | Z88: DCG-SHS | AA88: NA | AC88: 38 | AD88: 87 085 961.43 | AE88: YASMG | AG88: FELANA13 | AH88: 115 585 960.97 | AI88: 138 703 153.16 | AK88: 46237 | AL88: 0000-00-00 | AM88: SONO | AN88: YASSIE | AO88: GALE | AP88: C100 | AQ88: 2026-CO-000001 | AR88: DCG-SHS | AS88: STD | AV88: E | AW88: E | AX88: Felana RARIVOSON | AY88: RAZAFINDRAHAGA Setra | BA88: 23072 | BB88: C100 | BC88: 717 | BD88: 1 | BE88: 2026-07-29
A89: 136108 | B89: UNITE DE DISTRIBUTION TECHNOLOGIQUE - UDITEC | C89: JBL MICROPHONE JBLWIRELESSMIC | D89: PLATINUM MIC B20 WIRELESS PKPWM200 - suivant proforma N°SQ26-0005528 | E89: 76 | F89: UN | G89: 374999.99 | I89: =E89*G89 -> 28500000 | K89: MGA | L89: 0 | M89: 46237 | N89: 2026-08-03 | O89: 139314 | R89: 34 199 999.44 | S89: 20 | T89: 2 | V89: TCORADI | W89: True | X89: DCG | Y89: 2026-CO-000001 | Z89: DCG-SHS | AA89: NA | AC89: 76 | AD89: 28 499 999.54 | AE89: YASMG | AG89: FELANA13 | AH89: 115 585 960.97 | AI89: 138 703 153.16 | AK89: 46237 | AL89: 0000-00-00 | AM89: SONO | AN89: YASSIE | AO89: GALE | AP89: C100 | AQ89: 2026-CO-000001 | AR89: DCG-SHS | AS89: STD | AV89: E | AW89: E | AX89: Felana RARIVOSON | AY89: RAZAFINDRAHAGA Setra | BA89: 17182 | BB89: C100 | BC89: 717 | BD89: 2 | BE89: 2026-07-29
A90: 136109 | B90: MADAJOB | C90: PRESTATION DE SERVICE | D90: Prestation intérimaire: 01 Tech Testeur Service Perf pour 2 mois# DEVIS N°3916 DU 03/07/2026 | E90: 1 | F90: UN | G90: 1504400 | I90: =E90*G90 -> 1504400 | K90: MGA | L90: 0 | M90: 46237 | N90: 2026-08-03 | O90: 139268 | R90: 1 805 280.00 | S90: 20 | T90: 1 | V90: PRICTRL | W90: True | X90: DTG | Y90: E214_DTG | Z90: DRH-ADMIN | AA90: NA | AC90: 1 | AD90: 1 504 400.00 | AE90: YASMG | AG90: NADIA7 | AH90: 1 504 400.00 | AI90: 1 805 280.00 | AJ90: F | AK90: 46237 | AL90: 0000-00-00 | AN90: YASSIE | AO90: YASSIE | AP90: C500 | AQ90: E214_DTG | AR90: DRH-ADMIN | AS90: STD | AV90: E | AW90: E | AX90: RAVONINJATOVO Nadia | AY90: ANDRIANINA Rebecca | BA90: 14862 | BB90: C500 | BC90: 723 | BD90: 1 | BE90: 2026-07-28
A91: 136110 | B91: MADAJOB | C91: PRESTATION DE SERVICE | D91: Prestation intérimaire: 01 Support BI pour 2 mois# DEVIS N°3913 DU 03/07/2026 | E91: 1 | F91: UN | G91: 1566350 | I91: =E91*G91 -> 1566350 | K91: MGA | L91: 0 | M91: 46237 | N91: 2026-08-03 | O91: 139265 | R91: 1 879 620.00 | S91: 20 | T91: 1 | V91: PRICTRL | W91: True | X91: DFG | Y91: E214_DAF | Z91: DRH-ADMIN | AA91: NA | AC91: 1 | AD91: 1 566 350.00 | AE91: YASMG | AG91: NADIA7 | AH91: 1 566 350.00 | AI91: 1 879 620.00 | AK91: 46237 | AL91: 0000-00-00 | AN91: YASSIE | AO91: YASSIE | AP91: C700 | AQ91: E214_DAF | AR91: DRH-ADMIN | AS91: STD | AV91: E | AW91: E | AX91: RAVONINJATOVO Nadia | AY91: ANDRIANINA Rebecca | BA91: 14862 | BB91: C700 | BC91: 723 | BD91: 1 | BE91: 2026-07-28
A92: 136111 | B92: MADAJOB | C92: PRESTATION DE SERVICE | D92: Prestation intérimaire: 01 PHD pour 2 mois# DEVIS N°3912 DU 03/07/2026 | E92: 1 | F92: UN | G92: 1628300 | I92: =E92*G92 -> 1628300 | K92: MGA | L92: 0 | M92: 46237 | N92: 2026-08-03 | O92: 139264 | R92: 1 953 960.00 | S92: 20 | T92: 1 | V92: PRICTRL | W92: True | X92: DFG | Y92: E214_DAF | Z92: DRH-ADMIN | AA92: NA | AC92: 1 | AD92: 1 628 300.00 | AE92: YASMG | AG92: NADIA7 | AH92: 1 628 300.00 | AI92: 1 953 960.00 | AJ92: F | AK92: 46237 | AL92: 0000-00-00 | AN92: YASSIE | AO92: YASSIE | AP92: C700 | AQ92: E214_DAF | AR92: DRH-ADMIN | AS92: STD | AV92: E | AW92: E | AX92: RAVONINJATOVO Nadia | AY92: ANDRIANINA Rebecca | BA92: 14862 | BB92: C700 | BC92: 723 | BD92: 1 | BE92: 2026-07-28
A93: 136112 | B93: MADAJOB | C93: PRESTATION DE SERVICE | D93: Prestation intérimaire: 01 Gest de Stock Xts vendables TITAN3 pour 2 mois# DEVIS N°3910 DU 03/07/2026 | E93: 1 | F93: UN | G93: 1504400 | I93: =E93*G93 -> 1504400 | K93: MGA | L93: 0 | M93: 46237 | N93: 2026-08-03 | O93: 139262 | R93: 1 805 280.00 | S93: 20 | T93: 1 | V93: PRICTRL | W93: True | X93: DFG | Y93: E214_DAF | Z93: DRH-ADMIN | AA93: NA | AC93: 1 | AD93: 1 504 400.00 | AE93: YASMG | AG93: NADIA7 | AH93: 1 504 400.00 | AI93: 1 805 280.00 | AJ93: F | AK93: 46237 | AL93: 0000-00-00 | AN93: YASSIE | AO93: YASSIE | AP93: C700 | AQ93: E214_DAF | AR93: DRH-ADMIN | AS93: STD | AV93: E | AW93: E | AX93: RAVONINJATOVO Nadia | AY93: ANDRIANINA Rebecca | BA93: 14862 | BB93: C700 | BC93: 723 | BD93: 1 | BE93: 2026-07-28
A94: 136113 | B94: MADAJOB | C94: PRESTATION DE SERVICE | D94: Prestation intérimaire: 02 Juriste pour 2 mois# DEVIS N° 3911 DU 03/07/2026 | E94: 1 | F94: UN | G94: 4000000 | I94: =E94*G94 -> 4000000 | K94: MGA | L94: 0 | M94: 46237 | N94: 2026-08-03 | O94: 139263 | R94: 4 800 000.00 | S94: 20 | T94: 1 | V94: PRICTRL | W94: True | X94: DG | Y94: E214_DJU | Z94: DRH-ADMIN | AA94: NA | AC94: 1 | AD94: 4 000 000.00 | AE94: YASMG | AG94: NADIA7 | AH94: 4 000 000.00 | AI94: 4 800 000.00 | AK94: 46237 | AL94: 0000-00-00 | AN94: YASSIE | AO94: YASSIE | AP94: C400 | AQ94: E214_DJU | AR94: DRH-ADMIN | AS94: STD | AV94: E | AW94: E | AX94: RAVONINJATOVO Nadia | AY94: ANDRIANINA Rebecca | BA94: 14862 | BB94: C400 | BC94: 723 | BD94: 1 | BE94: 2026-07-28
A95: 136114 | B95: MADAJOB | C95: PRESTATION DE SERVICE | D95: Prestation intérimaire: 01 Gest de Stock Xts vendables pour 2 mois# DEVIS N° 3909 DU 03/07/2026 | E95: 1 | F95: UN | G95: 1439972 | I95: =E95*G95 -> 1439972 | K95: MGA | L95: 0 | M95: 46237 | N95: 2026-08-03 | O95: 139261 | R95: 1 727 966.40 | S95: 20 | T95: 1 | V95: PRICTRL | W95: True | X95: DFG | Y95: E214_DAF | Z95: DRH-ADMIN | AA95: NA | AC95: 1 | AD95: 1 439 972.00 | AE95: YASMG | AG95: NADIA7 | AH95: 1 439 972.00 | AI95: 1 727 966.40 | AK95: 46237 | AL95: 0000-00-00 | AN95: YASSIE | AO95: YASSIE | AP95: C700 | AQ95: E214_DAF | AR95: DRH-ADMIN | AS95: STD | AV95: E | AW95: E | AX95: RAVONINJATOVO Nadia | AY95: ANDRIANINA Rebecca | BA95: 14862 | BB95: C700 | BC95: 723 | BD95: 1 | BE95: 2026-07-28
A96: 136115 | B96: MADAJOB | C96: PRESTATION DE SERVICE | D96: Prestation intérimaire: 01 Chargé QVT/DEI pour 2 mois# DEVIS N° 3906 DU 03/07/2026 | E96: 1 | F96: UN | G96: 1628300 | I96: =E96*G96 -> 1628300 | K96: MGA | L96: 0 | M96: 46237 | N96: 2026-08-03 | O96: 139258 | R96: 1 953 960.00 | S96: 20 | T96: 1 | V96: PRICTRL | W96: True | X96: DRH | Y96: E214_DRH | Z96: DRH-ADMIN | AA96: NA | AC96: 1 | AD96: 1 628 300.00 | AE96: YASMG | AG96: NADIA7 | AH96: 1 628 300.00 | AI96: 1 953 960.00 | AK96: 46237 | AL96: 0000-00-00 | AN96: YASSIE | AO96: YASSIE | AP96: C600 | AQ96: E214_DRH | AR96: DRH-ADMIN | AS96: STD | AV96: E | AW96: E | AX96: RAVONINJATOVO Nadia | AY96: ANDRIANINA Rebecca | BA96: 14862 | BB96: C600 | BC96: 723 | BD96: 1 | BE96: 2026-07-28
A97: 136116 | B97: MADAJOB | C97: PRESTATION DE SERVICE | D97: Prestation intérimaire: 10 Coordinateur Sales Outsourcing Tanà et Région pour 2 mois# DEVIS N° 3908 DU 03/07/2026 | E97: 1 | F97: UN | G97: 13310000 | I97: =E97*G97 -> 13310000 | K97: MGA | L97: 0 | M97: 46237 | N97: 2026-08-03 | O97: 139260 | R97: 15 972 000.00 | S97: 20 | T97: 1 | V97: PRICTRL | W97: True | X97: DCG | Y97: E214_DRB | Z97: DRH-ADMIN | AA97: NA | AC97: 1 | AD97: 13 310 000.00 | AE97: YASMG | AG97: NADIA7 | AH97: 13 310 000.00 | AI97: 15 972 000.00 | AK97: 46237 | AL97: 0000-00-00 | AN97: YASSIE | AO97: YASSIE | AP97: C102 | AQ97: E214_DRB | AR97: DRH-ADMIN | AS97: STD | AV97: E | AW97: E | AX97: RAVONINJATOVO Nadia | AY97: ANDRIANINA Rebecca | BA97: 14862 | BB97: C102 | BC97: 723 | BD97: 1 | BE97: 2026-07-28
A98: 136117 | B98: MADAJOB | C98: PRESTATION DE SERVICE | D98: Prestation intérimaire: 01 Comptable pour 2 mois# DEVIS N° 3907 DU 03/07/2026 | E98: 1 | F98: UN | G98: 1504400 | I98: =E98*G98 -> 1504400 | K98: MGA | L98: 0 | M98: 46237 | N98: 2026-08-03 | O98: 139259 | R98: 1 805 280.00 | S98: 20 | T98: 1 | V98: PRICTRL | W98: True | X98: DFG | Y98: E214_DAF | Z98: DRH-ADMIN | AA98: NA | AC98: 1 | AD98: 1 504 400.00 | AE98: YASMG | AG98: NADIA7 | AH98: 1 504 400.00 | AI98: 1 805 280.00 | AK98: 46237 | AL98: 0000-00-00 | AN98: YASSIE | AO98: YASSIE | AP98: C700 | AQ98: E214_DAF | AR98: DRH-ADMIN | AS98: STD | AV98: E | AW98: E | AX98: RAVONINJATOVO Nadia | AY98: ANDRIANINA Rebecca | BA98: 14862 | BB98: C700 | BC98: 723 | BD98: 1 | BE98: 2026-07-28
A99: 136118 | B99: MADAJOB | C99: PRESTATION DE SERVICE | D99: Prestation intérimaire: 01 Gestionnaire Recouvrement pour 2 mois# DEVIS N° 3905 DU 03/07/2026 | E99: 1 | F99: UN | G99: 1439972 | I99: =E99*G99 -> 1439972 | K99: MGA | L99: 0 | M99: 46237 | N99: 2026-08-03 | O99: 139257 | R99: 1 727 966.40 | S99: 20 | T99: 1 | V99: PRICTRL | W99: True | X99: DFG | Y99: E214_DAF | Z99: DRH-ADMIN | AA99: NA | AC99: 1 | AD99: 1 439 972.00 | AE99: YASMG | AG99: NADIA7 | AH99: 1 439 972.00 | AI99: 1 727 966.40 | AK99: 46237 | AL99: 0000-00-00 | AN99: YASSIE | AO99: YASSIE | AP99: C700 | AQ99: E214_DAF | AR99: DRH-ADMIN | AS99: STD | AV99: E | AW99: E | AX99: RAVONINJATOVO Nadia | AY99: ANDRIANINA Rebecca | BA99: 14862 | BB99: C700 | BC99: 723 | BD99: 1 | BE99: 2026-07-28
A100: 136119 | B100: MADAJOB | C100: PRESTATION DE SERVICE | D100: Prestation intérimaire: 01 BO Admin et Orga pour 2 mois# DEVIS N° 3904 DU 03/07/2026 | E100: 1 | F100: UN | G100: 1566350 | I100: =E100*G100 -> 1566350 | K100: MGA | L100: 0 | M100: 46237 | N100: 2026-08-03 | O100: 139256 | R100: 1 879 620.00 | S100: 20 | T100: 1 | V100: PRICTRL | W100: True | X100: DFG | Y100: E214_DAF | Z100: DRH-ADMIN | AA100: NA | AC100: 1 | AD100: 1 566 350.00 | AE100: YASMG | AG100: NADIA7 | AH100: 1 566 350.00 | AI100: 1 879 620.00 | AK100: 46237 | AL100: 0000-00-00 | AN100: YASSIE | AO100: YASSIE | AP100: C700 | AQ100: E214_DAF | AR100: DRH-ADMIN | AS100: STD | AV100: E | AW100: E | AX100: RAVONINJATOVO Nadia | AY100: ANDRIANINA Rebecca | BA100: 14862 | BB100: C700 | BC100: 723 | BD100: 1 | BE100: 2026-07-28
A101: 136120 | B101: MADAJOB | C101: PRESTATION DE SERVICE | D101: Prestation intérimaire: 01 Assistants RH pour 2 mois# DEVIS N° 3903 DU 03/07/2026 | E101: 1 | F101: UN | G101: 1628300 | I101: =E101*G101 -> 1628300 | K101: MGA | L101: 0 | M101: 46237 | N101: 2026-08-03 | O101: 139255 | R101: 1 953 960.00 | S101: 20 | T101: 1 | V101: PRICTRL | W101: True | X101: DRH | Y101: E214_DRH | Z101: DRH-ADMIN | AA101: NA | AC101: 1 | AD101: 1 628 300.00 | AE101: YASMG | AG101: NADIA7 | AH101: 1 628 300.00 | AI101: 1 953 960.00 | AJ101: F | AK101: 46237 | AL101: 0000-00-00 | AN101: YASSIE | AO101: YASSIE | AP101: C600 | AQ101: E214_DRH | AR101: DRH-ADMIN | AS101: STD | AV101: E | AW101: E | AX101: RAVONINJATOVO Nadia | AY101: ANDRIANINA Rebecca | BA101: 14862 | BB101: C600 | BC101: 723 | BD101: 1 | BE101: 2026-07-28
A102: 136121 | B102: PRICE | C102: FLAT CABLE | D102: CABLE 5to12V - suivant devis N°V/26/15226 | E102: 525 | F102: PIE | G102: 26000 | I102: =E102*G102 -> 13650000 | K102: MGA | L102: 0 | M102: 46237 | N102: 2026-08-03 | O102: 139252 | R102: 16 380 000.00 | S102: 20 | T102: 1 | V102: FRNPAPF | W102: True | X102: DCG | Y102: CM_MBL_DCG | Z102: DCG-SHS | AA102: NA | AC102: 525 | AD102: 13 650 000.00 | AE102: YASMG | AG102: FELANA13 | AH102: 13 650 000.00 | AI102: 16 380 000.00 | AJ102: F | AK102: 46237 | AL102: 0000-00-00 | AM102: CABLE | AN102: YASSIE | AO102: GALE | AP102: C100 | AQ102: CM_MBL_DCG | AR102: DCG-SHS | AS102: STD | AV102: E | AW102: E | AX102: Felana RARIVOSON | AY102: RAZAFINDRAHAGA Setra | BA102: 10011 | BB102: C100 | BC102: 2632 | BD102: 1 | BE102: 2026-07-28
A103: 136122 | B103: MANAJ SARL | C103: PRESTATION DE SERVICE | D103: INSTALLATION BORNE TICKETING - YAS STORE AMBATOBE LP - AMBATOBE 1 - AMBOHIPO - AMPASAMPITO - ITAOSY - TSARALALANA - DEVIS n° MNJ2605-072 | E103: 1 | F103: UN | G103: 1950000 | I103: =E103*G103 -> 1950000 | K103: MGA | L103: 0 | M103: 46237 | N103: 2026-08-03 | O103: 139214 | R103: 1 950 000.00 | S103: 0 | T103: 1 | V103: PRICTRL | W103: True | X103: DCG | Y103: E250_DRB | Z103: DCG-DRB | AA103: NA | AC103: 1 | AD103: 1 950 000.00 | AE103: YASMG | AG103: FELANA13 | AH103: 6 450 000.00 | AI103: 6 450 000.00 | AK103: 46237 | AL103: 0000-00-00 | AM103: INSTALLATION BORNE TICKETING TANA & EST & MAJUNGA | AN103: YASSIE | AO103: YASSIE | AP103: C102 | AQ103: E250_DRB | AR103: DCG-DRB | AS103: STD | AV103: E | AW103: E | AX103: Felana RARIVOSON | AY103: RAZAFINDRAHAGA Setra | BA103: 14862 | BB103: C102 | BC103: 2536 | BD103: 1 | BE103: 2026-07-23
A104: 136122 | B104: MANAJ SARL | C104: PRESTATION DE SERVICE | D104: INSTALLATION BORNE TICKETING - YAS STORE FENERIVE EST - TAMATAVE : AVENUE - STREAMLINER - JOFFRE - GARE | E104: 1 | F104: UN | G104: 2200000 | I104: =E104*G104 -> 2200000 | K104: MGA | L104: 0 | M104: 46237 | N104: 2026-08-03 | O104: 139214 | R104: 2 200 000.00 | S104: 0 | T104: 2 | V104: PRICTRL | W104: True | X104: DCG | Y104: E250_DRB | Z104: DCG-DRB | AA104: NA | AC104: 1 | AD104: 2 200 000.00 | AE104: YASMG | AG104: FELANA13 | AH104: 6 450 000.00 | AI104: 6 450 000.00 | AK104: 46237 | AL104: 0000-00-00 | AM104: INSTALLATION BORNE TICKETING TANA & EST & MAJUNGA | AN104: YASSIE | AO104: YASSIE | AP104: C102 | AQ104: E250_DRB | AR104: DCG-DRB | AS104: STD | AV104: E | AW104: E | AX104: Felana RARIVOSON | AY104: RAZAFINDRAHAGA Setra | BA104: 14862 | BB104: C102 | BC104: 2536 | BD104: 2 | BE104: 2026-07-23
A105: 136122 | B105: MANAJ SARL | C105: PRESTATION DE SERVICE | D105: INSTALLATION BORNE TICKETING - YAS STORE MAJUNGA CATHEDRALE - WELLO - AMPASIKA - ANTANIMASAJA - BAOBAB CITY - AKASYA | E105: 1 | F105: UN | G105: 2300000 | I105: =E105*G105 -> 2300000 | K105: MGA | L105: 0 | M105: 46237 | N105: 2026-08-03 | O105: 139214 | R105: 2 300 000.00 | S105: 0 | T105: 3 | V105: PRICTRL | W105: True | X105: DCG | Y105: E250_DRB | Z105: DCG-DRB | AA105: NA | AC105: 1 | AD105: 2 300 000.00 | AE105: YASMG | AG105: FELANA13 | AH105: 6 450 000.00 | AI105: 6 450 000.00 | AK105: 46237 | AL105: 0000-00-00 | AM105: INSTALLATION BORNE TICKETING TANA & EST & MAJUNGA | AN105: YASSIE | AO105: YASSIE | AP105: C102 | AQ105: E250_DRB | AR105: DCG-DRB | AS105: STD | AV105: E | AW105: E | AX105: Felana RARIVOSON | AY105: RAZAFINDRAHAGA Setra | BA105: 14862 | BB105: C102 | BC105: 2536 | BD105: 3 | BE105: 2026-07-23
A106: 136123 | B106: MADAJOB | C106: PRESTATION DE SERVICE | D106: Prestation intérimaire: 02 Agent de mis sous pli pour 2 mois# devis N° 3902 du 03/07/2026 | E106: 1 | F106: UN | G106: 122400.12 | I106: =E106*G106 -> 122400.12 | K106: MGA | L106: 0 | M106: 46237 | N106: 2026-08-03 | O106: 139254 | R106: 146 880.14 | S106: 20 | T106: 1 | V106: PRICTRL | W106: True | X106: DSI | Y106: E214_DSI | Z106: DRH-ADMIN | AA106: NA | AC106: 1 | AD106: 122 400.12 | AE106: YASMG | AG106: NADIA7 | AH106: 122 400.12 | AI106: 146 880.14 | AK106: 46237 | AL106: 0000-00-00 | AN106: YASSIE | AO106: YASSIE | AP106: C800 | AQ106: E214_DSI | AR106: DRH-ADMIN | AS106: STD | AV106: E | AW106: E | AX106: RAVONINJATOVO Nadia | AY106: ANDRIANINA Rebecca | BA106: 14862 | BB106: C800 | BC106: 723 | BD106: 1 | BE106: 2026-07-28
A107: 136124 | B107: MADAJOB | C107: PRESTATION DE SERVICE | D107: Prestation intérimaire: 08 ADV Tanà et Région pour 2 mois# DEVIS N° 3901 DU 03/07/2026 | E107: 1 | F107: UN | G107: 6707900 | I107: =E107*G107 -> 6707900 | K107: MGA | L107: 0 | M107: 46237 | N107: 2026-08-03 | O107: 139253 | R107: 8 049 480.00 | S107: 20 | T107: 1 | V107: PRICTRL | W107: True | X107: DFG | Y107: E214_DAF | Z107: DRH-ADMIN | AA107: NA | AC107: 1 | AD107: 6 707 900.00 | AE107: YASMG | AG107: NADIA7 | AH107: 6 707 900.00 | AI107: 8 049 480.00 | AK107: 46237 | AL107: 0000-00-00 | AN107: YASSIE | AO107: YASSIE | AP107: C700 | AQ107: E214_DAF | AR107: DRH-ADMIN | AS107: STD | AV107: E | AW107: E | AX107: RAVONINJATOVO Nadia | AY107: ANDRIANINA Rebecca | BA107: 14862 | BB107: C700 | BC107: 723 | BD107: 1 | BE107: 2026-07-28
...

Sheet Base Test
A1: N__de_Cde | B1: Raison_sociale_Fournisseur | C1: Design__sommaire | D1: Designation_Complémentaire | E1: Quantité_comm | F1: Unité | G1: Prix_Unitaire | H1: PU USD | I1: Total HT | J1: Valeur remise | K1: % remise | L1: Total remisé | M1: Total HT USD | N1: Devise | O1: Remise | P1: Date_creat | Q1: Date_de_Validation | R1: N__DA | S1: Date_creat | T1: Date_de_Validation | U1: V_Total_Ligne_TTC | V1: TVA | W1: N__Poste_DA | X1: Site_Stock | Y1: Code_ss_famille | Z1: Saisie_de_réception__ | AA1: Code_Direction | AB1: Code_complément | AC1: SS_compte_anal | AD1: Centre_d_Analyse | AE1: Accord_Cadre | AF1: RAL | AG1: V_Montant_RAL | AH1: Code_Société | AI1: Avenant | AJ1: Acheteur | AK1: Tot_CA_HT | AL1: Tot_CA_TTC | AM1: Etat_Financ_ | AN1: Date_Période | AO1: Date_AR | AP1: Objet_CA | AQ1: Ctr_Emetteur_entete | AR1: Ctr_Livraison_entete | AS1: Sect_Imputation_entete | AT1: Code_Complémentaire_entete | AU1: Sous_Compte_d_Analyse_entete | AV1: Type_document | AW1: V_Expédition_soldée | AX1: Code_du_Modèle_de_Cde | AY1: V_Etat_commande_en_tête | AZ1: V_Etat_commande_ligne | BA1: Nom_Acheteur | BB1: Nom_demandeur | BC1: V_Critère_de_saisie | BD1: Code_Article | BE1: Section_d_imput | BF1: Code_Fournis | BG1: N_Poste | BH1: Date_de_livr__prev_
A2: 136199 | B2: VOYAGEXPERT | C2: PRESTATION DIVERS | D2: A-068 0010142 - APPEL 210087 LE 01MAY A 0057 AIR INFO - RANDRIAMANANTENA Rija Tsioritiana | E2: 1 | F2: PIE | G2: 44 | I2: =E2*G2 -> 44 | J2: 44 | N2: EUR | O2: 0 | P2: 46240 | Q2: 2026-08-06 | R2: 139429 | U2: -39.60 | V2: -10 | W2: 1 | Y2: PRICTRL | Z2: False | AA2: DTG | AB2: E215_DTG | AC2: DTG | AD2: NA | AF2: 0 | AG2: 0.00 | AH2: YASMG | AJ2: ELIE3 | AK2: 8 620.78 | AL2: 7 758.71 | AM2: F | AN2: 46240 | AO2: 0000-00-00 | AP2: Régul factures JUIN2026 -équipe DTG | AQ2: YASSIE | AR2: YASSIE | AS2: C500 | AT2: E215_DTG | AU2: DTG | AV2: IMPORT | AY2: E | AZ2: S | BA2: ANDRIAMANANTSOA Elie | BB2: RASAMOELINA Haritsoa Oliva | BD2: 11533 | BE2: C500 | BF2: 6711 | BG2: 1 | BH2: 2026-08-07
A3: 136199 | B3: VOYAGEXPERT | C3: PRESTATION DIVERS | D3: A-068 0010143 - APPEL 210623 LE 04MAY A 1930 INFO AIR - RANDRIAMANANTENA Rija Tsioritiana | E3: 1 | F3: PIE | G3: 44 | I3: =E3*G3 -> 44 | J3: 44 | N3: EUR | O3: 0 | P3: 46240 | Q3: 2026-08-06 | R3: 139429 | U3: -39.60 | V3: -10 | W3: 2 | Y3: PRICTRL | Z3: False | AA3: DTG | AB3: E215_DTG | AC3: DTG | AD3: NA | AF3: 0 | AG3: 0.00 | AH3: YASMG | AJ3: ELIE3 | AK3: 8 620.78 | AL3: 7 758.71 | AM3: F | AN3: 46240 | AO3: 0000-00-00 | AP3: Régul factures JUIN2026 -équipe DTG | AQ3: YASSIE | AR3: YASSIE | AS3: C500 | AT3: E215_DTG | AU3: DTG | AV3: IMPORT | AY3: E | AZ3: S | BA3: ANDRIAMANANTSOA Elie | BB3: RASAMOELINA Haritsoa Oliva | BD3: 11533 | BE3: C500 | BF3: 6711 | BG3: 2 | BH3: 2026-08-07
A4: 136199 | B4: VOYAGEXPERT | C4: PRESTATION DIVERS | D4: A-068 0010145 - APPEL 210246 LE 01MAY A 2017 BOARDING PASS - RANDRIAMANANTENA Rija Tsioritiana | E4: 1 | F4: PIE | G4: 44 | I4: =E4*G4 -> 44 | J4: 44 | N4: EUR | O4: 0 | P4: 46240 | Q4: 2026-08-06 | R4: 139429 | U4: -39.60 | V4: -10 | W4: 3 | Y4: PRICTRL | Z4: False | AA4: DTG | AB4: E215_DTG | AC4: DTG | AD4: NA | AF4: 0 | AG4: 0.00 | AH4: YASMG | AJ4: ELIE3 | AK4: 8 620.78 | AL4: 7 758.71 | AM4: F | AN4: 46240 | AO4: 0000-00-00 | AP4: Régul factures JUIN2026 -équipe DTG | AQ4: YASSIE | AR4: YASSIE | AS4: C500 | AT4: E215_DTG | AU4: DTG | AV4: IMPORT | AY4: E | AZ4: S | BA4: ANDRIAMANANTSOA Elie | BB4: RASAMOELINA Haritsoa Oliva | BD4: 11533 | BE4: C500 | BF4: 6711 | BG4: 3 | BH4: 2026-08-07
A5: 136128 | B5: ERICSSON AB SWEDEN | C5: REMISE | D5: Incentives | E5: 1 | F5: UN | G5: 643 | I5: =E5*G5 -> 643 | J5: 643 | N5: EUR | O5: 0 | P5: 46237 | Q5: 2026-08-04 | R5: 139336 | U5: -643.00 | V5: 0 | W5: 2 | Y5: GELACCS | Z5: True | AA5: DTG | AB5: 2026-DT-021002 | AC5: DTG | AD5: NA | AF5: 1 | AG5: -643.00 | AH5: YASMG | AJ5: ELIE3 | AK5: 2 574.00 | AL5: 2 574.00 | AN5: 46237 | AO5: 0000-00-00 | AP5: Achat de license capacité FH | AQ5: YASSIE | AR5: YASSIE | AS5: C500 | AT5: 2026-DT-021002 | AU5: DTG | AV5: IMPORT | AY5: E | AZ5: E | BA5: ANDRIAMANANTSOA Elie | BB5: RASAMOELINA Haritsoa Oliva | BD5: 2057 | BE5: C500 | BF5: 3211 | BG5: 2 | BH5: 2026-07-30
A6: 136410 | B6: HUAWEI TECHNOLOGIES (MADAGASCAR) S.A.R.L.U | C6: REMISE | D6: One Time Group Discount | E6: 1 | F6: UN | G6: 5676.6943 | I6: =E6*G6 -> 5676.6943 | J6: 5676.6943 | N6: EUR | O6: 0 | P6: 46253 | Q6: 2026-08-19 | R6: 139671 | U6: -6 812.03 | V6: 20 | W6: 3 | Y6: GELACCS | Z6: True | AA6: DTG | AB6: E330_DTG | AC6: DTG-CORE | AD6: NA | AF6: 1 | AG6: -5 676.69 | AH6: YASMG | AJ6: ELIE3 | AK6: 235 216.79 | AL6: 282 260.14 | AN6: 46253 | AO6: 0000-00-00 | AP6: Renouvellement du Support & Maintenance Huawei 2026 | AQ6: YASSIE | AR6: YASSIE | AS6: C500 | AT6: E330_DTG | AU6: DTG-CORE | AV6: STD | AY6: E | AZ6: E | BA6: ANDRIAMANANTSOA Elie | BB6: Toky Rasamimanana | BD6: 2057 | BE6: C500 | BF6: 2071 | BG6: 3 | BH6: 2026-08-31
A7: 136185 | B7: MEGAPRINT | C7: REMISE | D7: Remise | E7: 1 | F7: UN | G7: 45529.41 | I7: =E7*G7 -> 45529.41 | J7: 45529.41 | N7: MGA | O7: 0 | P7: 46239 | Q7: 2026-08-05 | R7: 139410 | U7: -54 635.29 | V7: 20 | W7: 2 | Y7: GELACCS | Z7: True | AA7: DSI | AB7: E218_DSI | AC7: DSI | AD7: NA | AF7: 1 | AG7: -45 529.41 | AH7: YASMG | AJ7: NADIA7 | AK7: 258 000.00 | AL7: 309 600.00 | AN7: 46239 | AO7: 0000-00-00 | AP7: Achat 200 Enveloppe GM blanche pour facturation | AQ7: YASSIE | AR7: GALE | AS7: C800 | AT7: E218_DSI | AU7: DSI | AV7: STD | AY7: E | AZ7: E | BA7: RAVONINJATOVO Nadia | BB7: NJIVA Mbolatiana | BD7: 2057 | BE7: C800 | BF7: 88 | BG7: 2 | BH7: 2026-08-04
A8: 136389 | B8: GREENLIGHT PLANET | C8: REMISE | D8: 1% Warranty Buffer Discount - PI N° USQT260100000041 | E8: 1 | F8: UN | G8: 55880.1 | I8: =E8*G8 -> 55880.1 | J8: 55880.1 | N8: USD | O8: 0 | P8: 46253 | Q8: 2026-08-19 | R8: 139649 | U8: -55 880.10 | V8: 0 | W8: 14 | Y8: GELACCS | Z8: True | AA8: DCG | AB8: CM_MBL_DCG | AC8: DCG-SHS | AD8: NA | AF8: 1 | AG8: -55 880.10 | AH8: YASMG | AJ8: FELANA13 | AK8: 3 855 843.70 | AL8: 3 855 843.70 | AM8: F | AN8: 46253 | AO8: 0000-00-00 | AP8: Réappro H2 - Mbalik | AQ8: YASSIE | AR8: GAL | AS8: C100 | AT8: CM_MBL_DCG | AU8: DCG-SHS | AV8: IMPORT | AY8: E | AZ8: E | BA8: Felana RARIVOSON | BB8: ANDRIAMIRIJA Luca | BD8: 2057 | BE8: C100 | BF8: 2411 | BG8: 14 | BH8: 2026-08-31
A9: 136078 | B9: LOXEA MADAGASCAR | C9: REMISE | D9: Remise | E9: 1 | F9: UN | G9: 100000 | I9: =E9*G9 -> 100000 | J9: 100000 | N9: MGA | O9: 0 | P9: 46237 | Q9: 2026-08-03 | R9: 139362 | U9: -120 000.00 | V9: 20 | W9: 3 | Y9: GELACCS | Z9: True | AA9: DSI | AB9: E215_DSI | AC9: DSI | AD9: NA | AF9: 1 | AG9: -100 000.00 | AH9: YASMG | AJ9: NADIA7 | AK9: 2 440 000.00 | AL9: 2 928 000.00 | AN9: 46237 | AO9: 0000-00-00 | AP9: Location LCD-Mission Tafita à Mahanoro 05 au 12 Août 2026 | AQ9: YASSIE | AR9: YASSIE | AS9: C800 | AT9: E215_DSI | AU9: DSI | AV9: STD | AY9: E | AZ9: E | BA9: RAVONINJATOVO Nadia | BB9: NJIVA Mbolatiana | BD9: 2057 | BE9: C800 | BF9: 629 | BG9: 3 | BH9: 2026-07-31
A10: 136486 | B10: UNITE DE DISTRIBUTION TECHNOLOGIQUE - UDITEC | C10: REMISE | E10: 1 | F10: UN | G10: 109750 | I10: =E10*G10 -> 109750 | J10: 109750 | N10: MGA | O10: 0 | P10: 46260 | Q10: 2026-08-26 | R10: 0 | U10: -131 700.00 | V10: 20 | W10: 0 | Y10: GELACCS | Z10: True | AA10: DFG | AB10: 2026-CO-000001 | AC10: DFG-ADV | AD10: NA | AF10: 1 | AG10: -109 750.00 | AH10: YASMG | AJ10: NADIA7 | AK10: 987 749.99 | AL10: 1 185 299.99 | AM10: F | AN10: 46260 | AO10: 0000-00-00 | AQ10: YASSIE | AR10: GALE | AS10: C700 | AT10: 2026-CO-000001 | AU10: DFG-ADV | AV10: STD | AY10: E | AZ10: E | BA10: RAVONINJATOVO Nadia | BD10: 2057 | BE10: C700 | BF10: 717 | BG10: 4 | BH10: 2026-08-27
A11: 136410 | B11: HUAWEI TECHNOLOGIES (MADAGASCAR) S.A.R.L.U | C11: REMISE | D11: One Time Discount | E11: 1 | F11: UN | G11: 130297.82 | I11: =E11*G11 -> 130297.82 | J11: 130297.82 | N11: EUR | O11: 0 | P11: 46253 | Q11: 2026-08-19 | R11: 139671 | U11: -156 357.39 | V11: 20 | W11: 2 | Y11: GELACCS | Z11: True | AA11: DTG | AB11: E330_DTG | AC11: DTG-CORE | AD11: NA | AF11: 1 | AG11: -130 297.82 | AH11: YASMG | AJ11: ELIE3 | AK11: 235 216.79 | AL11: 282 260.14 | AN11: 46253 | AO11: 0000-00-00 | AP11: Renouvellement du Support & Maintenance Huawei 2026 | AQ11: YASSIE | AR11: YASSIE | AS11: C500 | AT11: E330_DTG | AU11: DTG-CORE | AV11: STD | AY11: E | AZ11: E | BA11: ANDRIAMANANTSOA Elie | BB11: Toky Rasamimanana | BD11: 2057 | BE11: C500 | BF11: 2071 | BG11: 2 | BH11: 2026-08-31
A12: 136410 | B12: HUAWEI TECHNOLOGIES (MADAGASCAR) S.A.R.L.U | C12: REMISE | D12: One Time Discount for Phoenix Project | E12: 1 | F12: UN | G12: 150000 | I12: =E12*G12 -> 150000 | J12: 150000 | N12: EUR | O12: 0 | P12: 46253 | Q12: 2026-08-19 | R12: 139671 | U12: -180 000.00 | V12: 20 | W12: 4 | Y12: GELACCS | Z12: True | AA12: DTG | AB12: E330_DTG | AC12: DTG-CORE | AD12: NA | AF12: 1 | AG12: -150 000.00 | AH12: YASMG | AJ12: ELIE3 | AK12: 235 216.79 | AL12: 282 260.14 | AN12: 46253 | AO12: 0000-00-00 | AP12: Renouvellement du Support & Maintenance Huawei 2026 | AQ12: YASSIE | AR12: YASSIE | AS12: C500 | AT12: E330_DTG | AU12: DTG-CORE | AV12: STD | AY12: E | AZ12: E | BA12: ANDRIAMANANTSOA Elie | BB12: Toky Rasamimanana | BD12: 2057 | BE12: C500 | BF12: 2071 | BG12: 4 | BH12: 2026-08-31
A13: 136316 | B13: BATIMAX | C13: REMISE | D13: Remise | E13: 1 | F13: UN | G13: 180812.43 | I13: =E13*G13 -> 180812.43 | J13: 180812.43 | N13: MGA | O13: 0 | P13: 46247 | Q13: 2026-08-13 | R13: 139478 | U13: -216 974.92 | V13: 20 | W13: 5 | Y13: GELACCS | Z13: True | AA13: DTG | AB13: E222_DTG | AC13: DTG | AD13: NA | AF13: 1 | AG13: -180 812.43 | AH13: YASMG | AJ13: ELIE3 | AK13: 2 230 020.83 | AL13: 2 676 025.00 | AM13: F | AN13: 46247 | AO13: 0000-00-00 | AP13: Achat chaussures de sécurité motards TANA(P40-41-42) | AQ13: YASSIE | AR13: GALE | AS13: C500 | AT13: E222_DTG | AU13: DTG | AV13: STD | AY13: E | AZ13: E | BA13: ANDRIAMANANTSOA Elie | BB13: RASAMOELINA Haritsoa Oliva | BD13: 2057 | BE13: C500 | BF13: 16 | BG13: 5 | BH13: 2026-08-31
A14: 136225 | B14: HUAWEI TECHNOLOGIES CO., LTD | C14: REMISE | D14: One Time Strategy Discount | E14: 1 | F14: UN | G14: 256700.58 | I14: =E14*G14 -> 256700.58 | J14: 256700.58 | N14: EUR | O14: 0 | P14: 46241 | Q14: 2026-08-10 | R14: 139420 | U14: -256 700.58 | V14: 0 | W14: 37 | Y14: GELACCS | Z14: True | AA14: DTG | AB14: 2026-DT-012001 | AC14: DTG | AD14: NA | AF14: 1 | AG14: -256 700.58 | AH14: YASMG | AJ14: ELIE3 | AK14: 146 965.82 | AL14: 146 965.82 | AN14: 46241 | AO14: 0000-00-00 | AP14: 4G Capacity Expansion Q2-Q4 2026-TANA(Software) | AQ14: YASSIE | AR14: YASSIE | AS14: C500 | AT14: 2026-DT-012001 | AU14: DTG | AV14: IMPORT | AY14: E | AZ14: E | BA14: ANDRIAMANANTSOA Elie | BB14: RASAMOELINA Haritsoa Oliva | BD14: 2057 | BE14: C500 | BF14: 3621 | BG14: 37 | BH14: 2026-08-12
A15: 136079 | B15: MEGAPRINT | C15: REMISE | D15: Remise | E15: 1 | F15: UN | G15: 305294.1 | I15: =E15*G15 -> 305294.1 | J15: 305294.1 | N15: MGA | O15: 0 | P15: 46237 | Q15: 2026-08-03 | R15: 139295 | U15: -366 352.92 | V15: 20 | W15: 2 | Y15: GELACCS | Z15: True | AA15: DSI | AB15: E218_DSI | AC15: DSI | AD15: NA | AF15: 1 | AG15: -305 294.10 | AH15: YASMG | AJ15: NADIA7 | AK15: 1 530 000.00 | AL15: 1 836 000.00 | AN15: 46237 | AO15: 0000-00-00 | AP15: Achat 15000 Enveloppes GM En tête pour facturation | AQ15: YASSIE | AR15: GALE | AS15: C800 | AT15: E218_DSI | AU15: DSI | AV15: STD | AY15: E | AZ15: E | BA15: RAVONINJATOVO Nadia | BB15: NJIVA Mbolatiana | BD15: 2057 | BE15: C800 | BF15: 88 | BG15: 2 | BH15: 2026-07-31
A16: 136401 | B16: LOXEA MADAGASCAR | C16: REMISE | E16: 1 | F16: UN | G16: 312500 | I16: =E16*G16 -> 312500 | J16: 312500 | N16: MGA | O16: 0 | P16: 46253 | Q16: 2026-08-19 | R16: 0 | U16: -375 000.00 | V16: 20 | W16: 0 | Y16: GELACCS | Z16: True | AA16: DSI | AB16: E215_DSI | AC16: DSI | AD16: NA | AF16: 1 | AG16: -312 500.00 | AH16: YASMG | AJ16: NADIA7 | AK16: 7 625 000.00 | AL16: 9 150 000.00 | AN16: 46253 | AO16: 0000-00-00 | AP16: Location LCD-Mission Tafita à Nosy Be 24 Août au 17 Sept2026 | AQ16: YASSIE | AR16: YASSIE | AS16: C800 | AT16: E215_DSI | AU16: DSI | AV16: STD | AY16: E | AZ16: E | BA16: RAVONINJATOVO Nadia | BD16: 2057 | BE16: C800 | BF16: 629 | BG16: 3 | BH16: 2026-08-17
A17: 136197 | B17: HUAWEI TECHNOLOGIES (MADAGASCAR) S.A.R.L.U | C17: REMISE | D17: One Time Strategy Discount | E17: 1 | F17: UN | G17: 386341.54 | I17: =E17*G17 -> 386341.54 | J17: 386341.54 | N17: EUR | O17: 0 | P17: 46240 | Q17: 2026-08-10 | R17: 139430 | U17: -463 609.85 | V17: 20 | W17: 2 | Y17: GELACCS | Z17: True | AA17: DTG | AB17: 2026-DT-012001 | AC17: DTG | AD17: NA | AF17: 1 | AG17: -386 341.54 | AH17: YASMG | AJ17: ELIE3 | AK17: 305 765.08 | AL17: 366 918.09 | AN17: 46240 | AO17: 0000-00-00 | AP17: 4G Capacity Expansion Q2-Q42026-TANA(Service) | AQ17: YASSIE | AR17: YASSIE | AS17: C500 | AT17: 2026-DT-012001 | AU17: DTG | AV17: STD | AY17: E | AZ17: E | BA17: ANDRIAMANANTSOA Elie | BB17: RASAMOELINA Haritsoa Oliva | BD17: 2057 | BE17: C500 | BF17: 2071 | BG17: 2 | BH17: 2026-08-17
A18: 136523 | B18: TECHNI-FROID MADAGASCAR | C18: REMISE | D18: Remise 10% | E18: 1 | F18: UN | G18: 442320 | I18: =E18*G18 -> 442320 | J18: 442320 | N18: MGA | O18: 0 | P18: 46261 | Q18: 2026-08-27 | R18: 139741 | U18: -530 784.00 | V18: 20 | W18: 2 | Y18: GELACCS | Z18: True | AA18: DTG | AB18: 2026-DT-091001 | AC18: DTG-PROJETS | AD18: NA | AF18: 1 | AG18: -442 320.00 | AH18: YASMG | AJ18: ELIE3 | AK18: 3 980 880.00 | AL18: 4 777 056.00 | AN18: 46261 | AO18: 0000-00-00 | AP18: libération salle OCB R+1 et supervision ANM002 | AQ18: YASSIE | AR18: YASSIE | AS18: C500 | AT18: 2026-DT-091001 | AU18: DTG-PROJETS | AV18: STD | AY18: E | AZ18: E | BA18: ANDRIAMANANTSOA Elie | BB18: RASAMOELINA Haritsoa Oliva | BD18: 2057 | BE18: C500 | BF18: 1175 | BG18: 2 | BH18: 2026-08-31
A19: 136483 | B19: PRIMA CE SARLU | C19: REMISE | D19: Remise | E19: 1 | F19: UN | G19: 811080 | I19: =E19*G19 -> 811080 | J19: 811080 | N19: MGA | O19: 0 | P19: 46259 | Q19: 2026-08-25 | R19: 139618 | U19: -973 296.00 | V19: 20 | W19: 6 | Y19: GELACCS | Z19: True | AA19: DTG | AB19: 2026-DT-022001 | AC19: DTG-PROJETS | AD19: NA | AF19: 0 | AG19: 0.00 | AH19: YASMG | AJ19: ELIE3 | AK19: 4 596 120.00 | AL19: 5 515 344.00 | AN19: 46259 | AO19: 0000-00-00 | AP19: TS-TX GC FO sur ATS205 ZEBU TOA STAR | AQ19: YASSIE | AR19: YASSIE | AS19: C500 | AT19: 2026-DT-022001 | AU19: DTG-PROJETS | AV19: STD | AY19: L | AZ19: S | BA19: ANDRIAMANANTSOA Elie | BB19: RASAMOELINA Haritsoa Oliva | BD19: 2057 | BE19: C500 | BF19: 2633 | BG19: 6 | BH19: 0000-00-00
A20: 136226 | B20: HUAWEI INTERNATIONAL CO. LIMITED | C20: REMISE | D20: One Time Strategy Discount | E20: 1 | F20: UN | G20: 901019.57 | I20: =E20*G20 -> 901019.57 | J20: 901019.57 | N20: EUR | O20: 0 | P20: 46241 | Q20: 2026-08-10 | R20: 139450 | U20: -901 019.57 | V20: 0 | W20: 14 | Y20: GELACCS | Z20: True | AA20: DTG | AB20: 2026-DT-012001 | AC20: DTG | AD20: NA | AF20: 1 | AG20: -901 019.57 | AH20: YASMG | AJ20: ELIE3 | AK20: 141 878.71 | AL20: 141 878.71 | AN20: 46241 | AO20: 0000-00-00 | AP20: 4G Capacity Expansion Q2-Q4 2026-TANA(Hardware) | AQ20: YASSIE | AR20: GALE | AS20: C500 | AT20: 2026-DT-012001 | AU20: DTG | AV20: IMPORT | AY20: E | AZ20: E | BA20: ANDRIAMANANTSOA Elie | BB20: RASAMOELINA Haritsoa Oliva | BD20: 2057 | BE20: C500 | BF20: 2072 | BG20: 14 | BH20: 2026-08-28
A21: 136479 | B21: GLOBAL CONSTRUCTION MADAGASCAR | C21: REMISE | D21: Remise | E21: 1 | F21: UN | G21: 1302660 | I21: =E21*G21 -> 1302660 | J21: 1302660 | N21: MGA | O21: 0 | P21: 46259 | Q21: 2026-08-25 | R21: 139635 | U21: -1 563 192.00 | V21: 20 | W21: 2 | Y21: GELACCS | Z21: True | AA21: DTG | AB21: 2026-DT-091006 | AC21: DTG-PROJETS | AD21: NA | AF21: 1 | AG21: -1 302 660.00 | AH21: YASMG | AJ21: ELIE3 | AK21: 3 039 540.00 | AL21: 3 647 448.00 | AN21: 46259 | AO21: 0000-00-00 | AP21: Survey-Réhabilitation infra 2026-SAV003 | AQ21: YASSIE | AR21: YASSIE | AS21: C500 | AT21: 2026-DT-091006 | AU21: DTG-PROJETS | AV21: STD | AY21: E | AZ21: E | BA21: ANDRIAMANANTSOA Elie | BB21: RASAMOELINA Haritsoa Oliva | BD21: 2057 | BE21: C500 | BF21: 2404 | BG21: 2 | BH21: 2026-08-21
A22: 136481 | B22: GLOBAL CONSTRUCTION MADAGASCAR | C22: REMISE | D22: Remise | E22: 1 | F22: UN | G22: 1337940 | I22: =E22*G22 -> 1337940 | J22: 1337940 | N22: MGA | O22: 0 | P22: 46259 | Q22: 2026-08-25 | R22: 139636 | U22: -1 605 528.00 | V22: 20 | W22: 2 | Y22: GELACCS | Z22: True | AA22: DTG | AB22: 2026-DT-091006 | AC22: DTG-PROJETS | AD22: NA | AF22: 1 | AG22: -1 337 940.00 | AH22: YASMG | AJ22: ELIE3 | AK22: 3 121 860.00 | AL22: 3 746 232.00 | AN22: 46259 | AO22: 0000-00-00 | AP22: Survey-Réhabilitation infra 2026-SAV018 | AQ22: YASSIE | AR22: YASSIE | AS22: C500 | AT22: 2026-DT-091006 | AU22: DTG-PROJETS | AV22: STD | AY22: E | AZ22: E | BA22: ANDRIAMANANTSOA Elie | BB22: RASAMOELINA Haritsoa Oliva | BD22: 2057 | BE22: C500 | BF22: 2404 | BG22: 2 | BH22: 2026-08-21
A23: 136310 | B23: PRIMA CE SARLU | C23: REMISE | D23: Remise 7% | E23: 1 | F23: UN | G23: 1350300 | I23: =E23*G23 -> 1350300 | J23: 1350300 | N23: MGA | O23: 0 | P23: 46247 | Q23: 2026-08-13 | R23: 139424 | U23: -1 620 360.00 | V23: 20 | W23: 5 | Y23: GELACCS | Z23: True | AA23: DTG | AB23: 2026-DT-022001 | AC23: DTG-PROJETS | AD23: NA | AF23: 1 | AG23: -1 350 300.00 | AH23: YASMG | AJ23: ELIE3 | AK23: 17 939 700.00 | AL23: 21 527 640.00 | AN23: 46247 | AO23: 0000-00-00 | AP23: TX GC FO sur AAT067 FENOAMBANY | AQ23: YASSIE | AR23: YASSIE | AS23: C500 | AT23: 2026-DT-022001 | AU23: DTG-PROJETS | AV23: STD | AY23: E | AZ23: E | BA23: ANDRIAMANANTSOA Elie | BB23: RASAMOELINA Haritsoa Oliva | BD23: 2057 | BE23: C500 | BF23: 2633 | BG23: 5 | BH23: 0000-00-00
A24: 136480 | B24: GLOBAL CONSTRUCTION MADAGASCAR | C24: REMISE | D24: Remise | E24: 1 | F24: UN | G24: 1383970 | I24: =E24*G24 -> 1383970 | J24: 1383970 | N24: MGA | O24: 0 | P24: 46259 | Q24: 2026-08-25 | R24: 139637 | U24: -1 660 764.00 | V24: 20 | W24: 2 | Y24: GELACCS | Z24: True | AA24: DTG | AB24: 2026-DT-091006 | AC24: DTG-PROJETS | AD24: NA | AF24: 1 | AG24: -1 383 970.00 | AH24: YASMG | AJ24: ELIE3 | AK24: 2 570 230.00 | AL24: 3 084 276.00 | AN24: 46259 | AO24: 0000-00-00 | AP24: Survey-réhabilitation infra 2026-SOF001 | AQ24: YASSIE | AR24: YASSIE | AS24: C500 | AT24: 2026-DT-091006 | AU24: DTG-PROJETS | AV24: STD | AY24: E | AZ24: E | BA24: ANDRIAMANANTSOA Elie | BB24: RASAMOELINA Haritsoa Oliva | BD24: 2057 | BE24: C500 | BF24: 2404 | BG24: 2 | BH24: 2026-08-21
A25: 136314 | B25: EASY NETCOM | C25: REMISE | D25: Remise 10% # Devis Réf :026/05846/ENC-HR | E25: 1 | F25: UN | G25: 1964195 | I25: =E25*G25 -> 1964195 | J25: 1964195 | N25: MGA | O25: 0 | P25: 46247 | Q25: 2026-08-14 | R25: 139442 | U25: -2 357 034.00 | V25: 20 | W25: 5 | Y25: GELACCS | Z25: True | AA25: DTG | AB25: 2026-DT-022001 | AC25: DTG-PROJETS | AD25: NA | AF25: 1 | AG25: -1 964 195.00 | AH25: YASMG | AJ25: ELIE3 | AK25: 17 677 753.00 | AL25: 21 213 303.60 | AN25: 46247 | AO25: 0000-00-00 | AP25: TX GC FO sur SOF228 BEKORATSAKA | AQ25: YASSIE | AR25: YASSIE | AS25: C500 | AT25: 2026-DT-022001 | AU25: DTG-PROJETS | AV25: STD | AY25: L | AZ25: E | BA25: ANDRIAMANANTSOA Elie | BB25: RASAMOELINA Haritsoa Oliva | BD25: 2057 | BE25: C500 | BF25: 2053 | BG25: 5 | BH25: 0000-00-00
A26: 136404 | B26: AVRA BTP | C26: REMISE | D26: Remise # DEVIS N° 208/2026 - INDICE A | E26: 1 | F26: UN | G26: 3659153 | I26: =E26*G26 -> 3659153 | J26: 3659153 | N26: MGA | O26: 0 | P26: 46253 | Q26: 2026-08-19 | R26: 139596 | U26: -3 659 153.00 | V26: 0 | W26: 4 | Y26: GELACCS | Z26: True | AA26: DTG | AB26: 2026-DT-091001 | AC26: DTG-PROJETS | AD26: NA | AF26: 1 | AG26: -3 659 153.00 | AH26: YASMG | AJ26: ELIE3 | AK26: 14 000 000.00 | AL26: 14 000 000.00 | AN26: 46253 | AO26: 0000-00-00 | AP26: Création cloison salle CDMA au RDC Analakely | AQ26: YASSIE | AR26: YASSIE | AS26: C500 | AT26: 2026-DT-091001 | AU26: DTG-PROJETS | AV26: STD | AY26: E | AZ26: E | BA26: ANDRIAMANANTSOA Elie | BB26: RASAMOELINA Haritsoa Oliva | BD26: 2057 | BE26: C500 | BF26: 4038 | BG26: 4 | BH26: 2026-08-26
A27: 136391 | B27: SOCIETE ML STONE | C27: REMISE | D27: Remise | E27: 1 | F27: UN | G27: 39936223 | I27: =E27*G27 -> 39936223 | J27: 39936223 | N27: MGA | O27: 0 | P27: 46253 | Q27: 2026-08-19 | R27: 139597 | U27: -47 923 467.60 | V27: 20 | W27: 2 | Y27: GELACCS | Z27: True | AA27: DTG | AB27: 2026-DT-091006 | AC27: DTG-PROJETS | AD27: NA | AF27: 1 | AG27: -39 936 223.00 | AH27: YASMG | AJ27: ELIE3 | AK27: 220 000 000.00 | AL27: 264 000 000.00 | AN27: 46253 | AO27: 0000-00-00 | AP27: Réhablitation total Infra -BET012 Maevatanana | AQ27: YASSIE | AR27: YASSIE | AS27: C500 | AT27: 2026-DT-091006 | AU27: DTG-PROJETS | AV27: STD | AY27: E | AZ27: E | BA27: ANDRIAMANANTSOA Elie | BB27: RASAMOELINA Haritsoa Oliva | BD27: 2057 | BE27: C500 | BF27: 1103 | BG27: 2 | BH27: 2026-08-28
A28: 136391 | B28: SOCIETE ML STONE | C28: REMISE | D28: 2eme Remise | E28: 1 | F28: UN | G28: 47265496 | I28: =E28*G28 -> 47265496 | J28: 47265496 | N28: MGA | O28: 0 | P28: 46253 | Q28: 2026-08-19 | R28: 139597 | U28: -56 718 595.20 | V28: 20 | W28: 3 | Y28: GELACCS | Z28: True | AA28: DTG | AB28: 2026-DT-091006 | AC28: DTG-PROJETS | AD28: NA | AF28: 1 | AG28: -47 265 496.00 | AH28: YASMG | AJ28: ELIE3 | AK28: 220 000 000.00 | AL28: 264 000 000.00 | AN28: 46253 | AO28: 0000-00-00 | AP28: Réhablitation total Infra -BET012 Maevatanana | AQ28: YASSIE | AR28: YASSIE | AS28: C500 | AT28: 2026-DT-091006 | AU28: DTG-PROJETS | AV28: STD | AY28: E | AZ28: E | BA28: ANDRIAMANANTSOA Elie | BB28: RASAMOELINA Haritsoa Oliva | BD28: 2057 | BE28: C500 | BF28: 1103 | BG28: 3 | BH28: 2026-08-28
... A34: 136387 | B34: AVRA BTP | C34: REMISE | D34: Remise # DEVIS N° 151/2026- Indice : A | E34: 1 | F34: UN | G34: 153872414 | I34: =E34*G34 -> 153872414 | J34: 153872414 | N34: MGA | O34: 0 | P34: 46252 | Q34: 2026-08-18 | R34: 139601 | U34: -153 872 414.00 | V34: 0 | W34: 5 | Y34: GELACCS | Z34: True | AA34: DTG | AB34: 2026-DT-091006 | AC34: DTG-PROJETS | AD34: NA | AF34: 1 | AG34: -153 872 414.00 | AH34: YASMG | AJ34: ELIE3 | AK34: 514 000 000.00 | AL34: 514 000 000.00 | AN34: 46252 | AO34: 0000-00-00 | AP34: Constrution nouveau bâtiment Admin DIA032 Ambanja | AQ34: YASSIE | AR34: YASSIE | AS34: C500 | AT34: 2026-DT-091006 | AU34: DTG-PROJETS | AV34: STD | AY34: E | AZ34: E | BA34: ANDRIAMANANTSOA Elie | BB34: RASAMOELINA Haritsoa Oliva | BD34: 2057 | BE34: C500 | BF34: 4038 | BG34: 5 | BH34: 2026-08-31
A35: 136527 | B35: NETIS HOLDING LTD | C35: 1 x SC/APC Adapter+Pigtail SC/APC G657A2 0,9um d 30cm PTO | D35: PTO - with YAS Branding - 1 x SC/APC Adapter + Pigtail SC/APC G657A2 0,9µm diameter 30cm # PI N° : YAS-2026-08-14-001 | E35: 2800 | F35: UN | G35: 0.99 | I35: =E35*G35 -> 2772 | N35: USD | O35: 0 | P35: 46261 | Q35: 2026-08-31 | R35: 139746 | U35: 2 772.00 | V35: 0 | W35: 1 | Y35: RESCBIA | Z35: True | AA35: DTG | AB35: 2026-DT-101001 | AC35: DTG-DSTC-INSTA | AD35: NA | AF35: 2800 | AG35: 2 772.00 | AH35: YASMG | AJ35: ELIE3 | AK35: 2 772.00 | AL35: 2 772.00 | AN35: 46261 | AO35: 0000-00-00 | AP35: Achat 2800 PTO | AQ35: YASSIE | AR35: GALE | AS35: C500 | AT35: 2026-DT-101001 | AU35: DTG-DSTC-INSTA | AV35: IMPORT | AY35: E | AZ35: E | BA35: ANDRIAMANANTSOA Elie | BB35: RASAMOELINA Haritsoa Oliva | BD35: 22709 | BE35: C500 | BF35: 5097 | BG35: 1 | BH35: 2026-08-31
A36: 136225 | B36: HUAWEI TECHNOLOGIES CO., LTD | C36: LICENCE DE LOGICIELS | D36: RRC Connected User for LTE TDD (per RRC Connected User) | E36: 14280 | F36: UN | G36: 2.7164 | I36: =E36*G36 -> 38790.192 | N36: EUR | O36: 0 | P36: 46241 | Q36: 2026-08-10 | R36: 139420 | U36: 38 790.19 | V36: 0 | W36: 9 | Y36: DOCLICD | Z36: True | AA36: DTG | AB36: 2026-DT-012001 | AC36: DTG | AD36: NA | AF36: 14280 | AG36: 38 790.19 | AH36: YASMG | AJ36: ELIE3 | AK36: 146 965.82 | AL36: 146 965.82 | AN36: 46241 | AO36: 0000-00-00 | AP36: 4G Capacity Expansion Q2-Q4 2026-TANA(Software) | AQ36: YASSIE | AR36: YASSIE | AS36: C500 | AT36: 2026-DT-012001 | AU36: DTG | AV36: IMPORT | AY36: E | AZ36: E | BA36: ANDRIAMANANTSOA Elie | BB36: RASAMOELINA Haritsoa Oliva | BD36: 1548 | BE36: C500 | BF36: 3621 | BG36: 9 | BH36: 2026-08-12
A37: 136252 | B37: SHENZHEN SOPTO TECHNOLOGY CO LTD | C37: Fiber Cleaner SC type for SC/FC/ST connector SP TKFSM1.25/2. | D37: Fiber Cleaner SC type for SC/FC/ST connector SPTK-FSM-2.5 SC # Quotation No.: QS260731004 | E37: 150 | F37: PIE | G37: 2.84 | I37: =E37*G37 -> 426 | N37: USD | O37: 0 | P37: 46244 | Q37: 2026-08-10 | R37: 139452 | U37: 426.00 | V37: 0 | W37: 1 | Y37: RESCBLT | Z37: True | AA37: DTG | AB37: 2026-DT-103001 | AC37: DTG-DSTC-INSTA | AD37: NA | AF37: 150 | AG37: 426.00 | AH37: YASMG | AJ37: ELIE3 | AK37: 1 177.00 | AL37: 1 177.00 | AM37: F | AN37: 46244 | AO37: 0000-00-00 | AP37: Achat stylos de nettoyage pour fibre | AQ37: YASSIE | AR37: GALE | AS37: C500 | AT37: 2026-DT-103001 | AU37: DTG-DSTC-INSTA | AV37: IMPORT | AY37: E | AZ37: E | BA37: ANDRIAMANANTSOA Elie | BB37: RASAMOELINA Haritsoa Oliva | BD37: 9902 | BE37: C500 | BF37: 2747 | BG37: 1 | BH37: 2026-08-20
A38: 136252 | B38: SHENZHEN SOPTO TECHNOLOGY CO LTD | C38: Fiber Cleaner LC type SPTK-FSM-1.25-LC | D38: Fiber Cleaner LC type SPTK-FSM-1.25-LC # Quotation No.: QS260731004 | E38: 150 | F38: UN | G38: 2.84 | I38: =E38*G38 -> 426 | N38: USD | O38: 0 | P38: 46244 | Q38: 2026-08-10 | R38: 139452 | U38: 426.00 | V38: 0 | W38: 2 | Y38: RESCBLT | Z38: True | AA38: DTG | AB38: 2026-DT-103001 | AC38: DTG-DSTC-INSTA | AD38: NA | AF38: 150 | AG38: 426.00 | AH38: YASMG | AJ38: ELIE3 | AK38: 1 177.00 | AL38: 1 177.00 | AM38: F | AN38: 46244 | AO38: 0000-00-00 | AP38: Achat stylos de nettoyage pour fibre | AQ38: YASSIE | AR38: GALE | AS38: C500 | AT38: 2026-DT-103001 | AU38: DTG-DSTC-INSTA | AV38: IMPORT | AY38: E | AZ38: E | BA38: ANDRIAMANANTSOA Elie | BB38: RASAMOELINA Haritsoa Oliva | BD38: 31344 | BE38: C500 | BF38: 2747 | BG38: 2 | BH38: 2026-08-20
A39: 136389 | B39: GREENLIGHT PLANET | C39: Sun King 2 Mid Clamp 300mm | D39: Sun King 2*Mid Clamp/300mm Mini Rail for30mm Solar Panel - PI N° USQT260100000041 | E39: 100 | F39: UN | G39: 3.57 | I39: =E39*G39 -> 357 | N39: USD | O39: 0 | P39: 46253 | Q39: 2026-08-19 | R39: 139649 | U39: 357.00 | V39: 0 | W39: 10 | Y39: VENDABL | Z39: True | AA39: DCG | AB39: CM_MBL_DCG | AC39: DCG-SHS | AD39: NA | AF39: 100 | AG39: 357.00 | AH39: YASMG | AJ39: FELANA13 | AK39: 3 855 843.70 | AL39: 3 855 843.70 | AM39: F | AN39: 46253 | AO39: 0000-00-00 | AP39: Réappro H2 - Mbalik | AQ39: YASSIE | AR39: GAL | AS39: C100 | AT39: CM_MBL_DCG | AU39: DCG-SHS | AV39: IMPORT | AY39: E | AZ39: E | BA39: Felana RARIVOSON | BB39: ANDRIAMIRIJA Luca | BD39: 31408 | BE39: C100 | BF39: 2411 | BG39: 10 | BH39: 2026-08-31
A40: 136388 | B40: VOYAGEXPERT | C40: BILLET D 'AVION | D40: Frais émis aérien long courrier_ N° pièce F-68 0049062 sur vol AR TANA/NAIROBI# FACTURE N° F-068 0053086 DU 02/06/2026 | E40: 1 | F40: UN | G40: 4 | I40: =E40*G40 -> 4 | N40: EUR | O40: 0 | P40: 46253 | Q40: 2026-08-19 | R40: 139672 | U40: 3.60 | V40: -10 | W40: 1 | Y40: VDPBILL | Z40: False | AA40: DG | AB40: E215_DG | AC40: DG | AD40: NA | AF40: 0 | AG40: 0.00 | AH40: YASMG | AJ40: NADIA7 | AK40: 4.00 | AL40: 3.60 | AM40: F | AN40: 46253 | AO40: 0000-00-00 | AP40: Frais émis_N° pièce F-68 0049062 | AQ40: YASSIE | AR40: YASSIE | AS40: C900 | AT40: E215_DG | AU40: DG | AV40: IMPORT | AY40: S | AZ40: S | BA40: RAVONINJATOVO Nadia | BB40: RASOLOJAONA Miora | BD40: 1250 | BE40: C900 | BF40: 6711 | BG40: 1 | BH40: 2026-08-18
A41: 136496 | B41: VOYAGEXPERT | C41: VOYAGE | D41: Régul frais Voyagexpert Paris - DRH F-068 0052271# FACTURE N° F-068 0053086 DU 02/06/2026 | E41: 1 | F41: PIE | G41: 4 | I41: =E41*G41 -> 4 | N41: EUR | O41: 0 | P41: 46260 | Q41: 2026-08-26 | R41: 139674 | U41: 3.60 | V41: -10 | W41: 1 | Y41: VDPTRPP | Z41: True | AA41: DRH | AB41: E215_DRH | AC41: DRH-ADMIN | AD41: NA | AF41: 1 | AG41: 4.00 | AH41: YASMG | AJ41: NADIA7 | AK41: 4.00 | AL41: 3.60 | AM41: F | AN41: 46260 | AO41: 0000-00-00 | AQ41: YASSIE | AR41: YASSIE | AS41: C600 | AT41: E215_DRH | AU41: DRH-ADMIN | AV41: IMPORT | AY41: E | AZ41: E | BA41: RAVONINJATOVO Nadia | BB41: ANDRIANINA Rebecca | BD41: 12640 | BE41: C600 | BF41: 6711 | BG41: 1 | BH41: 2026-08-18
A42: 136225 | B42: HUAWEI TECHNOLOGIES CO., LTD | C42: LICENCE DE LOGICIELS | D42: UBBP Massive MIMO Extended Channel 1*16T16R License (FDD) | E42: 231 | F42: UN | G42: 6.08969 | I42: =E42*G42 -> 1406.7184 | N42: EUR | O42: 0 | P42: 46241 | Q42: 2026-08-10 | R42: 139420 | U42: 1 406.72 | V42: 0 | W42: 7 | Y42: DOCLICD | Z42: True | AA42: DTG | AB42: 2026-DT-012001 | AC42: DTG | AD42: NA | AF42: 231 | AG42: 1 406.72 | AH42: YASMG | AJ42: ELIE3 | AK42: 146 965.82 | AL42: 146 965.82 | AN42: 46241 | AO42: 0000-00-00 | AP42: 4G Capacity Expansion Q2-Q4 2026-TANA(Software) | AQ42: YASSIE | AR42: YASSIE | AS42: C500 | AT42: 2026-DT-012001 | AU42: DTG | AV42: IMPORT | AY42: E | AZ42: E | BA42: ANDRIAMANANTSOA Elie | BB42: RASAMOELINA Haritsoa Oliva | BD42: 1548 | BE42: C500 | BF42: 3621 | BG42: 7 | BH42: 2026-08-12
A43: 136225 | B43: HUAWEI TECHNOLOGIES CO., LTD | C43: LICENCE DE LOGICIELS | D43: UBBP Massive MIMO Extended Channel 1*16T16R License (TDD)(per 16T16R) | E43: 102 | F43: UN | G43: 6.08969 | I43: =E43*G43 -> 621.14838 | N43: EUR | O43: 0 | P43: 46241 | Q43: 2026-08-10 | R43: 139420 | U43: 621.15 | V43: 0 | W43: 15 | Y43: DOCLICD | Z43: True | AA43: DTG | AB43: 2026-DT-012001 | AC43: DTG | AD43: NA | AF43: 102 | AG43: 621.15 | AH43: YASMG | AJ43: ELIE3 | AK43: 146 965.82 | AL43: 146 965.82 | AN43: 46241 | AO43: 0000-00-00 | AP43: 4G Capacity Expansion Q2-Q4 2026-TANA(Software) | AQ43: YASSIE | AR43: YASSIE | AS43: C500 | AT43: 2026-DT-012001 | AU43: DTG | AV43: IMPORT | AY43: E | AZ43: E | BA43: ANDRIAMANANTSOA Elie | BB43: RASAMOELINA Haritsoa Oliva | BD43: 1548 | BE43: C500 | BF43: 3621 | BG43: 15 | BH43: 2026-08-12
A44: 136225 | B44: HUAWEI TECHNOLOGIES CO., LTD | C44: LICENCE DE LOGICIELS | D44: BB Transmit Channel (per Channel) | E44: 16 | F44: UN | G44: 6.28542 | I44: =E44*G44 -> 100.56672 | N44: EUR | O44: 0 | P44: 46241 | Q44: 2026-08-10 | R44: 139420 | U44: 100.57 | V44: 0 | W44: 3 | Y44: DOCLICD | Z44: True | AA44: DTG | AB44: 2026-DT-012001 | AC44: DTG | AD44: NA | AF44: 16 | AG44: 100.57 | AH44: YASMG | AJ44: ELIE3 | AK44: 146 965.82 | AL44: 146 965.82 | AN44: 46241 | AO44: 0000-00-00 | AP44: 4G Capacity Expansion Q2-Q4 2026-TANA(Software) | AQ44: YASSIE | AR44: YASSIE | AS44: C500 | AT44: 2026-DT-012001 | AU44: DTG | AV44: IMPORT | AY44: E | AZ44: E | BA44: ANDRIAMANANTSOA Elie | BB44: RASAMOELINA Haritsoa Oliva | BD44: 1548 | BE44: C500 | BF44: 3621 | BG44: 3 | BH44: 2026-08-12
A45: 136225 | B45: HUAWEI TECHNOLOGIES CO., LTD | C45: LICENCE DE LOGICIELS | D45: BB Receive Channel (per Channel) | E45: 16 | F45: UN | G45: 6.28542 | I45: =E45*G45 -> 100.56672 | N45: EUR | O45: 0 | P45: 46241 | Q45: 2026-08-10 | R45: 139420 | U45: 100.57 | V45: 0 | W45: 4 | Y45: DOCLICD | Z45: True | AA45: DTG | AB45: 2026-DT-012001 | AC45: DTG | AD45: NA | AF45: 16 | AG45: 100.57 | AH45: YASMG | AJ45: ELIE3 | AK45: 146 965.82 | AL45: 146 965.82 | AN45: 46241 | AO45: 0000-00-00 | AP45: 4G Capacity Expansion Q2-Q4 2026-TANA(Software) | AQ45: YASSIE | AR45: YASSIE | AS45: C500 | AT45: 2026-DT-012001 | AU45: DTG | AV45: IMPORT | AY45: E | AZ45: E | BA45: ANDRIAMANANTSOA Elie | BB45: RASAMOELINA Haritsoa Oliva | BD45: 1548 | BE45: C500 | BF45: 3621 | BG45: 4 | BH45: 2026-08-12
A46: 136389 | B46: GREENLIGHT PLANET | C46: Sun King 4 End Clamp 300mm Mini Rail for 30mm Solar Panel | D46: Sun King 4*End Clamp/300mm Mini Rail for30mm Solar Panel - PI N° USQT260100000041 | E46: 40 | F46: UN | G46: 6.77 | I46: =E46*G46 -> 270.8 | N46: USD | O46: 0 | P46: 46253 | Q46: 2026-08-19 | R46: 139649 | U46: 270.80 | V46: 0 | W46: 9 | Y46: VENDABL | Z46: True | AA46: DCG | AB46: CM_MBL_DCG | AC46: DCG-SHS | AD46: NA | AF46: 40 | AG46: 270.80 | AH46: YASMG | AJ46: FELANA13 | AK46: 3 855 843.70 | AL46: 3 855 843.70 | AM46: F | AN46: 46253 | AO46: 0000-00-00 | AP46: Réappro H2 - Mbalik | AQ46: YASSIE | AR46: GAL | AS46: C100 | AT46: CM_MBL_DCG | AU46: DCG-SHS | AV46: IMPORT | AY46: E | AZ46: E | BA46: Felana RARIVOSON | BB46: ANDRIAMIRIJA Luca | BD46: 31407 | BE46: C100 | BF46: 2411 | BG46: 9 | BH46: 2026-08-31
A47: 136389 | B47: GREENLIGHT PLANET | C47: SUN KING TORCH W-O PANEL | D47: Sun King Torch - PI N° USQT260100000041 | E47: 5050 | F47: UN | G47: 7.45 | I47: =E47*G47 -> 37622.5 | N47: USD | O47: 0 | P47: 46253 | Q47: 2026-08-19 | R47: 139649 | U47: 37 622.50 | V47: 0 | W47: 6 | Y47: VENDABL | Z47: True | AA47: DCG | AB47: CM_MBL_DCG | AC47: DCG-SHS | AD47: NA | AF47: 5050 | AG47: 37 622.50 | AH47: YASMG | AJ47: FELANA13 | AK47: 3 855 843.70 | AL47: 3 855 843.70 | AM47: F | AN47: 46253 | AO47: 0000-00-00 | AP47: Réappro H2 - Mbalik | AQ47: YASSIE | AR47: GAL | AS47: C100 | AT47: CM_MBL_DCG | AU47: DCG-SHS | AV47: IMPORT | AY47: E | AZ47: E | BA47: Felana RARIVOSON | BB47: ANDRIAMIRIJA Luca | BD47: 21127 | BE47: C100 | BF47: 2411 | BG47: 6 | BH47: 2026-08-31
A48: 136226 | B48: HUAWEI INTERNATIONAL CO. LIMITED | C48: Top Jumper Cable Unit for 2T/4T 4.3-10 Interface RRU-with co | D48: Top Jumper Cable Unit for 2T/4T 4.3-10 Interface RRU-with cold shrink sealing sleeve | E48: 16 | F48: UN | G48: 8.40105 | I48: =E48*G48 -> 134.4168 | N48: EUR | O48: 0 | P48: 46241 | Q48: 2026-08-10 | R48: 139450 | U48: 134.42 | V48: 0 | W48: 7 | Y48: PRMEQUI | Z48: True | AA48: DTG | AB48: 2026-DT-012001 | AC48: DTG | AD48: NA | AF48: 16 | AG48: 134.42 | AH48: YASMG | AJ48: ELIE3 | AK48: 141 878.71 | AL48: 141 878.71 | AN48: 46241 | AO48: 0000-00-00 | AP48: 4G Capacity Expansion Q2-Q4 2026-TANA(Hardware) | AQ48: YASSIE | AR48: GALE | AS48: C500 | AT48: 2026-DT-012001 | AU48: DTG | AV48: IMPORT | AY48: E | AZ48: E | BA48: ANDRIAMANANTSOA Elie | BB48: RASAMOELINA Haritsoa Oliva | BD48: 26044 | BE48: C500 | BF48: 2072 | BG48: 7 | BH48: 2026-08-28
A49: 136389 | B49: GREENLIGHT PLANET | C49: Sun King PowerHub 5000 0.3m Busbar | D49: Sun King PowerHub 5000 0.3m Busba - PI N° USQT260100000041 | E49: 40 | F49: UN | G49: 15.84 | I49: =E49*G49 -> 633.6 | N49: USD | O49: 0 | P49: 46253 | Q49: 2026-08-19 | R49: 139649 | U49: 633.60 | V49: 0 | W49: 11 | Y49: VENDABL | Z49: True | AA49: DCG | AB49: CM_MBL_DCG | AC49: DCG-SHS | AD49: NA | AF49: 40 | AG49: 633.60 | AH49: YASMG | AJ49: FELANA13 | AK49: 3 855 843.70 | AL49: 3 855 843.70 | AM49: F | AN49: 46253 | AO49: 0000-00-00 | AP49: Réappro H2 - Mbalik | AQ49: YASSIE | AR49: GAL | AS49: C100 | AT49: CM_MBL_DCG | AU49: DCG-SHS | AV49: IMPORT | AY49: E | AZ49: E | BA49: Felana RARIVOSON | BB49: ANDRIAMIRIJA Luca | BD49: 31406 | BE49: C100 | BF49: 2411 | BG49: 11 | BH49: 2026-08-31
A50: 136389 | B50: GREENLIGHT PLANET | C50: SK-324 BOOM GEN 2 EB | D50: Sun King Boom Gen 2 EasyBuy Solar Lantern - PI N° USQT260100000041 | E50: 5050 | F50: UN | G50: 20.28 | I50: =E50*G50 -> 102414 | N50: USD | O50: 0 | P50: 46253 | Q50: 2026-08-19 | R50: 139649 | U50: 102 414.00 | V50: 0 | W50: 1 | Y50: VENDABL | Z50: True | AA50: DCG | AB50: CM_MBL_DCG | AC50: DCG-SHS | AD50: NA | AF50: 5050 | AG50: 102 414.00 | AH50: YASMG | AJ50: FELANA13 | AK50: 3 855 843.70 | AL50: 3 855 843.70 | AM50: F | AN50: 46253 | AO50: 0000-00-00 | AP50: Réappro H2 - Mbalik | AQ50: YASSIE | AR50: GAL | AS50: C100 | AT50: CM_MBL_DCG | AU50: DCG-SHS | AV50: IMPORT | AY50: E | AZ50: E | BA50: Felana RARIVOSON | BB50: ANDRIAMIRIJA Luca | BD50: 26100 | BE50: C100 | BF50: 2411 | BG50: 1 | BH50: 2026-08-31
A51: 136293 | B51: GDS LTD | C51: CHAISE PLASTIQUE - MBALIK - JUILLET 2026 | D51: CHAISE PLASTIQUE - MBALIK - JUILLET 2026 | E51: 148 | F51: UN | G51: 21.18 | I51: =E51*G51 -> 3134.64 | N51: USD | O51: 0 | P51: 46247 | Q51: 2026-08-13 | R51: 139400 | U51: 3 134.64 | V51: 0 | W51: 2 | Y51: PLVPLES | Z51: True | AA51: DCG | AB51: E110_TR_DCOM | AC51: DCG-COM | AD51: NA | AF51: 148 | AG51: 3 134.64 | AH51: YASMG | AJ51: FELANA13 | AK51: 20 777.22 | AL51: 20 777.22 | AN51: 46247 | AO51: 0000-00-00 | AP51: COMMANDE MBALIK 2026 | AQ51: YASSIE | AR51: GALE | AS51: C100 | AT51: E110_TR_DCOM | AU51: DCG-COM | AV51: IMPORT | AY51: E | AZ51: E | BA51: Felana RARIVOSON | BB51: RAZAFINDRAHAGA Setra | BD51: 31284 | BE51: C100 | BF51: 5176 | BG51: 2 | BH51: 2026-08-07
A52: 136225 | B52: HUAWEI TECHNOLOGIES CO., LTD | C52: LICENCE DE LOGICIELS | D52: 20W Power License for 5000 Series RF Module (FDD) | E52: 64 | F52: UN | G52: 25.50961 | I52: =E52*G52 -> 1632.615 | N52: EUR | O52: 0 | P52: 46241 | Q52: 2026-08-10 | R52: 139420 | U52: 1 632.62 | V52: 0 | W52: 21 | Y52: DOCLICD | Z52: True | AA52: DTG | AB52: 2026-DT-012001 | AC52: DTG | AD52: NA | AF52: 64 | AG52: 1 632.62 | AH52: YASMG | AJ52: ELIE3 | AK52: 146 965.82 | AL52: 146 965.82 | AN52: 46241 | AO52: 0000-00-00 | AP52: 4G Capacity Expansion Q2-Q4 2026-TANA(Software) | AQ52: YASSIE | AR52: YASSIE | AS52: C500 | AT52: 2026-DT-012001 | AU52: DTG | AV52: IMPORT | AY52: E | AZ52: E | BA52: ANDRIAMANANTSOA Elie | BB52: RASAMOELINA Haritsoa Oliva | BD52: 1548 | BE52: C500 | BF52: 3621 | BG52: 21 | BH52: 2026-08-12
A53: 136225 | B53: HUAWEI TECHNOLOGIES CO., LTD | C53: LICENCE DE LOGICIELS | D53: UMPT Multi Mode license(LTE TDD) (per UMPT) | E53: 34 | F53: UN | G53: 26.14281 | I53: =E53*G53 -> 888.85554 | N53: EUR | O53: 0 | P53: 46241 | Q53: 2026-08-10 | R53: 139420 | U53: 888.86 | V53: 0 | W53: 16 | Y53: DOCLICD | Z53: True | AA53: DTG | AB53: 2026-DT-012001 | AC53: DTG | AD53: NA | AF53: 34 | AG53: 888.86 | AH53: YASMG | AJ53: ELIE3 | AK53: 146 965.82 | AL53: 146 965.82 | AN53: 46241 | AO53: 0000-00-00 | AP53: 4G Capacity Expansion Q2-Q4 2026-TANA(Software) | AQ53: YASSIE | AR53: YASSIE | AS53: C500 | AT53: 2026-DT-012001 | AU53: DTG | AV53: IMPORT | AY53: E | AZ53: E | BA53: ANDRIAMANANTSOA Elie | BB53: RASAMOELINA Haritsoa Oliva | BD53: 1548 | BE53: C500 | BF53: 3621 | BG53: 16 | BH53: 2026-08-12
A54: 136059 | B54: SIGN | C54: STICKERS AUTOCOLLANT - MBALIK - JUILLET 2025 | D54: Stickers Home Plus - 3,5x2 cm (sticker pour cacher logo Sunking sur l'image du boîtier du facing) - suivant proforma N° FP05186 | E54: 30500 | F54: UN | G54: 28 | I54: =E54*G54 -> 854000 | N54: MGA | O54: 0 | P54: 46237 | Q54: 2026-08-03 | R54: 139299 | U54: 1 024 800.00 | V54: 20 | W54: 4 | Y54: GELACCS | Z54: True | AA54: DCG | AB54: E110_TR_MBLK | AC54: DCG-SHS | AD54: NA | AF54: 30500 | AG54: 854 000.00 | AH54: YASMG | AJ54: FELANA13 | AK54: 39 000 000.00 | AL54: 46 800 000.00 | AN54: 46237 | AO54: 0000-00-00 | AP54: STICKERS MBALIK | AQ54: YASSIE | AR54: GALE | AS54: C100 | AT54: E110_TR_MBLK | AU54: DCG-SHS | AV54: STD | AY54: E | AZ54: E | BA54: Felana RARIVOSON | BB54: RAZAFINDRAHAGA Setra | BD54: 24694 | BE54: C100 | BF54: 1089 | BG54: 4 | BH54: 2026-07-29
A55: 136226 | B55: HUAWEI INTERNATIONAL CO. LIMITED | C55: DC Power Distribution Unit DCDU16D-02 | D55: DC Power Distribution Unit DCDU16D-02 | E55: 1 | F55: UN | G55: 31.21834 | I55: =E55*G55 -> 31.21834 | N55: EUR | O55: 0 | P55: 46241 | Q55: 2026-08-10 | R55: 139450 | U55: 31.22 | V55: 0 | W55: 11 | Y55: PRMEQUI | Z55: True | AA55: DTG | AB55: 2026-DT-012001 | AC55: DTG | AD55: NA | AF55: 1 | AG55: 31.22 | AH55: YASMG | AJ55: ELIE3 | AK55: 141 878.71 | AL55: 141 878.71 | AN55: 46241 | AO55: 0000-00-00 | AP55: 4G Capacity Expansion Q2-Q4 2026-TANA(Hardware) | AQ55: YASSIE | AR55: GALE | AS55: C500 | AT55: 2026-DT-012001 | AU55: DTG | AV55: IMPORT | AY55: E | AZ55: E | BA55: ANDRIAMANANTSOA Elie | BB55: RASAMOELINA Haritsoa Oliva | BD55: 24339 | BE55: C500 | BF55: 2072 | BG55: 11 | BH55: 2026-08-28
A56: 136320 | B56: AMPED INNOVATION | C56: WOW SOLAR 60 Solar Kit | D56: WOWsolar60 Solar Kit - PRO FORMA 1990 - PRO FORMA # 1990 DU 06/02/2026 | E56: 30000 | F56: UN | G56: 32.52 | I56: =E56*G56 -> 975600 | N56: USD | O56: 0 | P56: 46248 | Q56: 2026-08-14 | R56: 139593 | U56: 975 600.00 | V56: 0 | W56: 1 | Y56: PRMEQUI | Z56: True | AA56: DCG | AB56: CM_MBL_DCG | AC56: DCG-SHS | AD56: NA | AF56: 30000 | AG56: 975 600.00 | AH56: YASMG | AJ56: FELANA13 | AK56: 975 600.00 | AL56: 975 600.00 | AN56: 46248 | AO56: 0000-00-00 | AP56: Réappro H2 - WOWsolar60 | AQ56: YASSIE | AR56: GAL | AS56: C100 | AT56: CM_MBL_DCG | AU56: DCG-SHS | AV56: IMPORT | AY56: E | AZ56: E | BA56: Felana RARIVOSON | BB56: ANDRIAMIRIJA Luca | BD56: 20560 | BE56: C100 | BF56: 3293 | BG56: 1 | BH56: 2026-08-27
A57: 136389 | B57: GREENLIGHT PLANET | C57: SUN KING HOME PLUS | D57: Sun King HomePlus EasyBuy Solar Lamp System - PI N° USQT260100000041 | E57: 20200 | F57: UN | G57: 32.52 | I57: =E57*G57 -> 656904 | N57: USD | O57: 0 | P57: 46253 | Q57: 2026-08-19 | R57: 139649 | U57: 656 904.00 | V57: 0 | W57: 2 | Y57: VENDABL | Z57: True | AA57: DCG | AB57: CM_MBL_DCG | AC57: DCG-SHS | AD57: NA | AF57: 20200 | AG57: 656 904.00 | AH57: YASMG | AJ57: FELANA13 | AK57: 3 855 843.70 | AL57: 3 855 843.70 | AM57: F | AN57: 46253 | AO57: 0000-00-00 | AP57: Réappro H2 - Mbalik | AQ57: YASSIE | AR57: GAL | AS57: C100 | AT57: CM_MBL_DCG | AU57: DCG-SHS | AV57: IMPORT | AY57: E | AZ57: E | BA57: Felana RARIVOSON | BB57: ANDRIAMIRIJA Luca | BD57: 26101 | BE57: C100 | BF57: 2411 | BG57: 2 | BH57: 2026-08-31
