Workbook

Sheet Base extract
A1: Designation_Complémentaire | B1: Remise | C1: Total_Ligne_HT_Remisé | D1: V_Total_Ligne_TTC | E1: TVA | F1: N__DA | G1: N__Poste_DA | H1: Site_Stock | I1: Code_ss_famille | J1: Saisie_de_réception__ | K1: Code_Direction | L1: Code_complément | M1: SS_compte_anal | N1: Centre_d_Analyse | O1: Accord_Cadre | P1: RAL | Q1: V_Montant_RAL | R1: Code_Société | S1: Avenant | T1: Acheteur | U1: Tot_CA_HT | V1: Tot_CA_TTC | W1: Devise | X1: Etat_Financ_ | Y1: Date_creat | Z1: Date_de_Validation | AA1: Date_Période | AB1: Date_AR | AC1: Objet_CA | AD1: Ctr_Emetteur_entete | AE1: Ctr_Livraison_entete | AF1: Sect_Imputation_entete | AG1: Code_Complémentaire_entete | AH1: Sous_Compte_d_Analyse_entete | AI1: Type_document | AJ1: V_Expédition_soldée | AK1: Code_du_Modèle_de_Cde | AL1: V_Etat_commande_en_tête | AM1: V_Etat_commande_ligne | AN1: Nom_Acheteur | AO1: Raison_sociale_Fournisseur | AP1: Nom_demandeur | AQ1: V_Critère_de_saisie | AR1: Code_Article | AS1: Quantité_comm | AT1: Unité | AU1: Prix_Unitaire | AV1: Design__sommaire | AW1: Section_d_imput | AX1: Code_Fournis | AY1: N__de_Cde | AZ1: N_Poste | BA1: Date_de_livr__prev_
A2: E-gaming stand fibre Tuléar - Référence n°016/2026/MFE | B2: 0 | C2: 8878000 | D2: 8 878 000.00 | E2: 0 | F2: 138683 | G2: 1 | I2: MECSPDC | J2: True | K2: DCG | L2: E250_DRB | M2: DCG-DRB | N2: NA | P2: 1 | Q2: 8 878 000.00 | R2: YASMG | T2: FELANA13 | U2: 8 878 000.00 | V2: 8 878 000.00 | W2: MGA | X2: F | Y2: 46204 | Z2: 2026-07-01 | AA2: 46204 | AB2: 0000-00-00 | AC2: E-gaming stand fibre  Tuléar | AD2: YASSIE | AE2: YASSIE | AF2: C102 | AG2: E250_DRB | AH2: DCG-DRB | AI2: STD | AL2: E | AM2: E | AN2: Felana RARIVOSON | AO2: MALAGASY FEDERATION OF ESPORTS | AP2: ANDRIAMIRIJA Luca | AR2: 1267 | AS2: 1 | AT2: UN | AU2: 8878000 | AV2: SPONSORING | AW2: C102 | AX2: 6306 | AY2: 135491 | AZ2: 1 | BA2: 2026-06-25
A3: CLIMATISATION SALLE SUPERVISION METIS BAZARY BE FORT DAUPHIN # Proforma MG-YAS-26-A3537-D0001 | B3: 0 | C3: 11716818 | D3: 14 060 181.56 | E3: 20 | F3: 138672 | G3: 1 | I3: PRICTRL | J3: True | K3: DTG | L3: 2026-DT-061005 | M3: DTG-DOM-NRJ | N3: NA | P3: 1 | Q3: 11 716 817.97 | R3: YASMG | T3: ELIE3 | U3: 11 716 817.97 | V3: 14 060 181.56 | W3: MGA | Y3: 46204 | Z3: 2026-07-01 | AA3: 46204 | AB3: 0000-00-00 | AC3: CLIMATISATION SALLE SUPERVISION METIS BAZARY BE FORT DAUPHIN | AD3: YASSIE | AE3: YASSIE | AF3: C500 | AG3: 2026-DT-061005 | AH3: DTG-DOM-NRJ | AI3: STD | AL3: E | AM3: E | AN3: ANDRIAMANANTSOA Elie | AO3: NEA MADAGASCAR SA | AP3: RAKOTOMALALA Tahiana Nalaina | AR3: 10668 | AS3: 1 | AT3: UN | AU3: 11716818 | AV3: MAINTENANCE ENERGIE | AW3: C500 | AX3: 36 | AY3: 135492 | AZ3: 1 | BA3: 0000-00-00
A4: Couverture de 11 mois (de février à décembre 2026) Désinsectisation, Dératisation et Désinfection) pour les 33 stores de TANA | B4: 0 | C4: 27225000 | D4: 27 225 000.00 | E4: 0 | F4: 138776 | G4: 1 | I4: PRMBATX | J4: True | K4: DFG | L4: E218_DAF | M4: DFGA-LOG | N4: NA | P4: 11 | Q4: 27 225 000.00 | R4: YASMG | T4: NADIA7 | U4: 27 225 000.00 | V4: 27 225 000.00 | W4: MGA | Y4: 46204 | Z4: 2026-07-01 | AA4: 46204 | AB4: 0000-00-00 | AC4: Prestations d'interventions 3D couverture 11 mois 2026 | AD4: YASSIE | AE4: YASSIE | AF4: C700 | AG4: E218_DAF | AH4: DFGA-LOG | AI4: STD | AL4: E | AM4: E | AN4: RAVONINJATOVO Nadia | AO4: RAMANOARY NY ANDO LALAINA | AP4: RAKOTOMALALA Manambina Tafitasoa | AR4: 22111 | AS4: 11 | AT4: UN | AU4: 2475000 | AV4: DESINFECTION SITE | AW4: C700 | AX4: 6147 | AY4: 135493 | AZ4: 1 | BA4: 2026-07-02
A5: Prestation Logistique Evènementielle - Foire de la Fibre Tuléar - devis n°519D/TELMA S.A (YAS)/26 du 29/06/2026 | B5: 0 | C5: 24470000 | D5: 24 470 000.00 | E5: 0 | F5: 138766 | G5: 1 | I5: PRICTRL | J5: True | K5: DCG | L5: E250_DRB | M5: DCG-DRB | N5: NA | P5: 1 | Q5: 24 470 000.00 | R5: YASMG | T5: FELANA13 | U5: 24 470 000.00 | V5: 24 470 000.00 | W5: MGA | X5: F | Y5: 46204 | Z5: 2026-07-06 | AA5: 46204 | AB5: 0000-00-00 | AC5: Sandix Sono - Foire de la Fibre Tulear | AD5: YASSIE | AE5: YASSIE | AF5: C102 | AG5: E250_DRB | AH5: DCG-DRB | AI5: STD | AL5: E | AM5: E | AN5: Felana RARIVOSON | AO5: RAJAOFETRA ANDRIANAINA Sandy (SANDIX) | AP5: ANDRIAMIRIJA Luca | AR5: 14862 | AS5: 1 | AT5: UN | AU5: 24470000 | AV5: PRESTATION DE SERVICE | AW5: C102 | AX5: 3968 | AY5: 135494 | AZ5: 1 | BA5: 2026-07-01
A6: EAU VIVE Eau De Source Naturelle 50 cl - Pack de 12 # DEVIS N° B-PR0626-0097 DU 24/06/2026 - Contact livraison 0340036090 | B6: 0 | C6: 203000 | D6: 243 600.00 | E6: 20 | F6: 138380 | G6: 1 | I6: PRICTRL | J6: True | K6: DCG | L6: E219_DCG | M6: DCG-SHS | N6: NA | P6: 0 | Q6: 0.00 | R6: YASMG | T6: NADIA7 | U6: 990 916.67 | V6: 1 189 100.00 | W6: MGA | X6: F | Y6: 46205 | Z6: 2026-07-02 | AA6: 46205 | AB6: 0000-00-00 | AC6: MBALIK COLLATION Q2 2026 | AD6: YASSIE | AE6: YASSIE | AF6: C100 | AG6: E219_DCG | AH6: DCG-SHS | AI6: STD | AL6: L | AM6: S | AN6: RAVONINJATOVO Nadia | AO6: MORA MARKET | AP6: RAZAFINDRAHAGA Setra | AR6: 16984 | AS6: 12 | AT6: UN | AU6: 16916.667 | AV6: EAU | AW6: C100 | AX6: 4245 | AY6: 135495 | AZ6: 1 | BA6: 0000-00-00
A7: EAU VIVE Eau de source naturelle 1,5 L - Pack de 6 | B7: 0 | C7: 290416.67 | D7: 348 500.00 | E7: 20 | F7: 138380 | G7: 2 | I7: PRICTRL | J7: True | K7: DCG | L7: E219_DCG | M7: DCG-SHS | N7: NA | P7: 0 | Q7: 0.00 | R7: YASMG | T7: NADIA7 | U7: 990 916.67 | V7: 1 189 100.00 | W7: MGA | X7: F | Y7: 46205 | Z7: 2026-07-02 | AA7: 46205 | AB7: 0000-00-00 | AC7: MBALIK COLLATION Q2 2026 | AD7: YASSIE | AE7: YASSIE | AF7: C100 | AG7: E219_DCG | AH7: DCG-SHS | AI7: STD | AL7: L | AM7: S | AN7: RAVONINJATOVO Nadia | AO7: MORA MARKET | AP7: RAZAFINDRAHAGA Setra | AR7: 16984 | AS7: 17 | AT7: UN | AU7: 17083.333 | AV7: EAU | AW7: C100 | AX7: 4245 | AY7: 135495 | AZ7: 2 | BA7: 0000-00-00
A8: TAF Thé Vert Nature Sahambavy 100 Infusettes | B8: 0 | C8: 106000 | D8: 127 200.00 | E8: 20 | F8: 138380 | G8: 3 | I8: FRNCALM | J8: True | K8: DCG | L8: E219_DCG | M8: DCG-SHS | N8: NA | P8: 4 | Q8: 106 000.00 | R8: YASMG | T8: NADIA7 | U8: 990 916.67 | V8: 1 189 100.00 | W8: MGA | X8: F | Y8: 46205 | Z8: 2026-07-02 | AA8: 46205 | AB8: 0000-00-00 | AC8: MBALIK COLLATION Q2 2026 | AD8: YASSIE | AE8: YASSIE | AF8: C100 | AG8: E219_DCG | AH8: DCG-SHS | AI8: STD | AL8: L | AM8: E | AN8: RAVONINJATOVO Nadia | AO8: MORA MARKET | AP8: RAZAFINDRAHAGA Setra | AR8: 3818 | AS8: 4 | AT8: UN | AU8: 26500 | AV8: THE | AW8: C100 | AX8: 4245 | AY8: 135495 | AZ8: 3 | BA8: 2026-06-11
A9: CHOCOLATERIE ROBERT Cacao en Poudre 100% 225 G | B9: 0 | C9: 30000 | D9: 36 000.00 | E9: 20 | F9: 138380 | G9: 4 | I9: FRNCALM | J9: True | K9: DCG | L9: E219_DCG | M9: DCG-SHS | N9: NA | P9: 2 | Q9: 30 000.00 | R9: YASMG | T9: NADIA7 | U9: 990 916.67 | V9: 1 189 100.00 | W9: MGA | X9: F | Y9: 46205 | Z9: 2026-07-02 | AA9: 46205 | AB9: 0000-00-00 | AC9: MBALIK COLLATION Q2 2026 | AD9: YASSIE | AE9: YASSIE | AF9: C100 | AG9: E219_DCG | AH9: DCG-SHS | AI9: STD | AL9: L | AM9: E | AN9: RAVONINJATOVO Nadia | AO9: MORA MARKET | AP9: RAZAFINDRAHAGA Setra | AR9: 3820 | AS9: 2 | AT9: UN | AU9: 15000 | AV9: CACAO | AW9: C100 | AX9: 4245 | AY9: 135495 | AZ9: 4 | BA9: 2026-06-11
A10: COMPAGNIE LE CAFÉ Café Classic 100% Pure 50?G | B10: 0 | C10: 245333.33 | D10: 294 400.00 | E10: 20 | F10: 138380 | G10: 5 | I10: FRNCALM | J10: True | K10: DCG | L10: E219_DCG | M10: DCG-SHS | N10: NA | P10: 16 | Q10: 245 333.33 | R10: YASMG | T10: NADIA7 | U10: 990 916.67 | V10: 1 189 100.00 | W10: MGA | X10: F | Y10: 46205 | Z10: 2026-07-02 | AA10: 46205 | AB10: 0000-00-00 | AC10: MBALIK COLLATION Q2 2026 | AD10: YASSIE | AE10: YASSIE | AF10: C100 | AG10: E219_DCG | AH10: DCG-SHS | AI10: STD | AL10: L | AM10: E | AN10: RAVONINJATOVO Nadia | AO10: MORA MARKET | AP10: RAZAFINDRAHAGA Setra | AR10: 3816 | AS10: 16 | AT10: UN | AU10: 15333.333 | AV10: CAFE | AW10: C100 | AX10: 4245 | AY10: 135495 | AZ10: 5 | BA10: 2026-06-11
A11: Sucre Roux Brésilien 1 KG | B11: 0 | C11: 11166.67 | D11: 13 400.00 | E11: 20 | F11: 138380 | G11: 6 | I11: FRNCALM | J11: True | K11: DCG | L11: E219_DCG | M11: DCG-SHS | N11: NA | P11: 2 | Q11: 11 166.67 | R11: YASMG | T11: NADIA7 | U11: 990 916.67 | V11: 1 189 100.00 | W11: MGA | X11: F | Y11: 46205 | Z11: 2026-07-02 | AA11: 46205 | AB11: 0000-00-00 | AC11: MBALIK COLLATION Q2 2026 | AD11: YASSIE | AE11: YASSIE | AF11: C100 | AG11: E219_DCG | AH11: DCG-SHS | AI11: STD | AL11: L | AM11: E | AN11: RAVONINJATOVO Nadia | AO11: MORA MARKET | AP11: RAZAFINDRAHAGA Setra | AR11: 1168 | AS11: 2 | AT11: PCE | AU11: 5583.3333 | AV11: SUCRE | AW11: C100 | AX11: 4245 | AY11: 135495 | AZ11: 6 | BA11: 2026-06-11
A12: DELICE Lait en poudre 1 kg | B12: 0 | C12: 105000 | D12: 126 000.00 | E12: 20 | F12: 138380 | G12: 7 | I12: FRNCALM | J12: True | K12: DCG | L12: E219_DCG | M12: DCG-SHS | N12: NA | P12: 3 | Q12: 105 000.00 | R12: YASMG | T12: NADIA7 | U12: 990 916.67 | V12: 1 189 100.00 | W12: MGA | X12: F | Y12: 46205 | Z12: 2026-07-02 | AA12: 46205 | AB12: 0000-00-00 | AC12: MBALIK COLLATION Q2 2026 | AD12: YASSIE | AE12: YASSIE | AF12: C100 | AG12: E219_DCG | AH12: DCG-SHS | AI12: STD | AL12: L | AM12: E | AN12: RAVONINJATOVO Nadia | AO12: MORA MARKET | AP12: RAZAFINDRAHAGA Setra | AR12: 1166 | AS12: 3 | AT12: PCE | AU12: 35000 | AV12: LAIT | AW12: C100 | AX12: 4245 | AY12: 135495 | AZ12: 7 | BA12: 2026-06-11
A13: LOCATION IMPRIMANTE Consommation RICOH et Loyer mensuel TELMA SA, mois de Mai2026# FACTURE N°F850913 DU 02/06/2026 | B13: 0 | C13: 24937884 | D13: 29 925 460.80 | E13: 20 | F13: 138757 | G13: 1 | I13: LOCLOCT | J13: True | K13: DSI | L13: E250_DSI | M13: DSI | N13: NA | P13: 1 | Q13: 24 937 884.00 | R13: YASMG | T13: NADIA7 | U13: 24 937 884.00 | V13: 29 925 460.80 | W13: MGA | X13: F | Y13: 46205 | Z13: 2026-07-03 | AA13: 46205 | AB13: 0000-00-00 | AC13: Consommation RICOH et Loyer mensuel TELMA SA - Mai2026 | AD13: YASSIE | AE13: YASSIE | AF13: C800 | AG13: E250_DSI | AH13: DSI | AI13: STD | AL13: E | AM13: E | AN13: RAVONINJATOVO Nadia | AO13: SOCIETE DE DISTRIBUTION DE MAD (SODIM SARLU) | AP13: NJIVA Mbolatiana | AR13: 6991 | AS13: 1 | AT13: UN | AU13: 24937884 | AV13: LOCATION IMPRIMANTE | AW13: C800 | AX13: 127 | AY13: 135496 | AZ13: 1 | BA13: 2026-06-30
A14: COLLATION LE 02 JUILLET 2026 - Assortiments 2 pièces salées et 1 pièce sucré avec jus de fruits# DEVIS DU 29/06/2026 | B14: 0 | C14: 2100000 | D14: 2 520 000.00 | E14: 20 | F14: 138760 | G14: 1 | I14: PRICTRL | J14: True | K14: DSI | L14: E219_DSI | M14: DSI | N14: NA | P14: 70 | Q14: 2 100 000.00 | R14: YASMG | T14: NADIA7 | U14: 2 100 000.00 | V14: 2 520 000.00 | W14: MGA | X14: F | Y14: 46205 | Z14: 2026-07-02 | AA14: 46205 | AB14: 0000-00-00 | AC14: Collation Conférence Data Protection et AI_02Juillet2026 | AD14: YASSIE | AE14: YASSIE | AF14: C800 | AG14: E219_DSI | AH14: DSI | AI14: STD | AL14: E | AM14: E | AN14: RAVONINJATOVO Nadia | AO14: SOCIETE DE GESTION ET EXPLOITATION DE M/CAR | AP14: NJIVA Mbolatiana | AR14: 6965 | AS14: 70 | AT14: UN | AU14: 30000 | AV14: PRESTATION DE SERVICES EXTERNE | AW14: C800 | AX14: 119 | AY14: 135497 | AZ14: 1 | BA14: 2026-06-30
A15: Location de véhicule{s ) avec carburant 03 Juillet 2026 - Galaxy/Analakely - Ambohimalaza - Remisage# DEVIS N°PROFORMA 017-2026 DU 01/07/2026 | B15: 0 | C15: 2100000 | D15: 2 100 000.00 | E15: 0 | F15: 138780 | G15: 1 | I15: LOCLOCT | J15: True | K15: DSI | L15: E222_DSI | M15: DSI | N15: NA | P15: 7 | Q15: 2 100 000.00 | R15: YASMG | T15: NADIA7 | U15: 2 120 000.00 | V15: 2 120 000.00 | W15: MGA | X15: F | Y15: 46205 | Z15: 2026-07-02 | AA15: 46205 | AB15: 0000-00-00 | AC15: Location Car pour TB DSI_03 Juillet 2026 | AD15: YASSIE | AE15: YASSIE | AF15: C800 | AG15: E222_DSI | AH15: DSI | AI15: STD | AL15: E | AM15: E | AN15: RAVONINJATOVO Nadia | AO15: EXCEL TRANSPORT et TRAVEL | AP15: NJIVA Mbolatiana | AR15: 10626 | AS15: 7 | AT15: PIE | AU15: 300000 | AV15: LOCATION DE VOITURE COURTE DUREE | AW15: C800 | AX15: 6060 | AY15: 135498 | AZ15: 1 | BA15: 2026-07-01
A16: Frais de retrait | B16: 0 | C16: 20000 | D16: 20 000.00 | E16: 0 | F16: 138780 | G16: 2 | I16: EVROEVR | J16: True | K16: DSI | L16: E222_DSI | M16: DSI | N16: NA | P16: 1 | Q16: 20 000.00 | R16: YASMG | T16: NADIA7 | U16: 2 120 000.00 | V16: 2 120 000.00 | W16: MGA | X16: F | Y16: 46205 | Z16: 2026-07-02 | AA16: 46205 | AB16: 0000-00-00 | AC16: Location Car pour TB DSI_03 Juillet 2026 | AD16: YASSIE | AE16: YASSIE | AF16: C800 | AG16: E222_DSI | AH16: DSI | AI16: STD | AL16: E | AM16: E | AN16: RAVONINJATOVO Nadia | AO16: EXCEL TRANSPORT et TRAVEL | AP16: NJIVA Mbolatiana | AR16: 4213 | AS16: 1 | AT16: UN | AU16: 20000 | AV16: FRAIS DIVERS | AW16: C800 | AX16: 6060 | AY16: 135498 | AZ16: 2 | BA16: 2026-07-01
... A20: Système de sonorisation pour interprétariat sonorisation | B20: 0 | C20: 700000 | D20: 700 000.00 | E20: 0 | F20: 138762 | G20: 4 | I20: PRICTRL | J20: True | K20: DSI | L20: 2026-CP-SECU-D | M20: DSI | N20: NA | P20: 1 | Q20: 700 000.00 | R20: YASMG | T20: NADIA7 | U20: 4 225 000.00 | V20: 4 225 000.00 | W20: MGA | X20: F | Y20: 46205 | Z20: 2026-07-02 | AA20: 46205 | AB20: 0000-00-00 | AC20: Conférence Data Protection et AI_02Juillet2026 | AD20: YASSIE | AE20: YASSIE | AF20: C800 | AG20: 2026-CP-SECU-D | AH20: DSI | AI20: STD | AL20: E | AM20: E | AN20: RAVONINJATOVO Nadia | AO20: ANDRIANARY VERO HAINGO TIANA | AP20: NJIVA Mbolatiana | AR20: 6965 | AS20: 1 | AT20: UN | AU20: 700000 | AV20: PRESTATION DE SERVICES EXTERNE | AW20: C800 | AX20: 4371 | AY20: 135499 | AZ20: 4 | BA20: 2026-06-30
A21: DA Erick ANDRINIRINA Develppeur fullstack SOKA juin 2026# FACTURE N° F2600006 DU 16/06/2026 | B21: 0 | C21: 7646040 | D21: 7 646 040.00 | E21: 0 | F21: 138740 | G21: 1 | I21: PRICTRL | J21: True | K21: DG | L21: E250_DJU | M21: DG-DJUR | N21: NA | P21: 1 | Q21: 7 646 040.00 | R21: YASMG | T21: NADIA7 | U21: 7 646 040.00 | V21: 7 646 040.00 | W21: MGA | X21: F | Y21: 46205 | Z21: 2026-07-02 | AA21: 46205 | AB21: 0000-00-00 | AD21: YASSIE | AE21: YASSIE | AF21: C400 | AG21: E250_DJU | AH21: DG-DJUR | AI21: STD | AL21: E | AM21: E | AN21: RAVONINJATOVO Nadia | AO21: ANDRINIRINA ERICK | AP21: RAKOTONIRINA Hasy | AR21: 14862 | AS21: 1 | AT21: UN | AU21: 7646040 | AV21: PRESTATION DE SERVICE | AW21: C400 | AX21: 6519 | AY21: 135500 | AZ21: 1 | BA21: 2026-06-30
A22: Pour engagement du devis pour la LLD Mr Ando RATSIRAHONANA# DEVIS N° V.26.21100 DU 11/06/2026 | B22: 0 | C22: 179400000 | D22: 215 280 000.00 | E22: 20 | F22: 138775 | G22: 1 | I22: LVHLLDX | J22: True | K22: DG | L22: LLD_DJU | M22: DG-DJUR | N22: NA | P22: 60 | Q22: 179 400 000.00 | R22: YASMG | T22: NADIA7 | U22: 179 400 000.00 | V22: 215 280 000.00 | W22: MGA | X22: F | Y22: 46205 | Z22: 2026-07-02 | AA22: 46205 | AB22: 0000-00-00 | AD22: YASSIE | AE22: YASSIE | AF22: C400 | AG22: LLD_DJU | AH22: DG-DJUR | AI22: STD | AL22: E | AM22: E | AN22: RAVONINJATOVO Nadia | AO22: OCEAN TRADE CO | AP22: RAKOTONIRINA Hasy | AR22: 1247 | AS22: 60 | AT22: UN | AU22: 2990000 | AV22: LOCATION VEHICULE LLD | AW22: C400 | AX22: 102 | AY22: 135501 | AZ22: 1 | BA22: 2026-07-01
A23: Billet d'avion - TNR/WMN/TNR - RAMAHEFARISOA HAJANIRINA | B23: 0 | C23: 1672100 | D23: 1 672 100.00 | E23: 0 | F23: 138720 | G23: 1 | I23: PRMEQUI | J23: False | K23: DCG | L23: E215_DCG | M23: DCG-BEF | N23: NA | P23: 0 | Q23: 0.00 | R23: YASMG | T23: FELANA13 | U23: 1 672 100.00 | V23: 1 672 100.00 | W23: MGA | X23: F | Y23: 46205 | Z23: 2026-07-02 | AA23: 46205 | AB23: 0000-00-00 | AC23: Billet d'avion - RAMAHEFARISOA HAJANIRINA | AD23: YASSIE | AE23: YASSIE | AF23: C100 | AG23: E215_DCG | AH23: DCG-BEF | AI23: VOLINT | AL23: S | AM23: S | AN23: Felana RARIVOSON | AO23: VOYAGES BOURDON | AP23: ANDRIAMIRIJA Luca | AR23: 17513 | AS23: 1 | AT23: PIE | AU23: 1672100 | AV23: BILLET D'AVION | AW23: C100 | AX23: 2886 | AY23: 135502 | AZ23: 1 | BA23: 2026-06-29
A24: Billet d'Avion - David Randriamialy - TNR/NOS/TNR | B24: 0 | C24: 2542500 | D24: 2 542 500.00 | E24: 0 | F24: 138782 | G24: 1 | I24: PRMEQUI | J24: False | K24: DCG | L24: E215_DCG | M24: DCG-COM | N24: NA | P24: 0 | Q24: 0.00 | R24: YASMG | T24: FELANA13 | U24: 2 542 500.00 | V24: 2 542 500.00 | W24: MGA | X24: F | Y24: 46205 | Z24: 2026-07-02 | AA24: 46205 | AB24: 0000-00-00 | AC24: Billet d'Avion - David Randriamialy | AD24: YASSIE | AE24: YASSIE | AF24: C100 | AG24: E215_DCG | AH24: DCG-COM | AI24: VOLINT | AL24: S | AM24: S | AN24: Felana RARIVOSON | AO24: VOYAGES BOURDON | AP24: ANDRIAMIRIJA Luca | AR24: 17513 | AS24: 1 | AT24: PIE | AU24: 2542500 | AV24: BILLET D'AVION | AW24: C100 | AX24: 2886 | AY24: 135503 | AZ24: 1 | BA24: 2026-07-01
A25: Achat billet d'avion Fenotiana Patrick suite affectation | B25: 0 | C25: 949300 | D25: 949 300.00 | E25: 0 | F25: 138790 | G25: 1 | I25: PRMEQUI | J25: False | K25: DTG | L25: E215_DTG | M25: DRH-ADMIN | N25: NA | P25: 0 | Q25: 0.00 | R25: YASMG | T25: NADIA7 | U25: 2 847 900.00 | V25: 2 847 900.00 | W25: MGA | X25: F | Y25: 46205 | Z25: 2026-07-02 | AA25: 46205 | AB25: 0000-00-00 | AD25: YASSIE | AE25: YASSIE | AF25: C500 | AG25: E215_DTG | AH25: DRH-ADMIN | AI25: VOLINT | AL25: S | AM25: S | AN25: RAVONINJATOVO Nadia | AO25: VOYAGES BOURDON | AP25: ANDRIANINA Rebecca | AR25: 17513 | AS25: 1 | AT25: PIE | AU25: 949300 | AV25: BILLET D'AVION | AW25: C500 | AX25: 2886 | AY25: 135504 | AZ25: 1 | BA25: 2026-07-02
A26: Achat billet d'avion Christin suite affectation | B26: 0 | C26: 949300 | D26: 949 300.00 | E26: 0 | F26: 138790 | G26: 2 | I26: PRMEQUI | J26: False | K26: DTG | L26: E215_DTG | M26: DRH-ADMIN | N26: NA | P26: 0 | Q26: 0.00 | R26: YASMG | T26: NADIA7 | U26: 2 847 900.00 | V26: 2 847 900.00 | W26: MGA | X26: F | Y26: 46205 | Z26: 2026-07-02 | AA26: 46205 | AB26: 0000-00-00 | AD26: YASSIE | AE26: YASSIE | AF26: C500 | AG26: E215_DTG | AH26: DRH-ADMIN | AI26: VOLINT | AL26: S | AM26: S | AN26: RAVONINJATOVO Nadia | AO26: VOYAGES BOURDON | AP26: ANDRIANINA Rebecca | AR26: 17513 | AS26: 1 | AT26: PIE | AU26: 949300 | AV26: BILLET D'AVION | AW26: C500 | AX26: 2886 | AY26: 135504 | AZ26: 2 | BA26: 2026-07-02
A27: Achat billet d'avion Fitoa Emmanuel suite affectation | B27: 0 | C27: 949300 | D27: 949 300.00 | E27: 0 | F27: 138790 | G27: 3 | I27: PRMEQUI | J27: False | K27: DTG | L27: E215_DTG | M27: DRH-ADMIN | N27: NA | P27: 0 | Q27: 0.00 | R27: YASMG | T27: NADIA7 | U27: 2 847 900.00 | V27: 2 847 900.00 | W27: MGA | X27: F | Y27: 46205 | Z27: 2026-07-02 | AA27: 46205 | AB27: 0000-00-00 | AD27: YASSIE | AE27: YASSIE | AF27: C500 | AG27: E215_DTG | AH27: DRH-ADMIN | AI27: VOLINT | AL27: S | AM27: S | AN27: RAVONINJATOVO Nadia | AO27: VOYAGES BOURDON | AP27: ANDRIANINA Rebecca | AR27: 17513 | AS27: 1 | AT27: PIE | AU27: 949300 | AV27: BILLET D'AVION | AW27: C500 | AX27: 2886 | AY27: 135504 | AZ27: 3 | BA27: 2026-07-02
A28: Sponsoring - IOAI Summit 2026 - FA n°EDS-2026-0604 | B28: 0 | C28: 5000000 | D28: 5 000 000.00 | E28: 0 | F28: 138700 | G28: 1 | I28: MECSPDC | J28: True | K28: DCG | L28: E110_PS_DCOM | M28: DCG-COM-PART | N28: NA | P28: 1 | Q28: 5 000 000.00 | R28: YASMG | T28: FELANA13 | U28: 5 000 000.00 | V28: 5 000 000.00 | W28: MGA | X28: F | Y28: 46205 | Z28: 2026-07-02 | AA28: 46205 | AB28: 0000-00-00 | AC28: Sponsoring - IOAI Summit 2026 | AD28: YASSIE | AE28: YASSIE | AF28: C100 | AG28: E110_PS_DCOM | AH28: DCG-COM-PART | AI28: STD | AL28: E | AM28: E | AN28: Felana RARIVOSON | AO28: EDS GROUP | AP28: ANDRIAMIRIJA Luca | AR28: 1267 | AS28: 1 | AT28: UN | AU28: 5000000 | AV28: SPONSORING | AW28: C100 | AX28: 7133 | AY28: 135505 | AZ28: 1 | BA28: 2026-06-29
A29: Prestation de sécurité Nuit - Foire de la Fibre à Tuléar le 05 au 08 juillet 2026 - Proforma N° 0232562512/26 | B29: 0 | C29: 900000 | D29: 1 080 000.00 | E29: 20 | F29: 138781 | G29: 1 | I29: PRICTRL | J29: True | K29: DCG | L29: E259_DRB | M29: DCG-DRB | N29: NA | P29: 20 | Q29: 900 000.00 | R29: YASMG | T29: FELANA13 | U29: 900 000.00 | V29: 1 080 000.00 | W29: MGA | Y29: 46205 | Z29: 2026-07-02 | AA29: 46205 | AB29: 0000-00-00 | AC29: Sécurisation Nuit - Foire de la Fibre | AD29: YASSIE | AE29: YASSIE | AF29: C102 | AG29: E259_DRB | AH29: DCG-DRB | AI29: STD | AL29: E | AM29: E | AN29: Felana RARIVOSON | AO29: SECUR PRO | AP29: ANDRIAMIRIJA Luca | AR29: 14862 | AS29: 20 | AT29: UN | AU29: 45000 | AV29: PRESTATION DE SERVICE | AW29: C102 | AX29: 2145 | AY29: 135506 | AZ29: 1 | BA29: 2026-07-01
A30: Cafe Nespresso - Collation Q2 - Proforma n°B-PR0626-0258 | B30: 0 | C30: 1944000 | D30: 2 332 800.00 | E30: 20 | F30: 138708 | G30: 1 | I30: FRNCALM | J30: True | K30: DCG | L30: E219_DCG | M30: DCG-PS | N30: NA | P30: 35 | Q30: 1 944 000.00 | R30: YASMG | T30: FELANA13 | U30: 1 944 000.00 | V30: 2 332 800.00 | W30: MGA | X30: F | Y30: 46205 | Z30: 2026-07-02 | AA30: 46205 | AB30: 0000-00-00 | AC30: Café Collation Q2 - MKT | AD30: YASSIE | AE30: YASSIE | AF30: C100 | AG30: E219_DCG | AH30: DCG-PS | AI30: STD | AL30: E | AM30: E | AN30: Felana RARIVOSON | AO30: MORA MARKET | AP30: ANDRIAMIRIJA Luca | AR30: 3653 | AS30: 35 | AT30: UN | AU30: 55542.857 | AV30: CAFE NESPRESSO | AW30: C100 | AX30: 4245 | AY30: 135507 | AZ30: 1 | BA30: 2026-06-29
A31: Devis acompte validé pour la LLD de Mr Gary CHEUK Location pour 60 mois# DEVIS N° PF24062026-009 EV DU 24/06/2026 | B31: 0 | C31: 42000000 | D31: 50 400 000.00 | E31: 20 | F31: 138807 | G31: 1 | I31: LVHLLDX | J31: True | K31: DG | L31: LLD_DJU | M31: DG-DJUR | N31: NA | P31: 1 | Q31: 42 000 000.00 | R31: YASMG | T31: NADIA7 | U31: 42 000 000.00 | V31: 50 400 000.00 | W31: MGA | Y31: 46205 | Z31: 2026-07-02 | AA31: 46205 | AB31: 0000-00-00 | AD31: YASSIE | AE31: YASSIE | AF31: C400 | AG31: LLD_DJU | AH31: DG-DJUR | AI31: STD | AL31: E | AM31: E | AN31: RAVONINJATOVO Nadia | AO31: LOXEA MADAGASCAR | AP31: RAKOTONIRINA Hasy | AR31: 1247 | AS31: 1 | AT31: UN | AU31: 42000000 | AV31: LOCATION VEHICULE LLD | AW31: C400 | AX31: 629 | AY31: 135508 | AZ31: 1 | BA31: 2026-07-02
A32: Devis N° V.26.16817 DU 11/05/2026 | B32: 0 | C32: 261000000 | D32: 313 200 000.00 | E32: 20 | F32: 138806 | G32: 1 | I32: LVHLLDX | J32: True | K32: DG | L32: LLD_DG | M32: DG | N32: NA | P32: 60 | Q32: 261 000 000.00 | R32: YASMG | T32: NADIA7 | U32: 261 000 000.00 | V32: 313 200 000.00 | W32: MGA | X32: F | Y32: 46206 | Z32: 2026-07-03 | AA32: 46206 | AB32: 0000-00-00 | AC32: LLD Richard FIENENA-OCEANTRADE | AD32: YASSIE | AE32: YASSIE | AF32: C900 | AG32: LLD_DG | AH32: DG | AI32: STD | AL32: E | AM32: E | AN32: RAVONINJATOVO Nadia | AO32: OCEAN TRADE CO | AP32: RASOLOJAONA Miora | AR32: 1247 | AS32: 60 | AT32: UN | AU32: 4350000 | AV32: LOCATION VEHICULE LLD | AW32: C900 | AX32: 102 | AY32: 135509 | AZ32: 1 | BA32: 2026-07-02
A33: Gestion Warehouse AGL Phoenix Février à septembre 2026 (8 mois) | B33: 0 | C33: 195471360 | D33: 234 565 632.00 | E33: 20 | F33: 138787 | G33: 1 | I33: PRICTRL | J33: True | K33: DFG | L33: E250_DAF | M33: DFGA-LOG | N33: NA | P33: 8 | Q33: 195 471 360.00 | R33: YASMG | T33: NADIA7 | U33: 781 885 440.00 | V33: 938 262 528.00 | W33: MGA | Y33: 46206 | Z33: 2026-07-03 | AA33: 46206 | AB33: 0000-00-00 | AC33: Gestion Warehouse AGL Phoenix | AD33: YASSIE | AE33: YASSIE | AF33: C700 | AG33: E250_DAF | AH33: DFGA-LOG | AI33: STD | AL33: E | AM33: E | AN33: RAVONINJATOVO Nadia | AO33: AFRICA GLOBAL LOGISTICS | AP33: RAKOTOMALALA Manambina Tafitasoa | AR33: 6965 | AS33: 8 | AT33: UN | AU33: 24433920 | AV33: PRESTATION DE SERVICES EXTERNE | AW33: C700 | AX33: 713 | AY33: 135510 | AZ33: 1 | BA33: 2026-07-31
A34: Gestion Warehouse AGL Phoenix Février 26 à février 27 (12 mois) | B34: 0 | C34: 586414080 | D34: 703 696 896.00 | E34: 20 | F34: 138787 | G34: 2 | I34: PRICTRL | J34: True | K34: DFG | L34: E250_DAF | M34: DFGA-LOG | N34: NA | P34: 12 | Q34: 586 414 080.00 | R34: YASMG | T34: NADIA7 | U34: 781 885 440.00 | V34: 938 262 528.00 | W34: MGA | Y34: 46206 | Z34: 2026-07-03 | AA34: 46206 | AB34: 0000-00-00 | AC34: Gestion Warehouse AGL Phoenix | AD34: YASSIE | AE34: YASSIE | AF34: C700 | AG34: E250_DAF | AH34: DFGA-LOG | AI34: STD | AL34: E | AM34: E | AN34: RAVONINJATOVO Nadia | AO34: AFRICA GLOBAL LOGISTICS | AP34: RAKOTOMALALA Manambina Tafitasoa | AR34: 6965 | AS34: 12 | AT34: UN | AU34: 48867840 | AV34: PRESTATION DE SERVICES EXTERNE | AW34: C700 | AX34: 713 | AY34: 135510 | AZ34: 2 | BA34: 2026-07-31
A35: CARREFOUR SENSATION Infusion Thé Noir Saveur Fruits Rouges x25# DEVIS N° B-PR0626-0098 DU 08/06/2026 | B35: 0 | C35: 174000 | D35: 208 800.00 | E35: 20 | F35: 138388 | G35: 1 | I35: FRNCALM | J35: True | K35: DCG | L35: E219_DCG | M35: DCG-COM | N35: NA | P35: 12 | Q35: 174 000.00 | R35: YASMG | T35: NADIA7 | U35: 1 665 166.67 | V35: 1 998 200.00 | W35: MGA | X35: F | Y35: 46206 | Z35: 2026-07-03 | AA35: 46206 | AB35: 0000-00-00 | AC35: ADN COLLATION Q2 2026 | AD35: YASSIE | AE35: YASSIE | AF35: C100 | AG35: E219_DCG | AH35: DCG-COM | AI35: STD | AL35: E | AM35: E | AN35: RAVONINJATOVO Nadia | AO35: MORA MARKET | AP35: RAZAFINDRAHAGA Setra | AR35: 3818 | AS35: 12 | AT35: UN | AU35: 14500 | AV35: THE | AW35: C100 | AX35: 4245 | AY35: 135511 | AZ35: 1 | BA35: 2026-06-11
A36: COTTERLEY Thé Vert Agrumes 25 Sachets | B36: 0 | C36: 57000 | D36: 68 400.00 | E36: 20 | F36: 138388 | G36: 2 | I36: FRNCALM | J36: True | K36: DCG | L36: E219_DCG | M36: DCG-COM | N36: NA | P36: 6 | Q36: 57 000.00 | R36: YASMG | T36: NADIA7 | U36: 1 665 166.67 | V36: 1 998 200.00 | W36: MGA | X36: F | Y36: 46206 | Z36: 2026-07-03 | AA36: 46206 | AB36: 0000-00-00 | AC36: ADN COLLATION Q2 2026 | AD36: YASSIE | AE36: YASSIE | AF36: C100 | AG36: E219_DCG | AH36: DCG-COM | AI36: STD | AL36: E | AM36: E | AN36: RAVONINJATOVO Nadia | AO36: MORA MARKET | AP36: RAZAFINDRAHAGA Setra | AR36: 3818 | AS36: 6 | AT36: UN | AU36: 9500 | AV36: THE | AW36: C100 | AX36: 4245 | AY36: 135511 | AZ36: 2 | BA36: 2026-06-11
A37: COTTERLEY Thé Vert Subtilement Aromatisé 32,5?g X25 Sachets | B37: 0 | C37: 59500 | D37: 71 400.00 | E37: 20 | F37: 138388 | G37: 3 | I37: FRNCALM | J37: True | K37: DCG | L37: E219_DCG | M37: DCG-COM | N37: NA | P37: 6 | Q37: 59 500.00 | R37: YASMG | T37: NADIA7 | U37: 1 665 166.67 | V37: 1 998 200.00 | W37: MGA | X37: F | Y37: 46206 | Z37: 2026-07-03 | AA37: 46206 | AB37: 0000-00-00 | AC37: ADN COLLATION Q2 2026 | AD37: YASSIE | AE37: YASSIE | AF37: C100 | AG37: E219_DCG | AH37: DCG-COM | AI37: STD | AL37: E | AM37: E | AN37: RAVONINJATOVO Nadia | AO37: MORA MARKET | AP37: RAZAFINDRAHAGA Setra | AR37: 3818 | AS37: 6 | AT37: UN | AU37: 9916.6667 | AV37: THE | AW37: C100 | AX37: 4245 | AY37: 135511 | AZ37: 3 | BA37: 2026-06-11
A38: CHOCOLATERIE ROBERT Cacao en Poudre 100% 225 G | B38: 0 | C38: 195000 | D38: 234 000.00 | E38: 20 | F38: 138388 | G38: 4 | I38: FRNCALM | J38: True | K38: DCG | L38: E219_DCG | M38: DCG-COM | N38: NA | P38: 13 | Q38: 195 000.00 | R38: YASMG | T38: NADIA7 | U38: 1 665 166.67 | V38: 1 998 200.00 | W38: MGA | X38: F | Y38: 46206 | Z38: 2026-07-03 | AA38: 46206 | AB38: 0000-00-00 | AC38: ADN COLLATION Q2 2026 | AD38: YASSIE | AE38: YASSIE | AF38: C100 | AG38: E219_DCG | AH38: DCG-COM | AI38: STD | AL38: E | AM38: E | AN38: RAVONINJATOVO Nadia | AO38: MORA MARKET | AP38: RAZAFINDRAHAGA Setra | AR38: 3820 | AS38: 13 | AT38: UN | AU38: 15000 | AV38: CACAO | AW38: C100 | AX38: 4245 | AY38: 135511 | AZ38: 4 | BA38: 2026-06-11
A39: COMPAGNIE LE CAFÉ Café Classic 100% Pure 50G | B39: 0 | C39: 368000 | D39: 441 600.00 | E39: 20 | F39: 138388 | G39: 5 | I39: FRNCALM | J39: True | K39: DCG | L39: E219_DCG | M39: DCG-COM | N39: NA | P39: 24 | Q39: 368 000.00 | R39: YASMG | T39: NADIA7 | U39: 1 665 166.67 | V39: 1 998 200.00 | W39: MGA | X39: F | Y39: 46206 | Z39: 2026-07-03 | AA39: 46206 | AB39: 0000-00-00 | AC39: ADN COLLATION Q2 2026 | AD39: YASSIE | AE39: YASSIE | AF39: C100 | AG39: E219_DCG | AH39: DCG-COM | AI39: STD | AL39: E | AM39: E | AN39: RAVONINJATOVO Nadia | AO39: MORA MARKET | AP39: RAZAFINDRAHAGA Setra | AR39: 3816 | AS39: 24 | AT39: UN | AU39: 15333.333 | AV39: CAFE | AW39: C100 | AX39: 4245 | AY39: 135511 | AZ39: 5 | BA39: 2026-06-11
A40: Sucre Roux Brésilien 1 KG | B40: 0 | C40: 111666.67 | D40: 134 000.00 | E40: 20 | F40: 138388 | G40: 6 | I40: FRNCALM | J40: True | K40: DCG | L40: E219_DCG | M40: DCG-COM | N40: NA | P40: 20 | Q40: 111 666.67 | R40: YASMG | T40: NADIA7 | U40: 1 665 166.67 | V40: 1 998 200.00 | W40: MGA | X40: F | Y40: 46206 | Z40: 2026-07-03 | AA40: 46206 | AB40: 0000-00-00 | AC40: ADN COLLATION Q2 2026 | AD40: YASSIE | AE40: YASSIE | AF40: C100 | AG40: E219_DCG | AH40: DCG-COM | AI40: STD | AL40: E | AM40: E | AN40: RAVONINJATOVO Nadia | AO40: MORA MARKET | AP40: RAZAFINDRAHAGA Setra | AR40: 1168 | AS40: 20 | AT40: PCE | AU40: 5583.3333 | AV40: SUCRE | AW40: C100 | AX40: 4245 | AY40: 135511 | AZ40: 6 | BA40: 2026-06-11
A41: DELICE Lait en poudre 1 kg | B41: 0 | C41: 700000 | D41: 840 000.00 | E41: 20 | F41: 138388 | G41: 7 | I41: FRNCALM | J41: True | K41: DCG | L41: E219_DCG | M41: DCG-COM | N41: NA | P41: 20 | Q41: 700 000.00 | R41: YASMG | T41: NADIA7 | U41: 1 665 166.67 | V41: 1 998 200.00 | W41: MGA | X41: F | Y41: 46206 | Z41: 2026-07-03 | AA41: 46206 | AB41: 0000-00-00 | AC41: ADN COLLATION Q2 2026 | AD41: YASSIE | AE41: YASSIE | AF41: C100 | AG41: E219_DCG | AH41: DCG-COM | AI41: STD | AL41: E | AM41: E | AN41: RAVONINJATOVO Nadia | AO41: MORA MARKET | AP41: RAZAFINDRAHAGA Setra | AR41: 1166 | AS41: 20 | AT41: PCE | AU41: 35000 | AV41: LAIT | AW41: C100 | AX41: 4245 | AY41: 135511 | AZ41: 7 | BA41: 2026-06-11
A42: Billet d'avion - RAKOTOMIHAMINA ANDO - TNR/TLE/TNR | B42: 0 | C42: 2258500 | D42: 2 258 500.00 | E42: 0 | F42: 138813 | G42: 1 | I42: PRMEQUI | J42: False | K42: DCG | L42: E215_DCG | M42: DCG-PS | N42: NA | P42: 1 | Q42: 2 258 500.00 | R42: YASMG | T42: FELANA13 | U42: 2 258 500.00 | V42: 2 258 500.00 | W42: MGA | X42: F | Y42: 46206 | Z42: 2026-07-03 | AA42: 46206 | AB42: 0000-00-00 | AC42: Billet d'Avion - RAKOTOMIHAMINA ANDO | AD42: YASSIE | AE42: YASSIE | AF42: C100 | AG42: E215_DCG | AH42: DCG-PS | AI42: VOLINT | AL42: Z | AM42: Z | AN42: Felana RARIVOSON | AO42: VOYAGES BOURDON | AP42: ANDRIAMIRIJA Luca | AR42: 17513 | AS42: 1 | AT42: PIE | AU42: 2258500 | AV42: BILLET D'AVION | AW42: C100 | AX42: 2886 | AY42: 135512 | AZ42: 1 | BA42: 2026-07-03
A43: COFI 2026 - PIAGGIO APE 3 WHEELER MODEL - GRS RISE SERVICES - DEVIS DVISIE0226-002019 DU 13/06/2026 | B43: 0 | C43: 13250000 | D43: 15 900 000.00 | E43: 20 | F43: 138617 | G43: 1 | I43: PRMVEHI | J43: True | K43: DCG | L43: 2026-COFI | M43: DCG-DVI | N43: NA | P43: 1 | Q43: 13 250 000.00 | R43: YASMG | T43: FELANA13 | U43: 13 250 000.00 | V43: 15 900 000.00 | W43: MGA | X43: F | Y43: 46206 | Z43: 2026-07-06 | AA43: 46206 | AB43: 0000-00-00 | AC43: COFI 2026 - GRS RISE SERVICES | AD43: YASSIE | AE43: GALE | AF43: C104 | AG43: 2026-COFI | AH43: DCG-DVI | AI43: STD | AL43: E | AM43: E | AN43: Felana RARIVOSON | AO43: CT MOTORS | AP43: RAZAFINDRAHAGA Setra | AR43: 4155 | AS43: 1 | AT43: UN | AU43: 13250000 | AV43: MOTO | AW43: C104 | AX43: 664 | AY43: 135513 | AZ43: 1 | BA43: 2026-06-22
A44: ME ANDRIANASOLO ANDRY FIANKINANA paiement abonnement juillet 2026# FACTURE N° 09/26 DU 02/07/2026 | B44: 0 | C44: 11000000 | D44: 11 000 000.00 | E44: 0 | F44: 138818 | G44: 1 | I44: PRIAVJU | J44: True | K44: DG | L44: E251_DJU | M44: DG-DJUR | N44: NA | P44: 1 | Q44: 11 000 000.00 | R44: YASMG | T44: NADIA7 | U44: 11 000 000.00 | V44: 11 000 000.00 | W44: MGA | X44: F | Y44: 46206 | Z44: 2026-07-03 | AA44: 46206 | AB44: 0000-00-00 | AD44: YASSIE | AE44: YASSIE | AF44: C400 | AG44: E251_DJU | AH44: DG-DJUR | AI44: STD | AL44: E | AM44: E | AN44: RAVONINJATOVO Nadia | AO44: ME ANDRIANASOLO ANDRY FIANKINANA | AP44: RAKOTONIRINA Hasy | AR44: 1242 | AS44: 1 | AT44: UN | AU44: 11000000 | AV44: HONORAIRE AVOCAT | AW44: C400 | AX44: 1709 | AY44: 135514 | AZ44: 1 | BA44: 2026-07-03
A45: Billet d'avion - TNR/SMS/TNR - Armia et Galib | B45: 0 | C45: 3224800 | D45: 3 224 800.00 | E45: 0 | F45: 138817 | G45: 1 | I45: VDPBILL | J45: False | K45: DCG | L45: E215_DCG | M45: DCG-DVE | N45: NA | P45: 0 | Q45: 0.00 | R45: YASMG | T45: FELANA13 | U45: 3 224 800.00 | V45: 3 224 800.00 | W45: MGA | X45: F | Y45: 46206 | Z45: 2026-07-03 | AA45: 46206 | AB45: 0000-00-00 | AC45: Billet d'Avion - TNR/SMS/TNR | AD45: YASSIE | AE45: YASSIE | AF45: C103 | AG45: E215_DCG | AH45: DCG-DVE | AI45: VOLINT | AL45: S | AM45: S | AN45: Felana RARIVOSON | AO45: VOYAGES BOURDON | AP45: ANDRIAMIRIJA Luca | AR45: 1250 | AS45: 2 | AT45: UN | AU45: 1612400 | AV45: BILLET D 'AVION | AW45: C103 | AX45: 2886 | AY45: 135515 | AZ45: 1 | BA45: 2026-07-03
A46: DTG/DOM: Travaux supplémentaires Monsieur Solo Heriniaina ANDRIAMANAMPISON Taolagnaro | B46: 0 | C46: 3370000 | D46: 4 044 000.00 | E46: 20 | F46: 138621 | G46: 1 | I46: PRICTRL | J46: True | K46: DTG | L46: 2026-DT-102001 | M46: DTG-DOM | N46: NA | P46: 1 | Q46: 3 370 000.00 | R46: YASMG | T46: ELIE3 | U46: 3 370 000.00 | V46: 4 044 000.00 | W46: MGA | Y46: 46206 | Z46: 2026-07-03 | AA46: 46206 | AB46: 0000-00-00 | AC46: Travaux Solo Heriniaina ANDRIAMANAMPISON Taolagnaro | AD46: YASSIE | AE46: YASSIE | AF46: C500 | AG46: 2026-DT-102001 | AH46: DTG-DOM | AI46: STD | AL46: E | AM46: E | AN46: ANDRIAMANANTSOA Elie | AO46: HERTS MADAGASCAR SARLU | AP46: HERY RAMAROLAHY | AR46: 22418 | AS46: 1 | AT46: UN | AU46: 3370000 | AV46: Travaux GC filaire | AW46: C500 | AX46: 3051 | AY46: 135516 | AZ46: 1 | BA46: 0000-00-00
A47: Billet d'Avion - Nancy RAZAFINDRAFARA - TMM/TNR/SMS/TNR/TMM | B47: 0 | C47: 3659300 | D47: 3 659 300.00 | E47: 0 | F47: 138815 | G47: 1 | I47: PRMEQUI | J47: False | K47: DCG | L47: E215_DCG | M47: DCG-DRB | N47: NA | P47: 0 | Q47: 0.00 | R47: YASMG | T47: FELANA13 | U47: 3 659 300.00 | V47: 3 659 300.00 | W47: MGA | X47: F | Y47: 46206 | Z47: 2026-07-03 | AA47: 46206 | AB47: 0000-00-00 | AC47: Billet d'Avion - NANCY RAZAFINDRAFARA | AD47: YASSIE | AE47: YASSIE | AF47: C102 | AG47: E215_DCG | AH47: DCG-DRB | AI47: VOLINT | AL47: S | AM47: S | AN47: Felana RARIVOSON | AO47: VOYAGES BOURDON | AP47: ANDRIAMIRIJA Luca | AR47: 17513 | AS47: 1 | AT47: PIE | AU47: 3659300 | AV47: BILLET D'AVION | AW47: C102 | AX47: 2886 | AY47: 135517 | AZ47: 1 | BA47: 2026-07-03
A48: DTG/DOM: TRAVAUX TRANSPORT ET IMPLANTATION DE 04 POTEAUX POUR JACKIE AMELINA MORONDAVA | B48: 0 | C48: 300000 | D48: 300 000.00 | E48: 0 | F48: 138726 | G48: 1 | I48: PRICTRL | J48: True | K48: DTG | L48: 2026-DT-102001 | M48: DTG-DOM | N48: NA | P48: 1 | Q48: 300 000.00 | R48: YASMG | T48: ELIE3 | U48: 300 000.00 | V48: 300 000.00 | W48: MGA | Y48: 46206 | Z48: 2026-07-03 | AA48: 46206 | AB48: 0000-00-00 | AC48: TRAVAUX JACKIE AMELINA MORONDAVA | AD48: YASSIE | AE48: YASSIE | AF48: C500 | AG48: 2026-DT-102001 | AH48: DTG-DOM | AI48: STD | AL48: E | AM48: E | AN48: ANDRIAMANANTSOA Elie | AO48: ENTREPRISE ANDRY SOA | AP48: HERY RAMAROLAHY | AR48: 22418 | AS48: 1 | AT48: UN | AU48: 300000 | AV48: Travaux GC filaire | AW48: C500 | AX48: 2318 | AY48: 135518 | AZ48: 1 | BA48: 2026-07-06
A49: DTG/DOM: Travaux GC DE LA LIAISON FO CLIENT TAMATAVE Lot N°74 | B49: 0 | C49: 11380000 | D49: 13 656 000.00 | E49: 20 | F49: 138745 | G49: 1 | I49: PRICTRL | J49: True | K49: DTG | L49: 2026-DT-102001 | M49: DTG-DOM | N49: NA | P49: 0 | Q49: 0.00 | R49: YASMG | T49: ELIE3 | U49: 11 380 000.00 | V49: 13 656 000.00 | W49: MGA | Y49: 46206 | Z49: 2026-07-03 | AA49: 46206 | AB49: 0000-00-00 | AC49: Travaux GC DE LA LIAISON FO CLIENT TAMATAVE Lot N°74 | AD49: YASSIE | AE49: YASSIE | AF49: C500 | AG49: 2026-DT-102001 | AH49: DTG-DOM | AI49: STD | AL49: S | AM49: S | AN49: ANDRIAMANANTSOA Elie | AO49: PRIMA CE SARLU | AP49: HERY RAMAROLAHY | AR49: 22418 | AS49: 1 | AT49: UN | AU49: 11380000 | AV49: Travaux GC filaire | AW49: C500 | AX49: 2633 | AY49: 135519 | AZ49: 1 | BA49: 0000-00-00
A50: DTG/DOM: Implantation de 30 poteaux à Majunga 87ème vague # DEVIS 32/26-EHM | B50: 0 | C50: 4100000 | D50: 4 100 000.00 | E50: 0 | F50: 138746 | G50: 1 | I50: PRICTRL | J50: True | K50: DTG | L50: 2026-DT-102001 | M50: DTG-DOM | N50: NA | P50: 0 | Q50: 0.00 | R50: YASMG | T50: ELIE3 | U50: 4 100 000.00 | V50: 4 100 000.00 | W50: MGA | X50: F | Y50: 46206 | Z50: 2026-07-03 | AA50: 46206 | AB50: 0000-00-00 | AC50: Implantation de 30 poteaux à Majunga 87ème vague | AD50: YASSIE | AE50: YASSIE | AF50: C500 | AG50: 2026-DT-102001 | AH50: DTG-DOM | AI50: STD | AL50: S | AM50: S | AN50: ANDRIAMANANTSOA Elie | AO50: RANDRIANASOLO HANTA BEBY | AP50: HERY RAMAROLAHY | AR50: 22418 | AS50: 1 | AT50: UN | AU50: 4100000 | AV50: Travaux GC filaire | AW50: C500 | AX50: 2322 | AY50: 135520 | AZ50: 1 | BA50: 0000-00-00
A51: DTG/DOM: Implantation de 30 poteaux à Majunga 88ème vague# DEVIS: 33/26-EHM | B51: 0 | C51: 4100000 | D51: 4 100 000.00 | E51: 0 | F51: 138747 | G51: 1 | I51: PRICTRL | J51: True | K51: DTG | L51: 2026-DT-102001 | M51: DTG-DOM | N51: NA | P51: 0 | Q51: 0.00 | R51: YASMG | T51: ELIE3 | U51: 4 100 000.00 | V51: 4 100 000.00 | W51: MGA | X51: F | Y51: 46206 | Z51: 2026-07-03 | AA51: 46206 | AB51: 0000-00-00 | AC51: Implantation de 30 poteaux à Majunga 88ème vague | AD51: YASSIE | AE51: YASSIE | AF51: C500 | AG51: 2026-DT-102001 | AH51: DTG-DOM | AI51: STD | AL51: S | AM51: S | AN51: ANDRIAMANANTSOA Elie | AO51: RANDRIANASOLO HANTA BEBY | AP51: HERY RAMAROLAHY | AR51: 22418 | AS51: 1 | AT51: UN | AU51: 4100000 | AV51: Travaux GC filaire | AW51: C500 | AX51: 2322 | AY51: 135521 | AZ51: 1 | BA51: 0000-00-00
A52: DTG/DOM: Implantation de 30 poteaux à Majunga 89ème vague# DEVIS:34/26-EHM | B52: 0 | C52: 4100000 | D52: 4 100 000.00 | E52: 0 | F52: 138749 | G52: 1 | I52: PRICTRL | J52: True | K52: DTG | L52: 2026-DT-102001 | M52: DTG-DOM | N52: NA | P52: 0 | Q52: 0.00 | R52: YASMG | T52: ELIE3 | U52: 4 100 000.00 | V52: 4 100 000.00 | W52: MGA | X52: F | Y52: 46206 | Z52: 2026-07-06 | AA52: 46206 | AB52: 0000-00-00 | AC52: Implantation de 30 poteaux à Majunga 89ème vague | AD52: YASSIE | AE52: YASSIE | AF52: C500 | AG52: 2026-DT-102001 | AH52: DTG-DOM | AI52: STD | AL52: S | AM52: S | AN52: ANDRIAMANANTSOA Elie | AO52: RANDRIANASOLO HANTA BEBY | AP52: HERY RAMAROLAHY | AR52: 22418 | AS52: 1 | AT52: UN | AU52: 4100000 | AV52: Travaux GC filaire | AW52: C500 | AX52: 2322 | AY52: 135522 | AZ52: 1 | BA52: 0000-00-00
A53: DTG/DOM: Implantation de 30 poteaux à Majunga 90ème vague# DEVIS 35/26-EHM | B53: 0 | C53: 4100000 | D53: 4 100 000.00 | E53: 0 | F53: 138750 | G53: 1 | I53: PRICTRL | J53: True | K53: DTG | L53: 2026-DT-102001 | M53: DTG-DOM | N53: NA | P53: 1 | Q53: 4 100 000.00 | R53: YASMG | T53: ELIE3 | U53: 4 100 000.00 | V53: 4 100 000.00 | W53: MGA | X53: F | Y53: 46206 | Z53: 2026-07-03 | AA53: 46206 | AB53: 0000-00-00 | AC53: Implantation de 30 poteaux à Majunga 90ème vague | AD53: YASSIE | AE53: YASSIE | AF53: C500 | AG53: 2026-DT-102001 | AH53: DTG-DOM | AI53: STD | AL53: E | AM53: E | AN53: ANDRIAMANANTSOA Elie | AO53: RANDRIANASOLO HANTA BEBY | AP53: HERY RAMAROLAHY | AR53: 22418 | AS53: 1 | AT53: UN | AU53: 4100000 | AV53: Travaux GC filaire | AW53: C500 | AX53: 2322 | AY53: 135523 | AZ53: 1 | BA53: 0000-00-00
A54: DTG/DOM: Clement RABERANTO à MANDRITSARA | B54: 0 | C54: 1600000 | D54: 1 600 000.00 | E54: 0 | F54: 138752 | G54: 1 | I54: PRICTRL | J54: True | K54: DTG | L54: 2026-DT-102001 | M54: DTG-DOM | N54: NA | P54: 0 | Q54: 0.00 | R54: YASMG | T54: ELIE3 | U54: 1 600 000.00 | V54: 1 600 000.00 | W54: MGA | X54: F | Y54: 46206 | Z54: 2026-07-03 | AA54: 46206 | AB54: 0000-00-00 | AC54: Clement RABERANTO à MANDRITSARA | AD54: YASSIE | AE54: YASSIE | AF54: C500 | AG54: 2026-DT-102001 | AH54: DTG-DOM | AI54: STD | AL54: S | AM54: S | AN54: ANDRIAMANANTSOA Elie | AO54: BESSADARA ORLANDO | AP54: HERY RAMAROLAHY | AR54: 22418 | AS54: 1 | AT54: UN | AU54: 1600000 | AV54: Travaux GC filaire | AW54: C500 | AX54: 5337 | AY54: 135524 | AZ54: 1 | BA54: 0000-00-00
A55: DTG/DOM: Travaux Supplémentaires pour le déploiement du lien FO de LECOFRUIT (Gpe BASAN) | B55: 0 | C55: 28126500 | D55: 33 751 800.00 | E55: 20 | F55: 138763 | G55: 1 | I55: PRICTRL | J55: True | K55: DTG | L55: 2026-DT-102001 | M55: DTG-DOM | N55: NA | P55: 1 | Q55: 28 126 500.00 | R55: YASMG | T55: ELIE3 | U55: 28 126 500.00 | V55: 33 751 800.00 | W55: MGA | X55: F | Y55: 46206 | Z55: 2026-07-03 | AA55: 46206 | AB55: 0000-00-00 | AC55: Travaux Supplémentaires pour LECOFRUIT (Gpe BASAN) | AD55: YASSIE | AE55: YASSIE | AF55: C500 | AG55: 2026-DT-102001 | AH55: DTG-DOM | AI55: STD | AL55: E | AM55: E | AN55: ANDRIAMANANTSOA Elie | AO55: ENTREPRISE TAHIANA | AP55: HERY RAMAROLAHY | AR55: 22418 | AS55: 1 | AT55: UN | AU55: 28126500 | AV55: Travaux GC filaire | AW55: C500 | AX55: 2332 | AY55: 135525 | AZ55: 1 | BA55: 2026-07-06
A56: Régul-Application Support & Maintenance - Alfred Backlog (Q1-2026)(89%*14 577,87) | B56: 0 | C56: 12974.3 | D56: 15 569.16 | E56: 20 | F56: 138569 | G56: 1 | I56: PRICTRL | J56: True | K56: DTG | L56: E336_DTG | M56: DTG-DOM | N56: NA | P56: 1 | Q56: 12 974.30 | R56: YASMG | T56: ELIE3 | U56: 12 974.30 | V56: 15 569.16 | W56: USD | X56: F | Y56: 46206 | Z56: 2026-07-06 | AA56: 46206 | AB56: 0000-00-00 | AC56: Régul support maint Alfred Backlog(Q1-2026)-IC | AD56: YASSIE | AE56: YASSIE | AF56: C500 | AG56: E336_DTG | AH56: DTG-DOM | AI56: STD | AL56: E | AM56: E | AN56: ANDRIAMANANTSOA Elie | AO56: PULSE | AP56: RASAMOELINA Haritsoa Oliva | AR56: 14862 | AS56: 1 | AT56: UN | AU56: 12974.3 | AV56: PRESTATION DE SERVICE | AW56: C500 | AX56: 4 | AY56: 135526 | AZ56: 1 | BA56: 2026-06-18
A57: Régul-Application Support & Maintenance - Alfred Backlog (Y2025)(89%*55 897,86) #REF PRISM YMG-DTG-20260331-002 | B57: 0 | C57: 49733.07 | D57: 59 679.68 | E57: 20 | F57: 138568 | G57: 1 | I57: PRICTRL | J57: True | K57: DTG | L57: E336_DTG | M57: DTG-DOM | N57: NA | P57: 1 | Q57: 49 733.07 | R57: YASMG | T57: ELIE3 | U57: 49 733.07 | V57: 59 679.68 | W57: USD | X57: F | Y57: 46206 | Z57: 2026-07-06 | AA57: 46206 | AB57: 0000-00-00 | AC57: Régul support maintenance Alfred BacklogY2025-IC | AD57: YASSIE | AE57: YASSIE | AF57: C500 | AG57: E336_DTG | AH57: DTG-DOM | AI57: STD | AL57: E | AM57: E | AN57: ANDRIAMANANTSOA Elie | AO57: PULSE | AP57: RASAMOELINA Haritsoa Oliva | AR57: 14862 | AS57: 1 | AT57: UN | AU57: 49733.07 | AV57: PRESTATION DE SERVICE | AW57: C500 | AX57: 4 | AY57: 135527 | AZ57: 1 | BA57: 2026-06-18
A58: Pince dAncrage Câble ADSS  Fourreau Plastique  Courte Portée < 60m  Ø6-8mm  L300mm FOLAN | B58: 0 | C58: 3600 | D58: 3 600.00 | E58: 0 | F58: 138567 | G58: 1 | I58: PRMEQUI | J58: True | K58: DTG | L58: 2026-DT-061013 | M58: DTG-DOM | N58: NA | P58: 3000 | Q58: 3 600.00 | R58: YASMG | T58: ELIE3 | U58: 9 794.16 | V58: 9 794.16 | W58: EUR | Y58: 46206 | Z58: 2026-07-03 | AA58: 46206 | AB58: 0000-00-00 | AC58: Fournitures repose BKB RN12(accessoires)DTG-20260224-004 | AD58: YASSIE | AE58: GALE | AF58: C500 | AG58: 2026-DT-061013 | AH58: DTG-DOM | AI58: IMPORT | AL58: E | AM58: E | AN58: ANDRIAMANANTSOA Elie | AO58: FOLAN | AP58: RASAMOELINA Haritsoa Oliva | AR58: 23629 | AS58: 3000 | AT58: UN | AU58: 1.2 | AV58: PinceAncrage ADSS FourPlastiq Court 60m O6-8mmL300mmFOLAN | AW58: C500 | AX58: 2370 | AY58: 135528 | AZ58: 1 | BA58: 2026-06-30
A59: Console dAncrage Universelle FOLAN | B59: 0 | C59: 2580 | D59: 2 580.00 | E59: 0 | F59: 138567 | G59: 2 | I59: PRMEQUI | J59: True | K59: DTG | L59: 2026-DT-061013 | M59: DTG-DOM | N59: NA | P59: 1500 | Q59: 2 580.00 | R59: YASMG | T59: ELIE3 | U59: 9 794.16 | V59: 9 794.16 | W59: EUR | Y59: 46206 | Z59: 2026-07-03 | AA59: 46206 | AB59: 0000-00-00 | AC59: Fournitures repose BKB RN12(accessoires)DTG-20260224-004 | AD59: YASSIE | AE59: GALE | AF59: C500 | AG59: 2026-DT-061013 | AH59: DTG-DOM | AI59: IMPORT | AL59: E | AM59: E | AN59: ANDRIAMANANTSOA Elie | AO59: FOLAN | AP59: RASAMOELINA Haritsoa Oliva | AR59: 23630 | AS59: 1500 | AT59: UN | AU59: 1.72 | AV59: Console d Ancrage Universelle FOLAN | AW59: C500 | AX59: 2370 | AY59: 135528 | AZ59: 2 | BA59: 2026-06-30
A60: Croix de Lovage Taille L FOLAN | B60: 0 | C60: 364.2 | D60: 364.20 | E60: 0 | F60: 138567 | G60: 3 | I60: PRMEQUI | J60: True | K60: DTG | L60: 2026-DT-061013 | M60: DTG-DOM | N60: NA | P60: 60 | Q60: 364.20 | R60: YASMG | T60: ELIE3 | U60: 9 794.16 | V60: 9 794.16 | W60: EUR | Y60: 46206 | Z60: 2026-07-03 | AA60: 46206 | AB60: 0000-00-00 | AC60: Fournitures repose BKB RN12(accessoires)DTG-20260224-004 | AD60: YASSIE | AE60: GALE | AF60: C500 | AG60: 2026-DT-061013 | AH60: DTG-DOM | AI60: IMPORT | AL60: E | AM60: E | AN60: ANDRIAMANANTSOA Elie | AO60: FOLAN | AP60: RASAMOELINA Haritsoa Oliva | AR60: 23631 | AS60: 60 | AT60: UN | AU60: 6.07 | AV60: Croix de Lovage Taille S FOLAN | AW60: C500 | AX60: 2370 | AY60: 135528 | AZ60: 3 | BA60: 2026-06-30
A61: Feuillard 20x0,7mm Rouleau 50M FOLAN | B61: 0 | C61: 287.3 | D61: 287.30 | E61: 0 | F61: 138567 | G61: 4 | I61: PRMEQUI | J61: True | K61: DTG | L61: 2026-DT-061013 | M61: DTG-DOM | N61: NA | P61: 17 | Q61: 287.30 | R61: YASMG | T61: ELIE3 | U61: 9 794.16 | V61: 9 794.16 | W61: EUR | Y61: 46206 | Z61: 2026-07-03 | AA61: 46206 | AB61: 0000-00-00 | AC61: Fournitures repose BKB RN12(accessoires)DTG-20260224-004 | AD61: YASSIE | AE61: GALE | AF61: C500 | AG61: 2026-DT-061013 | AH61: DTG-DOM | AI61: IMPORT | AL61: E | AM61: E | AN61: ANDRIAMANANTSOA Elie | AO61: FOLAN | AP61: RASAMOELINA Haritsoa Oliva | AR61: 23633 | AS61: 17 | AT61: UN | AU61: 16.9 | AV61: Feuillard 20x0,7mm Rouleau 50M FOLAN | AW61: C500 | AX61: 2370 | AY61: 135528 | AZ61: 4 | BA61: 2026-06-30
A62: Agrafe pour feuillard 21mm (Sachet de 200) | B62: 0 | C62: 123.76 | D62: 123.76 | E62: 0 | F62: 138567 | G62: 5 | I62: GELACCS | J62: True | K62: DTG | L62: 2026-DT-061013 | M62: DTG-DOM | N62: NA | P62: 8 | Q62: 123.76 | R62: YASMG | T62: ELIE3 | U62: 9 794.16 | V62: 9 794.16 | W62: EUR | Y62: 46206 | Z62: 2026-07-03 | AA62: 46206 | AB62: 0000-00-00 | AC62: Fournitures repose BKB RN12(accessoires)DTG-20260224-004 | AD62: YASSIE | AE62: GALE | AF62: C500 | AG62: 2026-DT-061013 | AH62: DTG-DOM | AI62: IMPORT | AL62: E | AM62: E | AN62: ANDRIAMANANTSOA Elie | AO62: FOLAN | AP62: RASAMOELINA Haritsoa Oliva | AR62: 23634 | AS62: 8 | AT62: UN | AU62: 15.47 | AV62: Agrafe pour feuillard 21mm (Sachet de 200) | AW62: C500 | AX62: 2370 | AY62: 135528 | AZ62: 5 | BA62: 2026-06-30
A63: Boîtier Étanche Dôme 12-288FO pr 144FO+dispositifs détanchéité entrées 4et16(5-7 mm)+notice+12K7 12épissures FOLAN | B63: 0 | C63: 2838.9 | D63: 2 838.90 | E63: 0 | F63: 138567 | G63: 6 | I63: PRMEQUI | J63: True | K63: DTG | L63: 2026-DT-061013 | M63: DTG-DOM | N63: NA | P63: 30 | Q63: 2 838.90 | R63: YASMG | T63: ELIE3 | U63: 9 794.16 | V63: 9 794.16 | W63: EUR | Y63: 46206 | Z63: 2026-07-03 | AA63: 46206 | AB63: 0000-00-00 | AC63: Fournitures repose BKB RN12(accessoires)DTG-20260224-004 | AD63: YASSIE | AE63: GALE | AF63: C500 | AG63: 2026-DT-061013 | AH63: DTG-DOM | AI63: IMPORT | AL63: E | AM63: E | AN63: ANDRIAMANANTSOA Elie | AO63: FOLAN | AP63: RASAMOELINA Haritsoa Oliva | AR63: 23632 | AS63: 30 | AT63: UN | AU63: 94.63 | AV63: BoitierEtanche12-288pr144FOdispoentr4mntic12K7épissurFOLAN | AW63: C500 | AX63: 2370 | AY63: 135528 | AZ63: 6 | BA63: 2026-06-30
A64: CREMA & AROMA# DEVIS N° PF192096 DU 02/07/2026 | B64: 0 | C64: 129166.67 | D64: 155 000.00 | E64: 20 | F64: 138822 | G64: 1 | I64: LABCONS | J64: True | K64: DG | L64: E219_DG | M64: DG | N64: NA | P64: 50 | Q64: 129 166.67 | R64: YASMG | T64: NADIA7 | U64: 268 333.34 | V64: 320 000.00 | W64: MGA | Y64: 46206 | Z64: 2026-07-03 | AA64: 46206 | AB64: 0000-00-00 | AC64: DG-TRANSFO COLLATION Q2 2026 | AD64: YASSIE | AE64: YASSIE | AF64: C900 | AG64: E219_DG | AH64: DG | AI64: STD | AL64: E | AM64: E | AN64: RAVONINJATOVO Nadia | AO64: CENTRALE ALIMENTAIRE SARL | AP64: RASOLOJAONA Miora | AR64: 14620 | AS64: 50 | AT64: UN | AU64: 2583.3333 | AV64: CREMA AROMA GRAN ESPRESSO | AW64: C900 | AX64: 765 | AY64: 135529 | AZ64: 1 | BA64: 2026-07-03
A65: CREMA & AROMA GRAN CAFFE | B65: 0 | C65: 129166.67 | D65: 155 000.00 | E65: 20 | F65: 138822 | G65: 2 | I65: LABCONS | J65: True | K65: DG | L65: E219_DG | M65: DG | N65: NA | P65: 50 | Q65: 129 166.67 | R65: YASMG | T65: NADIA7 | U65: 268 333.34 | V65: 320 000.00 | W65: MGA | Y65: 46206 | Z65: 2026-07-03 | AA65: 46206 | AB65: 0000-00-00 | AC65: DG-TRANSFO COLLATION Q2 2026 | AD65: YASSIE | AE65: YASSIE | AF65: C900 | AG65: E219_DG | AH65: DG | AI65: STD | AL65: E | AM65: E | AN65: RAVONINJATOVO Nadia | AO65: CENTRALE ALIMENTAIRE SARL | AP65: RASOLOJAONA Miora | AR65: 14620 | AS65: 50 | AT65: UN | AU65: 2583.3333 | AV65: CREMA AROMA GRAN ESPRESSO | AW65: C900 | AX65: 765 | AY65: 135529 | AZ65: 2 | BA65: 2026-07-03
A66: FRAIS DE LIVRAISON | B66: 0 | C66: 10000 | D66: 10 000.00 | E66: 0 | F66: 138822 | G66: 3 | I66: TRNTERM | J66: True | K66: DG | L66: E219_DG | M66: DG | N66: NA | P66: 1 | Q66: 10 000.00 | R66: YASMG | T66: NADIA7 | U66: 268 333.34 | V66: 320 000.00 | W66: MGA | Y66: 46206 | Z66: 2026-07-03 | AA66: 46206 | AB66: 0000-00-00 | AC66: DG-TRANSFO COLLATION Q2 2026 | AD66: YASSIE | AE66: YASSIE | AF66: C900 | AG66: E219_DG | AH66: DG | AI66: STD | AL66: E | AM66: E | AN66: RAVONINJATOVO Nadia | AO66: CENTRALE ALIMENTAIRE SARL | AP66: RASOLOJAONA Miora | AR66: 3507 | AS66: 1 | AT66: PIE | AU66: 10000 | AV66: FRAIS DE LIVRAISON | AW66: C900 | AX66: 765 | AY66: 135529 | AZ66: 3 | BA66: 2026-07-03
A67: Sponsoring Festival SOMAROHO - FA n°FASW00329 du 12/06/2026 | B67: 0 | C67: 180000000 | D67: 180 000 000.00 | E67: 0 | F67: 138630 | G67: 1 | I67: MECSPDC | J67: True | K67: DCG | L67: E110_PS_DCOM | M67: DCG-COM-PART | N67: NA | P67: 1 | Q67: 180 000 000.00 | R67: YASMG | T67: FELANA13 | U67: 180 000 000.00 | V67: 180 000 000.00 | W67: MGA | X67: F | Y67: 46206 | Z67: 2026-07-06 | AA67: 46206 | AB67: 0000-00-00 | AC67: Sponsoring Festival SOMAROHO | AD67: YASSIE | AE67: YASSIE | AF67: C100 | AG67: E110_PS_DCOM | AH67: DCG-COM-PART | AI67: STD | AL67: E | AM67: E | AN67: Felana RARIVOSON | AO67: SW PRO SARL | AP67: ANDRIAMIRIJA Luca | AR67: 1267 | AS67: 1 | AT67: UN | AU67: 180000000 | AV67: SPONSORING | AW67: C100 | AX67: 2801 | AY67: 135530 | AZ67: 1 | BA67: 2026-06-23
A68: Location Salle & Sonorisation - Proforma n°22/2026/F | B68: 0 | C68: 300000 | D68: 300 000.00 | E68: 0 | F68: 138732 | G68: 1 | I68: LOCLOCT | J68: True | K68: DCG | L68: E219_DCG | M68: DCG-DVI | N68: NA | P68: 1 | Q68: 300 000.00 | R68: YASMG | T68: FELANA13 | U68: 1 830 000.00 | V68: 1 830 000.00 | W68: MGA | X68: F | Y68: 46209 | Z68: 2026-07-06 | AA68: 46209 | AB68: 0000-00-00 | AC68: Séminaire RAS_RC Bongolava | AD68: YASSIE | AE68: YASSIE | AF68: C104 | AG68: E219_DCG | AH68: DCG-DVI | AI68: STD | AL68: E | AM68: E | AN68: Felana RARIVOSON | AO68: RAFARASOA SUZANNE | AP68: ANDRIAMIRIJA Luca | AR68: 14417 | AS68: 1 | AT68: UN | AU68: 300000 | AV68: LOCATION | AW68: C104 | AX68: 6247 | AY68: 135531 | AZ68: 1 | BA68: 2026-06-30
A69: Déjeuner & Boisson - Proforma n°22/2026/F | B69: 0 | C69: 1530000 | D69: 1 530 000.00 | E69: 0 | F69: 138732 | G69: 2 | I69: VDPPERD | J69: True | K69: DCG | L69: E219_DCG | M69: DCG-DVI | N69: NA | P69: 90 | Q69: 1 530 000.00 | R69: YASMG | T69: FELANA13 | U69: 1 830 000.00 | V69: 1 830 000.00 | W69: MGA | X69: F | Y69: 46209 | Z69: 2026-07-06 | AA69: 46209 | AB69: 0000-00-00 | AC69: Séminaire RAS_RC Bongolava | AD69: YASSIE | AE69: YASSIE | AF69: C104 | AG69: E219_DCG | AH69: DCG-DVI | AI69: STD | AL69: E | AM69: E | AN69: Felana RARIVOSON | AO69: RAFARASOA SUZANNE | AP69: ANDRIAMIRIJA Luca | AR69: 12682 | AS69: 90 | AT69: UN | AU69: 17000 | AV69: COLLATION | AW69: C104 | AX69: 6247 | AY69: 135531 | AZ69: 2 | BA69: 2026-06-30
A70: TUYAU PEHD 32X2,4 PN12,5 100M # DEVIS : DEV26SAMB004289 | B70: 0 | C70: 18960000 | D70: 22 752 000.00 | E70: 20 | F70: 138767 | G70: 1 | I70: RESCBLT | J70: True | K70: DTG | L70: 2026-DT-102001 | M70: DTG-DOM | N70: NA | P70: 48 | Q70: 18 960 000.00 | R70: YASMG | T70: ELIE3 | U70: 15 309 570.00 | V70: 18 371 484.00 | W70: MGA | X70: F | Y70: 46209 | Z70: 2026-07-06 | AA70: 46209 | AB70: 0000-00-00 | AC70: Achat de Tuyaux PEHD | AD70: YASSIE | AE70: GALE | AF70: C500 | AG70: 2026-DT-102001 | AH70: DTG-DOM | AI70: STD | AL70: E | AM70: E | AN70: ANDRIAMANANTSOA Elie | AO70: SMTP | AP70: RASAMOELINA Haritsoa Oliva | AR70: 12516 | AS70: 48 | AT70: M | AU70: 395000 | AV70: TUYAUX PEHD NOIR 32X2,4 PN 12,5 | AW70: C500 | AX70: 1893 | AY70: 135532 | AZ70: 1 | BA70: 2026-07-06
A71: MANCHON PEHD A SERRER D32 # DEVIS : DEV26SAMB004289 | B71: 0 | C71: 141570 | D71: 169 884.00 | E71: 20 | F71: 138767 | G71: 2 | I71: OUTOUTL | J71: True | K71: DTG | L71: 2026-DT-102001 | M71: DTG-DOM | N71: NA | P71: 15 | Q71: 141 570.00 | R71: YASMG | T71: ELIE3 | U71: 15 309 570.00 | V71: 18 371 484.00 | W71: MGA | X71: F | Y71: 46209 | Z71: 2026-07-06 | AA71: 46209 | AB71: 0000-00-00 | AC71: Achat de Tuyaux PEHD | AD71: YASSIE | AE71: GALE | AF71: C500 | AG71: 2026-DT-102001 | AH71: DTG-DOM | AI71: STD | AL71: E | AM71: E | AN71: ANDRIAMANANTSOA Elie | AO71: SMTP | AP71: RASAMOELINA Haritsoa Oliva | AR71: 14460 | AS71: 15 | AT71: UN | AU71: 9438 | AV71: Manchon PEHD D32 à serrer | AW71: C500 | AX71: 1893 | AY71: 135532 | AZ71: 2 | BA71: 2026-07-06
A72: REMISE | B72: 0 | C72: -3792000 | D72: -4 550 400.00 | E72: 20 | F72: 138767 | G72: 3 | I72: GELACCS | J72: True | K72: DTG | L72: 2026-DT-102001 | M72: DTG-DOM | N72: NA | P72: 1 | Q72: -3 792 000.00 | R72: YASMG | T72: ELIE3 | U72: 15 309 570.00 | V72: 18 371 484.00 | W72: MGA | X72: F | Y72: 46209 | Z72: 2026-07-06 | AA72: 46209 | AB72: 0000-00-00 | AC72: Achat de Tuyaux PEHD | AD72: YASSIE | AE72: GALE | AF72: C500 | AG72: 2026-DT-102001 | AH72: DTG-DOM | AI72: STD | AL72: E | AM72: E | AN72: ANDRIAMANANTSOA Elie | AO72: SMTP | AP72: RASAMOELINA Haritsoa Oliva | AR72: 2057 | AS72: 1 | AT72: UN | AU72: -3792000 | AV72: REMISE | AW72: C500 | AX72: 1893 | AY72: 135532 | AZ72: 3 | BA72: 2026-07-06
A73: Location des camions pour transport STAND FIBRE - proforma N° PF YAS N° 160-06/LC/2026 | B73: 0 | C73: 13995000 | D73: 13 995 000.00 | E73: 0 | F73: 138713 | G73: 1 | I73: LOCLOCT | J73: True | K73: DCG | L73: E254_DCG | M73: DCG-DRB | N73: NA | P73: 0 | Q73: 0.00 | R73: YASMG | T73: FELANA13 | U73: 13 995 000.00 | V73: 13 995 000.00 | W73: MGA | X73: F | Y73: 46209 | Z73: 2026-07-06 | AA73: 46209 | AB73: 0000-00-00 | AC73: Location des camions pour transport STAND FIBRE | AD73: YASSIE | AE73: YASSIE | AF73: C102 | AG73: E254_DCG | AH73: DCG-DRB | AI73: STD | AL73: S | AM73: S | AN73: Felana RARIVOSON | AO73: LUCKKY COMPANY | AP73: ANDRIAMIRIJA Luca | AR73: 14417 | AS73: 1 | AT73: UN | AU73: 13995000 | AV73: LOCATION | AW73: C102 | AX73: 3726 | AY73: 135533 | AZ73: 1 | BA73: 0000-00-00
A74: Publi reportage de 2min dans Jt le 02/04/2026 - devis n°DV00000073 DU 02/04/2026 | B74: 0 | C74: 250000 | D74: 300 000.00 | E74: 20 | F74: 138703 | G74: 1 | I74: MEDMEDI | J74: True | K74: DCG | L74: E110_MD_DCOM | M74: DCG-COM-MEDIA | N74: NA | P74: 1 | Q74: 250 000.00 | R74: YASMG | T74: FELANA13 | U74: 310 000.00 | V74: 372 000.00 | W74: MGA | X74: F | Y74: 46209 | Z74: 2026-07-06 | AA74: 46209 | AB74: 0000-00-00 | AC74: Diffusion Publi reportage - Couverture Réseau RP | AD74: YASSIE | AE74: YASSIE | AF74: C100 | AG74: E110_MD_DCOM | AH74: DCG-COM-MEDIA | AI74: STD | AL74: E | AM74: E | AN74: Felana RARIVOSON | AO74: RTV RECORD | AP74: ANDRIAMIRIJA Luca | AR74: 1265 | AS74: 1 | AT74: UN | AU74: 250000 | AV74: PUBLICITE ET ANNONCE | AW74: C100 | AX74: 973 | AY74: 135534 | AZ74: 1 | BA74: 2026-06-29
A75: Animation Radio - devis n°DV000000135 DU 15/06/2026 | B75: 0 | C75: 60000 | D75: 72 000.00 | E75: 20 | F75: 138703 | G75: 2 | I75: MEDMEDI | J75: True | K75: DCG | L75: E110_MD_DCOM | M75: DCG-COM-MEDIA | N75: NA | P75: 1 | Q75: 60 000.00 | R75: YASMG | T75: FELANA13 | U75: 310 000.00 | V75: 372 000.00 | W75: MGA | X75: F | Y75: 46209 | Z75: 2026-07-06 | AA75: 46209 | AB75: 0000-00-00 | AC75: Diffusion Publi reportage - Couverture Réseau RP | AD75: YASSIE | AE75: YASSIE | AF75: C100 | AG75: E110_MD_DCOM | AH75: DCG-COM-MEDIA | AI75: STD | AL75: E | AM75: E | AN75: Felana RARIVOSON | AO75: RTV RECORD | AP75: ANDRIAMIRIJA Luca | AR75: 1265 | AS75: 1 | AT75: UN | AU75: 60000 | AV75: PUBLICITE ET ANNONCE | AW75: C100 | AX75: 973 | AY75: 135534 | AZ75: 2 | BA75: 2026-06-29
A76: Désinstallation des caméras et bouton panique - Yas Store Ampefiloha - n°PR2606-10070 DU 23/06/2026 | B76: 0 | C76: 494700 | D76: 593 640.00 | E76: 20 | F76: 138691 | G76: 1 | I76: PRICTRL | J76: True | K76: DCG | L76: E232_DRB | M76: DCG-DRB | N76: NA | P76: 1 | Q76: 494 700.00 | R76: YASMG | T76: FELANA13 | U76: 1 484 100.00 | V76: 1 780 920.00 | W76: MGA | Y76: 46209 | Z76: 2026-07-06 | AA76: 46209 | AB76: 0000-00-00 | AC76: Déménagement Stores | AD76: YASSIE | AE76: YASSIE | AF76: C102 | AG76: E232_DRB | AH76: DCG-DRB | AI76: STD | AL76: E | AM76: E | AN76: Felana RARIVOSON | AO76: TECHNOALARME | AP76: ANDRIAMIRIJA Luca | AR76: 14862 | AS76: 1 | AT76: UN | AU76: 494700 | AV76: PRESTATION DE SERVICE | AW76: C102 | AX76: 132 | AY76: 135535 | AZ76: 1 | BA76: 2026-06-25
A77: Désinstallation des caméras et bouton panique - Yas Zoom Ankarondrano - n°PR2606-10071 | B77: 0 | C77: 494700 | D77: 593 640.00 | E77: 20 | F77: 138691 | G77: 2 | I77: PRICTRL | J77: True | K77: DCG | L77: E232_DRB | M77: DCG-DRB | N77: NA | P77: 1 | Q77: 494 700.00 | R77: YASMG | T77: FELANA13 | U77: 1 484 100.00 | V77: 1 780 920.00 | W77: MGA | Y77: 46209 | Z77: 2026-07-06 | AA77: 46209 | AB77: 0000-00-00 | AC77: Déménagement Stores | AD77: YASSIE | AE77: YASSIE | AF77: C102 | AG77: E232_DRB | AH77: DCG-DRB | AI77: STD | AL77: E | AM77: E | AN77: Felana RARIVOSON | AO77: TECHNOALARME | AP77: ANDRIAMIRIJA Luca | AR77: 14862 | AS77: 1 | AT77: UN | AU77: 494700 | AV77: PRESTATION DE SERVICE | AW77: C102 | AX77: 132 | AY77: 135535 | AZ77: 2 | BA77: 2026-06-25
A78: Désinstallation des caméras et bouton panique - Yas Store Smart Tanjombato - n°PR2606-10072 | B78: 0 | C78: 494700 | D78: 593 640.00 | E78: 20 | F78: 138691 | G78: 3 | I78: PRICTRL | J78: True | K78: DCG | L78: E232_DRB | M78: DCG-DRB | N78: NA | P78: 1 | Q78: 494 700.00 | R78: YASMG | T78: FELANA13 | U78: 1 484 100.00 | V78: 1 780 920.00 | W78: MGA | Y78: 46209 | Z78: 2026-07-06 | AA78: 46209 | AB78: 0000-00-00 | AC78: Déménagement Stores | AD78: YASSIE | AE78: YASSIE | AF78: C102 | AG78: E232_DRB | AH78: DCG-DRB | AI78: STD | AL78: E | AM78: E | AN78: Felana RARIVOSON | AO78: TECHNOALARME | AP78: ANDRIAMIRIJA Luca | AR78: 14862 | AS78: 1 | AT78: UN | AU78: 494700 | AV78: PRESTATION DE SERVICE | AW78: C102 | AX78: 132 | AY78: 135535 | AZ78: 3 | BA78: 2026-06-25
A79: Location Sprinter le 18 et 19 juin 2026 - Proforma n°5790626 DU 16/06/2026 | B79: 0 | C79: 320000 | D79: 320 000.00 | E79: 0 | F79: 138680 | G79: 1 | I79: LOCLOCT | J79: True | K79: DCG | L79: E222_DRB | M79: DCG-DRB | N79: NA | P79: 2 | Q79: 320 000.00 | R79: YASMG | T79: FELANA13 | U79: 320 000.00 | V79: 320 000.00 | W79: MGA | X79: F | Y79: 46209 | Z79: 2026-07-06 | AA79: 46209 | AB79: 0000-00-00 | AC79: Location Sprinter - Foire de la Fibre | AD79: YASSIE | AE79: YASSIE | AF79: C102 | AG79: E222_DRB | AH79: DCG-DRB | AI79: STD | AL79: E | AM79: E | AN79: Felana RARIVOSON | AO79: RAMPARISON ANDRIAMIHAJA HANITRI (TOP LINK) | AP79: ANDRIAMIRIJA Luca | AR79: 14417 | AS79: 2 | AT79: UN | AU79: 160000 | AV79: LOCATION | AW79: C102 | AX79: 1104 | AY79: 135536 | AZ79: 1 | BA79: 2026-06-25
A80: IM- Un (01) VAD - Fianarantsoa-Tulear-Fianarantsoa du 01 au 09/07/2026 - PROFORMA N°308-A/FP/TELMA/2026 | B80: 0 | C80: 750000 | D80: 750 000.00 | E80: 0 | F80: 138662 | G80: 1 | I80: PRICTRL | J80: True | K80: DCG | L80: E214_DRB | M80: DCG-DRB | N80: NA | P80: 1 | Q80: 750 000.00 | R80: YASMG | T80: FELANA13 | U80: 750 000.00 | V80: 750 000.00 | W80: MGA | X80: F | Y80: 46209 | Z80: 2026-07-06 | AA80: 46209 | AB80: 0000-00-00 | AC80: IM VAD - Fianarantsoa-Tulear-Fianarantsoa | AD80: YASSIE | AE80: YASSIE | AF80: C102 | AG80: E214_DRB | AH80: DCG-DRB | AI80: STD | AL80: E | AM80: E | AN80: Felana RARIVOSON | AO80: LCS CONSULTING | AP80: ANDRIAMIRIJA Luca | AR80: 1264 | AS80: 1 | AT80: UN | AU80: 750000 | AV80: PRESTATION EXTERNE | AW80: C102 | AX80: 2490 | AY80: 135537 | AZ80: 1 | BA80: 2026-06-24
A81: IM- Treize (13) VAD - TANA-TULEAR-TANA (foire de la fibre 2026) du 29/06 au 12/07/2026 - PROFORMA N°310-A/FP/TELMA/2026 | B81: 0 | C81: 14120000 | D81: 14 120 000.00 | E81: 0 | F81: 138659 | G81: 1 | I81: PRICTRL | J81: True | K81: DCG | L81: E214_DRB | M81: DCG-DRB | N81: NA | P81: 1 | Q81: 14 120 000.00 | R81: YASMG | T81: FELANA13 | U81: 14 120 000.00 | V81: 14 120 000.00 | W81: MGA | X81: F | Y81: 46209 | Z81: 2026-07-06 | AA81: 46209 | AB81: 0000-00-00 | AC81: IM 13 VAD - TANA-TULEAR-TANA | AD81: YASSIE | AE81: YASSIE | AF81: C102 | AG81: E214_DRB | AH81: DCG-DRB | AI81: STD | AL81: E | AM81: E | AN81: Felana RARIVOSON | AO81: LCS CONSULTING | AP81: ANDRIAMIRIJA Luca | AR81: 1264 | AS81: 1 | AT81: UN | AU81: 14120000 | AV81: PRESTATION EXTERNE | AW81: C102 | AX81: 2490 | AY81: 135538 | AZ81: 1 | BA81: 2026-06-24
A82: Création de contenue et Egérie de la société YAS pour 2026 - Ambassadeur YAS # FActure N° INV-2026-001 | B82: 0 | C82: 45000000 | D82: 45 000 000.00 | E82: 0 | F82: 138655 | G82: 1 | I82: PRICTRL | J82: True | K82: DCG | L82: E110_AC_DCOM | M82: DCG-COM-PART | N82: NA | P82: 12 | Q82: 45 000 000.00 | R82: YASMG | T82: FELANA13 | U82: 45 000 000.00 | V82: 45 000 000.00 | W82: MGA | X82: F | Y82: 46209 | Z82: 2026-07-13 | AA82: 46209 | AB82: 0000-00-00 | AC82: Ambassadeur Oladad | AD82: YASSIE | AE82: YASSIE | AF82: C100 | AG82: E110_AC_DCOM | AH82: DCG-COM-PART | AI82: STD | AL82: E | AM82: E | AN82: Felana RARIVOSON | AO82: ANDRIATSILEFILAZANDRAMASY (OLADAD) | AP82: ANDRIAMIRIJA Luca | AR82: 14862 | AS82: 12 | AT82: UN | AU82: 3750000 | AV82: PRESTATION DE SERVICE | AW82: C100 | AX82: 5080 | AY82: 135539 | AZ82: 1 | BA82: 2026-06-24
A83: Organisation du salon régional du tourisme à Fianarantsoa - FA n°04/26 | B83: 0 | C83: 4000000 | D83: 4 000 000.00 | E83: 0 | F83: 138649 | G83: 1 | I83: MECSPDC | J83: True | K83: DCG | L83: E110_PS_DCOM | M83: DCG-COM-PART | N83: NA | P83: 1 | Q83: 4 000 000.00 | R83: YASMG | T83: FELANA13 | U83: 4 000 000.00 | V83: 4 000 000.00 | W83: MGA | X83: F | Y83: 46209 | Z83: 2026-07-06 | AA83: 46209 | AB83: 0000-00-00 | AC83: Salon Régional du Tourisme | AD83: YASSIE | AE83: YASSIE | AF83: C100 | AG83: E110_PS_DCOM | AH83: DCG-COM-PART | AI83: STD | AL83: E | AM83: E | AN83: Felana RARIVOSON | AO83: OFFICE REGIONAL DU TOURISME DE FIANARANTSOA | AP83: ANDRIAMIRIJA Luca | AR83: 1267 | AS83: 1 | AT83: UN | AU83: 4000000 | AV83: SPONSORING | AW83: C100 | AX83: 7128 | AY83: 135540 | AZ83: 1 | BA83: 2026-06-24
A84: Transport Mobiliers - YS Avenue Tamatave - AR n°AR2606RA50854950 | B84: 0 | C84: 437452.8 | D84: 524 943.36 | E84: 20 | F84: 138628 | G84: 1 | I84: TRNTERM | J84: True | K84: DCG | L84: E254_DCG | M84: DCG-DRB | N84: NA | P84: 1 | Q84: 437 452.80 | R84: YASMG | T84: FELANA13 | U84: 437 452.80 | V84: 524 943.36 | W84: MGA | Y84: 46209 | Z84: 2026-07-06 | AA84: 46209 | AB84: 0000-00-00 | AC84: Transport Mobiliers | AD84: YASSIE | AE84: YASSIE | AF84: C102 | AG84: E254_DCG | AH84: DCG-DRB | AI84: STD | AL84: E | AM84: E | AN84: Felana RARIVOSON | AO84: COLIS EXPRESS | AP84: ANDRIAMIRIJA Luca | AR84: 4276 | AS84: 1 | AT84: UN | AU84: 437452.8 | AV84: TRANSPORT | AW84: C102 | AX84: 30 | AY84: 135541 | AZ84: 1 | BA84: 2026-06-23
A85: Spot 30s - devis n°DV0000084 | B85: 0 | C85: 69120 | D85: 82 944.00 | E85: 20 | F85: 138606 | G85: 1 | I85: MEDMEDI | J85: True | K85: DCG | L85: E110_AP_DCOM | M85: DCG-COM-PART | N85: NA | P85: 5 | Q85: 69 120.00 | R85: YASMG | T85: FELANA13 | U85: 69 120.00 | V85: 82 944.00 | W85: MGA | Y85: 46209 | Z85: 2026-07-06 | AA85: 46209 | AB85: 0000-00-00 | AC85: Spot - Tournoi Inter Universitaire | AD85: YASSIE | AE85: YASSIE | AF85: C100 | AG85: E110_AP_DCOM | AH85: DCG-COM-PART | AI85: STD | AL85: E | AM85: E | AN85: Felana RARIVOSON | AO85: RTV RECORD | AP85: ANDRIAMIRIJA Luca | AR85: 1265 | AS85: 5 | AT85: UN | AU85: 13824 | AV85: PUBLICITE ET ANNONCE | AW85: C100 | AX85: 973 | AY85: 135542 | AZ85: 1 | BA85: 2026-06-22
A86: Sponsoring NPC 2eme Edition 2026 #FACTURE | B86: 0 | C86: 1500000 | D86: 1 500 000.00 | E86: 0 | F86: 138547 | G86: 1 | I86: MECSPDC | J86: True | K86: DCG | L86: E110_PS_DCOM | M86: DCG-COM-PART | N86: NA | P86: 1 | Q86: 1 500 000.00 | R86: YASMG | T86: FELANA13 | U86: 1 500 000.00 | V86: 1 500 000.00 | W86: MGA | X86: F | Y86: 46209 | Z86: 2026-07-06 | AA86: 46209 | AB86: 0000-00-00 | AC86: Sponsoring NPC 2026 | AD86: YASSIE | AE86: YASSIE | AF86: C100 | AG86: E110_PS_DCOM | AH86: DCG-COM-PART | AI86: STD | AL86: E | AM86: E | AN86: Felana RARIVOSON | AO86: Latitude communication | AP86: ANDRIAMIRIJA Luca | AR86: 1267 | AS86: 1 | AT86: UN | AU86: 1500000 | AV86: SPONSORING | AW86: C100 | AX86: 5970 | AY86: 135543 | AZ86: 1 | BA86: 2026-06-18
A87: Sponsor Officiel - Salon de l'Etudiant et de l'Emploi 2026 - FA n°123 SEE 2026 | B87: 0 | C87: 4000000 | D87: 4 000 000.00 | E87: 0 | F87: 138819 | G87: 1 | I87: MECSPDC | J87: True | K87: DCG | L87: E110_GE_DCOM | M87: DCG-COM-PART | N87: NA | P87: 1 | Q87: 4 000 000.00 | R87: YASMG | T87: FELANA13 | U87: 4 000 000.00 | V87: 4 000 000.00 | W87: MGA | X87: F | Y87: 46209 | Z87: 2026-07-06 | AA87: 46209 | AB87: 0000-00-00 | AC87: Sponsoring - Salon de l'Etudiant et de l'Emploi 2026 | AD87: YASSIE | AE87: YASSIE | AF87: C100 | AG87: E110_GE_DCOM | AH87: DCG-COM-PART | AI87: STD | AL87: E | AM87: E | AN87: Felana RARIVOSON | AO87: RATSIMBAZAFY PASKALINARISOA(PUBLIKA MADA) | AP87: ANDRIAMIRIJA Luca | AR87: 1267 | AS87: 1 | AT87: UN | AU87: 4000000 | AV87: SPONSORING | AW87: C100 | AX87: 755 | AY87: 135544 | AZ87: 1 | BA87: 2026-07-03
A88: IM équipe Coordinateur D2D - Razakatiana Tsiry - Fianarantsoa-Tulear-Fizanarantsoa - FA n°INV-13034 | B88: 0 | C88: 762000 | D88: 762 000.00 | E88: 0 | F88: 138816 | G88: 1 | I88: PRICTRL | J88: True | K88: DCG | L88: E214_DRB | M88: DCG-DRB | N88: NA | P88: 1 | Q88: 762 000.00 | R88: YASMG | T88: FELANA13 | U88: 2 822 500.00 | V88: 2 822 500.00 | W88: MGA | X88: F | Y88: 46209 | Z88: 2026-07-06 | AA88: 46209 | AB88: 0000-00-00 | AC88: IM équipes Coordinateurs D2D | AD88: YASSIE | AE88: YASSIE | AF88: C102 | AG88: E214_DRB | AH88: DCG-DRB | AI88: STD | AL88: E | AM88: E | AN88: Felana RARIVOSON | AO88: MADAJOB | AP88: ANDRIAMIRIJA Luca | AR88: 1264 | AS88: 1 | AT88: UN | AU88: 762000 | AV88: PRESTATION EXTERNE | AW88: C102 | AX88: 723 | AY88: 135545 | AZ88: 1 | BA88: 2026-07-03
A89: IM équipe Coordinateur D2D - Maya Raly Andrimihaja - TANA-TULEAR-TANA - FA n°INV-13035 | B89: 0 | C89: 952000 | D89: 952 000.00 | E89: 0 | F89: 138816 | G89: 2 | I89: PRICTRL | J89: True | K89: DCG | L89: E214_DRB | M89: DCG-DRB | N89: NA | P89: 1 | Q89: 952 000.00 | R89: YASMG | T89: FELANA13 | U89: 2 822 500.00 | V89: 2 822 500.00 | W89: MGA | X89: F | Y89: 46209 | Z89: 2026-07-06 | AA89: 46209 | AB89: 0000-00-00 | AC89: IM équipes Coordinateurs D2D | AD89: YASSIE | AE89: YASSIE | AF89: C102 | AG89: E214_DRB | AH89: DCG-DRB | AI89: STD | AL89: E | AM89: E | AN89: Felana RARIVOSON | AO89: MADAJOB | AP89: ANDRIAMIRIJA Luca | AR89: 1264 | AS89: 1 | AT89: UN | AU89: 952000 | AV89: PRESTATION EXTERNE | AW89: C102 | AX89: 723 | AY89: 135545 | AZ89: 2 | BA89: 2026-07-03
A90: IM équipe Coordinateur D2D - Nandrianina NAMBININTSOA FIONONANA - TANA-TULEAR-TANA - FA n°INV-13036 | B90: 0 | C90: 1108500 | D90: 1 108 500.00 | E90: 0 | F90: 138816 | G90: 3 | I90: PRICTRL | J90: True | K90: DCG | L90: E214_DRB | M90: DCG-DRB | N90: NA | P90: 1 | Q90: 1 108 500.00 | R90: YASMG | T90: FELANA13 | U90: 2 822 500.00 | V90: 2 822 500.00 | W90: MGA | X90: F | Y90: 46209 | Z90: 2026-07-06 | AA90: 46209 | AB90: 0000-00-00 | AC90: IM équipes Coordinateurs D2D | AD90: YASSIE | AE90: YASSIE | AF90: C102 | AG90: E214_DRB | AH90: DCG-DRB | AI90: STD | AL90: E | AM90: E | AN90: Felana RARIVOSON | AO90: MADAJOB | AP90: ANDRIAMIRIJA Luca | AR90: 1264 | AS90: 1 | AT90: UN | AU90: 1108500 | AV90: PRESTATION EXTERNE | AW90: C102 | AX90: 723 | AY90: 135545 | AZ90: 3 | BA90: 2026-07-03
A91: Nettoyage stand YAS foire de la FIBRE 6 et 7 juillet #Devis du 24/06/2026 | B91: 0 | C91: 350000 | D91: 420 000.00 | E91: 20 | F91: 138754 | G91: 1 | I91: PRICTRL | J91: True | K91: DCG | L91: E250_DRB | M91: DCG-DRB | N91: NA | P91: 1 | Q91: 350 000.00 | R91: YASMG | T91: FELANA13 | U91: 350 000.00 | V91: 420 000.00 | W91: MGA | X91: F | Y91: 46209 | Z91: 2026-07-06 | AA91: 46209 | AB91: 0000-00-00 | AC91: Foire de la Fibre Tuléar | AD91: YASSIE | AE91: YASSIE | AF91: C102 | AG91: E250_DRB | AH91: DCG-DRB | AI91: STD | AL91: Z | AM91: Z | AN91: Felana RARIVOSON | AO91: AUGIAS MADAGASCAR | AP91: ANDRIAMIRIJA Luca | AR91: 14862 | AS91: 1 | AT91: UN | AU91: 350000 | AV91: PRESTATION DE SERVICE | AW91: C102 | AX91: 14 | AY91: 135546 | AZ91: 1 | BA91: 2026-06-30
A92: Location Mobiliers - Foire de la Fibre Tuléar - PROFORMA N°0015/06/BS/2026 du 23/06/2026 | B92: 0 | C92: 3800000 | D92: 3 800 000.00 | E92: 0 | F92: 138812 | G92: 1 | I92: LOCLOCT | J92: True | K92: DCG | L92: E250_DRB | M92: DCG-DRB | N92: NA | P92: 1 | Q92: 3 800 000.00 | R92: YASMG | T92: FELANA13 | U92: 3 800 000.00 | V92: 3 800 000.00 | W92: MGA | X92: F | Y92: 46209 | Z92: 2026-07-06 | AA92: 46209 | AB92: 0000-00-00 | AC92: Location Mobiliers - Foire de la Fibre Tulear | AD92: YASSIE | AE92: YASSIE | AF92: C102 | AG92: E250_DRB | AH92: DCG-DRB | AI92: STD | AL92: E | AM92: E | AN92: Felana RARIVOSON | AO92: BAKAO SERVICES | AP92: ANDRIAMIRIJA Luca | AR92: 14417 | AS92: 1 | AT92: UN | AU92: 3800000 | AV92: LOCATION | AW92: C102 | AX92: 3278 | AY92: 135547 | AZ92: 1 | BA92: 2026-07-03
A93: Stickers Stand Fibre Jaune - 150*360cm - Devis n°FP05104 - Regul | B93: 0 | C93: 945000 | D93: 1 134 000.00 | E93: 20 | F93: 138800 | G93: 1 | I93: GOOAFIM | J93: True | K93: DCG | L93: E110_TR_DRB | M93: DCG-DRB | N93: NA | P93: 5 | Q93: 945 000.00 | R93: YASMG | T93: FELANA13 | U93: 1 102 600.00 | V93: 1 323 120.00 | W93: MGA | X93: F | Y93: 46209 | Z93: 2026-07-06 | AA93: 46209 | AB93: 0000-00-00 | AC93: Stickers Stand Fibre | AD93: YASSIE | AE93: YASSIE | AF93: C102 | AG93: E110_TR_DRB | AH93: DCG-DRB | AI93: STD | AL93: E | AM93: E | AN93: Felana RARIVOSON | AO93: SIGN | AP93: ANDRIAMIRIJA Luca | AR93: 3921 | AS93: 5 | AT93: UN | AU93: 189000 | AV93: STICKERS | AW93: C102 | AX93: 1089 | AY93: 135548 | AZ93: 1 | BA93: 2026-07-02
A94: Stickers Stand Fibre Jaune - 150*150cm - Devis n°FP05104 | B94: 0 | C94: 157600 | D94: 189 120.00 | E94: 20 | F94: 138800 | G94: 2 | I94: GOOAFIM | J94: True | K94: DCG | L94: E110_TR_DRB | M94: DCG-DRB | N94: NA | P94: 2 | Q94: 157 600.00 | R94: YASMG | T94: FELANA13 | U94: 1 102 600.00 | V94: 1 323 120.00 | W94: MGA | X94: F | Y94: 46209 | Z94: 2026-07-06 | AA94: 46209 | AB94: 0000-00-00 | AC94: Stickers Stand Fibre | AD94: YASSIE | AE94: YASSIE | AF94: C102 | AG94: E110_TR_DRB | AH94: DCG-DRB | AI94: STD | AL94: E | AM94: E | AN94: Felana RARIVOSON | AO94: SIGN | AP94: ANDRIAMIRIJA Luca | AR94: 3921 | AS94: 2 | AT94: UN | AU94: 78800 | AV94: STICKERS | AW94: C102 | AX94: 1089 | AY94: 135548 | AZ94: 2 | BA94: 2026-07-02
A95: Sponsoring coupe de lindépendance 2026 - Partenariat Ville Commune Antehiroka | B95: 0 | C95: 3000000 | D95: 3 000 000.00 | E95: 0 | F95: 138799 | G95: 1 | I95: MECSPDC | J95: True | K95: DCG | L95: E110_HM_DCOM | M95: DCG-COM-HMED | N95: NA | P95: 1 | Q95: 3 000 000.00 | R95: YASMG | T95: FELANA13 | U95: 3 000 000.00 | V95: 3 000 000.00 | W95: MGA | X95: F | Y95: 46209 | Z95: 2026-07-06 | AA95: 46209 | AB95: 0000-00-00 | AC95: Partenariat Commune Antehiroka | AD95: YASSIE | AE95: YASSIE | AF95: C100 | AG95: E110_HM_DCOM | AH95: DCG-COM-HMED | AI95: STD | AL95: E | AM95: E | AN95: Felana RARIVOSON | AO95: COMMUNE ANTEHIROKA | AP95: ANDRIAMIRIJA Luca | AR95: 1267 | AS95: 1 | AT95: UN | AU95: 3000000 | AV95: SPONSORING | AW95: C100 | AX95: 1482 | AY95: 135549 | AZ95: 1 | BA95: 2026-07-02
A96: Travaux de Maintenance option 2 - Montage et Démontage Stand # Devis du 1/07/2026 | B96: 0 | C96: 10460925 | D96: 12 553 110.00 | E96: 20 | F96: 138798 | G96: 1 | I96: PRICTRL | J96: False | K96: DCG | L96: E250_DRB | M96: DCG-DRB | N96: NA | P96: 0 | Q96: 0.00 | R96: YASMG | T96: FELANA13 | U96: 10 460 925.00 | V96: 12 553 110.00 | W96: MGA | X96: F | Y96: 46209 | Z96: 2026-07-06 | AA96: 46209 | AB96: 0000-00-00 | AC96: Montage et Démontage Stand - Foire de la FIbre Tuléar | AD96: YASSIE | AE96: YASSIE | AF96: C102 | AG96: E250_DRB | AH96: DCG-DRB | AI96: STD | AL96: S | AM96: S | AN96: Felana RARIVOSON | AO96: GLOBAL CONSTRUCTION MADAGASCAR | AP96: ANDRIAMIRIJA Luca | AR96: 11533 | AS96: 1 | AT96: PIE | AU96: 10460925 | AV96: PRESTATION DIVERS | AW96: C102 | AX96: 2404 | AY96: 135550 | AZ96: 1 | BA96: 2026-07-02
A97: COFI 2026 - Moto Honda Ace 125 SHH 6DK - Grs Vatsy Services # devis du 18/5/2026 | B97: 0 | C97: 14983334 | D97: 17 980 000.80 | E97: 20 | F97: 138797 | G97: 1 | I97: PRMVEHI | J97: True | K97: DCG | L97: 2026-COFI | M97: DCG-DVI | N97: NA | P97: 2 | Q97: 14 983 334.00 | R97: YASMG | T97: FELANA13 | U97: 14 983 334.00 | V97: 17 980 000.80 | W97: MGA | X97: F | Y97: 46209 | Z97: 2026-07-06 | AA97: 46209 | AB97: 0000-00-00 | AC97: Cofi 2026 - GRS Vatsy Services | AD97: YASSIE | AE97: GALE | AF97: C104 | AG97: 2026-COFI | AH97: DCG-DVI | AI97: STD | AL97: E | AM97: E | AN97: Felana RARIVOSON | AO97: MADAGASCAR AUTOMOBILE | AP97: ANDRIAMIRIJA Luca | AR97: 4155 | AS97: 2 | AT97: UN | AU97: 7491667 | AV97: MOTO | AW97: C104 | AX97: 1184 | AY97: 135551 | AZ97: 1 | BA97: 2026-07-02
... A106: Transport FIM 2026 : Transport Tana-Majunga + déplacement des matériels dans la ville de Majunga - PROFORMA N°125-06/LC/2026 | B106: 0 | C106: 4450000 | D106: 4 450 000.00 | E106: 0 | F106: 138673 | G106: 1 | I106: TRNTERM | J106: True | K106: DCG | L106: E254_DCG | M106: DCG-DVE | N106: NA | P106: 0 | Q106: 0.00 | R106: YASMG | T106: FELANA13 | U106: 4 450 000.00 | V106: 4 450 000.00 | W106: MGA | X106: F | Y106: 46209 | Z106: 2026-07-06 | AA106: 46209 | AB106: 0000-00-00 | AC106: FIM 2026 & YBT ET ATELIER ADMIN MAJUNGA | AD106: YASSIE | AE106: YASSIE | AF106: C103 | AG106: E254_DCG | AH106: DCG-DVE | AI106: STD | AL106: S | AM106: S | AN106: Felana RARIVOSON | AO106: LUCKKY COMPANY | AP106: RAZAFINDRAHAGA Setra | AR106: 4276 | AS106: 1 | AT106: UN | AU106: 4450000 | AV106: TRANSPORT | AW106: C103 | AX106: 3726 | AY106: 135556 | AZ106: 1 | BA106: 0000-00-00
A107: Maintenance corrective : Recharge Extincteurs HS utilisés aux formations et exercices# FACTURE PROFORMA VIMSI MADAGASCAR N° 0023 - 06 / 2026 du 09/06/2026 | B107: 0 | C107: 9457500 | D107: 11 349 000.00 | E107: 20 | F107: 138770 | G107: 1 | I107: TCORADI | J107: True | K107: HSSES | L107: E250_DHE | M107: HSSES | N107: NA | P107: 1 | Q107: 9 457 500.00 | R107: YASMG | T107: NADIA7 | U107: 9 657 500.00 | V107: 11 589 000.00 | W107: MGA | Y107: 46209 | Z107: 2026-07-06 | AA107: 46209 | AB107: 0000-00-00 | AC107: Recharge des extincteurs | AD107: YASSIE | AE107: YASSIE | AF107: C901 | AG107: E250_DHE | AH107: HSSES | AI107: STD | AL107: E | AM107: E | AN107: RAVONINJATOVO Nadia | AO107: VIMSI MADAGASCAR | AP107: TSILIZY Olga Hasina | AR107: 9841 | AS107: 1 | AT107: PIE | AU107: 9457500 | AV107: EXTINCTEURS | AW107: C901 | AX107: 4263 | AY107: 135557 | AZ107: 1 | BA107: 2026-07-01
A108: Frais de transport recharge extincteur | B108: 0 | C108: 200000 | D108: 240 000.00 | E108: 20 | F108: 138770 | G108: 2 | I108: TRNTERM | J108: True | K108: HSSES | L108: E250_DHE | M108: HSSES | N108: NA | P108: 1 | Q108: 200 000.00 | R108: YASMG | T108: NADIA7 | U108: 9 657 500.00 | V108: 11 589 000.00 | W108: MGA | Y108: 46209 | Z108: 2026-07-06 | AA108: 46209 | AB108: 0000-00-00 | AC108: Recharge des extincteurs | AD108: YASSIE | AE108: YASSIE | AF108: C901 | AG108: E250_DHE | AH108: HSSES | AI108: STD | AL108: E | AM108: E | AN108: RAVONINJATOVO Nadia | AO108: VIMSI MADAGASCAR | AP108: TSILIZY Olga Hasina | AR108: 4276 | AS108: 1 | AT108: UN | AU108: 200000 | AV108: TRANSPORT | AW108: C901 | AX108: 4263 | AY108: 135557 | AZ108: 2 | BA108: 2026-07-01
A109: Soudure d'une chambre suite survey construction digue à Ankorondrano - Andraharo - Maki Andohatapenaka ITP-20250806-00007- DAET 13674 | B109: 0 | C109: 745000 | D109: 894 000.00 | E109: 20 | F109: 138233 | G109: 1 | I109: PRICTRL | J109: True | K109: DTG | L109: 2026-DT-102001 | M109: DTG-DSTC-INST1 | N109: NA | P109: 1 | Q109: 745 000.00 | R109: YASMG | T109: ELIE3 | U109: 10 238 514.00 | V109: 12 286 216.80 | W109: MGA | Y109: 46209 | Z109: 2026-07-06 | AA109: 46209 | AB109: 0000-00-00 | AC109: DAET 13674/13694/13695 | AD109: YASSIE | AE109: YASSIE | AF109: C500 | AG109: 2026-DT-102001 | AH109: DTG-DSTC-INST1 | AI109: STD | AL109: E | AM109: E | AN109: ANDRIAMANANTSOA Elie | AO109: EASY NETCOM | AP109: RASAMOELINA Haritsoa Oliva | AR109: 22417 | AS109: 1 | AT109: UN | AU109: 745000 | AV109: Travaux filaire | AW109: C500 | AX109: 2053 | AY109: 135558 | AZ109: 1 | BA109: 2026-06-11
A110: Implantation (4u) poteaux 9m, Dépose (1u) poteaux 8m et Pose (4U) traverse à AMBOHIMANAMBOLA suite passage convois exceptionnels JIRAMA ITP-20250917-00001- DAET 13674 | B110: 0 | C110: 532000 | D110: 638 400.00 | E110: 20 | F110: 138233 | G110: 2 | I110: PRICTRL | J110: True | K110: DTG | L110: 2026-DT-102001 | M110: DTG-DSTC-INST1 | N110: NA | P110: 1 | Q110: 532 000.00 | R110: YASMG | T110: ELIE3 | U110: 10 238 514.00 | V110: 12 286 216.80 | W110: MGA | Y110: 46209 | Z110: 2026-07-06 | AA110: 46209 | AB110: 0000-00-00 | AC110: DAET 13674/13694/13695 | AD110: YASSIE | AE110: YASSIE | AF110: C500 | AG110: 2026-DT-102001 | AH110: DTG-DSTC-INST1 | AI110: STD | AL110: E | AM110: E | AN110: ANDRIAMANANTSOA Elie | AO110: EASY NETCOM | AP110: RASAMOELINA Haritsoa Oliva | AR110: 22417 | AS110: 1 | AT110: UN | AU110: 532000 | AV110: Travaux filaire | AW110: C500 | AX110: 2053 | AY110: 135558 | AZ110: 2 | BA110: 2026-06-11
A111: Dépose, Implantation (1u) poteau bois de 8m et Réglage câble FO près du FJKM Ankadimbahoaka ITP-20260123-00002- DAET 13674 | B111: 0 | C111: 395000 | D111: 474 000.00 | E111: 20 | F111: 138233 | G111: 3 | I111: PRICTRL | J111: True | K111: DTG | L111: 2026-DT-102001 | M111: DTG-DSTC-INST1 | N111: NA | P111: 1 | Q111: 395 000.00 | R111: YASMG | T111: ELIE3 | U111: 10 238 514.00 | V111: 12 286 216.80 | W111: MGA | Y111: 46209 | Z111: 2026-07-06 | AA111: 46209 | AB111: 0000-00-00 | AC111: DAET 13674/13694/13695 | AD111: YASSIE | AE111: YASSIE | AF111: C500 | AG111: 2026-DT-102001 | AH111: DTG-DSTC-INST1 | AI111: STD | AL111: E | AM111: E | AN111: ANDRIAMANANTSOA Elie | AO111: EASY NETCOM | AP111: RASAMOELINA Haritsoa Oliva | AR111: 22417 | AS111: 1 | AT111: UN | AU111: 395000 | AV111: Travaux filaire | AW111: C500 | AX111: 2053 | AY111: 135558 | AZ111: 3 | BA111: 2026-06-11
...

Sheet Base traitement
A1: N__de_Cde | B1: Raison_sociale_Fournisseur | C1: Design__sommaire | D1: Designation_Complémentaire | E1: Quantité_comm | F1: Unité | G1: Prix_Unitaire | H1: PU_USD | I1: Total_HT_USD_Neg | J1: Total_HT_USD | K1: Valeur_remise_USD | L1: %remise | M1: Remise | N1: Devise | O1: Date_creat_BC | P1: Date_de_Validation_BC | Q1: V_Etat_commande_en_tête | R1: V_Etat_commande_ligne | S1: Nom_demandeur | T1: N__DA | U1: Date_creation_DA | V1: Date_Validation_DA | W1: Code_Direction | X1: Acheteur | Y1: Nom_Acheteur | Z1: V_Total_Ligne_TTC | AA1: TVA | AB1: N__Poste_DA | AC1: Site_Stock | AD1: Code_ss_famille | AE1: Saisie_de_réception__ | AF1: Code_complément | AG1: SS_compte_anal | AH1: Centre_d_Analyse | AI1: Accord_Cadre | AJ1: RAL | AK1: V_Montant_RAL | AL1: Code_Société | AM1: Avenant | AN1: Tot_CA_HT | AO1: Tot_CA_TTC | AP1: Etat_Financ_ | AQ1: Date_Période | AR1: Date_AR | AS1: Objet_CA | AT1: Ctr_Emetteur_entete | AU1: Ctr_Livraison_entete | AV1: Sect_Imputation_entete | AW1: Code_Complémentaire_entete | AX1: Sous_Compte_d_Analyse_entete | AY1: Type_document | AZ1: V_Expédition_soldée | BA1: Code_du_Modèle_de_Cde | BB1: V_Critère_de_saisie | BC1: Code_Article | BD1: Section_d_imput | BE1: Code_Fournis | BF1: N_Poste | BG1: Date_de_livr__prev_
A2: 135730 | B2: SANIFER | C2: REMISE | D2: REMISE | E2: 1 | F2: UN | G2: -45000 | H2: =IF(N2="USD",G2,IF(N2="MGA",G2/4600,IF(N2="EUR",G2*1.17,IF(N2="GBP",G2*1.35,"")))) -> -9.7826087 | I2: =H2*E2 -> -9.7826087 | J2: 9.7826087 | K2: =I2*(-1) -> 9.7826087 | M2: 0 | N2: MGA | O2: 46217 | P2: 2026-07-14 | Q2: E | R2: E | S2: RABIANOAVY Nasandratra Henintsoa | T2: 138912 | W2: DTG | X2: ELIE3 | Y2: ANDRIAMANANTSOA Elie | Z2: -54 000.00 | AA2: 20 | AB2: 0 | AD2: GELACCS | AE2: True | AF2: 2026-DT-103002 | AG2: DTG-DSTC-INTER | AH2: NA | AJ2: 1 | AK2: -45 000.00 | AL2: YASMG | AN2: 405 000.00 | AO2: 486 000.00 | AP2: F | AQ2: 46217 | AR2: 0000-00-00 | AS2: DSTC-SEI: Achat Urgente PRISE RJ45 CAT6 mosaïque | AT2: YASSIE | AU2: GALE | AV2: C500 | AW2: 2026-DT-103002 | AX2: DTG-DSTC-INTER | AY2: STD | BC2: 2057 | BD2: C500 | BE2: 116 | BF2: 2 | BG2: 2026-07-15
A3: 136018 | B3: PELCOM INTERNATIONAL SARL (OXEO) | C3: REMISE | E3: 1 | F3: UN | G3: -56000 | H3: =IF(N3="USD",G3,IF(N3="MGA",G3/4600,IF(N3="EUR",G3*1.17,IF(N3="GBP",G3*1.35,"")))) -> -12.173913 | I3: =H3*E3 -> -12.173913 | J3: 12.173913 | K3: =I3*(-1) -> 12.173913 | M3: 0 | N3: MGA | O3: 46233 | P3: 2026-07-30 | Q3: E | R3: E | T3: 0 | W3: DFG | X3: NADIA7 | Y3: RAVONINJATOVO Nadia | Z3: -67 200.00 | AA3: 20 | AB3: 0 | AD3: GELACCS | AE3: True | AF3: E218_DAF | AG3: DFG-DAF | AH3: NA | AJ3: 1 | AK3: -56 000.00 | AL3: YASMG | AN3: 1 060 000.00 | AO3: 1 272 000.00 | AP3: F | AQ3: 46233 | AR3: 0000-00-00 | AS3: DEVIS MICRO CASQUE_TEAM RECOUVREMENT_JUILLET 2026 | AT3: YASSIE | AU3: YASSIE | AV3: C700 | AW3: E218_DAF | AX3: DFG-DAF | AY3: STD | BC3: 2057 | BD3: C700 | BE3: 2079 | BF3: 2 | BG3: 2026-08-03
A4: 135643 | B4: PRIMA CE SARLU | C4: REMISE | D4: Remise 7% | E4: 1 | F4: UN | G4: -59500 | H4: =IF(N4="USD",G4,IF(N4="MGA",G4/4600,IF(N4="EUR",G4*1.17,IF(N4="GBP",G4*1.35,"")))) -> -12.934783 | I4: =H4*E4 -> -12.934783 | J4: 12.934783 | K4: =I4*(-1) -> 12.934783 | M4: 0 | N4: MGA | O4: 46210 | P4: 2026-07-07 | Q4: S | R4: S | S4: RASAMOELINA Haritsoa Oliva | T4: 138675 | W4: DTG | X4: ELIE3 | Y4: ANDRIAMANANTSOA Elie | Z4: -71 400.00 | AA4: 20 | AB4: 2 | AD4: GELACCS | AE4: True | AF4: 2026-DT-022001 | AG4: DTG-PROJETS | AH4: NA | AJ4: 0 | AK4: 0.00 | AL4: YASMG | AN4: 790 500.00 | AO4: 948 600.00 | AQ4: 46210 | AR4: 0000-00-00 | AS4: Tirage FO entre RDC et salle trans 2ème Etages | AT4: YASSIE | AU4: YASSIE | AV4: C500 | AW4: 2026-DT-022001 | AX4: DTG-PROJETS | AY4: STD | BC4: 2057 | BD4: C500 | BE4: 2633 | BF4: 2 | BG4: 0000-00-00
A5: 136016 | B5: CT MOTORS | C5: REMISE | D5: Remise 5% | E5: 1 | F5: UN | G5: -73333.337 | H5: =IF(N5="USD",G5,IF(N5="MGA",G5/4600,IF(N5="EUR",G5*1.17,IF(N5="GBP",G5*1.35,"")))) -> -15.94203 | I5: =H5*E5 -> -15.94203 | J5: 15.94203 | K5: =I5*(-1) -> 15.94203 | M5: 0 | N5: MGA | O5: 46232 | P5: 2026-07-29 | Q5: E | R5: E | S5: RASAMOELINA Haritsoa Oliva | T5: 139280 | W5: DTG | X5: ELIE3 | Y5: ANDRIAMANANTSOA Elie | Z5: -88 000.00 | AA5: 20 | AB5: 2 | AD5: GELACCS | AE5: True | AF5: E218_DTG | AG5: DTG | AH5: NA | AJ5: 1 | AK5: -73 333.34 | AL5: YASMG | AN5: 1 393 333.40 | AO5: 1 672 000.09 | AP5: F | AQ5: 46232 | AR5: 0000-00-00 | AS5: Achat Gant Street Black (22 paires)-motards Tanà | AT5: YASSIE | AU5: GALE | AV5: C500 | AW5: E218_DTG | AX5: DTG | AY5: STD | BC5: 2057 | BD5: C500 | BE5: 664 | BF5: 2 | BG5: 2026-08-04
A6: 135649 | B6: UNITE DE DISTRIBUTION TECHNOLOGIQUE - UDITEC | C6: REMISE | D6: Remise | E6: 1 | F6: UN | G6: -134750 | H6: =IF(N6="USD",G6,IF(N6="MGA",G6/4600,IF(N6="EUR",G6*1.17,IF(N6="GBP",G6*1.35,"")))) -> -29.293478 | I6: =H6*E6 -> -29.293478 | J6: 29.293478 | K6: =I6*(-1) -> 29.293478 | M6: 0 | N6: MGA | O6: 46211 | P6: 2026-07-08 | Q6: E | R6: E | S6: RASAMOELINA Haritsoa Oliva | T6: 138778 | W6: DTG | X6: ELIE3 | Y6: ANDRIAMANANTSOA Elie | Z6: -161 700.00 | AA6: 20 | AB6: 2 | AD6: GELACCS | AE6: True | AF6: 2026-DT-061003 | AG6: DTG-DOM | AH6: NA | AJ6: 1 | AK6: -134 750.00 | AL6: YASMG | AN6: 1 212 749.98 | AO6: 1 455 299.98 | AP6: F | AQ6: 46211 | AR6: 0000-00-00 | AS6: Achat 03 armoire basse PM -DOM Diégo&Ambilobe | AT6: YASSIE | AU6: GALE | AV6: C500 | AW6: 2026-DT-061003 | AX6: DTG-DOM | AY6: STD | BC6: 2057 | BD6: C500 | BE6: 717 | BF6: 2 | BG6: 2026-07-10
A7: 136000 | B7: UNITE DE DISTRIBUTION TECHNOLOGIQUE - UDITEC | C7: REMISE | D7: Remise | E7: 1 | F7: UN | G7: -154000 | H7: =IF(N7="USD",G7,IF(N7="MGA",G7/4600,IF(N7="EUR",G7*1.17,IF(N7="GBP",G7*1.35,"")))) -> -33.478261 | I7: =H7*E7 -> -33.478261 | J7: 33.478261 | K7: =I7*(-1) -> 33.478261 | M7: 0 | N7: MGA | O7: 46232 | P7: 2026-07-29 | Q7: E | R7: E | S7: RASAMOELINA Haritsoa Oliva | T7: 139275 | W7: DTG | X7: ELIE3 | Y7: ANDRIAMANANTSOA Elie | Z7: -184 800.00 | AA7: 20 | AB7: 2 | AD7: GELACCS | AE7: True | AF7: 2026-DT-061003 | AG7: DTG-DOM | AH7: NA | AJ7: 1 | AK7: -154 000.00 | AL7: YASMG | AN7: 1 386 000.00 | AO7: 1 663 200.00 | AP7: F | AQ7: 46232 | AR7: 0000-00-00 | AS7: Achat 4 onduleurs pour Data Center Nosy Be | AT7: YASSIE | AU7: GALE | AV7: C500 | AW7: 2026-DT-061003 | AX7: DTG-DOM | AY7: STD | BC7: 2057 | BD7: C500 | BE7: 717 | BF7: 2 | BG7: 2026-08-04
A8: 136001 | B8: BATIMAX | C8: REMISE | D8: Remise | E8: 1 | F8: UN | G8: -178749.99 | H8: =IF(N8="USD",G8,IF(N8="MGA",G8/4600,IF(N8="EUR",G8*1.17,IF(N8="GBP",G8*1.35,"")))) -> -38.858694 | I8: =H8*E8 -> -38.858694 | J8: 38.858694 | K8: =I8*(-1) -> 38.858694 | M8: 0 | N8: MGA | O8: 46232 | P8: 2026-07-29 | Q8: E | R8: E | S8: RASAMOELINA Haritsoa Oliva | T8: 139168 | W8: DTG | X8: ELIE3 | Y8: ANDRIAMANANTSOA Elie | Z8: -214 499.99 | AA8: 20 | AB8: 4 | AD8: GELACCS | AE8: True | AF8: E218_DTG | AG8: DTG | AH8: NA | AJ8: 1 | AK8: -178 749.99 | AL8: YASMG | AN8: 2 204 583.27 | AO8: 2 645 499.93 | AQ8: 46232 | AR8: 0000-00-00 | AS8: Achat chaussures de sécurité-motards TANA | AT8: YASSIE | AU8: GALE | AV8: C500 | AW8: E218_DTG | AX8: DTG | AY8: STD | BC8: 2057 | BD8: C500 | BE8: 16 | BF8: 4 | BG8: 2026-07-31
A9: 135739 | B9: PRIMA CE SARLU | C9: REMISE | D9: Remise 7% | E9: 1 | F9: UN | G9: -290626 | H9: =IF(N9="USD",G9,IF(N9="MGA",G9/4600,IF(N9="EUR",G9*1.17,IF(N9="GBP",G9*1.35,"")))) -> -63.179565 | I9: =H9*E9 -> -63.179565 | J9: 63.179565 | K9: =I9*(-1) -> 63.179565 | M9: 0 | N9: MGA | O9: 46217 | P9: 2026-07-14 | Q9: L | R9: S | S9: RASAMOELINA Haritsoa Oliva | T9: 138981 | W9: DTG | X9: ELIE3 | Y9: ANDRIAMANANTSOA Elie | Z9: -348 751.20 | AA9: 20 | AB9: 2 | AD9: GELACCS | AE9: True | AF9: 2026-DT-022001 | AG9: DTG-PROJETS | AH9: NA | AJ9: 0 | AK9: 0.00 | AL9: YASMG | AN9: 3 861 174.00 | AO9: 4 633 408.80 | AQ9: 46217 | AR9: 0000-00-00 | AS9: TX GC FO sur VAK140 ABE ANDRAIKIBA | AT9: YASSIE | AU9: YASSIE | AV9: C500 | AW9: 2026-DT-022001 | AX9: DTG-PROJETS | AY9: STD | BC9: 2057 | BD9: C500 | BE9: 2633 | BF9: 2 | BG9: 0000-00-00
A10: 135787 | B10: COLIS EXPRESS | C10: REMISE | E10: 1 | F10: UN | G10: -327125 | H10: =IF(N10="USD",G10,IF(N10="MGA",G10/4600,IF(N10="EUR",G10*1.17,IF(N10="GBP",G10*1.35,"")))) -> -71.11413 | I10: =H10*E10 -> -71.11413 | J10: 71.11413 | K10: =I10*(-1) -> 71.11413 | M10: 0 | N10: MGA | O10: 46218 | P10: 2026-07-15 | Q10: E | R10: E | T10: 0 | W10: DCG | X10: NADIA7 | Y10: RAVONINJATOVO Nadia | Z10: -392 550.00 | AA10: 20 | AB10: 0 | AD10: GELACCS | AE10: True | AF10: E254_DCG | AG10: DRH-ADMIN | AH10: NA | AJ10: 1 | AK10: -327 125.00 | AL10: YASMG | AN10: 1 500 000.00 | AO10: 1 800 000.00 | AQ10: 46218 | AR10: 0000-00-00 | AT10: YASSIE | AU10: YASSIE | AV10: C104 | AW10: E254_DCG | AX10: DRH-ADMIN | AY10: STD | BC10: 2057 | BD10: C104 | BE10: 30 | BF10: 2 | BG10: 2026-06-29
A11: 135735 | B11: SOCIETE DE METALLURGIE DE L OCEAN INDIEN (ABC | C11: REMISE | D11: REMISE (15%*123916.67*18) | E11: 1 | F11: UN | G11: -334575.01 | H11: =IF(N11="USD",G11,IF(N11="MGA",G11/4600,IF(N11="EUR",G11*1.17,IF(N11="GBP",G11*1.35,"")))) -> -72.733698 | I11: =H11*E11 -> -72.733698 | J11: 72.733698 | K11: =I11*(-1) -> 72.733698 | M11: 0 | N11: MGA | O11: 46217 | P11: 2026-07-14 | Q11: E | R11: E | S11: RABIANOAVY Nasandratra Henintsoa | T11: 138913 | W11: DTG | X11: ELIE3 | Y11: ANDRIAMANANTSOA Elie | Z11: -401 490.01 | AA11: 20 | AB11: 0 | AD11: GELACCS | AE11: True | AF11: 2026-DT-103002 | AG11: DTG-DSTC-INTER | AH11: NA | AJ11: 1 | AK11: -334 575.01 | AL11: YASMG | AN11: 1 895 925.05 | AO11: 2 275 110.06 | AQ11: 46217 | AR11: 0000-00-00 | AS11: DSTC-SEI: Achat Urgente GOULOTTE CLIPPAGE DIRECT DLP 85X50 | AT11: YASSIE | AU11: GALE | AV11: C500 | AW11: 2026-DT-103002 | AX11: DTG-DSTC-INTER | AY11: STD | BC11: 2057 | BD11: C500 | BE11: 1 | BF11: 2 | BG11: 2026-07-15
A12: 135737 | B12: EASY NETCOM | C12: REMISE | D12: Remise 5% | E12: 1 | F12: UN | G12: -336696 | H12: =IF(N12="USD",G12,IF(N12="MGA",G12/4600,IF(N12="EUR",G12*1.17,IF(N12="GBP",G12*1.35,"")))) -> -73.194783 | I12: =H12*E12 -> -73.194783 | J12: 73.194783 | K12: =I12*(-1) -> 73.194783 | M12: 0 | N12: MGA | O12: 46217 | P12: 2026-07-14 | Q12: L | R12: S | S12: RASAMOELINA Haritsoa Oliva | T12: 138982 | W12: DTG | X12: ELIE3 | Y12: ANDRIAMANANTSOA Elie | Z12: -404 035.20 | AA12: 20 | AB12: 5 | AD12: GELACCS | AE12: True | AF12: 2026-DT-022001 | AG12: DTG-PROJETS | AH12: NA | AJ12: 0 | AK12: 0.00 | AL12: YASMG | AN12: 6 397 232.00 | AO12: 7 676 678.40 | AQ12: 46217 | AR12: 0000-00-00 | AS12: TX GC FO BOE141 Croisement Tsaratanana | AT12: YASSIE | AU12: YASSIE | AV12: C500 | AW12: 2026-DT-022001 | AX12: DTG-PROJETS | AY12: STD | BC12: 2057 | BD12: C500 | BE12: 2053 | BF12: 5 | BG12: 0000-00-00
A13: 136033 | B13: PRIMA CE SARLU | C13: REMISE | D13: Remise 7% | E13: 1 | F13: UN | G13: -431200 | H13: =IF(N13="USD",G13,IF(N13="MGA",G13/4600,IF(N13="EUR",G13*1.17,IF(N13="GBP",G13*1.35,"")))) -> -93.73913 | I13: =H13*E13 -> -93.73913 | J13: 93.73913 | K13: =I13*(-1) -> 93.73913 | M13: 0 | N13: MGA | O13: 46233 | P13: 2026-07-30 | Q13: E | R13: E | S13: RASAMOELINA Haritsoa Oliva | T13: 139245 | W13: DTG | X13: ELIE3 | Y13: ANDRIAMANANTSOA Elie | Z13: -517 440.00 | AA13: 20 | AB13: 5 | AD13: GELACCS | AE13: True | AF13: 2026-DT-022001 | AG13: DTG-PROJETS | AH13: NA | AJ13: 1 | AK13: -431 200.00 | AL13: YASMG | AN13: 5 728 800.00 | AO13: 6 874 560.00 | AQ13: 46233 | AR13: 0000-00-00 | AS13: TX GC FO AAT066 AMPOROFORO | AT13: YASSIE | AU13: YASSIE | AV13: C500 | AW13: 2026-DT-022001 | AX13: DTG-PROJETS | AY13: STD | BC13: 2057 | BD13: C500 | BE13: 2633 | BF13: 5 | BG13: 0000-00-00
A14: 135572 | B14: SOCIETE QUBETA IMPORT-EXPORT SARLU | C14: REMISE | D14: Remise | E14: 1 | F14: UN | G14: -474000 | H14: =IF(N14="USD",G14,IF(N14="MGA",G14/4600,IF(N14="EUR",G14*1.17,IF(N14="GBP",G14*1.35,"")))) -> -103.04348 | I14: =H14*E14 -> -103.04348 | J14: 103.04348 | K14: =I14*(-1) -> 103.04348 | M14: 0 | N14: MGA | O14: 46209 | P14: 2026-07-06 | Q14: E | R14: E | S14: RASAMOELINA Haritsoa Oliva | T14: 138809 | W14: DTG | X14: ELIE3 | Y14: ANDRIAMANANTSOA Elie | Z14: -568 800.00 | AA14: 20 | AB14: 3 | AD14: GELACCS | AE14: True | AF14: 2026-DT-061003 | AG14: DTG-DOM | AH14: NA | AJ14: 1 | AK14: -474 000.00 | AL14: YASMG | AN14: 4 266 000.00 | AO14: 5 119 200.00 | AP14: F | AQ14: 46209 | AR14: 0000-00-00 | AS14: Achats mobiliers de bureau-DOM BRICKAVILLE | AT14: YASSIE | AU14: GALE | AV14: C500 | AW14: 2026-DT-061003 | AX14: DTG-DOM | AY14: STD | BC14: 2057 | BD14: C500 | BE14: 3052 | BF14: 3 | BG14: 2026-07-10
A15: 135982 | B15: FITAHIA FANOMEZANTSOA NIRINA BIEN AIME | C15: REMISE | E15: 1 | F15: UN | G15: -500000 | H15: =IF(N15="USD",G15,IF(N15="MGA",G15/4600,IF(N15="EUR",G15*1.17,IF(N15="GBP",G15*1.35,"")))) -> -108.69565 | I15: =H15*E15 -> -108.69565 | J15: 108.69565 | K15: =I15*(-1) -> 108.69565 | M15: 0 | N15: MGA | O15: 46230 | P15: 2026-08-03 | Q15: E | R15: E | T15: 0 | W15: DCG | X15: FELANA13 | Y15: Felana RARIVOSON | Z15: -500 000.00 | AA15: 0 | AB15: 0 | AD15: GELACCS | AE15: True | AF15: E110_PRO_DCOM | AG15: DCG-COM | AH15: NA | AJ15: 1 | AK15: -500 000.00 | AL15: YASMG | AN15: 700 000.00 | AO15: 700 000.00 | AP15: F | AQ15: 46230 | AR15: 0000-00-00 | AS15: Couverture Photos le 11 et 18 juillet 2026 | AT15: YASSIE | AU15: YASSIE | AV15: C100 | AW15: E110_PRO_DCOM | AX15: DCG-COM | AY15: STD | BC15: 2057 | BD15: C100 | BE15: 5633 | BF15: 3 | BG15: 2026-07-31
A16: 136013 | B16: HASSANALY CHAHICK (LUXOR) | C16: REMISE | D16: Remise 15% | E16: 1 | F16: UN | G16: -556875 | H16: =IF(N16="USD",G16,IF(N16="MGA",G16/4600,IF(N16="EUR",G16*1.17,IF(N16="GBP",G16*1.35,"")))) -> -121.05978 | I16: =H16*E16 -> -121.05978 | J16: 121.05978 | K16: =I16*(-1) -> 121.05978 | M16: 0 | N16: MGA | O16: 46232 | P16: 2026-07-29 | Q16: E | R16: E | S16: RASAMOELINA Haritsoa Oliva | T16: 139223 | W16: DTG | X16: ELIE3 | Y16: ANDRIAMANANTSOA Elie | Z16: -668 250.00 | AA16: 20 | AB16: 2 | AD16: GELACCS | AE16: True | AF16: 2026-DT-061003 | AG16: DTG-DOM | AH16: NA | AJ16: 1 | AK16: -556 875.00 | AL16: YASMG | AN16: 3 155 625.00 | AO16: 3 786 750.00 | AP16: F | AQ16: 46232 | AR16: 0000-00-00 | AS16: Achat Vestiaire métal 2 étage-Fort Dauphin et les BV | AT16: YASSIE | AU16: GALE | AV16: C500 | AW16: 2026-DT-061003 | AX16: DTG-DOM | AY16: STD | BC16: 2057 | BD16: C500 | BE16: 75 | BF16: 2 | BG16: 2026-08-04
A17: 135738 | B17: PRIMA CE SARLU | C17: REMISE | D17: Remise 7% | E17: 1 | F17: UN | G17: -685510 | H17: =IF(N17="USD",G17,IF(N17="MGA",G17/4600,IF(N17="EUR",G17*1.17,IF(N17="GBP",G17*1.35,"")))) -> -149.02391 | I17: =H17*E17 -> -149.02391 | J17: 149.02391 | K17: =I17*(-1) -> 149.02391 | M17: 0 | N17: MGA | O17: 46217 | P17: 2026-07-14 | Q17: S | R17: S | S17: RASAMOELINA Haritsoa Oliva | T17: 138979 | W17: DTG | X17: ELIE3 | Y17: ANDRIAMANANTSOA Elie | Z17: -822 612.00 | AA17: 20 | AB17: 2 | AD17: GELACCS | AE17: True | AF17: 2026-DT-022001 | AG17: DTG-PROJETS | AH17: NA | AJ17: 0 | AK17: 0.00 | AL17: YASMG | AN17: 9 107 490.00 | AO17: 10 928 988.00 | AQ17: 46217 | AR17: 0000-00-00 | AS17: TX GC FO sur VAK138 VINANY | AT17: YASSIE | AU17: YASSIE | AV17: C500 | AW17: 2026-DT-022001 | AX17: DTG-PROJETS | AY17: STD | BC17: 2057 | BD17: C500 | BE17: 2633 | BF17: 2 | BG17: 0000-00-00
A18: 135918 | B18: HENRI FRAISE FILS ET CIE | C18: REMISE | D18: REMISE EXCEPTIONNELLE | E18: 1 | F18: UN | G18: -755291 | H18: =IF(N18="USD",G18,IF(N18="MGA",G18/4600,IF(N18="EUR",G18*1.17,IF(N18="GBP",G18*1.35,"")))) -> -164.1937 | I18: =H18*E18 -> -164.1937 | J18: 164.1937 | K18: =I18*(-1) -> 164.1937 | M18: 0 | N18: MGA | O18: 46225 | P18: 2026-07-22 | Q18: E | R18: E | S18: RAKOTOMALALA Tahiana Nalaina | T18: 139061 | W18: DTG | X18: ELIE3 | Y18: ANDRIAMANANTSOA Elie | Z18: -906 349.20 | AA18: 20 | AB18: 2 | AD18: GELACCS | AE18: True | AF18: 2026-DT-061005 | AG18: DTG-DOM-NRJ | AH18: NA | AJ18: 1 | AK18: -755 291.00 | AL18: YASMG | AN18: 14 350 523.00 | AO18: 17 220 627.60 | AP18: F | AQ18: 46225 | AR18: 0000-00-00 | AS18: ACHAT INVERSEUR DE SOURCE AUTOMATIQUE ATI 63A | AT18: YASSIE | AU18: GALE | AV18: C500 | AW18: 2026-DT-061005 | AX18: DTG-DOM-NRJ | AY18: STD | BC18: 2057 | BD18: C500 | BE18: 703 | BF18: 2 | BG18: 2026-07-31
A19: 135733 | B19: QUINCAILLERIE 2000 | C19: REMISE | D19: Remise 10% | E19: 1 | F19: UN | G19: -780000 | H19: =IF(N19="USD",G19,IF(N19="MGA",G19/4600,IF(N19="EUR",G19*1.17,IF(N19="GBP",G19*1.35,"")))) -> -169.56522 | I19: =H19*E19 -> -169.56522 | J19: 169.56522 | K19: =I19*(-1) -> 169.56522 | M19: 0 | N19: MGA | O19: 46217 | P19: 2026-07-14 | Q19: E | R19: E | S19: RASAMOELINA Haritsoa Oliva | T19: 138939 | W19: DTG | X19: ELIE3 | Y19: ANDRIAMANANTSOA Elie | Z19: -936 000.00 | AA19: 20 | AB19: 2 | AD19: GELACCS | AE19: True | AF19: 2026-DT-101001 | AG19: DTG-DSTC-INSTA | AH19: NA | AJ19: 1 | AK19: -780 000.00 | AL19: YASMG | AN19: 7 020 000.00 | AO19: 8 424 000.00 | AQ19: 46217 | AR19: 0000-00-00 | AS19: Achat moulure 25x16 pr les installations | AT19: YASSIE | AU19: GALE | AV19: C500 | AW19: 2026-DT-101001 | AX19: DTG-DSTC-INSTA | AY19: STD | BC19: 2057 | BD19: C500 | BE19: 1817 | BF19: 2 | BG19: 2026-07-20
A20: 135713 | B20: ICHTUS SERVICE | C20: REMISE | D20: REMISE | E20: 20 | F20: UN | G20: -44000 | H20: =IF(N20="USD",G20,IF(N20="MGA",G20/4600,IF(N20="EUR",G20*1.17,IF(N20="GBP",G20*1.35,"")))) -> -9.5652174 | I20: =H20*E20 -> -191.30435 | J20: 191.30435 | K20: =I20*(-1) -> 191.30435 | M20: 0 | N20: MGA | O20: 46216 | P20: 2026-07-13 | Q20: E | R20: E | S20: RANDRIARIMALALA Prisca | T20: 138914 | W20: DTG | X20: ELIE3 | Y20: ANDRIAMANANTSOA Elie | Z20: -880 000.00 | AA20: 0 | AB20: 0 | AD20: GELACCS | AE20: True | AF20: 2025-DT-021011 | AG20: DTG-PROJETS | AH20: NA | AJ20: 20 | AK20: -880 000.00 | AL20: YASMG | AN20: 10 920 000.00 | AO20: 10 920 000.00 | AP20: F | AQ20: 46216 | AR20: 0000-00-00 | AS20: BC ICHTUS - Confection support d'antenne STARLINK__Phoenix | AT20: YASSIE | AU20: GALE | AV20: C500 | AW20: 2025-DT-021011 | AX20: DTG-PROJETS | AY20: STD | BC20: 2057 | BD20: C500 | BE20: 6102 | BF20: 2 | BG20: 2026-07-17
A21: 136032 | B21: SOCIETE DE METALLURGIE DE L OCEAN INDIEN (ABC | C21: REMISE | D21: Remise | E21: 1 | F21: UN | G21: -1125000 | H21: =IF(N21="USD",G21,IF(N21="MGA",G21/4600,IF(N21="EUR",G21*1.17,IF(N21="GBP",G21*1.35,"")))) -> -244.56522 | I21: =H21*E21 -> -244.56522 | J21: 244.56522 | K21: =I21*(-1) -> 244.56522 | M21: 0 | N21: MGA | O21: 46233 | P21: 2026-07-30 | Q21: E | R21: E | S21: RASAMOELINA Haritsoa Oliva | T21: 139230 | W21: DTG | X21: ELIE3 | Y21: ANDRIAMANANTSOA Elie | Z21: -1 350 000.00 | AA21: 20 | AB21: 2 | AD21: GELACCS | AE21: True | AF21: 2026-DT-061003 | AG21: DTG-DOM | AH21: NA | AJ21: 1 | AK21: -1 125 000.00 | AL21: YASMG | AN21: 6 375 000.00 | AO21: 7 650 000.00 | AQ21: 46233 | AR21: 0000-00-00 | AS21: Achat Rack 19"//42U Indoor(Normalisation-Rack-DataCenter) | AT21: YASSIE | AU21: GALE | AV21: C500 | AW21: 2026-DT-061003 | AX21: DTG-DOM | AY21: STD | BC21: 2057 | BD21: C500 | BE21: 1 | BF21: 2 | BG21: 2026-08-06
A22: 136003 | B22: PRIMA CE SARLU | C22: REMISE | D22: Remise 7% | E22: 1 | F22: UN | G22: -1748985 | H22: =IF(N22="USD",G22,IF(N22="MGA",G22/4600,IF(N22="EUR",G22*1.17,IF(N22="GBP",G22*1.35,"")))) -> -380.21413 | I22: =H22*E22 -> -380.21413 | J22: 380.21413 | K22: =I22*(-1) -> 380.21413 | M22: 0 | N22: MGA | O22: 46232 | P22: 2026-07-29 | Q22: L | R22: S | S22: RASAMOELINA Haritsoa Oliva | T22: 139211 | W22: DTG | X22: ELIE3 | Y22: ANDRIAMANANTSOA Elie | Z22: -2 098 782.00 | AA22: 20 | AB22: 5 | AD22: GELACCS | AE22: True | AF22: 2026-DT-022001 | AG22: DTG-PROJETS | AH22: NA | AJ22: 0 | AK22: 0.00 | AL22: YASMG | AN22: 23 236 515.00 | AO22: 27 883 818.00 | AQ22: 46232 | AR22: 0000-00-00 | AS22: Travaux GC FO sur IHO058 AMBINANY(COHAB HELIOS) | AT22: YASSIE | AU22: YASSIE | AV22: C500 | AW22: 2026-DT-022001 | AX22: DTG-PROJETS | AY22: STD | BC22: 2057 | BD22: C500 | BE22: 2633 | BF22: 5 | BG22: 0000-00-00
A23: 135968 | B23: PRIMA CE SARLU | C23: REMISE | D23: Remise 15% | E23: 1 | F23: UN | G23: -3273900 | H23: =IF(N23="USD",G23,IF(N23="MGA",G23/4600,IF(N23="EUR",G23*1.17,IF(N23="GBP",G23*1.35,"")))) -> -711.71739 | I23: =H23*E23 -> -711.71739 | J23: 711.71739 | K23: =I23*(-1) -> 711.71739 | M23: 0 | N23: MGA | O23: 46226 | P23: 2026-07-23 | Q23: L | R23: S | S23: RASAMOELINA Haritsoa Oliva | T23: 139132 | W23: DTG | X23: ELIE3 | Y23: ANDRIAMANANTSOA Elie | Z23: -3 928 680.00 | AA23: 20 | AB23: 2 | AD23: GELACCS | AE23: True | AF23: 2026-DT-022001 | AG23: DTG-PROJETS | AH23: NA | AJ23: 0 | AK23: 0.00 | AL23: YASMG | AN23: 18 552 100.00 | AO23: 22 262 520.00 | AQ23: 46226 | AR23: 0000-00-00 | AS23: TX GC FO sur SOF225 ANALAMISONDROTRA | AT23: YASSIE | AU23: YASSIE | AV23: C500 | AW23: 2026-DT-022001 | AX23: DTG-PROJETS | AY23: STD | BC23: 2057 | BD23: C500 | BE23: 2633 | BF23: 2 | BG23: 0000-00-00
A24: 135532 | B24: SMTP | C24: REMISE | D24: REMISE | E24: 1 | F24: UN | G24: -3792000 | H24: =IF(N24="USD",G24,IF(N24="MGA",G24/4600,IF(N24="EUR",G24*1.17,IF(N24="GBP",G24*1.35,"")))) -> -824.34783 | I24: =H24*E24 -> -824.34783 | J24: 824.34783 | K24: =I24*(-1) -> 824.34783 | M24: 0 | N24: MGA | O24: 46209 | P24: 2026-07-06 | Q24: E | R24: E | S24: RASAMOELINA Haritsoa Oliva | T24: 138767 | W24: DTG | X24: ELIE3 | Y24: ANDRIAMANANTSOA Elie | Z24: -4 550 400.00 | AA24: 20 | AB24: 3 | AD24: GELACCS | AE24: True | AF24: 2026-DT-102001 | AG24: DTG-DOM | AH24: NA | AJ24: 1 | AK24: -3 792 000.00 | AL24: YASMG | AN24: 15 309 570.00 | AO24: 18 371 484.00 | AP24: F | AQ24: 46209 | AR24: 0000-00-00 | AS24: Achat de Tuyaux PEHD | AT24: YASSIE | AU24: GALE | AV24: C500 | AW24: 2026-DT-102001 | AX24: DTG-DOM | AY24: STD | BC24: 2057 | BD24: C500 | BE24: 1893 | BF24: 3 | BG24: 2026-07-06
A25: 135651 | B25: PRIMA CE SARLU | C25: REMISE | D25: Remise 12% | E25: 1 | F25: UN | G25: -4329240 | H25: =IF(N25="USD",G25,IF(N25="MGA",G25/4600,IF(N25="EUR",G25*1.17,IF(N25="GBP",G25*1.35,"")))) -> -941.13913 | I25: =H25*E25 -> -941.13913 | J25: 941.13913 | K25: =I25*(-1) -> 941.13913 | M25: 0 | N25: MGA | O25: 46211 | P25: 2026-07-08 | Q25: L | R25: S | S25: RASAMOELINA Haritsoa Oliva | T25: 138788 | W25: DTG | X25: ELIE3 | Y25: ANDRIAMANANTSOA Elie | Z25: -5 195 088.00 | AA25: 20 | AB25: 2 | AD25: GELACCS | AE25: True | AF25: 2025-DT-021010 | AG25: DTG-PROJETS | AH25: NA | AJ25: 0 | AK25: 0.00 | AL25: YASMG | AN25: 31 747 760.00 | AO25: 38 097 312.00 | AQ25: 46211 | AR25: 0000-00-00 | AS25: TX GC FO entre ANM012 Alarobia et ANM002 | AT25: YASSIE | AU25: YASSIE | AV25: C500 | AW25: 2025-DT-021010 | AX25: DTG-PROJETS | AY25: STD | BC25: 2057 | BD25: C500 | BE25: 2633 | BF25: 2 | BG25: 0000-00-00
A26: 136039 | B26: EASY NETCOM | C26: REMISE | D26: Remise 12% | E26: 1 | F26: UN | G26: -4534181 | H26: =IF(N26="USD",G26,IF(N26="MGA",G26/4600,IF(N26="EUR",G26*1.17,IF(N26="GBP",G26*1.35,"")))) -> -985.69152 | I26: =H26*E26 -> -985.69152 | J26: 985.69152 | K26: =I26*(-1) -> 985.69152 | M26: 0 | N26: MGA | O26: 46233 | P26: 2026-07-30 | Q26: E | R26: E | S26: RASAMOELINA Haritsoa Oliva | T26: 139301 | W26: DTG | X26: ELIE3 | Y26: ANDRIAMANANTSOA Elie | Z26: -5 441 017.20 | AA26: 20 | AB26: 4 | AD26: GELACCS | AE26: True | AF26: 2026-DT-022001 | AG26: DTG-PROJETS | AH26: NA | AJ26: 1 | AK26: -4 534 181.00 | AL26: YASMG | AN26: 33 250 657.00 | AO26: 39 900 788.40 | AQ26: 46233 | AR26: 0000-00-00 | AS26: TX GC FO ANO005_MARILLAC | AT26: YASSIE | AU26: YASSIE | AV26: C500 | AW26: 2026-DT-022001 | AX26: DTG-PROJETS | AY26: STD | BC26: 2057 | BD26: C500 | BE26: 2053 | BF26: 4 | BG26: 0000-00-00
A27: 135742 | B27: FRANCE PUB | C27: REMISE | D27: Remise | E27: 1 | F27: UN | G27: -5378760 | H27: =IF(N27="USD",G27,IF(N27="MGA",G27/4600,IF(N27="EUR",G27*1.17,IF(N27="GBP",G27*1.35,"")))) -> -1169.2957 | I27: =H27*E27 -> -1169.2957 | J27: 1169.2957 | K27: =I27*(-1) -> 1169.2957 | M27: 0 | N27: MGA | O27: 46217 | P27: 2026-07-14 | Q27: E | R27: E | S27: RASAMOELINA Haritsoa Oliva | T27: 139004 | W27: DTG | X27: ELIE3 | Y27: ANDRIAMANANTSOA Elie | Z27: -6 454 512.00 | AA27: 20 | AB27: 2 | AD27: GELACCS | AE27: True | AF27: 2026-DT-091006 | AG27: DTG-PROJETS | AH27: NA | AJ27: 1 | AK27: -5 378 760.00 | AL27: YASMG | AN27: 31 979 640.00 | AO27: 38 375 568.00 | AQ27: 46217 | AR27: 0000-00-00 | AS27: Lightbox Yas Campus Galaxy Andraharo | AT27: YASSIE | AU27: YASSIE | AV27: C500 | AW27: 2026-DT-091006 | AX27: DTG-PROJETS | AY27: STD | BC27: 2057 | BD27: C500 | BE27: 3678 | BF27: 2 | BG27: 2026-07-20
A28: 135745 | B28: PRIMA CE SARLU | C28: REMISE | D28: Remise 30% | E28: 1 | F28: UN | G28: -5887200 | H28: =IF(N28="USD",G28,IF(N28="MGA",G28/4600,IF(N28="EUR",G28*1.17,IF(N28="GBP",G28*1.35,"")))) -> -1279.8261 | I28: =H28*E28 -> -1279.8261 | J28: 1279.8261 | K28: =I28*(-1) -> 1279.8261 | M28: 0 | N28: MGA | O28: 46217 | P28: 2026-07-14 | Q28: L | R28: S | S28: RASAMOELINA Haritsoa Oliva | T28: 138960 | W28: DTG | X28: ELIE3 | Y28: ANDRIAMANANTSOA Elie | Z28: -7 064 640.00 | AA28: 20 | AB28: 2 | AD28: GELACCS | AE28: True | AF28: E314_DTG | AG28: DTG-DOM | AH28: NA | AJ28: 0 | AK28: 0.00 | AL28: YASMG | AN28: 13 736 800.00 | AO28: 16 484 160.00 | AP28: F | AQ28: 46217 | AR28: 0000-00-00 | AS28: TX GC BKB SOANIERANA IVONGO - MANANARA NORD | AT28: YASSIE | AU28: YASSIE | AV28: C500 | AW28: E314_DTG | AX28: DTG-DOM | AY28: STD | BC28: 2057 | BD28: C500 | BE28: 2633 | BF28: 2 | BG28: 0000-00-00
A29: 135970 | B29: EASY NETCOM | C29: REMISE | D29: Remise 15% | E29: 1 | F29: UN | G29: -6210566 | H29: =IF(N29="USD",G29,IF(N29="MGA",G29/4600,IF(N29="EUR",G29*1.17,IF(N29="GBP",G29*1.35,"")))) -> -1350.123 | I29: =H29*E29 -> -1350.123 | J29: 1350.123 | K29: =I29*(-1) -> 1350.123 | M29: 0 | N29: MGA | O29: 46226 | P29: 2026-07-23 | Q29: L | R29: S | S29: RASAMOELINA Haritsoa Oliva | T29: 139141 | W29: DTG | X29: ELIE3 | Y29: ANDRIAMANANTSOA Elie | Z29: -7 452 679.20 | AA29: 20 | AB29: 5 | AD29: GELACCS | AE29: True | AF29: 2026-DT-022001 | AG29: DTG-PROJETS | AH29: NA | AJ29: 0 | AK29: 0.00 | AL29: YASMG | AN29: 35 193 206.00 | AO29: 42 231 847.20 | AQ29: 46226 | AR29: 0000-00-00 | AS29: TX GC FO sur VAK134 ANJOMA RAMARTINA 2 | AT29: YASSIE | AU29: YASSIE | AV29: C500 | AW29: 2026-DT-022001 | AX29: DTG-PROJETS | AY29: STD | BC29: 2057 | BD29: C500 | BE29: 2053 | BF29: 5 | BG29: 0000-00-00
A30: 136011 | B30: PRIMA CE SARLU | C30: REMISE | D30: Remise 15% | E30: 1 | F30: UN | G30: -6250125 | H30: =IF(N30="USD",G30,IF(N30="MGA",G30/4600,IF(N30="EUR",G30*1.17,IF(N30="GBP",G30*1.35,"")))) -> -1358.7228 | I30: =H30*E30 -> -1358.7228 | J30: 1358.7228 | K30: =I30*(-1) -> 1358.7228 | M30: 0 | N30: MGA | O30: 46232 | P30: 2026-07-29 | Q30: L | R30: S | S30: RASAMOELINA Haritsoa Oliva | T30: 139210 | W30: DTG | X30: ELIE3 | Y30: ANDRIAMANANTSOA Elie | Z30: -7 500 150.00 | AA30: 20 | AB30: 5 | AD30: GELACCS | AE30: True | AF30: 2026-DT-022001 | AG30: DTG-PROJETS | AH30: NA | AJ30: 0 | AK30: 0.00 | AL30: YASMG | AN30: 35 417 375.00 | AO30: 42 500 850.00 | AQ30: 46232 | AR30: 0000-00-00 | AS30: TX GC FO sur SOF229 Ambodiampana | AT30: YASSIE | AU30: YASSIE | AV30: C500 | AW30: 2026-DT-022001 | AX30: DTG-PROJETS | AY30: STD | BC30: 2057 | BD30: C500 | BE30: 2633 | BF30: 5 | BG30: 0000-00-00
A31: 135575 | B31: AVRA BTP | C31: REMISE | E31: 1 | F31: UN | G31: -6555930.4 | H31: =IF(N31="USD",G31,IF(N31="MGA",G31/4600,IF(N31="EUR",G31*1.17,IF(N31="GBP",G31*1.35,"")))) -> -1425.2023 | I31: =H31*E31 -> -1425.2023 | J31: 1425.2023 | K31: =I31*(-1) -> 1425.2023 | M31: 0 | N31: MGA | O31: 46209 | P31: 2026-07-06 | Q31: E | R31: E | T31: 0 | W31: DFG | X31: NADIA7 | Y31: RAVONINJATOVO Nadia | Z31: -6 555 930.40 | AA31: 0 | AB31: 0 | AD31: GELACCS | AE31: True | AF31: 2026-CO-000001 | AG31: DFG-ADV | AH31: NA | AJ31: 1 | AK31: -6 555 930.40 | AL31: YASMG | AN31: 14 000 000.00 | AO31: 14 000 000.00 | AP31: F | AQ31: 46209 | AR31: 0000-00-00 | AT31: YASSIE | AU31: YASSIE | AV31: C700 | AW31: 2026-CO-000001 | AX31: DFG-ADV | AY31: STD | BC31: 2057 | BD31: C700 | BE31: 4038 | BF31: 2 | BG31: 2026-07-08
A32: 135700 | B32: AFRO EGYPT | C32: REMISE | D32: Remise | E32: 1 | F32: UN | G32: -11385000 | H32: =IF(N32="USD",G32,IF(N32="MGA",G32/4600,IF(N32="EUR",G32*1.17,IF(N32="GBP",G32*1.35,"")))) -> -2475 | I32: =H32*E32 -> -2475 | J32: 2475 | K32: =I32*(-1) -> 2475 | M32: 0 | N32: MGA | O32: 46216 | P32: 2026-08-05 | Q32: E | R32: E | S32: RASAMOELINA Haritsoa Oliva | T32: 138882 | W32: DTG | X32: ELIE3 | Y32: ANDRIAMANANTSOA Elie | Z32: -13 662 000.00 | AA32: 20 | AB32: 2 | AD32: GELACCS | AE32: True | AF32: 2026-DT-101001 | AG32: DTG-DSTC-INSTA | AH32: NA | AJ32: 1 | AK32: -11 385 000.00 | AL32: YASMG | AN32: 29 955 000.00 | AO32: 35 946 000.00 | AP32: F | AQ32: 46216 | AR32: 0000-00-00 | AS32: Renfort rétablissement FTTx Yas à Toamasina(13j) | AT32: YASSIE | AU32: YASSIE | AV32: C500 | AW32: 2026-DT-101001 | AX32: DTG-DSTC-INSTA | AY32: STD | BC32: 2057 | BD32: C500 | BE32: 1033 | BF32: 2 | BG32: 2026-07-16
A33: 135578 | B33: PRIMA CE SARLU | C33: REMISE | D33: Remise 30% | E33: 1 | F33: UN | G33: -14250000 | H33: =IF(N33="USD",G33,IF(N33="MGA",G33/4600,IF(N33="EUR",G33*1.17,IF(N33="GBP",G33*1.35,"")))) -> -3097.8261 | I33: =H33*E33 -> -3097.8261 | J33: 3097.8261 | K33: =I33*(-1) -> 3097.8261 | M33: 0 | N33: MGA | O33: 46209 | P33: 2026-07-06 | Q33: L | R33: S | S33: RASAMOELINA Haritsoa Oliva | T33: 138710 | W33: DTG | X33: ELIE3 | Y33: ANDRIAMANANTSOA Elie | Z33: -17 100 000.00 | AA33: 20 | AB33: 2 | AD33: GELACCS | AE33: True | AF33: 2026-DT-061013 | AG33: DTG-DOM | AH33: NA | AJ33: 0 | AK33: 0.00 | AL33: YASMG | AN33: 33 250 000.00 | AO33: 39 900 000.00 | AQ33: 46209 | AR33: 0000-00-00 | AS33: (TS)Fourniture,pose poutre en BA -Mananara-SoanieranaIvongo | AT33: YASSIE | AU33: YASSIE | AV33: C500 | AW33: 2026-DT-061013 | AX33: DTG-DOM | AY33: STD | BC33: 2057 | BD33: C500 | BE33: 2633 | BF33: 2 | BG33: 0000-00-00
A34: 135921 | B34: PRIMA CE SARLU | C34: REMISE | D34: Remise1 30%+ Remise2 (3 998 000 MGA) | E34: 1 | F34: UN | G34: -24140000 | H34: =IF(N34="USD",G34,IF(N34="MGA",G34/4600,IF(N34="EUR",G34*1.17,IF(N34="GBP",G34*1.35,"")))) -> -5247.8261 | I34: =H34*E34 -> -5247.8261 | J34: 5247.8261 | K34: =I34*(-1) -> 5247.8261 | M34: 0 | N34: MGA | O34: 46225 | P34: 2026-08-05 | Q34: E | R34: E | S34: RASAMOELINA Haritsoa Oliva | T34: 139043 | W34: DTG | X34: ELIE3 | Y34: ANDRIAMANANTSOA Elie | Z34: -28 968 000.00 | AA34: 20 | AB34: 2 | AD34: GELACCS | AE34: True | AF34: 2026-DT-061013 | AG34: DTG-DOM | AH34: NA | AJ34: 1 | AK34: -24 140 000.00 | AL34: YASMG | AN34: 43 000 000.00 | AO34: 51 600 000.00 | AP34: F | AQ34: 46225 | AR34: 0000-00-00 | AS34: TS-TX sécurisation BKB sur ponts : Ambatosarotra.. | AT34: YASSIE | AU34: YASSIE | AV34: C500 | AW34: 2026-DT-061013 | AX34: DTG-DOM | AY34: STD | BC34: 2057 | BD34: C500 | BE34: 2633 | BF34: 2 | BG34: 0000-00-00
A35: 136057 | B35: CLICK UP | C35: AUTRES LICENCES | D35: ClickUp Enterprise Plan Seats - 6/28/2026 au 12/27/2026 - suivant devis N°INV67574 | E35: 1 | F35: UN | G35: 20374.2 | H35: =IF(N35="USD",G35,IF(N35="MGA",G35/4600,IF(N35="EUR",G35*1.17,IF(N35="GBP",G35*1.35,"")))) -> 20374.2 | I35: =H35*E35 -> 20374.2 | J35: 20374.2 | M35: 0 | N35: USD | O35: 46234 | P35: 2026-07-31 | Q35: E | R35: E | S35: RAZAFINDRAHAGA Setra | T35: 139272 | W35: DCG | X35: FELANA13 | Y35: Felana RARIVOSON | Z35: 20 374.20 | AA35: 0 | AB35: 1 | AD35: DOCLICD | AE35: True | AF35: E320_DSI | AG35: DCG | AH35: NA | AJ35: 1 | AK35: 20 374.20 | AL35: YASMG | AN35: 20 374.20 | AO35: 20 374.20 | AP35: F | AQ35: 46234 | AR35: 0000-00-00 | AS35: ClickUp Enterprise Plan Seats | AT35: YASSIE | AU35: YASSIE | AV35: C100 | AW35: E320_DSI | AX35: DCG | AY35: IMPORT | BC35: 1550 | BD35: C100 | BE35: 3319 | BF35: 1 | BG35: 2026-07-28
A36: 136056 | B36: SIGN | C36: STICKERS AUTOCOLLANT - MBALIK - JUILLET 2025 | D36: Stickers Home Plus Max Produit 1 - 3,5 cm x 1 cm- suivant proforma N°FP05185 | E36: 525 | F36: UN | G36: 12.2476 | H36: =IF(N36="USD",G36,IF(N36="MGA",G36/4600,IF(N36="EUR",G36*1.17,IF(N36="GBP",G36*1.35,"")))) -> 0.0026625217 | I36: =H36*E36 -> 1.3978239 | J36: 1.3978239 | M36: 0 | N36: MGA | O36: 46234 | P36: 2026-07-31 | Q36: E | R36: E | S36: RAZAFINDRAHAGA Setra | T36: 139300 | W36: DCG | X36: FELANA13 | Y36: Felana RARIVOSON | Z36: 7 715.99 | AA36: 20 | AB36: 6 | AD36: GELACCS | AE36: True | AF36: E110_TR_MBLK | AG36: DCG-SHS | AH36: NA | AJ36: 525 | AK36: 6 429.99 | AL36: YASMG | AN36: 2 806 884.99 | AO36: 3 368 261.99 | AP36: F | AQ36: 46234 | AR36: 0000-00-00 | AS36: STICKERS MBALIK | AT36: YASSIE | AU36: GALE | AV36: C100 | AW36: E110_TR_MBLK | AX36: DCG-SHS | AY36: STD | BC36: 24694 | BD36: C100 | BE36: 1089 | BF36: 6 | BG36: 2026-07-29
A37: 136056 | B37: SIGN | C37: STICKERS AUTOCOLLANT - MBALIK - JUILLET 2025 | D37: Stickers Home Plus Max Produit 2 - 4 cm x 1,8 cm- suivant proforma N°FP05185 | E37: 525 | F37: UN | G37: 25.2 | H37: =IF(N37="USD",G37,IF(N37="MGA",G37/4600,IF(N37="EUR",G37*1.17,IF(N37="GBP",G37*1.35,"")))) -> 0.0054782609 | I37: =H37*E37 -> 2.876087 | J37: 2.876087 | M37: 0 | N37: MGA | O37: 46234 | P37: 2026-07-31 | Q37: E | R37: E | S37: RAZAFINDRAHAGA Setra | T37: 139300 | W37: DCG | X37: FELANA13 | Y37: Felana RARIVOSON | Z37: 15 876.00 | AA37: 20 | AB37: 7 | AD37: GELACCS | AE37: True | AF37: E110_TR_MBLK | AG37: DCG-SHS | AH37: NA | AJ37: 525 | AK37: 13 230.00 | AL37: YASMG | AN37: 2 806 884.99 | AO37: 3 368 261.99 | AP37: F | AQ37: 46234 | AR37: 0000-00-00 | AS37: STICKERS MBALIK | AT37: YASSIE | AU37: GALE | AV37: C100 | AW37: E110_TR_MBLK | AX37: DCG-SHS | AY37: STD | BC37: 24694 | BD37: C100 | BE37: 1089 | BF37: 7 | BG37: 2026-07-29
A38: 136056 | B38: SIGN | C38: STICKERS AUTOCOLLANT - MBALIK - JUILLET 2025 | D38: Stickers Home Plus Max Fiantohana 2 ans - 3cm x 3 cm - suivant proforma N°FP05185 | E38: 525 | F38: UN | G38: 32 | H38: =IF(N38="USD",G38,IF(N38="MGA",G38/4600,IF(N38="EUR",G38*1.17,IF(N38="GBP",G38*1.35,"")))) -> 0.0069565217 | I38: =H38*E38 -> 3.6521739 | J38: 3.6521739 | M38: 0 | N38: MGA | O38: 46234 | P38: 2026-07-31 | Q38: E | R38: E | S38: RAZAFINDRAHAGA Setra | T38: 139300 | W38: DCG | X38: FELANA13 | Y38: Felana RARIVOSON | Z38: 20 160.00 | AA38: 20 | AB38: 1 | AD38: GELACCS | AE38: True | AF38: E110_TR_MBLK | AG38: DCG-SHS | AH38: NA | AJ38: 525 | AK38: 16 800.00 | AL38: YASMG | AN38: 2 806 884.99 | AO38: 3 368 261.99 | AP38: F | AQ38: 46234 | AR38: 0000-00-00 | AS38: STICKERS MBALIK | AT38: YASSIE | AU38: GALE | AV38: C100 | AW38: E110_TR_MBLK | AX38: DCG-SHS | AY38: STD | BC38: 24694 | BD38: C100 | BE38: 1089 | BF38: 1 | BG38: 2026-07-29
A39: 136056 | B39: SIGN | C39: STICKERS AUTOCOLLANT - MBALIK - JUILLET 2025 | D39: Stickers Home Plus Max Packaging 806 - 7 cm x 2 cm - suivant proforma N°FP05185 | E39: 525 | F39: UN | G39: 49 | H39: =IF(N39="USD",G39,IF(N39="MGA",G39/4600,IF(N39="EUR",G39*1.17,IF(N39="GBP",G39*1.35,"")))) -> 0.010652174 | I39: =H39*E39 -> 5.5923913 | J39: 5.5923913 | M39: 0 | N39: MGA | O39: 46234 | P39: 2026-07-31 | Q39: E | R39: E | S39: RAZAFINDRAHAGA Setra | T39: 139300 | W39: DCG | X39: FELANA13 | Y39: Felana RARIVOSON | Z39: 30 870.00 | AA39: 20 | AB39: 3 | AD39: GELACCS | AE39: True | AF39: E110_TR_MBLK | AG39: DCG-SHS | AH39: NA | AJ39: 525 | AK39: 25 725.00 | AL39: YASMG | AN39: 2 806 884.99 | AO39: 3 368 261.99 | AP39: F | AQ39: 46234 | AR39: 0000-00-00 | AS39: STICKERS MBALIK | AT39: YASSIE | AU39: GALE | AV39: C100 | AW39: E110_TR_MBLK | AX39: DCG-SHS | AY39: STD | BC39: 24694 | BD39: C100 | BE39: 1089 | BF39: 3 | BG39: 2026-07-29
A40: 136056 | B40: SIGN | C40: STICKERS AUTOCOLLANT - MBALIK - JUILLET 2025 | D40: STICKERS MBALIK FIANTOHANA 2 TAONA - 6.3 cm x 6.3 cm - suivant proforma N° FP05187 | E40: 525 | F40: UN | G40: 140 | H40: =IF(N40="USD",G40,IF(N40="MGA",G40/4600,IF(N40="EUR",G40*1.17,IF(N40="GBP",G40*1.35,"")))) -> 0.030434783 | I40: =H40*E40 -> 15.978261 | J40: 15.978261 | M40: 0 | N40: MGA | O40: 46234 | P40: 2026-07-31 | Q40: E | R40: E | S40: RAZAFINDRAHAGA Setra | T40: 139300 | W40: DCG | X40: FELANA13 | Y40: Felana RARIVOSON | Z40: 88 200.00 | AA40: 20 | AB40: 10 | AD40: GELACCS | AE40: True | AF40: E110_TR_MBLK | AG40: DCG-SHS | AH40: NA | AJ40: 525 | AK40: 73 500.00 | AL40: YASMG | AN40: 2 806 884.99 | AO40: 3 368 261.99 | AP40: F | AQ40: 46234 | AR40: 0000-00-00 | AS40: STICKERS MBALIK | AT40: YASSIE | AU40: GALE | AV40: C100 | AW40: E110_TR_MBLK | AX40: DCG-SHS | AY40: STD | BC40: 24694 | BD40: C100 | BE40: 1089 | BF40: 10 | BG40: 2026-07-29
A41: 136056 | B41: SIGN | C41: STICKERS AUTOCOLLANT - MBALIK - JUILLET 2025 | D41: Stickers Home Plus Max Caractéristiques facing - 10,5 cm x 8,5cm - suivant proforma N°FP05185 | E41: 525 | F41: UN | G41: 312 | H41: =IF(N41="USD",G41,IF(N41="MGA",G41/4600,IF(N41="EUR",G41*1.17,IF(N41="GBP",G41*1.35,"")))) -> 0.067826087 | I41: =H41*E41 -> 35.608696 | J41: 35.608696 | M41: 0 | N41: MGA | O41: 46234 | P41: 2026-07-31 | Q41: E | R41: E | S41: RAZAFINDRAHAGA Setra | T41: 139300 | W41: DCG | X41: FELANA13 | Y41: Felana RARIVOSON | Z41: 196 560.00 | AA41: 20 | AB41: 2 | AD41: GELACCS | AE41: True | AF41: E110_TR_MBLK | AG41: DCG-SHS | AH41: NA | AJ41: 525 | AK41: 163 800.00 | AL41: YASMG | AN41: 2 806 884.99 | AO41: 3 368 261.99 | AP41: F | AQ41: 46234 | AR41: 0000-00-00 | AS41: STICKERS MBALIK | AT41: YASSIE | AU41: GALE | AV41: C100 | AW41: E110_TR_MBLK | AX41: DCG-SHS | AY41: STD | BC41: 24694 | BD41: C100 | BE41: 1089 | BF41: 2 | BG41: 2026-07-29
A42: 136056 | B42: SIGN | C42: STICKERS AUTOCOLLANT - MBALIK - JUILLET 2025 | D42: Stickers Home Plus Max Side Noir - 16,5 cm x 6,5cm - suivant proforma N°FP05185 | E42: 525 | F42: UN | G42: 376 | H42: =IF(N42="USD",G42,IF(N42="MGA",G42/4600,IF(N42="EUR",G42*1.17,IF(N42="GBP",G42*1.35,"")))) -> 0.08173913 | I42: =H42*E42 -> 42.913043 | J42: 42.913043 | M42: 0 | N42: MGA | O42: 46234 | P42: 2026-07-31 | Q42: E | R42: E | S42: RAZAFINDRAHAGA Setra | T42: 139300 | W42: DCG | X42: FELANA13 | Y42: Felana RARIVOSON | Z42: 236 880.00 | AA42: 20 | AB42: 4 | AD42: GELACCS | AE42: True | AF42: E110_TR_MBLK | AG42: DCG-SHS | AH42: NA | AJ42: 525 | AK42: 197 400.00 | AL42: YASMG | AN42: 2 806 884.99 | AO42: 3 368 261.99 | AP42: F | AQ42: 46234 | AR42: 0000-00-00 | AS42: STICKERS MBALIK | AT42: YASSIE | AU42: GALE | AV42: C100 | AW42: E110_TR_MBLK | AX42: DCG-SHS | AY42: STD | BC42: 24694 | BD42: C100 | BE42: 1089 | BF42: 4 | BG42: 2026-07-29
A43: 136056 | B43: SIGN | C43: FRAIS DE POSE | D43: POSE ANDRAHARO - suivant proforma N° FP05187 | E43: 525 | F43: UN | G43: 380 | H43: =IF(N43="USD",G43,IF(N43="MGA",G43/4600,IF(N43="EUR",G43*1.17,IF(N43="GBP",G43*1.35,"")))) -> 0.082608696 | I43: =H43*E43 -> 43.369565 | J43: 43.369565 | M43: 0 | N43: MGA | O43: 46234 | P43: 2026-07-31 | Q43: E | R43: E | S43: RAZAFINDRAHAGA Setra | T43: 139300 | W43: DCG | X43: FELANA13 | Y43: Felana RARIVOSON | Z43: 239 400.00 | AA43: 20 | AB43: 11 | AD43: ELEMCEL | AE43: True | AF43: E110_TR_MBLK | AG43: DCG-SHS | AH43: NA | AJ43: 525 | AK43: 199 500.00 | AL43: YASMG | AN43: 2 806 884.99 | AO43: 3 368 261.99 | AP43: F | AQ43: 46234 | AR43: 0000-00-00 | AS43: STICKERS MBALIK | AT43: YASSIE | AU43: GALE | AV43: C100 | AW43: E110_TR_MBLK | AX43: DCG-SHS | AY43: STD | BC43: 2061 | BD43: C100 | BE43: 1089 | BF43: 11 | BG43: 2026-07-29
A44: 136056 | B44: SIGN | C44: STICKERS AUTOCOLLANT - MBALIK - JUILLET 2025 | D44: Stickers Home Plus Max Facing vert - 14,7 cm x 13,5 cm - suivant proforma N°FP05185 | E44: 525 | F44: UN | G44: 700 | H44: =IF(N44="USD",G44,IF(N44="MGA",G44/4600,IF(N44="EUR",G44*1.17,IF(N44="GBP",G44*1.35,"")))) -> 0.15217391 | I44: =H44*E44 -> 79.891304 | J44: 79.891304 | M44: 0 | N44: MGA | O44: 46234 | P44: 2026-07-31 | Q44: E | R44: E | S44: RAZAFINDRAHAGA Setra | T44: 139300 | W44: DCG | X44: FELANA13 | Y44: Felana RARIVOSON | Z44: 441 000.00 | AA44: 20 | AB44: 5 | AD44: GELACCS | AE44: True | AF44: E110_TR_MBLK | AG44: DCG-SHS | AH44: NA | AJ44: 525 | AK44: 367 500.00 | AL44: YASMG | AN44: 2 806 884.99 | AO44: 3 368 261.99 | AP44: F | AQ44: 46234 | AR44: 0000-00-00 | AS44: STICKERS MBALIK | AT44: YASSIE | AU44: GALE | AV44: C100 | AW44: E110_TR_MBLK | AX44: DCG-SHS | AY44: STD | BC44: 24694 | BD44: C100 | BE44: 1089 | BF44: 5 | BG44: 2026-07-29
A45: 136056 | B45: SIGN | C45: FRAIS DE POSE | D45: POSE ANDRAHARO - suivant proforma N°FP05185 | E45: 525 | F45: UN | G45: 1000 | H45: =IF(N45="USD",G45,IF(N45="MGA",G45/4600,IF(N45="EUR",G45*1.17,IF(N45="GBP",G45*1.35,"")))) -> 0.2173913 | I45: =H45*E45 -> 114.13043 | J45: 114.13043 | M45: 0 | N45: MGA | O45: 46234 | P45: 2026-07-31 | Q45: E | R45: E | S45: RAZAFINDRAHAGA Setra | T45: 139300 | W45: DCG | X45: FELANA13 | Y45: Felana RARIVOSON | Z45: 630 000.00 | AA45: 20 | AB45: 8 | AD45: ELEMCEL | AE45: True | AF45: E110_TR_MBLK | AG45: DCG-SHS | AH45: NA | AJ45: 525 | AK45: 525 000.00 | AL45: YASMG | AN45: 2 806 884.99 | AO45: 3 368 261.99 | AP45: F | AQ45: 46234 | AR45: 0000-00-00 | AS45: STICKERS MBALIK | AT45: YASSIE | AU45: GALE | AV45: C100 | AW45: E110_TR_MBLK | AX45: DCG-SHS | AY45: STD | BC45: 2061 | BD45: C100 | BE45: 1089 | BF45: 8 | BG45: 2026-07-29
A46: 136056 | B46: SIGN | C46: STICKERS AUTOCOLLANT - MBALIK - JUILLET 2025 | D46: STICKERS MBALIK TV 32 - 32.7 cm x 20 cm - suivant proforma N°FP05187 | E46: 525 | F46: UN | G46: 2320 | H46: =IF(N46="USD",G46,IF(N46="MGA",G46/4600,IF(N46="EUR",G46*1.17,IF(N46="GBP",G46*1.35,"")))) -> 0.50434783 | I46: =H46*E46 -> 264.78261 | J46: 264.78261 | M46: 0 | N46: MGA | O46: 46234 | P46: 2026-07-31 | Q46: E | R46: E | S46: RAZAFINDRAHAGA Setra | T46: 139300 | W46: DCG | X46: FELANA13 | Y46: Felana RARIVOSON | Z46: 1 461 600.00 | AA46: 20 | AB46: 9 | AD46: GELACCS | AE46: True | AF46: E110_TR_MBLK | AG46: DCG-SHS | AH46: NA | AJ46: 525 | AK46: 1 218 000.00 | AL46: YASMG | AN46: 2 806 884.99 | AO46: 3 368 261.99 | AP46: F | AQ46: 46234 | AR46: 0000-00-00 | AS46: STICKERS MBALIK | AT46: YASSIE | AU46: GALE | AV46: C100 | AW46: E110_TR_MBLK | AX46: DCG-SHS | AY46: STD | BC46: 24694 | BD46: C100 | BE46: 1089 | BF46: 9 | BG46: 2026-07-29
... A49: 136053 | B49: ADVANCED TECHNOLOGY APPLICATION | C49: PRESTATION DE SERVICE | D49: Lancement BC ATEA - Tx trans sur BET068 - Top Gun # PF257/26 | E49: 1 | F49: UN | G49: 9950000 | H49: =IF(N49="USD",G49,IF(N49="MGA",G49/4600,IF(N49="EUR",G49*1.17,IF(N49="GBP",G49*1.35,"")))) -> 2163.0435 | I49: =H49*E49 -> 2163.0435 | J49: 2163.0435 | M49: 0 | N49: MGA | O49: 46234 | P49: 2026-07-31 | Q49: E | R49: E | S49: RANDRIARIMALALA Prisca | T49: 139311 | W49: DTG | X49: ELIE3 | Y49: ANDRIAMANANTSOA Elie | Z49: 11 940 000.00 | AA49: 20 | AB49: 1 | AD49: PRICTRL | AE49: True | AF49: 2025-DT-021011 | AG49: DTG-PROJETS | AH49: NA | AJ49: 1 | AK49: 9 950 000.00 | AL49: YASMG | AN49: 9 950 000.00 | AO49: 11 940 000.00 | AP49: F | AQ49: 46234 | AR49: 0000-00-00 | AS49: BC ATEA - Tx VSAT sur BET068 - Top Gun | AT49: YASSIE | AU49: YASSIE | AV49: C500 | AW49: 2025-DT-021011 | AX49: DTG-PROJETS | AY49: STD | BC49: 14862 | BD49: C500 | BE49: 2025 | BF49: 1 | BG49: 2026-08-31
A50: 136052 | B50: NEA MADAGASCAR SA | C50: TRAVAUX D ENERGIE | D50: Travaux Energie Lié au projet Swap GE fin de vie 2026: Installation GE 33KVA et Inverseur CTI63 | E50: 1 | F50: UN | G50: 58580141 | H50: =IF(N50="USD",G50,IF(N50="MGA",G50/4600,IF(N50="EUR",G50*1.17,IF(N50="GBP",G50*1.35,"")))) -> 12734.813 | I50: =H50*E50 -> 12734.813 | J50: 12734.813 | M50: 0 | N50: MGA | O50: 46234 | P50: 2026-08-04 | Q50: E | R50: E | S50: RABENINTANY Paris Andrianirina | T50: 139330 | W50: DTG | X50: ELIE3 | Y50: ANDRIAMANANTSOA Elie | Z50: 70 296 169.49 | AA50: 20 | AB50: 1 | AD50: INFPYLX | AE50: True | AF50: 2026-DT-051003 | AG50: DTG-ENERGIE | AH50: NA | AJ50: 1 | AK50: 58 580 141.24 | AL50: YASMG | AN50: 58 580 141.24 | AO50: 70 296 169.49 | AQ50: 46234 | AR50: 0000-00-00 | AS50: Installation GE et Inverseur Site ALA002 Amparafaravola | AT50: YASSIE | AU50: YASSIE | AV50: C500 | AW50: 2026-DT-051003 | AX50: DTG-ENERGIE | AY50: STD | BC50: 1522 | BD50: C500 | BE50: 36 | BF50: 1 | BG50: 2026-08-06
A51: 136051 | B51: TSARAVOLA VOLOLONANDRASANA AMBININTSOA | C51: LOCATION BUREAU | D51: Location salle de réunion à Manakara du 270726 au 310726 - Facture du 23/7/2026 | E51: 1 | F51: PIE | G51: 750000 | H51: =IF(N51="USD",G51,IF(N51="MGA",G51/4600,IF(N51="EUR",G51*1.17,IF(N51="GBP",G51*1.35,"")))) -> 163.04348 | I51: =H51*E51 -> 163.04348 | J51: 163.04348 | M51: 0 | N51: MGA | O51: 46234 | P51: 2026-07-31 | Q51: E | R51: E | S51: ANDRIANINA Rebecca | T51: 139353 | W51: DRH | X51: FELANA13 | Y51: Felana RARIVOSON | Z51: 750 000.00 | AA51: 0 | AB51: 1 | AD51: LOCLOCT | AE51: True | AF51: E250_DRH | AG51: DRH-ADMIN | AH51: NA | AJ51: 1 | AK51: 750 000.00 | AL51: YASMG | AN51: 750 000.00 | AO51: 750 000.00 | AP51: F | AQ51: 46234 | AR51: 0000-00-00 | AT51: YASSIE | AU51: YASSIE | AV51: C600 | AW51: E250_DRH | AX51: DRH-ADMIN | AY51: STD | BC51: 13858 | BD51: C600 | BE51: 7235 | BF51: 1 | BG51: 2026-07-31
A52: 136050 | B52: VOYAGES BOURDON | C52: BILLET D'AVION | D52: Achat billet d'avion TANJONA Tech Pol et sa famille suite affectation | E52: 1 | F52: PIE | G52: 4315000 | H52: =IF(N52="USD",G52,IF(N52="MGA",G52/4600,IF(N52="EUR",G52*1.17,IF(N52="GBP",G52*1.35,"")))) -> 938.04348 | I52: =H52*E52 -> 938.04348 | J52: 938.04348 | M52: 0 | N52: MGA | O52: 46234 | P52: 2026-07-31 | Q52: S | R52: S | S52: ANDRIANINA Rebecca | T52: 139347 | W52: DRH | X52: FELANA13 | Y52: Felana RARIVOSON | Z52: 4 315 000.00 | AA52: 0 | AB52: 1 | AD52: PRMEQUI | AE52: False | AF52: E215_DRH | AG52: DRH-ADMIN | AH52: NA | AJ52: 0 | AK52: 0.00 | AL52: YASMG | AN52: 4 315 000.00 | AO52: 4 315 000.00 | AP52: F | AQ52: 46234 | AR52: 0000-00-00 | AT52: YASSIE | AU52: YASSIE | AV52: C600 | AW52: E215_DRH | AX52: DRH-ADMIN | AY52: VOLINT | BC52: 17513 | BD52: C600 | BE52: 2886 | BF52: 1 | BG52: 2026-07-30
A53: 136049 | B53: SIDEF | C53: MACHINE A CAFE | D53: MACHINE A CAFE 4en1 COMPATIBLE NESPRESSO DOLCE GUSTO 1400W 20BARS TAU - DEVIS DT1057625 DU 27/07/26 - A contacter pour la livraison Fanja 0340017302 | E53: 1 | F53: UN | G53: 653125 | H53: =IF(N53="USD",G53,IF(N53="MGA",G53/4600,IF(N53="EUR",G53*1.17,IF(N53="GBP",G53*1.35,"")))) -> 141.9837 | I53: =H53*E53 -> 141.9837 | J53: 141.9837 | M53: 0 | N53: MGA | O53: 46234 | P53: 2026-07-31 | Q53: E | R53: E | S53: RAZAFINDRAHAGA Setra | T53: 139317 | W53: DCG | X53: FELANA13 | Y53: Felana RARIVOSON | Z53: 783 750.00 | AA53: 20 | AB53: 1 | AD53: MOEMOBR | AE53: True | AF53: E218_DCG | AG53: DCG-DRB | AH53: NA | AJ53: 1 | AK53: 653 125.00 | AL53: YASMG | AN53: 653 125.00 | AO53: 783 750.00 | AP53: F | AQ53: 46234 | AR53: 0000-00-00 | AS53: MACHINE A CAFE | AT53: YASSIE | AU53: YASSIE | AV53: C102 | AW53: E218_DCG | AX53: DCG-DRB | AY53: STD | BC53: 3661 | BD53: C102 | BE53: 752 | BF53: 1 | BG53: 2026-07-29
A54: 136048 | B54: GREENLIGHT PLANET | C54: HOME PLUS MAX WITH PANELS | D54: SK-525 Home Plus Max with Panels - PI n°010726-01 | E54: 505 | F54: UN | G54: 110.47525 | H54: =IF(N54="USD",G54,IF(N54="MGA",G54/4600,IF(N54="EUR",G54*1.17,IF(N54="GBP",G54*1.35,"")))) -> 110.47525 | I54: =H54*E54 -> 55790.001 | J54: 55790.001 | M54: 0 | N54: USD | O54: 46234 | P54: 2026-07-31 | Q54: E | R54: E | S54: ANDRIAMIRIJA Luca | T54: 139163 | W54: DCG | X54: FELANA13 | Y54: Felana RARIVOSON | Z54: 55 790.00 | AA54: 0 | AB54: 1 | AD54: VENDABL | AE54: True | AF54: CM_MBL_DCG | AG54: DCG-SHS | AH54: NA | AJ54: 505 | AK54: 55 790.00 | AL54: YASMG | AN54: 122 145.00 | AO54: 122 145.00 | AQ54: 46234 | AR54: 0000-00-00 | AS54: Sun King Kenya Order | AT54: YASSIE | AU54: GAL | AV54: C100 | AW54: CM_MBL_DCG | AX54: DCG-SHS | AY54: IMPORT | BC54: 26103 | BD54: C100 | BE54: 2411 | BF54: 1 | BG54: 2026-07-21
A55: 136048 | B55: GREENLIGHT PLANET | C55: Sun King 32 inch LED TV | D55: SK-737 Sun King 32" TV - PI N°010726-01 | E55: 505 | F55: PIE | G55: 131.39603 | H55: =IF(N55="USD",G55,IF(N55="MGA",G55/4600,IF(N55="EUR",G55*1.17,IF(N55="GBP",G55*1.35,"")))) -> 131.39603 | I55: =H55*E55 -> 66354.995 | J55: 66354.995 | M55: 0 | N55: USD | O55: 46234 | P55: 2026-07-31 | Q55: E | R55: E | S55: ANDRIAMIRIJA Luca | T55: 139163 | W55: DCG | X55: FELANA13 | Y55: Felana RARIVOSON | Z55: 66 355.00 | AA55: 0 | AB55: 2 | AD55: TCOTRNS | AE55: True | AF55: CM_MBL_DCG | AG55: DCG-SHS | AH55: NA | AJ55: 505 | AK55: 66 355.00 | AL55: YASMG | AN55: 122 145.00 | AO55: 122 145.00 | AQ55: 46234 | AR55: 0000-00-00 | AS55: Sun King Kenya Order | AT55: YASSIE | AU55: GAL | AV55: C100 | AW55: CM_MBL_DCG | AX55: DCG-SHS | AY55: IMPORT | BC55: 12160 | BD55: C100 | BE55: 2411 | BF55: 2 | BG55: 2026-07-21
A56: 136047 | B56: VOYAGES BOURDON | C56: BILLET D 'AVION | D56: Voyage - Transfo | E56: 1 | F56: UN | G56: 14689300 | H56: =IF(N56="USD",G56,IF(N56="MGA",G56/4600,IF(N56="EUR",G56*1.17,IF(N56="GBP",G56*1.35,"")))) -> 3193.3261 | I56: =H56*E56 -> 3193.3261 | J56: 3193.3261 | M56: 0 | N56: MGA | O56: 46233 | P56: 2026-07-30 | Q56: S | R56: S | S56: RASOLOJAONA Miora | T56: 139344 | W56: DG | X56: NADIA7 | Y56: RAVONINJATOVO Nadia | Z56: 14 689 300.00 | AA56: 0 | AB56: 1 | AD56: VDPBILL | AE56: False | AF56: E225_DG | AG56: DG | AH56: NA | AJ56: 0 | AK56: 0.00 | AL56: YASMG | AN56: 14 689 300.00 | AO56: 14 689 300.00 | AP56: F | AQ56: 46233 | AR56: 0000-00-00 | AS56: Voyage - Transfo | AT56: YASSIE | AU56: YASSIE | AV56: C900 | AW56: E225_DG | AX56: DG | AY56: VOLEXT | BC56: 1250 | BD56: C900 | BE56: 2886 | BF56: 1 | BG56: 2026-07-30
A57: 136046 | B57: SOCIETE PRONET SARLU | C57: PRESTATION NETTOYAGE | D57: NETTOYAGE DESHERBAGE ET ENLEVEMENT DE DECHET - EXTERIEUR DATA CENTER ATS001# DEVIS N° 217/26-MH DU 22/07/2026 | E57: 1 | F57: UN | G57: 47158.333 | H57: =IF(N57="USD",G57,IF(N57="MGA",G57/4600,IF(N57="EUR",G57*1.17,IF(N57="GBP",G57*1.35,"")))) -> 10.251812 | I57: =H57*E57 -> 10.251812 | J57: 10.251812 | M57: 0 | N57: MGA | O57: 46233 | P57: 2026-07-30 | Q57: E | R57: E | S57: RAKOTOMALALA Manambina Tafitasoa | T57: 139335 | W57: DFG | X57: NADIA7 | Y57: RAVONINJATOVO Nadia | Z57: 56 590.00 | AA57: 20 | AB57: 1 | AD57: SGNANET | AE57: True | AF57: E218_DAF | AG57: DFGA-LOG | AH57: NA | AJ57: 1 | AK57: 47 158.33 | AL57: YASMG | AN57: 952 731.66 | AO57: 1 143 278.00 | AP57: F | AQ57: 46233 | AR57: 0000-00-00 | AS57: NETTOYAGE DESHERBAGE ET ENLEVEMENT DE DECHET 3 SITES | AT57: YASSIE | AU57: YASSIE | AV57: C700 | AW57: E218_DAF | AX57: DFGA-LOG | AY57: STD | BC57: 3072 | BD57: C700 | BE57: 4740 | BF57: 1 | BG57: 2026-07-31
A58: 136046 | B58: SOCIETE PRONET SARLU | C58: PRESTATION NETTOYAGE | D58: NETTOYAGE DESHERBAGE ET ENLEVEMENT DE DECHET - EXTEUEUR TERRAIN YAS SAMAZAMAY ATS002# DEVIS N° 219/26-MH DU 22/07/2026 | E58: 1 | F58: UN | G58: 451483.33 | H58: =IF(N58="USD",G58,IF(N58="MGA",G58/4600,IF(N58="EUR",G58*1.17,IF(N58="GBP",G58*1.35,"")))) -> 98.148551 | I58: =H58*E58 -> 98.148551 | J58: 98.148551 | M58: 0 | N58: MGA | O58: 46233 | P58: 2026-07-30 | Q58: E | R58: E | S58: RAKOTOMALALA Manambina Tafitasoa | T58: 139335 | W58: DFG | X58: NADIA7 | Y58: RAVONINJATOVO Nadia | Z58: 541 780.00 | AA58: 20 | AB58: 3 | AD58: SGNANET | AE58: True | AF58: E218_DAF | AG58: DFGA-LOG | AH58: NA | AJ58: 1 | AK58: 451 483.33 | AL58: YASMG | AN58: 952 731.66 | AO58: 1 143 278.00 | AP58: F | AQ58: 46233 | AR58: 0000-00-00 | AS58: NETTOYAGE DESHERBAGE ET ENLEVEMENT DE DECHET 3 SITES | AT58: YASSIE | AU58: YASSIE | AV58: C700 | AW58: E218_DAF | AX58: DFGA-LOG | AY58: STD | BC58: 3072 | BD58: C700 | BE58: 4740 | BF58: 3 | BG58: 2026-07-31
A59: 136046 | B59: SOCIETE PRONET SARLU | C59: PRESTATION NETTOYAGE | D59: NETTOYAGE DESHERBAGE ET ENLEVEMENT DE DECHET - EXTEUEUR SITE SALAZAMAY# DEVIS N° 218/26-MH DU 22/07/2026 | E59: 1 | F59: UN | G59: 454090 | H59: =IF(N59="USD",G59,IF(N59="MGA",G59/4600,IF(N59="EUR",G59*1.17,IF(N59="GBP",G59*1.35,"")))) -> 98.715217 | I59: =H59*E59 -> 98.715217 | J59: 98.715217 | M59: 0 | N59: MGA | O59: 46233 | P59: 2026-07-30 | Q59: E | R59: E | S59: RAKOTOMALALA Manambina Tafitasoa | T59: 139335 | W59: DFG | X59: NADIA7 | Y59: RAVONINJATOVO Nadia | Z59: 544 908.00 | AA59: 20 | AB59: 2 | AD59: SGNANET | AE59: True | AF59: E218_DAF | AG59: DFGA-LOG | AH59: NA | AJ59: 1 | AK59: 454 090.00 | AL59: YASMG | AN59: 952 731.66 | AO59: 1 143 278.00 | AP59: F | AQ59: 46233 | AR59: 0000-00-00 | AS59: NETTOYAGE DESHERBAGE ET ENLEVEMENT DE DECHET 3 SITES | AT59: YASSIE | AU59: YASSIE | AV59: C700 | AW59: E218_DAF | AX59: DFGA-LOG | AY59: STD | BC59: 3072 | BD59: C700 | BE59: 4740 | BF59: 2 | BG59: 2026-07-31
A60: 136045 | B60: CHANDARANA CIE | C60: BOITE COLLE | D60: Colle de bureau | E60: 5 | F60: PIE | G60: 1250 | H60: =IF(N60="USD",G60,IF(N60="MGA",G60/4600,IF(N60="EUR",G60*1.17,IF(N60="GBP",G60*1.35,"")))) -> 0.27173913 | I60: =H60*E60 -> 1.3586957 | J60: 1.3586957 | M60: 5 | N60: MGA | O60: 46233 | P60: 2026-07-30 | Q60: E | R60: E | S60: RAKOTOMALALA Manambina Tafitasoa | T60: 139291 | W60: DFG | X60: NADIA7 | Y60: RAVONINJATOVO Nadia | Z60: 7 125.00 | AA60: 20 | AB60: 23 | AD60: FRNPAPF | AE60: True | AF60: E218_DAF | AG60: DFGA-LOG | AH60: NA | AJ60: 5 | AK60: 5 937.50 | AL60: YASMG | AN60: 31 065 326.66 | AO60: 37 278 392.00 | AP60: F | AQ60: 46233 | AR60: 0000-00-00 | AS60: FOURNITURE DE BUREAU Q3 2026 - Validation DG le 27/07/2026 | AT60: YASSIE | AU60: GALE | AV60: C700 | AW60: E218_DAF | AX60: DFGA-LOG | AY60: STD | BC60: 7866 | BD60: C700 | BE60: 1074 | BF60: 23 | BG60: 2026-07-31
A61: 136045 | B61: CHANDARANA CIE | C61: POST IT GM COULEUR | D61: Post it | E61: 119 | F61: PIE | G61: 1500 | H61: =IF(N61="USD",G61,IF(N61="MGA",G61/4600,IF(N61="EUR",G61*1.17,IF(N61="GBP",G61*1.35,"")))) -> 0.32608696 | I61: =H61*E61 -> 38.804348 | J61: 38.804348 | M61: 5 | N61: MGA | O61: 46233 | P61: 2026-07-30 | Q61: E | R61: E | S61: RAKOTOMALALA Manambina Tafitasoa | T61: 139291 | W61: DFG | X61: NADIA7 | Y61: RAVONINJATOVO Nadia | Z61: 203 490.00 | AA61: 20 | AB61: 6 | AD61: PRMEQUI | AE61: True | AF61: E218_DAF | AG61: DFGA-LOG | AH61: NA | AJ61: 119 | AK61: 169 575.00 | AL61: YASMG | AN61: 31 065 326.66 | AO61: 37 278 392.00 | AP61: F | AQ61: 46233 | AR61: 0000-00-00 | AS61: FOURNITURE DE BUREAU Q3 2026 - Validation DG le 27/07/2026 | AT61: YASSIE | AU61: GALE | AV61: C700 | AW61: E218_DAF | AX61: DFGA-LOG | AY61: STD | BC61: 13410 | BD61: C700 | BE61: 1074 | BF61: 6 | BG61: 2026-07-31
A62: 136045 | B62: CHANDARANA CIE | C62: CRAYON | D62: Crayon | E62: 40 | F62: UN | G62: 3083.33 | H62: =IF(N62="USD",G62,IF(N62="MGA",G62/4600,IF(N62="EUR",G62*1.17,IF(N62="GBP",G62*1.35,"")))) -> 0.67028913 | I62: =H62*E62 -> 26.811565 | J62: 26.811565 | M62: 5 | N62: MGA | O62: 46233 | P62: 2026-07-30 | Q62: E | R62: E | S62: RAKOTOMALALA Manambina Tafitasoa | T62: 139291 | W62: DFG | X62: NADIA7 | Y62: RAVONINJATOVO Nadia | Z62: 140 599.85 | AA62: 20 | AB62: 21 | AD62: FRNPAPF | AE62: True | AF62: E218_DAF | AG62: DFGA-LOG | AH62: NA | AJ62: 40 | AK62: 117 166.54 | AL62: YASMG | AN62: 31 065 326.66 | AO62: 37 278 392.00 | AP62: F | AQ62: 46233 | AR62: 0000-00-00 | AS62: FOURNITURE DE BUREAU Q3 2026 - Validation DG le 27/07/2026 | AT62: YASSIE | AU62: GALE | AV62: C700 | AW62: E218_DAF | AX62: DFGA-LOG | AY62: STD | BC62: 4024 | BD62: C700 | BE62: 1074 | BF62: 21 | BG62: 2026-07-31
A63: 136045 | B63: CHANDARANA CIE | C63: ELASTIQUE DE BUREAU | D63: Elastique jaune | E63: 1000 | F63: UN | G63: 3833.33 | H63: =IF(N63="USD",G63,IF(N63="MGA",G63/4600,IF(N63="EUR",G63*1.17,IF(N63="GBP",G63*1.35,"")))) -> 0.83333261 | I63: =H63*E63 -> 833.33261 | J63: 833.33261 | M63: 5 | N63: MGA | O63: 46233 | P63: 2026-07-30 | Q63: E | R63: E | S63: RAKOTOMALALA Manambina Tafitasoa | T63: 139291 | W63: DFG | X63: NADIA7 | Y63: RAVONINJATOVO Nadia | Z63: 4 369 996.20 | AA63: 20 | AB63: 7 | AD63: FRNPAPF | AE63: True | AF63: E218_DAF | AG63: DFGA-LOG | AH63: NA | AJ63: 1000 | AK63: 3 641 663.50 | AL63: YASMG | AN63: 31 065 326.66 | AO63: 37 278 392.00 | AP63: F | AQ63: 46233 | AR63: 0000-00-00 | AS63: FOURNITURE DE BUREAU Q3 2026 - Validation DG le 27/07/2026 | AT63: YASSIE | AU63: GALE | AV63: C700 | AW63: E218_DAF | AX63: DFGA-LOG | AY63: STD | BC63: 3356 | BD63: C700 | BE63: 1074 | BF63: 7 | BG63: 2026-07-31
A64: 136045 | B64: CHANDARANA CIE | C64: LAVE VITRE | D64: Savon lave vitre | E64: 301 | F64: PIE | G64: 4500 | H64: =IF(N64="USD",G64,IF(N64="MGA",G64/4600,IF(N64="EUR",G64*1.17,IF(N64="GBP",G64*1.35,"")))) -> 0.97826087 | I64: =H64*E64 -> 294.45652 | J64: 294.45652 | M64: 10 | N64: MGA | O64: 46233 | P64: 2026-07-30 | Q64: E | R64: E | S64: RAKOTOMALALA Manambina Tafitasoa | T64: 139291 | W64: DFG | X64: NADIA7 | Y64: RAVONINJATOVO Nadia | Z64: 1 462 860.00 | AA64: 20 | AB64: 20 | AD64: MATQUIN | AE64: True | AF64: E218_DAF | AG64: DFGA-LOG | AH64: NA | AJ64: 301 | AK64: 1 219 050.00 | AL64: YASMG | AN64: 31 065 326.66 | AO64: 37 278 392.00 | AP64: F | AQ64: 46233 | AR64: 0000-00-00 | AS64: FOURNITURE DE BUREAU Q3 2026 - Validation DG le 27/07/2026 | AT64: YASSIE | AU64: GALE | AV64: C700 | AW64: E218_DAF | AX64: DFGA-LOG | AY64: STD | BC64: 10599 | BD64: C700 | BE64: 1074 | BF64: 20 | BG64: 2026-07-31
A65: 136045 | B65: CHANDARANA CIE | C65: Pile alkaline LR06 | D65: PILE ALCALINE R3 | E65: 520 | F65: UN | G65: 4666.67 | H65: =IF(N65="USD",G65,IF(N65="MGA",G65/4600,IF(N65="EUR",G65*1.17,IF(N65="GBP",G65*1.35,"")))) -> 1.0144935 | I65: =H65*E65 -> 527.53661 | J65: 527.53661 | M65: 5 | N65: MGA | O65: 46233 | P65: 2026-07-30 | Q65: E | R65: E | S65: RAKOTOMALALA Manambina Tafitasoa | T65: 139291 | W65: DFG | X65: NADIA7 | Y65: RAVONINJATOVO Nadia | Z65: 2 766 401.98 | AA65: 20 | AB65: 12 | AD65: GELACCS | AE65: True | AF65: E218_DAF | AG65: DFGA-LOG | AH65: NA | AJ65: 520 | AK65: 2 305 334.98 | AL65: YASMG | AN65: 31 065 326.66 | AO65: 37 278 392.00 | AP65: F | AQ65: 46233 | AR65: 0000-00-00 | AS65: FOURNITURE DE BUREAU Q3 2026 - Validation DG le 27/07/2026 | AT65: YASSIE | AU65: GALE | AV65: C700 | AW65: E218_DAF | AX65: DFGA-LOG | AY65: STD | BC65: 15101 | BD65: C700 | BE65: 1074 | BF65: 12 | BG65: 2026-07-31
A66: 136045 | B66: CHANDARANA CIE | C66: ELASTIQUE DE BUREAU | D66: Elastique coul ass | E66: 232 | F66: UN | G66: 4750 | H66: =IF(N66="USD",G66,IF(N66="MGA",G66/4600,IF(N66="EUR",G66*1.17,IF(N66="GBP",G66*1.35,"")))) -> 1.0326087 | I66: =H66*E66 -> 239.56522 | J66: 239.56522 | M66: 5 | N66: MGA | O66: 46233 | P66: 2026-07-30 | Q66: E | R66: E | S66: RAKOTOMALALA Manambina Tafitasoa | T66: 139291 | W66: DFG | X66: NADIA7 | Y66: RAVONINJATOVO Nadia | Z66: 1 256 280.00 | AA66: 20 | AB66: 24 | AD66: FRNPAPF | AE66: True | AF66: E218_DAF | AG66: DFGA-LOG | AH66: NA | AJ66: 232 | AK66: 1 046 900.00 | AL66: YASMG | AN66: 31 065 326.66 | AO66: 37 278 392.00 | AP66: F | AQ66: 46233 | AR66: 0000-00-00 | AS66: FOURNITURE DE BUREAU Q3 2026 - Validation DG le 27/07/2026 | AT66: YASSIE | AU66: GALE | AV66: C700 | AW66: E218_DAF | AX66: DFGA-LOG | AY66: STD | BC66: 3356 | BD66: C700 | BE66: 1074 | BF66: 24 | BG66: 2026-07-31
A67: 136045 | B67: CHANDARANA CIE | C67: MARKER TABLEAU BLANC 4 CO | D67: Marker tableau blanc 4 couleurs | E67: 334 | F67: PIE | G67: 4750 | H67: =IF(N67="USD",G67,IF(N67="MGA",G67/4600,IF(N67="EUR",G67*1.17,IF(N67="GBP",G67*1.35,"")))) -> 1.0326087 | I67: =H67*E67 -> 344.8913 | J67: 344.8913 | M67: 5 | N67: MGA | O67: 46233 | P67: 2026-07-30 | Q67: E | R67: E | S67: RAKOTOMALALA Manambina Tafitasoa | T67: 139291 | W67: DFG | X67: NADIA7 | Y67: RAVONINJATOVO Nadia | Z67: 1 808 610.00 | AA67: 20 | AB67: 9 | AD67: FRNPAPF | AE67: True | AF67: E218_DAF | AG67: DFGA-LOG | AH67: NA | AJ67: 334 | AK67: 1 507 175.00 | AL67: YASMG | AN67: 31 065 326.66 | AO67: 37 278 392.00 | AP67: F | AQ67: 46233 | AR67: 0000-00-00 | AS67: FOURNITURE DE BUREAU Q3 2026 - Validation DG le 27/07/2026 | AT67: YASSIE | AU67: GALE | AV67: C700 | AW67: E218_DAF | AX67: DFGA-LOG | AY67: STD | BC67: 10693 | BD67: C700 | BE67: 1074 | BF67: 9 | BG67: 2026-07-31
... A84: 136045 | B84: CHANDARANA CIE | C84: PAPIER A3 | D84: Papier A3 | E84: 175 | F84: RAM | G84: 36500 | H84: =IF(N84="USD",G84,IF(N84="MGA",G84/4600,IF(N84="EUR",G84*1.17,IF(N84="GBP",G84*1.35,"")))) -> 7.9347826 | I84: =H84*E84 -> 1388.587 | J84: 1388.587 | M84: 0 | N84: MGA | O84: 46233 | P84: 2026-07-30 | Q84: E | R84: E | S84: RAKOTOMALALA Manambina Tafitasoa | T84: 139291 | W84: DFG | X84: NADIA7 | Y84: RAVONINJATOVO Nadia | Z84: 7 665 000.00 | AA84: 20 | AB84: 17 | AD84: FRNPAPF | AE84: True | AF84: E218_DAF | AG84: DFGA-LOG | AH84: NA | AJ84: 175 | AK84: 6 387 500.00 | AL84: YASMG | AN84: 31 065 326.66 | AO84: 37 278 392.00 | AP84: F | AQ84: 46233 | AR84: 0000-00-00 | AS84: FOURNITURE DE BUREAU Q3 2026 - Validation DG le 27/07/2026 | AT84: YASSIE | AU84: GALE | AV84: C700 | AW84: E218_DAF | AX84: DFGA-LOG | AY84: STD | BC84: 3289 | BD84: C700 | BE84: 1074 | BF84: 17 | BG84: 2026-07-31
A85: 136044 | B85: NOTION | C85: FREIGHT | D85: AIR FREIGHT | E85: 2000 | F85: UN | G85: 6.14 | H85: =IF(N85="USD",G85,IF(N85="MGA",G85/4600,IF(N85="EUR",G85*1.17,IF(N85="GBP",G85*1.35,"")))) -> 6.14 | I85: =H85*E85 -> 12280 | J85: 12280 | M85: 0 | N85: USD | O85: 46233 | P85: 2026-07-30 | Q85: E | R85: E | S85: ANDRIANATOANDRO Johanna | T85: 139338 | W85: DCG | X85: FELANA13 | Y85: Felana RARIVOSON | Z85: 12 280.00 | AA85: 0 | AB85: 2 | AD85: TRITRAD | AE85: True | AF85: CFI_TERM_DCG | AG85: DCG-PS | AH85: NA | AJ85: 2000 | AK85: 12 280.00 | AL85: YASMG | AN85: 59 280.00 | AO85: 59 280.00 | AQ85: 46233 | AR85: 0000-00-00 | AS85: COMMANDE BOXNOTION 4G - VALIDEE LE 30/07/2026 | AT85: YASSIE | AU85: GAL | AV85: C100 | AW85: CFI_TERM_DCG | AX85: DCG-PS | AY85: IMPORT | BC85: 10030 | BD85: C100 | BE85: 4083 | BF85: 2 | BG85: 2026-07-30
A86: 136044 | B86: NOTION | C86: BOX NOTION 4G LTE | D86: BOX NOTION 4G - PROFORMA INVOICE NHK00270202026 | E86: 2000 | F86: UN | G86: 23.5 | H86: =IF(N86="USD",G86,IF(N86="MGA",G86/4600,IF(N86="EUR",G86*1.17,IF(N86="GBP",G86*1.35,"")))) -> 23.5 | I86: =H86*E86 -> 47000 | J86: 47000 | M86: 0 | N86: USD | O86: 46233 | P86: 2026-07-30 | Q86: E | R86: E | S86: ANDRIANATOANDRO Johanna | T86: 139338 | W86: DCG | X86: FELANA13 | Y86: Felana RARIVOSON | Z86: 47 000.00 | AA86: 0 | AB86: 1 | AD86: VENDABL | AE86: True | AF86: CFI_TERM_DCG | AG86: DCG-PS | AH86: NA | AJ86: 2000 | AK86: 47 000.00 | AL86: YASMG | AN86: 59 280.00 | AO86: 59 280.00 | AQ86: 46233 | AR86: 0000-00-00 | AS86: COMMANDE BOXNOTION 4G - VALIDEE LE 30/07/2026 | AT86: YASSIE | AU86: GAL | AV86: C100 | AW86: CFI_TERM_DCG | AX86: DCG-PS | AY86: IMPORT | BC86: 15036 | BD86: C100 | BE86: 4083 | BF86: 1 | BG86: 2026-07-30
A87: 136043 | B87: NOTION | C87: FREIGHT | D87: SEA FREIGHT | E87: 3000 | F87: UN | G87: 3 | H87: =IF(N87="USD",G87,IF(N87="MGA",G87/4600,IF(N87="EUR",G87*1.17,IF(N87="GBP",G87*1.35,"")))) -> 3 | I87: =H87*E87 -> 9000 | J87: 9000 | M87: 0 | N87: USD | O87: 46233 | P87: 2026-07-30 | Q87: E | R87: E | S87: ANDRIANATOANDRO Johanna | T87: 139339 | W87: DCG | X87: FELANA13 | Y87: Felana RARIVOSON | Z87: 9 000.00 | AA87: 0 | AB87: 2 | AD87: TRITRAD | AE87: True | AF87: CFI_TERM_DCG | AG87: DCG-PS | AH87: NA | AJ87: 3000 | AK87: 9 000.00 | AL87: YASMG | AN87: 79 500.00 | AO87: 79 500.00 | AQ87: 46233 | AR87: 0000-00-00 | AS87: BOXNOTION 4G - VALIDEE LE 30/07/2026 | AT87: YASSIE | AU87: GAL | AV87: C100 | AW87: CFI_TERM_DCG | AX87: DCG-PS | AY87: IMPORT | BC87: 10030 | BD87: C100 | BE87: 4083 | BF87: 2 | BG87: 2026-07-30
A88: 136043 | B88: NOTION | C88: BOX NOTION 4G LTE | D88: BOX NOTION 4G - PROFORMA INVOICE NHK00270702026 | E88: 3000 | F88: UN | G88: 23.5 | H88: =IF(N88="USD",G88,IF(N88="MGA",G88/4600,IF(N88="EUR",G88*1.17,IF(N88="GBP",G88*1.35,"")))) -> 23.5 | I88: =H88*E88 -> 70500 | J88: 70500 | M88: 0 | N88: USD | O88: 46233 | P88: 2026-07-30 | Q88: E | R88: E | S88: ANDRIANATOANDRO Johanna | T88: 139339 | W88: DCG | X88: FELANA13 | Y88: Felana RARIVOSON | Z88: 70 500.00 | AA88: 0 | AB88: 1 | AD88: VENDABL | AE88: True | AF88: CFI_TERM_DCG | AG88: DCG-PS | AH88: NA | AJ88: 3000 | AK88: 70 500.00 | AL88: YASMG | AN88: 79 500.00 | AO88: 79 500.00 | AQ88: 46233 | AR88: 0000-00-00 | AS88: BOXNOTION 4G - VALIDEE LE 30/07/2026 | AT88: YASSIE | AU88: GAL | AV88: C100 | AW88: CFI_TERM_DCG | AX88: DCG-PS | AY88: IMPORT | BC88: 15036 | BD88: C100 | BE88: 4083 | BF88: 1 | BG88: 2026-07-30
A89: 136042 | B89: GLOBAL CONSTRUCTION MADAGASCAR | C89: Travaux de réhabilitation | D89: Fourniture et pose vitre clair ep:6mm y compris remplacements serrures, remise en état du chassis en alu et toutes sujétions de mises en ouvres(Porte principale)-Data Center Nosy Be | E89: 1 | F89: UN | G89: 926500 | H89: =IF(N89="USD",G89,IF(N89="MGA",G89/4600,IF(N89="EUR",G89*1.17,IF(N89="GBP",G89*1.35,"")))) -> 201.41304 | I89: =H89*E89 -> 201.41304 | J89: 201.41304 | M89: 0 | N89: MGA | O89: 46233 | P89: 2026-07-30 | Q89: E | R89: E | S89: RASAMOELINA Haritsoa Oliva | T89: 139293 | W89: DTG | X89: ELIE3 | Y89: ANDRIAMANANTSOA Elie | Z89: 1 111 800.00 | AA89: 20 | AB89: 1 | AD89: PRICTRL | AE89: True | AF89: 2026-DT-091006 | AG89: DTG-PROJETS | AH89: NA | AJ89: 1 | AK89: 926 500.00 | AL89: YASMG | AN89: 926 500.00 | AO89: 1 111 800.00 | AP89: F | AQ89: 46233 | AR89: 0000-00-00 | AS89: Remplacement vitrage Data Center DIA013 Nosy Be | AT89: YASSIE | AU89: YASSIE | AV89: C500 | AW89: 2026-DT-091006 | AX89: DTG-PROJETS | AY89: STD | BC89: 22422 | BD89: C500 | BE89: 2404 | BF89: 1 | BG89: 2026-08-04
A90: 136041 | B90: RAZAFIMAHATRATRA ANDRIATSITOHAINA | C90: Travaux filaire | D90: DTG/DOM: Survey et inventaire avant désinstallation des câbles sur D00 DTG-208603 # PF N° : 011/ART/2026 | E90: 1 | F90: UN | G90: 4170500 | H90: =IF(N90="USD",G90,IF(N90="MGA",G90/4600,IF(N90="EUR",G90*1.17,IF(N90="GBP",G90*1.35,"")))) -> 906.63043 | I90: =H90*E90 -> 906.63043 | J90: 906.63043 | M90: 0 | N90: MGA | O90: 46233 | P90: 2026-07-30 | Q90: E | R90: E | S90: HERY RAMAROLAHY | T90: 139319 | W90: DTG | X90: ELIE3 | Y90: ANDRIAMANANTSOA Elie | Z90: 4 170 500.00 | AA90: 0 | AB90: 1 | AD90: PRICTRL | AE90: True | AF90: 2026-DT-102001 | AG90: DTG-DOM | AH90: NA | AJ90: 1 | AK90: 4 170 500.00 | AL90: YASMG | AN90: 4 170 500.00 | AO90: 4 170 500.00 | AQ90: 46233 | AR90: 0000-00-00 | AS90: désinstallation des câbles sur D00 DTG-208603 | AT90: YASSIE | AU90: YASSIE | AV90: C500 | AW90: 2026-DT-102001 | AX90: DTG-DOM | AY90: STD | BC90: 22417 | BD90: C500 | BE90: 3129 | BF90: 1 | BG90: 2026-08-05
A91: 136040 | B91: ECO FUSION | C91: Habillages batiments | D91: HABILLAGE VITRE PORTE# DEVIS N°142/07/E/26 DU 22/07/2026 | E91: 8 | F91: PIE | G91: 12000 | H91: =IF(N91="USD",G91,IF(N91="MGA",G91/4600,IF(N91="EUR",G91*1.17,IF(N91="GBP",G91*1.35,"")))) -> 2.6086957 | I91: =H91*E91 -> 20.869565 | J91: 20.869565 | M91: 0 | N91: MGA | O91: 46233 | P91: 2026-07-30 | Q91: E | R91: E | S91: RASOLOJAONA Miora | T91: 139342 | W91: DG | X91: NADIA7 | Y91: RAVONINJATOVO Nadia | Z91: 96 000.00 | AA91: 0 | AB91: 1 | AD91: PRMBATX | AE91: True | AF91: E218_DG | AG91: DG | AH91: NA | AJ91: 8 | AK91: 96 000.00 | AL91: YASMG | AN91: 507 500.00 | AO91: 507 500.00 | AQ91: 46233 | AR91: 0000-00-00 | AS91: HABILLAGE VITRE PORTE | AT91: YASSIE | AU91: YASSIE | AV91: C900 | AW91: E218_DG | AX91: DG | AY91: STD | BC91: 13113 | BD91: C900 | BE91: 1136 | BF91: 1 | BG91: 2026-07-30
A92: 136040 | B92: ECO FUSION | C92: FRAIS DIVERS | E92: 1 | F92: UN | G92: 411500 | H92: =IF(N92="USD",G92,IF(N92="MGA",G92/4600,IF(N92="EUR",G92*1.17,IF(N92="GBP",G92*1.35,"")))) -> 89.456522 | I92: =H92*E92 -> 89.456522 | J92: 89.456522 | M92: 0 | N92: MGA | O92: 46233 | P92: 2026-07-30 | Q92: E | R92: E | T92: 0 | W92: DG | X92: NADIA7 | Y92: RAVONINJATOVO Nadia | Z92: 411 500.00 | AA92: 0 | AB92: 0 | AD92: EVROEVR | AE92: True | AF92: E218_DG | AG92: DG | AH92: NA | AJ92: 1 | AK92: 411 500.00 | AL92: YASMG | AN92: 507 500.00 | AO92: 507 500.00 | AQ92: 46233 | AR92: 0000-00-00 | AS92: HABILLAGE VITRE PORTE | AT92: YASSIE | AU92: YASSIE | AV92: C900 | AW92: E218_DG | AX92: DG | AY92: STD | BC92: 4213 | BD92: C900 | BE92: 1136 | BF92: 2 | BG92: 2026-07-30
A93: 136039 | B93: EASY NETCOM | C93: Travaux GC et tirage FO | D93: HSSES # PF Réf :025/03832/ENC-HR | E93: 1 | F93: UN | G93: 2018408 | H93: =IF(N93="USD",G93,IF(N93="MGA",G93/4600,IF(N93="EUR",G93*1.17,IF(N93="GBP",G93*1.35,"")))) -> 438.78435 | I93: =H93*E93 -> 438.78435 | J93: 438.78435 | M93: 0 | N93: MGA | O93: 46233 | P93: 2026-07-30 | Q93: E | R93: E | S93: RASAMOELINA Haritsoa Oliva | T93: 139301 | W93: DTG | X93: ELIE3 | Y93: ANDRIAMANANTSOA Elie | Z93: 2 422 089.60 | AA93: 20 | AB93: 2 | AD93: PRICTRL | AE93: True | AF93: 2026-DT-022001 | AG93: DTG-PROJETS | AH93: NA | AJ93: 1 | AK93: 2 018 408.00 | AL93: YASMG | AN93: 33 250 657.00 | AO93: 39 900 788.40 | AQ93: 46233 | AR93: 0000-00-00 | AS93: TX GC FO ANO005_MARILLAC | AT93: YASSIE | AU93: YASSIE | AV93: C500 | AW93: 2026-DT-022001 | AX93: DTG-PROJETS | AY93: STD | BC93: 22421 | BD93: C500 | BE93: 2053 | BF93: 2 | BG93: 0000-00-00
A94: 136039 | B94: EASY NETCOM | C94: Travaux GC et tirage FO | D94: INSTALLATION # PF Réf :025/03832/ENC-HR | E94: 1 | F94: UN | G94: 3000000 | H94: =IF(N94="USD",G94,IF(N94="MGA",G94/4600,IF(N94="EUR",G94*1.17,IF(N94="GBP",G94*1.35,"")))) -> 652.17391 | I94: =H94*E94 -> 652.17391 | J94: 652.17391 | M94: 0 | N94: MGA | O94: 46233 | P94: 2026-07-30 | Q94: E | R94: E | S94: RASAMOELINA Haritsoa Oliva | T94: 139301 | W94: DTG | X94: ELIE3 | Y94: ANDRIAMANANTSOA Elie | Z94: 3 600 000.00 | AA94: 20 | AB94: 1 | AD94: PRICTRL | AE94: True | AF94: 2026-DT-022001 | AG94: DTG-PROJETS | AH94: NA | AJ94: 1 | AK94: 3 000 000.00 | AL94: YASMG | AN94: 33 250 657.00 | AO94: 39 900 788.40 | AQ94: 46233 | AR94: 0000-00-00 | AS94: TX GC FO ANO005_MARILLAC | AT94: YASSIE | AU94: YASSIE | AV94: C500 | AW94: 2026-DT-022001 | AX94: DTG-PROJETS | AY94: STD | BC94: 22421 | BD94: C500 | BE94: 2053 | BF94: 1 | BG94: 0000-00-00
A95: 136039 | B95: EASY NETCOM | C95: Travaux GC et tirage FO | D95: TRAVAUX GENIE CIVL SOUTERRAIN # PF Réf :025/03832/ENC-HR | E95: 1 | F95: UN | G95: 32766430 | H95: =IF(N95="USD",G95,IF(N95="MGA",G95/4600,IF(N95="EUR",G95*1.17,IF(N95="GBP",G95*1.35,"")))) -> 7123.137 | I95: =H95*E95 -> 7123.137 | J95: 7123.137 | M95: 0 | N95: MGA | O95: 46233 | P95: 2026-07-30 | Q95: E | R95: E | S95: RASAMOELINA Haritsoa Oliva | T95: 139301 | W95: DTG | X95: ELIE3 | Y95: ANDRIAMANANTSOA Elie | Z95: 39 319 716.00 | AA95: 20 | AB95: 3 | AD95: PRICTRL | AE95: True | AF95: 2026-DT-022001 | AG95: DTG-PROJETS | AH95: NA | AJ95: 1 | AK95: 32 766 430.00 | AL95: YASMG | AN95: 33 250 657.00 | AO95: 39 900 788.40 | AQ95: 46233 | AR95: 0000-00-00 | AS95: TX GC FO ANO005_MARILLAC | AT95: YASSIE | AU95: YASSIE | AV95: C500 | AW95: 2026-DT-022001 | AX95: DTG-PROJETS | AY95: STD | BC95: 22421 | BD95: C500 | BE95: 2053 | BF95: 3 | BG95: 0000-00-00
A96: 136038 | B96: RAZAFIMAHATRATRA ANDRIATSITOHAINA | C96: Travaux filaire | D96: DTG/DOM: Survey et inventaire avant désinstallation des câbles sur SR01 DTG-208604 # PF N° : 012/ART/2026 | E96: 1 | F96: UN | G96: 1290000 | H96: =IF(N96="USD",G96,IF(N96="MGA",G96/4600,IF(N96="EUR",G96*1.17,IF(N96="GBP",G96*1.35,"")))) -> 280.43478 | I96: =H96*E96 -> 280.43478 | J96: 280.43478 | M96: 0 | N96: MGA | O96: 46233 | P96: 2026-07-30 | Q96: E | R96: E | S96: HERY RAMAROLAHY | T96: 139320 | W96: DTG | X96: ELIE3 | Y96: ANDRIAMANANTSOA Elie | Z96: 1 290 000.00 | AA96: 0 | AB96: 1 | AD96: PRICTRL | AE96: True | AF96: 2026-DT-102001 | AG96: DTG-DOM | AH96: NA | AJ96: 1 | AK96: 1 290 000.00 | AL96: YASMG | AN96: 1 290 000.00 | AO96: 1 290 000.00 | AQ96: 46233 | AR96: 0000-00-00 | AS96: désinstallation des câbles sur SR01 DTG-208604 | AT96: YASSIE | AU96: YASSIE | AV96: C500 | AW96: 2026-DT-102001 | AX96: DTG-DOM | AY96: STD | BC96: 22417 | BD96: C500 | BE96: 3129 | BF96: 1 | BG96: 2026-08-05
A97: 136037 | B97: LUCKKY COMPANY | C97: TRANSPORT SUR SITE TRANSPORT DE BIENS | D97: TRANSPORT EQUIPEMENT DWDM SUR SITE (Nord) # PROFORMA N° 162-07-LC-26 | E97: 1 | F97: UN | G97: 9500000 | H97: =IF(N97="USD",G97,IF(N97="MGA",G97/4600,IF(N97="EUR",G97*1.17,IF(N97="GBP",G97*1.35,"")))) -> 2065.2174 | I97: =H97*E97 -> 2065.2174 | J97: 2065.2174 | M97: 0 | N97: MGA | O97: 46233 | P97: 2026-07-30 | Q97: E | R97: E | S97: RABARISON Eric | T97: 139251 | W97: DTG | X97: ELIE3 | Y97: ANDRIAMANANTSOA Elie | Z97: 9 500 000.00 | AA97: 0 | AB97: 1 | AD97: TRNTERM | AE97: True | AF97: 2026-DT-023001 | AG97: DTG-PROJETS | AH97: NA | AJ97: 1 | AK97: 9 500 000.00 | AL97: YASMG | AN97: 9 500 000.00 | AO97: 9 500 000.00 | AQ97: 46233 | AR97: 0000-00-00 | AS97: DPDI-Projet DWDM Nord -Transport équipements sur site | AT97: YASSIE | AU97: YASSIE | AV97: C500 | AW97: 2026-DT-023001 | AX97: DTG-PROJETS | AY97: STD | BC97: 1284 | BD97: C500 | BE97: 3726 | BF97: 1 | BG97: 0000-00-00
A98: 136036 | B98: JOCKER GRAPHICS | C98: HABILLAGE DIVERSE | D98: LIGHTBOX & HABILLAGE NOUVEAU STORE MANDRITSARA - suivant devis DEV0160 | E98: 1 | F98: UN | G98: 13500659 | H98: =IF(N98="USD",G98,IF(N98="MGA",G98/4600,IF(N98="EUR",G98*1.17,IF(N98="GBP",G98*1.35,"")))) -> 2934.9259 | I98: =H98*E98 -> 2934.9259 | J98: 2934.9259 | M98: 0 | N98: MGA | O98: 46233 | P98: 2026-07-30 | Q98: E | R98: E | S98: RAZAFINDRAHAGA Setra | T98: 139222 | W98: DCG | X98: FELANA13 | Y98: Felana RARIVOSON | Z98: 16 200 791.10 | AA98: 20 | AB98: 1 | AD98: FRNPAPF | AE98: True | AF98: 2026-CO-000001 | AG98: DCG-DRB | AH98: NA | AJ98: 1 | AK98: 13 500 659.25 | AL98: YASMG | AN98: 13 500 659.25 | AO98: 16 200 791.10 | AQ98: 46233 | AR98: 0000-00-00 | AS98: HABILLAGE STORE MANDRITSARA | AT98: YASSIE | AU98: YASSIE | AV98: C102 | AW98: 2026-CO-000001 | AX98: DCG-DRB | AY98: STD | BC98: 3443 | BD98: C102 | BE98: 1645 | BF98: 1 | BG98: 2026-07-24
A99: 136035 | B99: LUCKKY COMPANY | C99: Transport des matériels techniques | D99: Transport et manutention des matériels ( Câble et Caniveau) de Tanà vers Maroantsetra # N°PF YAS 175-07/LC-26 | E99: 1 | F99: M | G99: 7000000 | H99: =IF(N99="USD",G99,IF(N99="MGA",G99/4600,IF(N99="EUR",G99*1.17,IF(N99="GBP",G99*1.35,"")))) -> 1521.7391 | I99: =H99*E99 -> 1521.7391 | J99: 1521.7391 | M99: 0 | N99: MGA | O99: 46233 | P99: 2026-07-30 | Q99: E | R99: E | S99: RASAMOELINA Haritsoa Oliva | T99: 139217 | W99: DTG | X99: ELIE3 | Y99: ANDRIAMANANTSOA Elie | Z99: 7 000 000.00 | AA99: 0 | AB99: 1 | AD99: PRICTRL | AE99: True | AF99: 2026-DT-061001 | AG99: DTG-DOM | AH99: NA | AJ99: 1 | AK99: 7 000 000.00 | AL99: YASMG | AN99: 7 000 000.00 | AO99: 7 000 000.00 | AP99: F | AQ99: 46233 | AR99: 0000-00-00 | AS99: Transport manutention(Câble-Caniveau)-Tanà vers Maroantsetra | AT99: YASSIE | AU99: YASSIE | AV99: C500 | AW99: 2026-DT-061001 | AX99: DTG-DOM | AY99: STD | BC99: 22420 | BD99: C500 | BE99: 3726 | BF99: 1 | BG99: 0000-00-00
A100: 136034 | B100: MASS IN SARL | C100: Starlink Mini Kit | D100: Starlink Mini Kit# DEVIS N° DE140343 du 22/07/2026 | E100: 1 | F100: UN | G100: 1457500 | H100: =IF(N100="USD",G100,IF(N100="MGA",G100/4600,IF(N100="EUR",G100*1.17,IF(N100="GBP",G100*1.35,"")))) -> 316.84783 | I100: =H100*E100 -> 316.84783 | J100: 316.84783 | M100: 0 | N100: MGA | O100: 46233 | P100: 2026-09-14 | Q100: E | R100: E | S100: RAJAONARY Jenny Antsanirina | T100: 139302 | W100: DG | X100: NADIA7 | Y100: RAVONINJATOVO Nadia | Z100: 1 749 000.00 | AA100: 20 | AB100: 1 | AD100: PRMEQUI | AE100: True | AF100: E218_DG | AG100: DG-DCP | AH100: NA | AJ100: 1 | AK100: 1 457 500.00 | AL100: YASMG | AN100: 1 457 500.00 | AO100: 1 749 000.00 | AQ100: 46233 | AR100: 0000-00-00 | AT100: YASSIE | AU100: GALE | AV100: C200 | AW100: E218_DG | AX100: DG-DCP | AY100: STD | BC100: 22996 | BD100: C200 | BE100: 2544 | BF100: 1 | BG100: 2026-09-16
A101: 136033 | B101: PRIMA CE SARLU | C101: Travaux GC et tirage FO | D101: TIRAGE CABLES | E101: 1 | F101: UN | G101: 200000 | H101: =IF(N101="USD",G101,IF(N101="MGA",G101/4600,IF(N101="EUR",G101*1.17,IF(N101="GBP",G101*1.35,"")))) -> 43.478261 | I101: =H101*E101 -> 43.478261 | J101: 43.478261 | M101: 0 | N101: MGA | O101: 46233 | P101: 2026-07-30 | Q101: E | R101: E | S101: RASAMOELINA Haritsoa Oliva | T101: 139245 | W101: DTG | X101: ELIE3 | Y101: ANDRIAMANANTSOA Elie | Z101: 240 000.00 | AA101: 20 | AB101: 4 | AD101: PRICTRL | AE101: True | AF101: 2026-DT-022001 | AG101: DTG-PROJETS | AH101: NA | AJ101: 1 | AK101: 200 000.00 | AL101: YASMG | AN101: 5 728 800.00 | AO101: 6 874 560.00 | AQ101: 46233 | AR101: 0000-00-00 | AS101: TX GC FO AAT066 AMPOROFORO | AT101: YASSIE | AU101: YASSIE | AV101: C500 | AW101: 2026-DT-022001 | AX101: DTG-PROJETS | AY101: STD | BC101: 22421 | BD101: C500 | BE101: 2633 | BF101: 4 | BG101: 0000-00-00
A102: 136033 | B102: PRIMA CE SARLU | C102: Travaux GC et tirage FO | D102: HSSES | E102: 1 | F102: UN | G102: 300000 | H102: =IF(N102="USD",G102,IF(N102="MGA",G102/4600,IF(N102="EUR",G102*1.17,IF(N102="GBP",G102*1.35,"")))) -> 65.217391 | I102: =H102*E102 -> 65.217391 | J102: 65.217391 | M102: 0 | N102: MGA | O102: 46233 | P102: 2026-07-30 | Q102: E | R102: E | S102: RASAMOELINA Haritsoa Oliva | T102: 139245 | W102: DTG | X102: ELIE3 | Y102: ANDRIAMANANTSOA Elie | Z102: 360 000.00 | AA102: 20 | AB102: 2 | AD102: PRICTRL | AE102: True | AF102: 2026-DT-022001 | AG102: DTG-PROJETS | AH102: NA | AJ102: 1 | AK102: 300 000.00 | AL102: YASMG | AN102: 5 728 800.00 | AO102: 6 874 560.00 | AQ102: 46233 | AR102: 0000-00-00 | AS102: TX GC FO AAT066 AMPOROFORO | AT102: YASSIE | AU102: YASSIE | AV102: C500 | AW102: 2026-DT-022001 | AX102: DTG-PROJETS | AY102: STD | BC102: 22421 | BD102: C500 | BE102: 2633 | BF102: 2 | BG102: 0000-00-00
A103: 136033 | B103: PRIMA CE SARLU | C103: Travaux GC et tirage FO | D103: TRAVAUX GENIE CIVL SOUTERRAIN | E103: 1 | F103: UN | G103: 2160000 | H103: =IF(N103="USD",G103,IF(N103="MGA",G103/4600,IF(N103="EUR",G103*1.17,IF(N103="GBP",G103*1.35,"")))) -> 469.56522 | I103: =H103*E103 -> 469.56522 | J103: 469.56522 | M103: 0 | N103: MGA | O103: 46233 | P103: 2026-07-30 | Q103: E | R103: E | S103: RASAMOELINA Haritsoa Oliva | T103: 139245 | W103: DTG | X103: ELIE3 | Y103: ANDRIAMANANTSOA Elie | Z103: 2 592 000.00 | AA103: 20 | AB103: 3 | AD103: PRICTRL | AE103: True | AF103: 2026-DT-022001 | AG103: DTG-PROJETS | AH103: NA | AJ103: 1 | AK103: 2 160 000.00 | AL103: YASMG | AN103: 5 728 800.00 | AO103: 6 874 560.00 | AQ103: 46233 | AR103: 0000-00-00 | AS103: TX GC FO AAT066 AMPOROFORO | AT103: YASSIE | AU103: YASSIE | AV103: C500 | AW103: 2026-DT-022001 | AX103: DTG-PROJETS | AY103: STD | BC103: 22421 | BD103: C500 | BE103: 2633 | BF103: 3 | BG103: 0000-00-00
A104: 136033 | B104: PRIMA CE SARLU | C104: Travaux GC et tirage FO | D104: INSTALLATION | E104: 1 | F104: UN | G104: 3500000 | H104: =IF(N104="USD",G104,IF(N104="MGA",G104/4600,IF(N104="EUR",G104*1.17,IF(N104="GBP",G104*1.35,"")))) -> 760.86957 | I104: =H104*E104 -> 760.86957 | J104: 760.86957 | M104: 0 | N104: MGA | O104: 46233 | P104: 2026-07-30 | Q104: E | R104: E | S104: RASAMOELINA Haritsoa Oliva | T104: 139245 | W104: DTG | X104: ELIE3 | Y104: ANDRIAMANANTSOA Elie | Z104: 4 200 000.00 | AA104: 20 | AB104: 1 | AD104: PRICTRL | AE104: True | AF104: 2026-DT-022001 | AG104: DTG-PROJETS | AH104: NA | AJ104: 1 | AK104: 3 500 000.00 | AL104: YASMG | AN104: 5 728 800.00 | AO104: 6 874 560.00 | AQ104: 46233 | AR104: 0000-00-00 | AS104: TX GC FO AAT066 AMPOROFORO | AT104: YASSIE | AU104: YASSIE | AV104: C500 | AW104: 2026-DT-022001 | AX104: DTG-PROJETS | AY104: STD | BC104: 22421 | BD104: C500 | BE104: 2633 | BF104: 1 | BG104: 0000-00-00
A105: 136032 | B105: SOCIETE DE METALLURGIE DE L OCEAN INDIEN (ABC | C105: BAIE DE BRASSAGE TECHNIC 800X800 42U | D105: [372071] BAIE DE BRASSAGE AVEC PORTE VITREE ET PERFOREE EN KIT 19 in 42U 800X800MM NOIR | E105: 3 | F105: PIE | G105: 2500000 | H105: =IF(N105="USD",G105,IF(N105="MGA",G105/4600,IF(N105="EUR",G105*1.17,IF(N105="GBP",G105*1.35,"")))) -> 543.47826 | I105: =H105*E105 -> 1630.4348 | J105: 1630.4348 | M105: 0 | N105: MGA | O105: 46233 | P105: 2026-07-30 | Q105: E | R105: E | S105: RASAMOELINA Haritsoa Oliva | T105: 139230 | W105: DTG | X105: ELIE3 | Y105: ANDRIAMANANTSOA Elie | Z105: 9 000 000.00 | AA105: 20 | AB105: 1 | AD105: TCORADI | AE105: True | AF105: 2026-DT-061003 | AG105: DTG-DOM | AH105: NA | AJ105: 3 | AK105: 7 500 000.00 | AL105: YASMG | AN105: 6 375 000.00 | AO105: 7 650 000.00 | AQ105: 46233 | AR105: 0000-00-00 | AS105: Achat Rack 19"//42U Indoor(Normalisation-Rack-DataCenter) | AT105: YASSIE | AU105: GALE | AV105: C500 | AW105: 2026-DT-061003 | AX105: DTG-DOM | AY105: STD | BC105: 7676 | BD105: C500 | BE105: 1 | BF105: 1 | BG105: 2026-08-06
A106: 136031 | B106: SOCIETE QUBETA IMPORT-EXPORT SARLU | C106: Taille crayon metallique | D106: Taille Crayon | E106: 220 | F106: PIE | G106: 333.34 | H106: =IF(N106="USD",G106,IF(N106="MGA",G106/4600,IF(N106="EUR",G106*1.17,IF(N106="GBP",G106*1.35,"")))) -> 0.072465217 | I106: =H106*E106 -> 15.942348 | J106: 15.942348 | M106: 5 | N106: MGA | O106: 46233 | P106: 2026-07-30 | Q106: E | R106: E | S106: RAKOTOMALALA Manambina Tafitasoa | T106: 139312 | W106: DFG | X106: NADIA7 | Y106: RAVONINJATOVO Nadia | Z106: 83 601.67 | AA106: 20 | AB106: 13 | AD106: FRNPAPF | AE106: True | AF106: E218_DAF | AG106: DFGA-LOG | AH106: NA | AJ106: 220 | AK106: 69 668.06 | AL106: YASMG | AN106: 20 945 885.84 | AO106: 25 135 063.02 | AQ106: 46233 | AR106: 0000-00-00 | AS106: FOURNITURE DE BUREAU Q3 2026 - Validation DG le 27/07/2026 | AT106: YASSIE | AU106: GALE | AV106: C700 | AW106: E218_DAF | AX106: DFGA-LOG | AY106: STD | BC106: 12295 | BD106: C700 | BE106: 3052 | BF106: 13 | BG106: 2026-07-30
A107: 136031 | B107: SOCIETE QUBETA IMPORT-EXPORT SARLU | C107: SURLIGNEUR 4 COULEURS STAEDLER | D107: SURLIGNEUR 4 COULEURS | E107: 640 | F107: PIE | G107: 625 | H107: =IF(N107="USD",G107,IF(N107="MGA",G107/4600,IF(N107="EUR",G107*1.17,IF(N107="GBP",G107*1.35,"")))) -> 0.13586957 | I107: =H107*E107 -> 86.956522 | J107: 86.956522 | M107: 5 | N107: MGA | O107: 46233 | P107: 2026-07-30 | Q107: E | R107: E | S107: RAKOTOMALALA Manambina Tafitasoa | T107: 139312 | W107: DFG | X107: NADIA7 | Y107: RAVONINJATOVO Nadia | Z107: 456 000.00 | AA107: 20 | AB107: 26 | AD107: FRNPAPF | AE107: True | AF107: E218_DAF | AG107: DFGA-LOG | AH107: NA | AJ107: 640 | AK107: 380 000.00 | AL107: YASMG | AN107: 20 945 885.84 | AO107: 25 135 063.02 | AQ107: 46233 | AR107: 0000-00-00 | AS107: FOURNITURE DE BUREAU Q3 2026 - Validation DG le 27/07/2026 | AT107: YASSIE | AU107: GALE | AV107: C700 | AW107: E218_DAF | AX107: DFGA-LOG | AY107: STD | BC107: 12282 | BD107: C700 | BE107: 3052 | BF107: 26 | BG107: 2026-07-30
A108: 136031 | B108: SOCIETE QUBETA IMPORT-EXPORT SARLU | C108: DESAGRAPHEUSE | D108: Désagrapheuse | E108: 29 | F108: PIE | G108: 833.33 | H108: =IF(N108="USD",G108,IF(N108="MGA",G108/4600,IF(N108="EUR",G108*1.17,IF(N108="GBP",G108*1.35,"")))) -> 0.1811587 | I108: =H108*E108 -> 5.2536022 | J108: 5.2536022 | M108: 5 | N108: MGA | O108: 46233 | P108: 2026-07-30 | Q108: E | R108: E | S108: RAKOTOMALALA Manambina Tafitasoa | T108: 139312 | W108: DFG | X108: NADIA7 | Y108: RAVONINJATOVO Nadia | Z108: 27 549.89 | AA108: 20 | AB108: 4 | AD108: FRNPAPF | AE108: True | AF108: E218_DAF | AG108: DFGA-LOG | AH108: NA | AJ108: 29 | AK108: 22 958.24 | AL108: YASMG | AN108: 20 945 885.84 | AO108: 25 135 063.02 | AQ108: 46233 | AR108: 0000-00-00 | AS108: FOURNITURE DE BUREAU Q3 2026 - Validation DG le 27/07/2026 | AT108: YASSIE | AU108: GALE | AV108: C700 | AW108: E218_DAF | AX108: DFGA-LOG | AY108: STD | BC108: 9522 | BD108: C700 | BE108: 3052 | BF108: 4 | BG108: 2026-07-30
A109: 136031 | B109: SOCIETE QUBETA IMPORT-EXPORT SARLU | C109: AGRAPHE 24/6 | D109: Agraphe 24/6# DEVIS N°DEV/2026/007205 DU 15/06/2026 | E109: 751 | F109: PIE | G109: 833.33 | H109: =IF(N109="USD",G109,IF(N109="MGA",G109/4600,IF(N109="EUR",G109*1.17,IF(N109="GBP",G109*1.35,"")))) -> 0.1811587 | I109: =H109*E109 -> 136.05018 | J109: 136.05018 | M109: 5 | N109: MGA | O109: 46233 | P109: 2026-07-30 | Q109: E | R109: E | S109: RAKOTOMALALA Manambina Tafitasoa | T109: 139312 | W109: DFG | X109: NADIA7 | Y109: RAVONINJATOVO Nadia | Z109: 713 447.15 | AA109: 20 | AB109: 1 | AD109: GOOHABI | AE109: True | AF109: E218_DAF | AG109: DFGA-LOG | AH109: NA | AJ109: 751 | AK109: 594 539.29 | AL109: YASMG | AN109: 20 945 885.84 | AO109: 25 135 063.02 | AQ109: 46233 | AR109: 0000-00-00 | AS109: FOURNITURE DE BUREAU Q3 2026 - Validation DG le 27/07/2026 | AT109: YASSIE | AU109: GALE | AV109: C700 | AW109: E218_DAF | AX109: DFGA-LOG | AY109: STD | BC109: 13362 | BD109: C700 | BE109: 3052 | BF109: 1 | BG109: 2026-07-30
A110: 136031 | B110: SOCIETE QUBETA IMPORT-EXPORT SARLU | C110: CAHIER PM 100p | D110: Cahier PM 100 pages | E110: 1074 | F110: PIE | G110: 1166.67 | H110: =IF(N110="USD",G110,IF(N110="MGA",G110/4600,IF(N110="EUR",G110*1.17,IF(N110="GBP",G110*1.35,"")))) -> 0.25362391 | I110: =H110*E110 -> 272.39208 | J110: 272.39208 | M110: 5 | N110: MGA | O110: 46233 | P110: 2026-07-30 | Q110: E | R110: E | S110: RAKOTOMALALA Manambina Tafitasoa | T110: 139312 | W110: DFG | X110: NADIA7 | Y110: RAVONINJATOVO Nadia | Z110: 1 428 424.08 | AA110: 20 | AB110: 9 | AD110: GOOHABI | AE110: True | AF110: E218_DAF | AG110: DFGA-LOG | AH110: NA | AJ110: 1074 | AK110: 1 190 353.40 | AL110: YASMG | AN110: 20 945 885.84 | AO110: 25 135 063.02 | AQ110: 46233 | AR110: 0000-00-00 | AS110: FOURNITURE DE BUREAU Q3 2026 - Validation DG le 27/07/2026 | AT110: YASSIE | AU110: GALE | AV110: C700 | AW110: E218_DAF | AX110: DFGA-LOG | AY110: STD | BC110: 13363 | BD110: C700 | BE110: 3052 | BF110: 9 | BG110: 2026-07-30
A111: 136031 | B111: SOCIETE QUBETA IMPORT-EXPORT SARLU | C111: BOITE COLLE | D111: Colle bureau | E111: 327 | F111: PIE | G111: 1250 | H111: =IF(N111="USD",G111,IF(N111="MGA",G111/4600,IF(N111="EUR",G111*1.17,IF(N111="GBP",G111*1.35,"")))) -> 0.27173913 | I111: =H111*E111 -> 88.858696 | J111: 88.858696 | M111: 5 | N111: MGA | O111: 46233 | P111: 2026-07-30 | Q111: E | R111: E | S111: RAKOTOMALALA Manambina Tafitasoa | T111: 139312 | W111: DFG | X111: NADIA7 | Y111: RAVONINJATOVO Nadia | Z111: 465 975.00 | AA111: 20 | AB111: 18 | AD111: FRNPAPF | AE111: True | AF111: E218_DAF | AG111: DFGA-LOG | AH111: NA | AJ111: 327 | AK111: 388 312.50 | AL111: YASMG | AN111: 20 945 885.84 | AO111: 25 135 063.02 | AQ111: 46233 | AR111: 0000-00-00 | AS111: FOURNITURE DE BUREAU Q3 2026 - Validation DG le 27/07/2026 | AT111: YASSIE | AU111: GALE | AV111: C700 | AW111: E218_DAF | AX111: DFGA-LOG | AY111: STD | BC111: 7866 | BD111: C700 | BE111: 3052 | BF111: 18 | BG111: 2026-07-30
A112: 136031 | B112: SOCIETE QUBETA IMPORT-EXPORT SARLU | C112: BLANCO | D112: BLANCO | E112: 500 | F112: PCE | G112: 1250 | H112: =IF(N112="USD",G112,IF(N112="MGA",G112/4600,IF(N112="EUR",G112*1.17,IF(N112="GBP",G112*1.35,"")))) -> 0.27173913 | I112: =H112*E112 -> 135.86957 | J112: 135.86957 | M112: 5 | N112: MGA | O112: 46233 | P112: 2026-07-30 | Q112: E | R112: E | S112: RAKOTOMALALA Manambina Tafitasoa | T112: 139312 | W112: DFG | X112: NADIA7 | Y112: RAVONINJATOVO Nadia | Z112: 712 500.00 | AA112: 20 | AB112: 8 | AD112: FRNPAPF | AE112: True | AF112: E218_DAF | AG112: DFGA-LOG | AH112: NA | AJ112: 500 | AK112: 593 750.00 | AL112: YASMG | AN112: 20 945 885.84 | AO112: 25 135 063.02 | AQ112: 46233 | AR112: 0000-00-00 | AS112: FOURNITURE DE BUREAU Q3 2026 - Validation DG le 27/07/2026 | AT112: YASSIE | AU112: GALE | AV112: C700 | AW112: E218_DAF | AX112: DFGA-LOG | AY112: STD | BC112: 1197 | BD112: C700 | BE112: 3052 | BF112: 8 | BG112: 2026-07-30
... A149: 136030 | B149: COMPUTEK TECHNOLOGY SARL | C149: ENVELOPPE GM KRAFT POCHETTE 28 | D149: Enveloppe A3 KRAFT | E149: 278 | F149: PIE | G149: 24000 | H149: =IF(N149="USD",G149,IF(N149="MGA",G149/4600,IF(N149="EUR",G149*1.17,IF(N149="GBP",G149*1.35,"")))) -> 5.2173913 | I149: =H149*E149 -> 1450.4348 | J149: 1450.4348 | M149: 0 | N149: MGA | O149: 46233 | P149: 2026-07-30 | Q149: E | R149: E | S149: RAKOTOMALALA Manambina Tafitasoa | T149: 139316 | W149: DFG | X149: NADIA7 | Y149: RAVONINJATOVO Nadia | Z149: 8 006 400.00 | AA149: 20 | AB149: 12 | AD149: FRNPAPF | AE149: True | AF149: E218_DAF | AG149: DFGA-LOG | AH149: NA | AJ149: 278 | AK149: 6 672 000.00 | AL149: YASMG | AN149: 28 429 534.19 | AO149: 34 115 441.03 | AQ149: 46233 | AR149: 0000-00-00 | AS149: FOURNITURE DE BUREAU Q3 2026 - Validation DG le 27/07/2026 | AT149: YASSIE | AU149: GALE | AV149: C700 | AW149: E218_DAF | AX149: DFGA-LOG | AY149: STD | BC149: 9776 | BD149: C700 | BE149: 1101 | BF149: 12 | BG149: 2026-07-31
A150: 136029 | B150: UNITE DE DISTRIBUTION TECHNOLOGIQUE - UDITEC | C150: VTT 26 SPORTSMAX 18V SPMAXPM1CT/4 | D150: COFI 2026 - FUNMAX 26"VTT FNMAX-2601-PL - GRS MYA - DEVIS N° SQ26-0010576 DU 22/07/2026 | E150: 2 | F150: PIE | G150: 261749.99 | H150: =IF(N150="USD",G150,IF(N150="MGA",G150/4600,IF(N150="EUR",G150*1.17,IF(N150="GBP",G150*1.35,"")))) -> 56.902173 | I150: =H150*E150 -> 113.80435 | J150: 113.80435 | M150: 0 | N150: MGA | O150: 46233 | P150: 2026-07-30 | Q150: E | R150: E | S150: RAZAFINDRAHAGA Setra | T150: 139285 | W150: DCG | X150: FELANA13 | Y150: Felana RARIVOSON | Z150: 628 199.99 | AA150: 20 | AB150: 1 | AD150: VEHPDRP | AE150: True | AF150: 2026-COFI | AG150: DCG-DVI | AH150: NA | AJ150: 2 | AK150: 523 499.99 | AL150: YASMG | AN150: 523 499.99 | AO150: 628 199.99 | AP150: F | AQ150: 46233 | AR150: 0000-00-00 | AS150: COFI 2026 - VTT GRS MYA | AT150: YASSIE | AU150: GALE | AV150: C104 | AW150: 2026-COFI | AX150: DCG-DVI | AY150: STD | BC150: 12643 | BD150: C104 | BE150: 717 | BF150: 1 | BG150: 2026-07-28
A151: 136028 | B151: CT MOTORS | C151: MOTO | D151: COFI 2026 - PIAGGIO APE 3 WHEELER MODEL - GRS ZENITH - DEVIS N° DVISIE0226-002304 DU 07/07/2026 | E151: 2 | F151: UN | G151: 13250000 | H151: =IF(N151="USD",G151,IF(N151="MGA",G151/4600,IF(N151="EUR",G151*1.17,IF(N151="GBP",G151*1.35,"")))) -> 2880.4348 | I151: =H151*E151 -> 5760.8696 | J151: 5760.8696 | M151: 0 | N151: MGA | O151: 46233 | P151: 2026-07-30 | Q151: E | R151: E | S151: RAZAFINDRAHAGA Setra | T151: 139289 | W151: DCG | X151: FELANA13 | Y151: Felana RARIVOSON | Z151: 31 800 000.00 | AA151: 20 | AB151: 1 | AD151: PRMVEHI | AE151: True | AF151: 2026-COFI | AG151: DCG-DVI | AH151: NA | AJ151: 2 | AK151: 26 500 000.00 | AL151: YASMG | AN151: 26 500 000.00 | AO151: 31 800 000.00 | AP151: F | AQ151: 46233 | AR151: 0000-00-00 | AS151: COFI 2026 - PIAGGIO GRS ZENITH | AT151: YASSIE | AU151: GALE | AV151: C104 | AW151: 2026-COFI | AX151: DCG-DVI | AY151: STD | BC151: 4155 | BD151: C104 | BE151: 664 | BF151: 1 | BG151: 2026-07-28
A152: 136027 | B152: CT MOTORS | C152: MOTO | D152: COFI 2026 - PIAGGIO APE 3 WHEELER MODEL - GRS MYA - DEVIS N° DVISIE0226-002522 DU 21/07/2026 | E152: 1 | F152: UN | G152: 13250000 | H152: =IF(N152="USD",G152,IF(N152="MGA",G152/4600,IF(N152="EUR",G152*1.17,IF(N152="GBP",G152*1.35,"")))) -> 2880.4348 | I152: =H152*E152 -> 2880.4348 | J152: 2880.4348 | M152: 0 | N152: MGA | O152: 46233 | P152: 2026-07-30 | Q152: E | R152: E | S152: RAZAFINDRAHAGA Setra | T152: 139290 | W152: DCG | X152: FELANA13 | Y152: Felana RARIVOSON | Z152: 15 900 000.00 | AA152: 20 | AB152: 1 | AD152: PRMVEHI | AE152: True | AF152: 2026-COFI | AG152: DCG-DVI | AH152: NA | AJ152: 1 | AK152: 13 250 000.00 | AL152: YASMG | AN152: 13 250 000.00 | AO152: 15 900 000.00 | AP152: F | AQ152: 46233 | AR152: 0000-00-00 | AS152: COFI 2026 - PIAGGIO GRS MYA | AT152: YASSIE | AU152: GALE | AV152: C104 | AW152: 2026-COFI | AX152: DCG-DVI | AY152: STD | BC152: 4155 | BD152: C104 | BE152: 664 | BF152: 1 | BG152: 2026-07-28
A153: 136026 | B153: MALT COMMUNITY | C153: PRESTATION DE SERVICES EXTERNE | D153: Renewal Analytics & Data Specialist (Telco / CVM) Africa - 13 Jul 2026 to 13 Jul 2026 - N°FRIM260000033987 | E153: 1 | F153: UN | G153: 3278.85 | H153: =IF(N153="USD",G153,IF(N153="MGA",G153/4600,IF(N153="EUR",G153*1.17,IF(N153="GBP",G153*1.35,"")))) -> 3836.2545 | I153: =H153*E153 -> 3836.2545 | J153: 3836.2545 | M153: 0 | N153: EUR | O153: 46233 | P153: 2026-07-30 | Q153: E | R153: E | S153: RAZAFINDRAHAGA Setra | T153: 139296 | W153: DCG | X153: FELANA13 | Y153: Felana RARIVOSON | Z153: 2 950.97 | AA153: -10 | AB153: 2 | AD153: PRICTRL | AE153: True | AF153: E250_DCG | AG153: DCG-PS | AH153: NA | AJ153: 1 | AK153: 3 278.85 | AL153: YASMG | AN153: 13 001.15 | AO153: 11 701.04 | AQ153: 46233 | AR153: 0000-00-00 | AS153: Analytics & Data Specialist (Telco / CVM) Africa | AT153: YASSIE | AU153: YASSIE | AV153: C100 | AW153: E250_DCG | AX153: DCG-PS | AY153: IMPORT | BC153: 6965 | BD153: C100 | BE153: 7046 | BF153: 2 | BG153: 2026-07-29
A154: 136026 | B154: MALT COMMUNITY | C154: PRESTATION DE SERVICES EXTERNE | D154: Renewal Analytics & Data Specialist (Telco / CVM) Africa - 11 Jun 2026 to 7 Jul 2026 - N°FRIM260000033989 | E154: 1 | F154: UN | G154: 9722.3 | H154: =IF(N154="USD",G154,IF(N154="MGA",G154/4600,IF(N154="EUR",G154*1.17,IF(N154="GBP",G154*1.35,"")))) -> 11375.091 | I154: =H154*E154 -> 11375.091 | J154: 11375.091 | M154: 0 | N154: EUR | O154: 46233 | P154: 2026-07-30 | Q154: E | R154: E | S154: RAZAFINDRAHAGA Setra | T154: 139296 | W154: DCG | X154: FELANA13 | Y154: Felana RARIVOSON | Z154: 8 750.07 | AA154: -10 | AB154: 1 | AD154: PRICTRL | AE154: True | AF154: E250_DCG | AG154: DCG-PS | AH154: NA | AJ154: 1 | AK154: 9 722.30 | AL154: YASMG | AN154: 13 001.15 | AO154: 11 701.04 | AQ154: 46233 | AR154: 0000-00-00 | AS154: Analytics & Data Specialist (Telco / CVM) Africa | AT154: YASSIE | AU154: YASSIE | AV154: C100 | AW154: E250_DCG | AX154: DCG-PS | AY154: IMPORT | BC154: 6965 | BD154: C100 | BE154: 7046 | BF154: 1 | BG154: 2026-07-29
...

Sheet TCD
A3: Étiquettes de lignes | B3: Somme de Total_HT_USD | C3: Somme de Valeur_remise_USD | D3: Moyenne de %remise
A4: 135491 | B4: 1930
A5: 135492 | B5: 2547.1343
A6: 135493 | B6: 5918.4783
A7: 135494 | B7: 5319.5652
A8: 135495 | B8: 215.41667
A9: 135496 | B9: 5421.2791
A10: 135497 | B10: 456.52174
A11: 135498 | B11: 460.86957
A12: 135499 | B12: 918.47826
A13: 135500 | B13: 1662.1826
A14: 135501 | B14: 39000
A15: 135502 | B15: 363.5
... A44: 135531 | B44: 397.82609
A45: 135532 | B45: 4976.863 | C45: 824.34783
A46: 135533 | B46: 3042.3913
A47: 135534 | B47: 67.391304
A48: 135535 | B48: 322.63043
A49: 135536 | B49: 69.565217
A50: 135537 | B50: 163.04348
A51: 135538 | B51: 3069.5652
A52: 135539 | B52: 9782.6087
A53: 135540 | B53: 869.56522
A54: 135541 | B54: 95.098435
A55: 135542 | B55: 15.026087
A56: 135543 | B56: 326.08696
A57: 135544 | B57: 869.56522
... A74: 135561 | B74: 284.78261
A75: 135562 | B75: 253.04348 | D75: 15
A76: 135563 | B76: 428.43478
A77: 135564 | B77: 518.26087
A78: 135565 | B78: 867.13043
A79: 135566 | B79: 384.78261
A80: 135567 | B80: 39130.435
A81: 135568 | B81: 652.17391
A82: 135569 | B82: 3000
A83: 135570 | B83: 49.565217
A84: 135571 | B84: 3000
A85: 135572 | B85: 1133.4783 | C85: 103.04348
A86: 135573 | B86: 3686.087 | D86: 60
A87: 135574 | B87: 257.0859
A88: 135575 | B88: 5893.8828 | C88: 1425.2023
A89: 135576 | B89: 53.890478
A90: 135577 | B90: 40.195652
A91: 135578 | B91: 13423.913 | C91: 3097.8261
A92: 135579 | B92: 23913.043
A93: 135580 | B93: 6847.8261
A94: 135581 | B94: 39130.435
A95: 135582 | B95: 186659.7
A96: 135583 | B96: 158.69565
A97: 135584 | B97: 108.69565
A98: 135585 | B98: 57.608696
A99: 135586 | B99: 93.93913
A100: 135587 | B100: 978.26087
A101: 135588 | B101: 10.434783
A102: 135589 | B102: 31.313043
A103: 135590 | B103: 65.217391
... A117: 135604 | B117: 260.86957
A118: 135605 | B118: 9195.6522 | D118: 12.5
A119: 135606 | B119: 1427.1739
A120: 135607 | B120: 1974.6378
A121: 135608 | B121: 2318.8406
A122: 135609 | B122: 2699.2754
A123: 135610 | B123: 44872.826
A124: 135611 | B124: 239.13043
A125: 135612 | B125: 195.65217
A126: 135613 | B126: 104.15217
A127: 135614 | B127: 150.73913
A128: 135615 | B128: 10082.25
A129: 135616 | B129: 4347.8261
A130: 135617 | B130: 2634.7826
... A155: 135642 | B155: 1156.5217
A156: 135643 | B156: 197.71739 | C156: 12.934783
A157: 135644 | B157: 1744.227
A158: 135645 | B158: 422.8913
A159: 135646 | B159: 809
A160: 135647 | B160: 5906.5761
A161: 135648 | B161: 39.130435
A162: 135649 | B162: 322.22826 | C162: 29.293478
A163: 135650 | B163: 613.6327
A164: 135651 | B164: 8783.9652 | C164: 941.13913
A165: 135652 | B165: 39130.435
A166: 135653 | B166: 25325.217
A167: 135654 | B167: 39808.696
A168: 135655 | B168: 31200
A169: 135656 | B169: 9600
A170: 135657 | B170: 1230.9028
A171: 135658 | B171: 1936.9565
A172: 135659 | B172: 7.2608696
A173: 135660 | B173: 14745.95
A174: 135661 | B174: 466.95652
A175: 135662 | B175: 105.56997
A176: 135663 | B176: 328.69565
... A194: 135681 | B194: 326.08696
A195: 135682 | B195: 23418.72 | D195: 30
A196: 135683 | B196: 3043.4783
A197: 135684 | B197: 5000
A198: 135685 | B198: 2187.0078
A199: 135686 | B199: 2173.913
A200: 135687 | B200: 347.82609
...

Sheet TCD volume & valeur
A3: Étiquettes de lignes | B3: Nombre de N°BC | D3: Étiquettes de lignes | E3: Somme de Total_HT_USD
A4: DCG | B4: 0.48653501 | D4: DCG | E4: 2814537.7
A5: DFG | B5: 0.062836625 | D5: DFG | E5: 414800.34
A6: DG | B6: 0.046678636 | D6: DG | E6: 525666.43
A7: DRH | B7: 0.035906643 | D7: DRH | E7: 34417.551
A8: DSI | B8: 0.041292639 | D8: DSI | E8: 1051787.1
A9: DTG | B9: 0.29802513 | D9: DTG | E9: 918240.5
A10: HSSES | B10: 0.028725314 | D10: HSSES | E10: 17558.475
A11: Total général | B11: 1 | D11: Total général | E11: 5777008.1
A14: Étiquettes de lignes | B14: Nombre de N°BC | D14: Étiquettes de lignes | E14: Somme de Total_HT_USD
A15: ELIE3 | B15: 0.28007181 | D15: ELIE3 | E15: 909353.22
A16: FELANA13 | B16: 0.47576302 | D16: FELANA13 | E16: 2810460.3
A17: NADIA7 | B17: 0.24416517 | D17: NADIA7 | E17: 2057194.5
A18: Total général | B18: 1 | D18: Total général | E18: 5777008.1

Sheet Assemblage
A1: N°BC | B1: Fournisseur | C1: Désignation | D1: Design__sommaire | E1: Designation_Complémentaire | F1: Total HT USD | G1: Valeur_remise_USD | H1: %Remise | I1: %remise_ancien | J1: %restant | K1: Valeur total remisé | L1: Date de creation BC | M1: Date de Validation BC | N1: V_Etat_commande_en_tête | O1: V_Etat_commande_ligne | P1: N°DA | Q1: Date_émission_DA | R1: Date_Validation_Demandeur | S1: Date_signature_DA | T1: Délais_achat | U1: Code_Direction | V1: Acheteur | W1: Code_Fournis
A2: 135491 | B2: =VLOOKUP(A2,'Base traitement'!A:BG,2,FALSE) -> MALAGASY FEDERATION OF ESPORTS | C2: =VLOOKUP(A2,'Base traitement'!A:BG,45,FALSE) -> E-gaming stand fibre  Tuléar | D2: =VLOOKUP(A2,'Base traitement'!A:BG,3,FALSE) -> SPONSORING | E2: =VLOOKUP(A2,'Base traitement'!A:BG,4,FALSE) -> E-gaming stand fibre Tuléar - Référence n°016/2026/MFE | F2: 1930 | K2: =F2-G2 -> 1930 | L2: =VLOOKUP(A2,'Base traitement'!A:BG,15,FALSE) -> 46204 | M2: =VLOOKUP(A2,'Base traitement'!A:BG,16,FALSE) -> 2026-07-01 | N2: =VLOOKUP(A2,'Base traitement'!A:BG,17,FALSE) -> E | O2: =VLOOKUP(A2,'Base traitement'!A:BG,18,FALSE) -> E | P2: =VLOOKUP(A2,'Base traitement'!A:BG,20,FALSE) -> 138683 | Q2: =VLOOKUP(P2,Assemb_DA!A:H,7,FALSE) -> 46198 | R2: =VLOOKUP(P2,Assemb_DA!A:H,8,FALSE) -> 2026-06-25 | S2: =VLOOKUP(P2,Assemb_DA!A:I,9,FALSE) -> 2026-06-29 | T2: =S2-Q2 -> 4 | U2: =VLOOKUP(A2,'Base traitement'!A:BG,23,FALSE) -> DCG | V2: =VLOOKUP(A2,'Base traitement'!A:BG,24,FALSE) -> FELANA13 | W2: =VLOOKUP(A2,'Base traitement'!A:BG,57,FALSE) -> 6306
A3: 135492 | B3: =VLOOKUP(A3,'Base traitement'!A:BG,2,FALSE) -> NEA MADAGASCAR SA | C3: =VLOOKUP(A3,'Base traitement'!A:BG,45,FALSE) -> CLIMATISATION SALLE SUPERVISION METIS BAZARY BE FORT DAUPHIN | D3: =VLOOKUP(A3,'Base traitement'!A:BG,3,FALSE) -> MAINTENANCE ENERGIE | E3: =VLOOKUP(A3,'Base traitement'!A:BG,4,FALSE) -> CLIMATISATION SALLE SUPERVISION METIS BAZARY BE FORT DAUPHIN # Proforma MG-YAS-26-A3537-D0001 | F3: 2547.1343 | K3: =F3-G3 -> 2547.1343 | L3: =VLOOKUP(A3,'Base traitement'!A:BG,15,FALSE) -> 46204 | M3: =VLOOKUP(A3,'Base traitement'!A:BG,16,FALSE) -> 2026-07-01 | N3: =VLOOKUP(A3,'Base traitement'!A:BG,17,FALSE) -> E | O3: =VLOOKUP(A3,'Base traitement'!A:BG,18,FALSE) -> E | P3: =VLOOKUP(A3,'Base traitement'!A:BG,20,FALSE) -> 138672 | Q3: =VLOOKUP(P3,Assemb_DA!A:H,7,FALSE) -> 46197 | R3: =VLOOKUP(P3,Assemb_DA!A:H,8,FALSE) -> 2026-06-24 | S3: =VLOOKUP(P3,Assemb_DA!A:I,9,FALSE) -> 2026-06-29 | T3: =S3-Q3 -> 5 | U3: =VLOOKUP(A3,'Base traitement'!A:BG,23,FALSE) -> DTG | V3: =VLOOKUP(A3,'Base traitement'!A:BG,24,FALSE) -> ELIE3 | W3: =VLOOKUP(A3,'Base traitement'!A:BG,57,FALSE) -> 36
A4: 135493 | B4: =VLOOKUP(A4,'Base traitement'!A:BG,2,FALSE) -> RAMANOARY NY ANDO LALAINA | C4: =VLOOKUP(A4,'Base traitement'!A:BG,45,FALSE) -> Prestations d'interventions 3D couverture 11 mois 2026 | D4: =VLOOKUP(A4,'Base traitement'!A:BG,3,FALSE) -> DESINFECTION SITE | E4: =VLOOKUP(A4,'Base traitement'!A:BG,4,FALSE) -> Couverture de 11 mois (de février à décembre 2026) Désinsectisation, Dératisation et Désinfection) pour les 33 stores de TANA | F4: 5918.4783 | K4: =F4-G4 -> 5918.4783 | L4: =VLOOKUP(A4,'Base traitement'!A:BG,15,FALSE) -> 46204 | M4: =VLOOKUP(A4,'Base traitement'!A:BG,16,FALSE) -> 2026-07-01 | N4: =VLOOKUP(A4,'Base traitement'!A:BG,17,FALSE) -> E | O4: =VLOOKUP(A4,'Base traitement'!A:BG,18,FALSE) -> E | P4: =VLOOKUP(A4,'Base traitement'!A:BG,20,FALSE) -> 138776 | Q4: =VLOOKUP(P4,Assemb_DA!A:H,7,FALSE) -> 46204 | R4: =VLOOKUP(P4,Assemb_DA!A:H,8,FALSE) -> 2026-07-01 | S4: =VLOOKUP(P4,Assemb_DA!A:I,9,FALSE) -> 2026-07-01 | T4: =S4-Q4 -> 0 | U4: =VLOOKUP(A4,'Base traitement'!A:BG,23,FALSE) -> DFG | V4: =VLOOKUP(A4,'Base traitement'!A:BG,24,FALSE) -> NADIA7 | W4: =VLOOKUP(A4,'Base traitement'!A:BG,57,FALSE) -> 6147
A5: 135494 | B5: =VLOOKUP(A5,'Base traitement'!A:BG,2,FALSE) -> RAJAOFETRA ANDRIANAINA Sandy (SANDIX) | C5: =VLOOKUP(A5,'Base traitement'!A:BG,45,FALSE) -> Sandix Sono - Foire de la Fibre Tulear | D5: =VLOOKUP(A5,'Base traitement'!A:BG,3,FALSE) -> PRESTATION DE SERVICE | E5: =VLOOKUP(A5,'Base traitement'!A:BG,4,FALSE) -> Prestation Logistique Evènementielle - Foire de la Fibre Tuléar - devis n°519D/TELMA S.A (YAS)/26 du 29/06/2026 | F5: 5319.5652 | K5: =F5-G5 -> 5319.5652 | L5: =VLOOKUP(A5,'Base traitement'!A:BG,15,FALSE) -> 46204 | M5: =VLOOKUP(A5,'Base traitement'!A:BG,16,FALSE) -> 2026-07-06 | N5: =VLOOKUP(A5,'Base traitement'!A:BG,17,FALSE) -> E | O5: =VLOOKUP(A5,'Base traitement'!A:BG,18,FALSE) -> E | P5: =VLOOKUP(A5,'Base traitement'!A:BG,20,FALSE) -> 138766 | Q5: =VLOOKUP(P5,Assemb_DA!A:H,7,FALSE) -> 46204 | R5: =VLOOKUP(P5,Assemb_DA!A:H,8,FALSE) -> 2026-07-01 | S5: =VLOOKUP(P5,Assemb_DA!A:I,9,FALSE) -> 2026-07-01 | T5: =S5-Q5 -> 0 | U5: =VLOOKUP(A5,'Base traitement'!A:BG,23,FALSE) -> DCG | V5: =VLOOKUP(A5,'Base traitement'!A:BG,24,FALSE) -> FELANA13 | W5: =VLOOKUP(A5,'Base traitement'!A:BG,57,FALSE) -> 3968
A6: 135495 | B6: =VLOOKUP(A6,'Base traitement'!A:BG,2,FALSE) -> MORA MARKET | C6: =VLOOKUP(A6,'Base traitement'!A:BG,45,FALSE) -> MBALIK COLLATION Q2 2026 | D6: =VLOOKUP(A6,'Base traitement'!A:BG,3,FALSE) -> SUCRE | E6: =VLOOKUP(A6,'Base traitement'!A:BG,4,FALSE) -> Sucre Roux Brésilien 1 KG | F6: 215.41667 | K6: =F6-G6 -> 215.41667 | L6: =VLOOKUP(A6,'Base traitement'!A:BG,15,FALSE) -> 46205 | M6: =VLOOKUP(A6,'Base traitement'!A:BG,16,FALSE) -> 2026-07-02 | N6: =VLOOKUP(A6,'Base traitement'!A:BG,17,FALSE) -> L | O6: =VLOOKUP(A6,'Base traitement'!A:BG,18,FALSE) -> E | P6: =VLOOKUP(A6,'Base traitement'!A:BG,20,FALSE) -> 138380 | Q6: =VLOOKUP(P6,Assemb_DA!A:H,7,FALSE) -> 46184 | R6: =VLOOKUP(P6,Assemb_DA!A:H,8,FALSE) -> 2026-06-11 | S6: =VLOOKUP(P6,Assemb_DA!A:I,9,FALSE) -> 2026-06-18 | T6: =S6-Q6 -> 7 | U6: =VLOOKUP(A6,'Base traitement'!A:BG,23,FALSE) -> DCG | V6: =VLOOKUP(A6,'Base traitement'!A:BG,24,FALSE) -> NADIA7 | W6: =VLOOKUP(A6,'Base traitement'!A:BG,57,FALSE) -> 4245
A7: 135496 | B7: =VLOOKUP(A7,'Base traitement'!A:BG,2,FALSE) -> SOCIETE DE DISTRIBUTION DE MAD (SODIM SARLU) | C7: =VLOOKUP(A7,'Base traitement'!A:BG,45,FALSE) -> Consommation RICOH et Loyer mensuel TELMA SA - Mai2026 | D7: =VLOOKUP(A7,'Base traitement'!A:BG,3,FALSE) -> LOCATION IMPRIMANTE | E7: =VLOOKUP(A7,'Base traitement'!A:BG,4,FALSE) -> LOCATION IMPRIMANTE Consommation RICOH et Loyer mensuel TELMA SA, mois de Mai2026# FACTURE N°F850913 DU 02/06/2026 | F7: 5421.2791 | K7: =F7-G7 -> 5421.2791 | L7: =VLOOKUP(A7,'Base traitement'!A:BG,15,FALSE) -> 46205 | M7: =VLOOKUP(A7,'Base traitement'!A:BG,16,FALSE) -> 2026-07-03 | N7: =VLOOKUP(A7,'Base traitement'!A:BG,17,FALSE) -> E | O7: =VLOOKUP(A7,'Base traitement'!A:BG,18,FALSE) -> E | P7: =VLOOKUP(A7,'Base traitement'!A:BG,20,FALSE) -> 138757 | Q7: =VLOOKUP(P7,Assemb_DA!A:H,7,FALSE) -> 46203 | R7: =VLOOKUP(P7,Assemb_DA!A:H,8,FALSE) -> 2026-06-30 | S7: =VLOOKUP(P7,Assemb_DA!A:I,9,FALSE) -> 2026-07-01 | T7: =S7-Q7 -> 1 | U7: =VLOOKUP(A7,'Base traitement'!A:BG,23,FALSE) -> DSI | V7: =VLOOKUP(A7,'Base traitement'!A:BG,24,FALSE) -> NADIA7 | W7: =VLOOKUP(A7,'Base traitement'!A:BG,57,FALSE) -> 127
A8: 135497 | B8: =VLOOKUP(A8,'Base traitement'!A:BG,2,FALSE) -> SOCIETE DE GESTION ET EXPLOITATION DE M/CAR | C8: =VLOOKUP(A8,'Base traitement'!A:BG,45,FALSE) -> Collation Conférence Data Protection et AI_02Juillet2026 | D8: =VLOOKUP(A8,'Base traitement'!A:BG,3,FALSE) -> PRESTATION DE SERVICES EXTERNE | E8: =VLOOKUP(A8,'Base traitement'!A:BG,4,FALSE) -> COLLATION LE 02 JUILLET 2026 - Assortiments 2 pièces salées et 1 pièce sucré avec jus de fruits# DEVIS DU 29/06/2026 | F8: 456.52174 | K8: =F8-G8 -> 456.52174 | L8: =VLOOKUP(A8,'Base traitement'!A:BG,15,FALSE) -> 46205 | M8: =VLOOKUP(A8,'Base traitement'!A:BG,16,FALSE) -> 2026-07-02 | N8: =VLOOKUP(A8,'Base traitement'!A:BG,17,FALSE) -> E | O8: =VLOOKUP(A8,'Base traitement'!A:BG,18,FALSE) -> E | P8: =VLOOKUP(A8,'Base traitement'!A:BG,20,FALSE) -> 138760 | Q8: =VLOOKUP(P8,Assemb_DA!A:H,7,FALSE) -> 46203 | R8: =VLOOKUP(P8,Assemb_DA!A:H,8,FALSE) -> 2026-06-30 | S8: =VLOOKUP(P8,Assemb_DA!A:I,9,FALSE) -> 2026-07-01 | T8: =S8-Q8 -> 1 | U8: =VLOOKUP(A8,'Base traitement'!A:BG,23,FALSE) -> DSI | V8: =VLOOKUP(A8,'Base traitement'!A:BG,24,FALSE) -> NADIA7 | W8: =VLOOKUP(A8,'Base traitement'!A:BG,57,FALSE) -> 119
A9: 135498 | B9: =VLOOKUP(A9,'Base traitement'!A:BG,2,FALSE) -> EXCEL TRANSPORT et TRAVEL | C9: =VLOOKUP(A9,'Base traitement'!A:BG,45,FALSE) -> Location Car pour TB DSI_03 Juillet 2026 | D9: =VLOOKUP(A9,'Base traitement'!A:BG,3,FALSE) -> FRAIS DIVERS | E9: =VLOOKUP(A9,'Base traitement'!A:BG,4,FALSE) -> Frais de retrait | F9: 460.86957 | K9: =F9-G9 -> 460.86957 | L9: =VLOOKUP(A9,'Base traitement'!A:BG,15,FALSE) -> 46205 | M9: =VLOOKUP(A9,'Base traitement'!A:BG,16,FALSE) -> 2026-07-02 | N9: =VLOOKUP(A9,'Base traitement'!A:BG,17,FALSE) -> E | O9: =VLOOKUP(A9,'Base traitement'!A:BG,18,FALSE) -> E | P9: =VLOOKUP(A9,'Base traitement'!A:BG,20,FALSE) -> 138780 | Q9: =VLOOKUP(P9,Assemb_DA!A:H,7,FALSE) -> 46204 | R9: =VLOOKUP(P9,Assemb_DA!A:H,8,FALSE) -> 2026-07-01 | S9: =VLOOKUP(P9,Assemb_DA!A:I,9,FALSE) -> 2026-07-01 | T9: =S9-Q9 -> 0 | U9: =VLOOKUP(A9,'Base traitement'!A:BG,23,FALSE) -> DSI | V9: =VLOOKUP(A9,'Base traitement'!A:BG,24,FALSE) -> NADIA7 | W9: =VLOOKUP(A9,'Base traitement'!A:BG,57,FALSE) -> 6060
A10: 135499 | B10: =VLOOKUP(A10,'Base traitement'!A:BG,2,FALSE) -> ANDRIANARY VERO HAINGO TIANA | C10: =VLOOKUP(A10,'Base traitement'!A:BG,45,FALSE) -> Conférence Data Protection et AI_02Juillet2026 | D10: =VLOOKUP(A10,'Base traitement'!A:BG,3,FALSE) -> PRESTATION DE SERVICES EXTERNE | E10: =VLOOKUP(A10,'Base traitement'!A:BG,4,FALSE) -> Transport aller-retours de la cabine et des matériels Système de sonorisation pour interprétariat sonorisation | F10: 918.47826 | K10: =F10-G10 -> 918.47826 | L10: =VLOOKUP(A10,'Base traitement'!A:BG,15,FALSE) -> 46205 | M10: =VLOOKUP(A10,'Base traitement'!A:BG,16,FALSE) -> 2026-07-02 | N10: =VLOOKUP(A10,'Base traitement'!A:BG,17,FALSE) -> E | O10: =VLOOKUP(A10,'Base traitement'!A:BG,18,FALSE) -> E | P10: =VLOOKUP(A10,'Base traitement'!A:BG,20,FALSE) -> 138762 | Q10: =VLOOKUP(P10,Assemb_DA!A:H,7,FALSE) -> 46203 | R10: =VLOOKUP(P10,Assemb_DA!A:H,8,FALSE) -> 2026-06-30 | S10: =VLOOKUP(P10,Assemb_DA!A:I,9,FALSE) -> 2026-07-01 | T10: =S10-Q10 -> 1 | U10: =VLOOKUP(A10,'Base traitement'!A:BG,23,FALSE) -> DSI | V10: =VLOOKUP(A10,'Base traitement'!A:BG,24,FALSE) -> NADIA7 | W10: =VLOOKUP(A10,'Base traitement'!A:BG,57,FALSE) -> 4371
A11: 135500 | B11: =VLOOKUP(A11,'Base traitement'!A:BG,2,FALSE) -> ANDRINIRINA ERICK | C11: DA Erick ANDRINIRINA Develppeur fullstack SOKA juin 2026 | D11: =VLOOKUP(A11,'Base traitement'!A:BG,3,FALSE) -> PRESTATION DE SERVICE | E11: =VLOOKUP(A11,'Base traitement'!A:BG,4,FALSE) -> DA Erick ANDRINIRINA Develppeur fullstack SOKA juin 2026# FACTURE N° F2600006 DU 16/06/2026 | F11: 1662.1826 | K11: =F11-G11 -> 1662.1826 | L11: =VLOOKUP(A11,'Base traitement'!A:BG,15,FALSE) -> 46205 | M11: =VLOOKUP(A11,'Base traitement'!A:BG,16,FALSE) -> 2026-07-02 | N11: =VLOOKUP(A11,'Base traitement'!A:BG,17,FALSE) -> E | O11: =VLOOKUP(A11,'Base traitement'!A:BG,18,FALSE) -> E | P11: =VLOOKUP(A11,'Base traitement'!A:BG,20,FALSE) -> 138740 | Q11: =VLOOKUP(P11,Assemb_DA!A:H,7,FALSE) -> 46203 | R11: =VLOOKUP(P11,Assemb_DA!A:H,8,FALSE) -> 2026-06-30 | S11: =VLOOKUP(P11,Assemb_DA!A:I,9,FALSE) -> 2026-07-02 | T11: =S11-Q11 -> 2 | U11: =VLOOKUP(A11,'Base traitement'!A:BG,23,FALSE) -> DG | V11: =VLOOKUP(A11,'Base traitement'!A:BG,24,FALSE) -> NADIA7 | W11: =VLOOKUP(A11,'Base traitement'!A:BG,57,FALSE) -> 6519
A12: 135501 | B12: =VLOOKUP(A12,'Base traitement'!A:BG,2,FALSE) -> OCEAN TRADE CO | C12: Pour engagement du devis validé pour la LLD Mr Ando RATSIRAHONANA | D12: =VLOOKUP(A12,'Base traitement'!A:BG,3,FALSE) -> LOCATION VEHICULE LLD | E12: =VLOOKUP(A12,'Base traitement'!A:BG,4,FALSE) -> Pour engagement du devis pour la LLD Mr Ando RATSIRAHONANA# DEVIS N° V.26.21100 DU 11/06/2026 | F12: 39000 | K12: =F12-G12 -> 39000 | L12: =VLOOKUP(A12,'Base traitement'!A:BG,15,FALSE) -> 46205 | M12: =VLOOKUP(A12,'Base traitement'!A:BG,16,FALSE) -> 2026-07-02 | N12: =VLOOKUP(A12,'Base traitement'!A:BG,17,FALSE) -> E | O12: =VLOOKUP(A12,'Base traitement'!A:BG,18,FALSE) -> E | P12: =VLOOKUP(A12,'Base traitement'!A:BG,20,FALSE) -> 138775 | Q12: =VLOOKUP(P12,Assemb_DA!A:H,7,FALSE) -> 46204 | R12: =VLOOKUP(P12,Assemb_DA!A:H,8,FALSE) -> 2026-07-01 | S12: =VLOOKUP(P12,Assemb_DA!A:I,9,FALSE) -> 2026-07-02 | T12: =S12-Q12 -> 1 | U12: =VLOOKUP(A12,'Base traitement'!A:BG,23,FALSE) -> DG | V12: =VLOOKUP(A12,'Base traitement'!A:BG,24,FALSE) -> NADIA7 | W12: =VLOOKUP(A12,'Base traitement'!A:BG,57,FALSE) -> 102
A13: 135502 | B13: =VLOOKUP(A13,'Base traitement'!A:BG,2,FALSE) -> VOYAGES BOURDON | C13: =VLOOKUP(A13,'Base traitement'!A:BG,45,FALSE) -> Billet d'avion - RAMAHEFARISOA HAJANIRINA | D13: =VLOOKUP(A13,'Base traitement'!A:BG,3,FALSE) -> BILLET D'AVION | E13: =VLOOKUP(A13,'Base traitement'!A:BG,4,FALSE) -> Billet d'avion - TNR/WMN/TNR - RAMAHEFARISOA HAJANIRINA | F13: 363.5 | K13: =F13-G13 -> 363.5 | L13: =VLOOKUP(A13,'Base traitement'!A:BG,15,FALSE) -> 46205 | M13: =VLOOKUP(A13,'Base traitement'!A:BG,16,FALSE) -> 2026-07-02 | N13: =VLOOKUP(A13,'Base traitement'!A:BG,17,FALSE) -> S | O13: =VLOOKUP(A13,'Base traitement'!A:BG,18,FALSE) -> S | P13: =VLOOKUP(A13,'Base traitement'!A:BG,20,FALSE) -> 138720 | Q13: =VLOOKUP(P13,Assemb_DA!A:H,7,FALSE) -> 46202 | R13: =VLOOKUP(P13,Assemb_DA!A:H,8,FALSE) -> 2026-06-29 | S13: =VLOOKUP(P13,Assemb_DA!A:I,9,FALSE) -> 2026-06-29 | T13: =S13-Q13 -> 0 | U13: =VLOOKUP(A13,'Base traitement'!A:BG,23,FALSE) -> DCG | V13: =VLOOKUP(A13,'Base traitement'!A:BG,24,FALSE) -> FELANA13 | W13: =VLOOKUP(A13,'Base traitement'!A:BG,57,FALSE) -> 2886
A14: 135503 | B14: =VLOOKUP(A14,'Base traitement'!A:BG,2,FALSE) -> VOYAGES BOURDON | C14: =VLOOKUP(A14,'Base traitement'!A:BG,45,FALSE) -> Billet d'Avion - David Randriamialy | D14: =VLOOKUP(A14,'Base traitement'!A:BG,3,FALSE) -> BILLET D'AVION | E14: =VLOOKUP(A14,'Base traitement'!A:BG,4,FALSE) -> Billet d'Avion - David Randriamialy - TNR/NOS/TNR | F14: 552.71739 | K14: =F14-G14 -> 552.71739 | L14: =VLOOKUP(A14,'Base traitement'!A:BG,15,FALSE) -> 46205 | M14: =VLOOKUP(A14,'Base traitement'!A:BG,16,FALSE) -> 2026-07-02 | N14: =VLOOKUP(A14,'Base traitement'!A:BG,17,FALSE) -> S | O14: =VLOOKUP(A14,'Base traitement'!A:BG,18,FALSE) -> S | P14: =VLOOKUP(A14,'Base traitement'!A:BG,20,FALSE) -> 138782 | Q14: =VLOOKUP(P14,Assemb_DA!A:H,7,FALSE) -> 46204 | R14: =VLOOKUP(P14,Assemb_DA!A:H,8,FALSE) -> 2026-07-01 | S14: =VLOOKUP(P14,Assemb_DA!A:I,9,FALSE) -> 2026-07-02 | T14: =S14-Q14 -> 1 | U14: =VLOOKUP(A14,'Base traitement'!A:BG,23,FALSE) -> DCG | V14: =VLOOKUP(A14,'Base traitement'!A:BG,24,FALSE) -> FELANA13 | W14: =VLOOKUP(A14,'Base traitement'!A:BG,57,FALSE) -> 2886
A15: 135504 | B15: =VLOOKUP(A15,'Base traitement'!A:BG,2,FALSE) -> VOYAGES BOURDON | C15: Achat billet d'avion 03 Techniciens Polyvalents suite affectation | D15: =VLOOKUP(A15,'Base traitement'!A:BG,3,FALSE) -> BILLET D'AVION | E15: =VLOOKUP(A15,'Base traitement'!A:BG,4,FALSE) -> Achat billet d'avion Fenotiana Patrick suite affectation | F15: 619.1087 | K15: =F15-G15 -> 619.1087 | L15: =VLOOKUP(A15,'Base traitement'!A:BG,15,FALSE) -> 46205 | M15: =VLOOKUP(A15,'Base traitement'!A:BG,16,FALSE) -> 2026-07-02 | N15: =VLOOKUP(A15,'Base traitement'!A:BG,17,FALSE) -> S | O15: =VLOOKUP(A15,'Base traitement'!A:BG,18,FALSE) -> S | P15: =VLOOKUP(A15,'Base traitement'!A:BG,20,FALSE) -> 138790 | Q15: =VLOOKUP(P15,Assemb_DA!A:H,7,FALSE) -> 46205 | R15: =VLOOKUP(P15,Assemb_DA!A:H,8,FALSE) -> 2026-07-02 | S15: =VLOOKUP(P15,Assemb_DA!A:I,9,FALSE) -> 2026-07-02 | T15: =S15-Q15 -> 0 | U15: =VLOOKUP(A15,'Base traitement'!A:BG,23,FALSE) -> DTG | V15: =VLOOKUP(A15,'Base traitement'!A:BG,24,FALSE) -> NADIA7 | W15: =VLOOKUP(A15,'Base traitement'!A:BG,57,FALSE) -> 2886
A16: 135505 | B16: =VLOOKUP(A16,'Base traitement'!A:BG,2,FALSE) -> EDS GROUP | C16: =VLOOKUP(A16,'Base traitement'!A:BG,45,FALSE) -> Sponsoring - IOAI Summit 2026 | D16: =VLOOKUP(A16,'Base traitement'!A:BG,3,FALSE) -> SPONSORING | E16: =VLOOKUP(A16,'Base traitement'!A:BG,4,FALSE) -> Sponsoring - IOAI Summit 2026 - FA n°EDS-2026-0604 | F16: 1086.9565 | K16: =F16-G16 -> 1086.9565 | L16: =VLOOKUP(A16,'Base traitement'!A:BG,15,FALSE) -> 46205 | M16: =VLOOKUP(A16,'Base traitement'!A:BG,16,FALSE) -> 2026-07-02 | N16: =VLOOKUP(A16,'Base traitement'!A:BG,17,FALSE) -> E | O16: =VLOOKUP(A16,'Base traitement'!A:BG,18,FALSE) -> E | P16: =VLOOKUP(A16,'Base traitement'!A:BG,20,FALSE) -> 138700 | Q16: =VLOOKUP(P16,Assemb_DA!A:H,7,FALSE) -> 46202 | R16: =VLOOKUP(P16,Assemb_DA!A:H,8,FALSE) -> 2026-06-29 | S16: =VLOOKUP(P16,Assemb_DA!A:I,9,FALSE) -> 2026-07-01 | T16: =S16-Q16 -> 2 | U16: =VLOOKUP(A16,'Base traitement'!A:BG,23,FALSE) -> DCG | V16: =VLOOKUP(A16,'Base traitement'!A:BG,24,FALSE) -> FELANA13 | W16: =VLOOKUP(A16,'Base traitement'!A:BG,57,FALSE) -> 7133
A17: 135506 | B17: =VLOOKUP(A17,'Base traitement'!A:BG,2,FALSE) -> SECUR PRO | C17: =VLOOKUP(A17,'Base traitement'!A:BG,45,FALSE) -> Sécurisation Nuit - Foire de la Fibre | D17: =VLOOKUP(A17,'Base traitement'!A:BG,3,FALSE) -> PRESTATION DE SERVICE | E17: =VLOOKUP(A17,'Base traitement'!A:BG,4,FALSE) -> Prestation de sécurité Nuit - Foire de la Fibre à Tuléar le 05 au 08 juillet 2026 - Proforma N° 0232562512/26 | F17: 195.65217 | K17: =F17-G17 -> 195.65217 | L17: =VLOOKUP(A17,'Base traitement'!A:BG,15,FALSE) -> 46205 | M17: =VLOOKUP(A17,'Base traitement'!A:BG,16,FALSE) -> 2026-07-02 | N17: =VLOOKUP(A17,'Base traitement'!A:BG,17,FALSE) -> E | O17: =VLOOKUP(A17,'Base traitement'!A:BG,18,FALSE) -> E | P17: =VLOOKUP(A17,'Base traitement'!A:BG,20,FALSE) -> 138781 | Q17: =VLOOKUP(P17,Assemb_DA!A:H,7,FALSE) -> 46204 | R17: =VLOOKUP(P17,Assemb_DA!A:H,8,FALSE) -> 2026-07-01 | S17: =VLOOKUP(P17,Assemb_DA!A:I,9,FALSE) -> 2026-07-02 | T17: =S17-Q17 -> 1 | U17: =VLOOKUP(A17,'Base traitement'!A:BG,23,FALSE) -> DCG | V17: =VLOOKUP(A17,'Base traitement'!A:BG,24,FALSE) -> FELANA13 | W17: =VLOOKUP(A17,'Base traitement'!A:BG,57,FALSE) -> 2145
A18: 135507 | B18: =VLOOKUP(A18,'Base traitement'!A:BG,2,FALSE) -> MORA MARKET | C18: =VLOOKUP(A18,'Base traitement'!A:BG,45,FALSE) -> Café Collation Q2 - MKT | D18: =VLOOKUP(A18,'Base traitement'!A:BG,3,FALSE) -> CAFE NESPRESSO | E18: =VLOOKUP(A18,'Base traitement'!A:BG,4,FALSE) -> Cafe Nespresso - Collation Q2 - Proforma n°B-PR0626-0258 | F18: 422.6087 | K18: =F18-G18 -> 422.6087 | L18: =VLOOKUP(A18,'Base traitement'!A:BG,15,FALSE) -> 46205 | M18: =VLOOKUP(A18,'Base traitement'!A:BG,16,FALSE) -> 2026-07-02 | N18: =VLOOKUP(A18,'Base traitement'!A:BG,17,FALSE) -> E | O18: =VLOOKUP(A18,'Base traitement'!A:BG,18,FALSE) -> E | P18: =VLOOKUP(A18,'Base traitement'!A:BG,20,FALSE) -> 138708 | Q18: =VLOOKUP(P18,Assemb_DA!A:H,7,FALSE) -> 46202 | R18: =VLOOKUP(P18,Assemb_DA!A:H,8,FALSE) -> 2026-06-29 | S18: =VLOOKUP(P18,Assemb_DA!A:I,9,FALSE) -> 2026-07-01 | T18: =S18-Q18 -> 2 | U18: =VLOOKUP(A18,'Base traitement'!A:BG,23,FALSE) -> DCG | V18: =VLOOKUP(A18,'Base traitement'!A:BG,24,FALSE) -> FELANA13 | W18: =VLOOKUP(A18,'Base traitement'!A:BG,57,FALSE) -> 4245
A19: 135508 | B19: =VLOOKUP(A19,'Base traitement'!A:BG,2,FALSE) -> LOXEA MADAGASCAR | C19: Engagement du devis acompte validé pour la LLD de Mr Gary CHEUK | D19: =VLOOKUP(A19,'Base traitement'!A:BG,3,FALSE) -> LOCATION VEHICULE LLD | E19: =VLOOKUP(A19,'Base traitement'!A:BG,4,FALSE) -> Devis acompte validé pour la LLD de Mr Gary CHEUK Location pour 60 mois# DEVIS N° PF24062026-009 EV DU 24/06/2026 | F19: 9130.4348 | K19: =F19-G19 -> 9130.4348 | L19: =VLOOKUP(A19,'Base traitement'!A:BG,15,FALSE) -> 46205 | M19: =VLOOKUP(A19,'Base traitement'!A:BG,16,FALSE) -> 2026-07-02 | N19: =VLOOKUP(A19,'Base traitement'!A:BG,17,FALSE) -> E | O19: =VLOOKUP(A19,'Base traitement'!A:BG,18,FALSE) -> E | P19: =VLOOKUP(A19,'Base traitement'!A:BG,20,FALSE) -> 138807 | Q19: =VLOOKUP(P19,Assemb_DA!A:H,7,FALSE) -> 46205 | R19: =VLOOKUP(P19,Assemb_DA!A:H,8,FALSE) -> 2026-07-02 | S19: =VLOOKUP(P19,Assemb_DA!A:I,9,FALSE) -> 2026-07-02 | T19: =S19-Q19 -> 0 | U19: =VLOOKUP(A19,'Base traitement'!A:BG,23,FALSE) -> DG | V19: =VLOOKUP(A19,'Base traitement'!A:BG,24,FALSE) -> NADIA7 | W19: =VLOOKUP(A19,'Base traitement'!A:BG,57,FALSE) -> 629
A20: 135509 | B20: =VLOOKUP(A20,'Base traitement'!A:BG,2,FALSE) -> OCEAN TRADE CO | C20: =VLOOKUP(A20,'Base traitement'!A:BG,45,FALSE) -> LLD Richard FIENENA-OCEANTRADE | D20: =VLOOKUP(A20,'Base traitement'!A:BG,3,FALSE) -> LOCATION VEHICULE LLD | E20: =VLOOKUP(A20,'Base traitement'!A:BG,4,FALSE) -> Devis N° V.26.16817 DU 11/05/2026 | F20: 56739.13 | K20: =F20-G20 -> 56739.13 | L20: =VLOOKUP(A20,'Base traitement'!A:BG,15,FALSE) -> 46206 | M20: =VLOOKUP(A20,'Base traitement'!A:BG,16,FALSE) -> 2026-07-03 | N20: =VLOOKUP(A20,'Base traitement'!A:BG,17,FALSE) -> E | O20: =VLOOKUP(A20,'Base traitement'!A:BG,18,FALSE) -> E | P20: =VLOOKUP(A20,'Base traitement'!A:BG,20,FALSE) -> 138806 | Q20: =VLOOKUP(P20,Assemb_DA!A:H,7,FALSE) -> 46205 | R20: =VLOOKUP(P20,Assemb_DA!A:H,8,FALSE) -> 2026-07-02 | S20: =VLOOKUP(P20,Assemb_DA!A:I,9,FALSE) -> 2026-07-02 | T20: =S20-Q20 -> 0 | U20: =VLOOKUP(A20,'Base traitement'!A:BG,23,FALSE) -> DG | V20: =VLOOKUP(A20,'Base traitement'!A:BG,24,FALSE) -> NADIA7 | W20: =VLOOKUP(A20,'Base traitement'!A:BG,57,FALSE) -> 102
A21: 135510 | B21: =VLOOKUP(A21,'Base traitement'!A:BG,2,FALSE) -> AFRICA GLOBAL LOGISTICS | C21: =VLOOKUP(A21,'Base traitement'!A:BG,45,FALSE) -> Gestion Warehouse AGL Phoenix | D21: =VLOOKUP(A21,'Base traitement'!A:BG,3,FALSE) -> PRESTATION DE SERVICES EXTERNE | E21: =VLOOKUP(A21,'Base traitement'!A:BG,4,FALSE) -> Gestion Warehouse AGL Phoenix Février à septembre 2026 (8 mois) | F21: 169975.1 | K21: =F21-G21 -> 169975.1 | L21: =VLOOKUP(A21,'Base traitement'!A:BG,15,FALSE) -> 46206 | M21: =VLOOKUP(A21,'Base traitement'!A:BG,16,FALSE) -> 2026-07-03 | N21: =VLOOKUP(A21,'Base traitement'!A:BG,17,FALSE) -> E | O21: =VLOOKUP(A21,'Base traitement'!A:BG,18,FALSE) -> E | P21: =VLOOKUP(A21,'Base traitement'!A:BG,20,FALSE) -> 138787 | Q21: =VLOOKUP(P21,Assemb_DA!A:H,7,FALSE) -> 46205 | R21: =VLOOKUP(P21,Assemb_DA!A:H,8,FALSE) -> 2026-07-02 | S21: =VLOOKUP(P21,Assemb_DA!A:I,9,FALSE) -> 2026-07-02 | T21: =S21-Q21 -> 0 | U21: =VLOOKUP(A21,'Base traitement'!A:BG,23,FALSE) -> DFG | V21: =VLOOKUP(A21,'Base traitement'!A:BG,24,FALSE) -> NADIA7 | W21: =VLOOKUP(A21,'Base traitement'!A:BG,57,FALSE) -> 713
A22: 135511 | B22: =VLOOKUP(A22,'Base traitement'!A:BG,2,FALSE) -> MORA MARKET | C22: =VLOOKUP(A22,'Base traitement'!A:BG,45,FALSE) -> ADN COLLATION Q2 2026 | D22: =VLOOKUP(A22,'Base traitement'!A:BG,3,FALSE) -> SUCRE | E22: =VLOOKUP(A22,'Base traitement'!A:BG,4,FALSE) -> Sucre Roux Brésilien 1 KG | F22: 361.99275 | K22: =F22-G22 -> 361.99275 | L22: =VLOOKUP(A22,'Base traitement'!A:BG,15,FALSE) -> 46206 | M22: =VLOOKUP(A22,'Base traitement'!A:BG,16,FALSE) -> 2026-07-03 | N22: =VLOOKUP(A22,'Base traitement'!A:BG,17,FALSE) -> E | O22: =VLOOKUP(A22,'Base traitement'!A:BG,18,FALSE) -> E | P22: =VLOOKUP(A22,'Base traitement'!A:BG,20,FALSE) -> 138388 | Q22: =VLOOKUP(P22,Assemb_DA!A:H,7,FALSE) -> 46184 | R22: =VLOOKUP(P22,Assemb_DA!A:H,8,FALSE) -> 2026-06-11 | S22: =VLOOKUP(P22,Assemb_DA!A:I,9,FALSE) -> 2026-06-17 | T22: =S22-Q22 -> 6 | U22: =VLOOKUP(A22,'Base traitement'!A:BG,23,FALSE) -> DCG | V22: =VLOOKUP(A22,'Base traitement'!A:BG,24,FALSE) -> NADIA7 | W22: =VLOOKUP(A22,'Base traitement'!A:BG,57,FALSE) -> 4245
