Workbook

Sheet DASHBOARD
A1: YTD Performance | C1: OPCOs | D1: MADAGASCAR | E1: COMOROS | F1: SENEGAL | G1: TANZANIA | H1: TOGO
C2: Target YTD
A4: Section | B4: KPI | I4: Key Highlights and Drivers
A5: Savings | B5: % of Saving after Negotiations | C5: 0.1 | D5: =SUMIF('PR-PO SLA & Contract%'!C4:C477, "MADAGASCAR", 'PR-PO SLA & Contract%'!S4:S477)/SUMIF('PR-PO SLA & Contract%'!C4:C477, "MADAGASCAR", 'PR-PO SLA & Contract%'!Q4:Q477) -> 0.1284376 | E5: =SUMIF('PR-PO SLA & Contract%'!C4:C477, "COMOROS", 'PR-PO SLA & Contract%'!S4:S477)/SUMIF('PR-PO SLA & Contract%'!C4:C477, "COMOROS", 'PR-PO SLA & Contract%'!Q4:Q477) -> #DIV/0! | F5: =SUMIF('PR-PO SLA & Contract%'!C4:C477, "Senegal", 'PR-PO SLA & Contract%'!S4:S477)/SUMIF('PR-PO SLA & Contract%'!C4:C477, "Senegal", 'PR-PO SLA & Contract%'!Q4:Q477) -> #DIV/0! | G5: =SUMIF('PR-PO SLA & Contract%'!C4:C477, "Tanzania", 'PR-PO SLA & Contract%'!S4:S477)/SUMIF('PR-PO SLA & Contract%'!C4:C477, "Tanzania", 'PR-PO SLA & Contract%'!Q4:Q477) -> #DIV/0! | H5: =SUMIF('PR-PO SLA & Contract%'!C4:C477, "Togo", 'PR-PO SLA & Contract%'!S4:S477)/SUMIF('PR-PO SLA & Contract%'!C4:C477, "Togo", 'PR-PO SLA & Contract%'!Q4:Q477) -> #DIV/0!
B6: Absolute YTD Savings ($) | D6: =SUMIFS('PR-PO SLA & Contract%'!S4:S477, 'PR-PO SLA & Contract%'!C4:C477, "MADAGASCAR",'PR-PO SLA & Contract%'!P4:P477, "Usd") -> 2179415.8 | E6: =SUMIFS('PR-PO SLA & Contract%'!S4:S477, 'PR-PO SLA & Contract%'!C4:C477, "COMOROS",'PR-PO SLA & Contract%'!P4:P477, "Usd") -> 0 | F6: =SUMIFS('PR-PO SLA & Contract%'!S4:S477, 'PR-PO SLA & Contract%'!C4:C477, "SENEGAL",'PR-PO SLA & Contract%'!P4:P477, "Usd") -> 0 | G6: =SUMIFS('PR-PO SLA & Contract%'!S4:S477, 'PR-PO SLA & Contract%'!C4:C477, "Tanzania",'PR-PO SLA & Contract%'!P4:P477, "Usd") -> 0 | H6: =SUMIFS('PR-PO SLA & Contract%'!S4:S477, 'PR-PO SLA & Contract%'!C4:C477, "Togo",'PR-PO SLA & Contract%'!P4:P477, "Usd") -> 0
A7: Purchase Request - Purchase Order | B7: TAT for PR Approval (Days) | C7: 4 | D7: =AVERAGEIF('PR-PO SLA & Contract%'!C4:C477, "MADAGASCAR", 'PR-PO SLA & Contract%'!I4:I477) -> 3.4989429 | E7: =AVERAGEIF('PR-PO SLA & Contract%'!C4:C477, "COMOROS", 'PR-PO SLA & Contract%'!I4:I477) -> #DIV/0! | F7: =AVERAGEIF('PR-PO SLA & Contract%'!C4:C477, "Senegal", 'PR-PO SLA & Contract%'!I4:I477) -> #DIV/0! | G7: =AVERAGEIF('PR-PO SLA & Contract%'!C4:C477, "Tanzania", 'PR-PO SLA & Contract%'!I4:I477) -> #DIV/0! | H7: =AVERAGEIF('PR-PO SLA & Contract%'!C4:C477, "Togo", 'PR-PO SLA & Contract%'!I4:I477) -> #DIV/0!
B8: TAT for PR Approval vs. SLA Compliance (%) | C8: 0.9 | D8: =COUNTIFS('PR-PO SLA & Contract%'!I4:I477, "<=4", 'PR-PO SLA & Contract%'!C4:C477, "MADAGASCAR")/COUNTIF('PR-PO SLA & Contract%'!C4:C477, "MADAGASCAR") -> 0.81606765 | E8: =COUNTIFS('PR-PO SLA & Contract%'!I4:I477, "<=4", 'PR-PO SLA & Contract%'!C4:C477, "COMOROS")/COUNTIF('PR-PO SLA & Contract%'!C4:C477, "COMOROS") -> #DIV/0! | F8: =COUNTIFS('PR-PO SLA & Contract%'!I4:I477, "<=4", 'PR-PO SLA & Contract%'!C4:C477, "Senegal")/COUNTIF('PR-PO SLA & Contract%'!C4:C477, "Senegal") -> #DIV/0! | G8: =COUNTIFS('PR-PO SLA & Contract%'!I4:I477, "<=4", 'PR-PO SLA & Contract%'!C4:C477, "Tanzania")/COUNTIF('PR-PO SLA & Contract%'!C4:C477, "Tanzania") -> #DIV/0! | H8: =COUNTIFS('PR-PO SLA & Contract%'!I4:I477, "<=4", 'PR-PO SLA & Contract%'!C4:C477, "Togo")/COUNTIF('PR-PO SLA & Contract%'!C4:C477, "Togo") -> #DIV/0!
B9: TAT for PR to PO SLA Conversion (Days) | C9: 4 | D9: =AVERAGEIF('PR-PO SLA & Contract%'!C4:C477, "MADAGASCAR", 'PR-PO SLA & Contract%'!K4:K477) -> 2.3255814 | E9: =AVERAGEIF('PR-PO SLA & Contract%'!C4:C477, "COMOROS", 'PR-PO SLA & Contract%'!K4:K477) -> #DIV/0! | F9: =AVERAGEIF('PR-PO SLA & Contract%'!C4:C477, "Senegal", 'PR-PO SLA & Contract%'!K4:K477) -> #DIV/0! | G9: =AVERAGEIF('PR-PO SLA & Contract%'!C4:C477, "Tanzania", 'PR-PO SLA & Contract%'!K4:K477) -> #DIV/0! | H9: =AVERAGEIF('PR-PO SLA & Contract%'!C4:C477, "Togo", 'PR-PO SLA & Contract%'!K4:K477) -> #DIV/0!
B10: TAT for PO Approval vs. SLA Compliance (%) | C10: 0.9 | D10: =COUNTIFS('PR-PO SLA & Contract%'!M4:M477, "<=4", 'PR-PO SLA & Contract%'!C4:C477, "Madagascar")/COUNTIF('PR-PO SLA & Contract%'!C4:C477, "Madagascar") -> 0.98097252 | E10: =COUNTIFS('PR-PO SLA & Contract%'!M4:M477, "<=4", 'PR-PO SLA & Contract%'!C4:C477, "COMOROS")/COUNTIF('PR-PO SLA & Contract%'!C4:C477, "COMOROS") -> #DIV/0! | F10: =COUNTIFS('PR-PO SLA & Contract%'!M4:M477, "<=4", 'PR-PO SLA & Contract%'!C4:C477, "Senegal")/COUNTIF('PR-PO SLA & Contract%'!C4:C477, "Senegal") -> #DIV/0! | G10: =COUNTIFS('PR-PO SLA & Contract%'!M4:M477, "<=4", 'PR-PO SLA & Contract%'!C4:C477, "Tanzania")/COUNTIF('PR-PO SLA & Contract%'!C4:C477, "Tanzania") -> #DIV/0! | H10: =COUNTIFS('PR-PO SLA & Contract%'!M4:M477, "<=4", 'PR-PO SLA & Contract%'!C4:C477, "Togo")/COUNTIF('PR-PO SLA & Contract%'!C4:C477, "Togo") -> #DIV/0!
A11: Custom Clearance | B11: TAT for custom clearance (AIR): SLA compliance (Days) | C11: 5 | D11: =IF( COUNTIFS(Customs_Clearance!C4:C40041,"MADAGASCAR",Customs_Clearance!I4:I40041,"AIR")=0, 0, AVERAGEIFS(Customs_Clearance!L4:L40041,Customs_Clearance!C4:C40041,"MADAGASCAR",Customs_Clearance!I4:I40041,"AIR") ) -> 4.1111111 | E11: =IF( COUNTIFS(Customs_Clearance!C4:C44,"COMOROS",Customs_Clearance!I4:I44,"AIR")=0, 0, AVERAGEIFS(Customs_Clearance!L4:L44,Customs_Clearance!C4:C44,"COMOROS",Customs_Clearance!I4:I44,"AIR") ) -> 0 | F11: =IF( COUNTIFS(Customs_Clearance!C4:C40041,"SENEGAL",Customs_Clearance!I4:I40041,"AIR")=0, 0, AVERAGEIFS(Customs_Clearance!L4:L40041,Customs_Clearance!C4:C40041,"SENEGAL",Customs_Clearance!I4:I40041,"AIR") ) -> 0 | G11: =IF( COUNTIFS(Customs_Clearance!C4:C40041,"TANZANIA",Customs_Clearance!I4:I40041,"AIR")=0, 0, AVERAGEIFS(Customs_Clearance!L4:L40041,Customs_Clearance!C4:C40041,"TANZANIA",Customs_Clearance!I4:I40041,"AIR") ) -> 0 | H11: =IF( COUNTIFS(Customs_Clearance!C4:C40041,"Togo",Customs_Clearance!I4:I40041,"AIR")=0, 0, AVERAGEIFS(Customs_Clearance!L4:L40041,Customs_Clearance!C4:C40041,"Togo",Customs_Clearance!I4:I40041,"AIR") ) -> 0
B12: TAT for custom clearance (SEA): SLA compliance (Days) | C12: 10 | D12: =IF( COUNTIFS(Customs_Clearance!C4:C40041,"MADAGASCAR",Customs_Clearance!I4:I40041,"SEA")=0, 0, AVERAGEIFS(Customs_Clearance!L4:L40041,Customs_Clearance!C4:C40041,"MADAGASCAR",Customs_Clearance!I4:I40041,"SEA") ) -> 9.6666667 | E12: =IF( COUNTIFS(Customs_Clearance!C4:C40041,"COMOROS",Customs_Clearance!I4:I40041,"SEA")=0, 0, AVERAGEIFS(Customs_Clearance!L4:L40041,Customs_Clearance!C4:C40041,"COMOROS",Customs_Clearance!I4:I40041,"SEA") ) -> 0 | F12: =IF( COUNTIFS(Customs_Clearance!C4:C40041,"SENEGAL",Customs_Clearance!I4:I40041,"SEA")=0, 0, AVERAGEIFS(Customs_Clearance!L4:L40041,Customs_Clearance!C4:C40041,"SENEGAL",Customs_Clearance!I4:I40041,"SEA") ) -> 0 | G12: =IF( COUNTIFS(Customs_Clearance!C4:C40041,"Tanzania",Customs_Clearance!I4:I40041,"SEA")=0, 0, AVERAGEIFS(Customs_Clearance!L4:L40041,Customs_Clearance!C4:C40041,"Tanzania",Customs_Clearance!I4:I40041,"SEA") ) -> 0 | H12: =IF( COUNTIFS(Customs_Clearance!C4:C40041,"Togo",Customs_Clearance!I4:I40041,"SEA")=0, 0, AVERAGEIFS(Customs_Clearance!L4:L40041,Customs_Clearance!C4:C40041,"Togo",Customs_Clearance!I4:I40041,"SEA") ) -> 0
A13: Contracts Compliance | B13: % Purchase on Contracts (Count) | C13: 0.7 | D13: =COUNTIFS('PR-PO SLA & Contract%'!E4:E477, "YES", 'PR-PO SLA & Contract%'!C4:C477, "Madagascar")/COUNTIF('PR-PO SLA & Contract%'!C4:C477, "Madagascar") -> 0.87526427 | E13: =COUNTIFS('PR-PO SLA & Contract%'!E4:E477, "YES", 'PR-PO SLA & Contract%'!C4:C477, "COMOROS")/COUNTIF('PR-PO SLA & Contract%'!C4:C477, "COMOROS") -> #DIV/0! | F13: =COUNTIFS('PR-PO SLA & Contract%'!E4:E477, "YES", 'PR-PO SLA & Contract%'!C4:C477, "Senegal")/COUNTIF('PR-PO SLA & Contract%'!C4:C477, "Senegal") -> #DIV/0! | G13: =COUNTIFS('PR-PO SLA & Contract%'!E4:E477, "YES", 'PR-PO SLA & Contract%'!C4:C477, "Tanzania")/COUNTIF('PR-PO SLA & Contract%'!C4:C477, "Tanzania") -> #DIV/0! | H13: =COUNTIFS('PR-PO SLA & Contract%'!E4:E477, "YES", 'PR-PO SLA & Contract%'!C4:C477, "Togo")/COUNTIF('PR-PO SLA & Contract%'!C4:C477, "Togo") -> #DIV/0!
B14: % Purchase on Contracts (Value) | C14: 0.7 | D14: =IFERROR(SUMIFS('PR-PO SLA & Contract%'!$R:$R,'PR-PO SLA & Contract%'!$E:$E,"Yes",'PR-PO SLA & Contract%'!$C:$C,DASHBOARD!D$1)/SUMIFS('PR-PO SLA & Contract%'!$R:$R,'PR-PO SLA & Contract%'!$C:$C,DASHBOARD!D$1),0) -> 0.97785958 | E14: =IFERROR(SUMIFS('PR-PO SLA & Contract%'!$R:$R,'PR-PO SLA & Contract%'!$E:$E,"Yes",'PR-PO SLA & Contract%'!$C:$C,DASHBOARD!E$1)/SUMIFS('PR-PO SLA & Contract%'!$R:$R,'PR-PO SLA & Contract%'!$C:$C,DASHBOARD!E$1),0) -> 0 | F14: =IFERROR(SUMIFS('PR-PO SLA & Contract%'!$R:$R,'PR-PO SLA & Contract%'!$E:$E,"Yes",'PR-PO SLA & Contract%'!$C:$C,DASHBOARD!F$1)/SUMIFS('PR-PO SLA & Contract%'!$R:$R,'PR-PO SLA & Contract%'!$C:$C,DASHBOARD!F$1),0) -> 0 | G14: =IFERROR(SUMIFS('PR-PO SLA & Contract%'!$R:$R,'PR-PO SLA & Contract%'!$E:$E,"Yes",'PR-PO SLA & Contract%'!$C:$C,DASHBOARD!G$1)/SUMIFS('PR-PO SLA & Contract%'!$R:$R,'PR-PO SLA & Contract%'!$C:$C,DASHBOARD!G$1),0) -> 0 | H14: =IFERROR(SUMIFS('PR-PO SLA & Contract%'!$R:$R,'PR-PO SLA & Contract%'!$E:$E,"Yes",'PR-PO SLA & Contract%'!$C:$C,DASHBOARD!H$1)/SUMIFS('PR-PO SLA & Contract%'!$R:$R,'PR-PO SLA & Contract%'!$C:$C,DASHBOARD!H$1),0) -> 0
A15: Payment | B15: PPOT (% Due invoices paid) | C15: 0.7 | D15: =IF(COUNTIF(PPOT!C4:C876,"Madagascar")=0, 0, COUNTIFS(PPOT!O4:O876,"YES",PPOT!C4:C876,"Madagascar") / COUNTIF(PPOT!C4:C876,"Madagascar") ) -> 0.7293578 | E15: =IF(COUNTIF(PPOT!C4:C876,"COMOROS")=0, 0, COUNTIFS(PPOT!O4:O876,"YES",PPOT!C4:C876,"COMOROS") / COUNTIF(PPOT!C4:C876,"COMOROS") ) -> 0 | F15: =IF(COUNTIF(PPOT!C4:C876,"Senegal")=0, 0, COUNTIFS(PPOT!O4:O876,"YES",PPOT!C4:C876,"Senegal") / COUNTIF(PPOT!C4:C876,"Senegal") ) -> 0 | G15: =IF(COUNTIF(PPOT!C4:C876,"Tanzania")=0, 0, COUNTIFS(PPOT!O4:O876,"YES",PPOT!C4:C876,"Tanzania") / COUNTIF(PPOT!C4:C876,"Tanzania") ) -> 0 | H15: =IF(COUNTIF(PPOT!C4:C876,"Togo")=0, 0, COUNTIFS(PPOT!O4:O876,"YES",PPOT!C4:C876,"Togo") / COUNTIF(PPOT!C4:C876,"Togo") ) -> 0
B16: Ranking | D16: =RANK(D31,$D$31:$H$31,0) -> #DIV/0! | E16: =RANK(E31,$D$31:$H$31,0) -> #DIV/0! | F16: =RANK(F31,$D$31:$H$31,0) -> #DIV/0! | G16: =RANK(G31,$D$31:$H$31,0) -> #DIV/0! | H16: =RANK(H31,$D$31:$H$31,0) -> #DIV/0!
B18: The section below is to aid in normalizing scores, weighting them for ranking purposes.
C20: Weighting | D20: MADAGASCAR | E20: COMOROS | F20: SENEGAL | G20: TANZANIA | H20: TOGO
B21: =CONCATENATE("Normalized"," ",B5) -> Normalized % of Saving after Negotiations | C21: 0.15 | D21: =(D5-MIN($D$5:$H$5))/(MAX($D$5:$H$5)-MIN($D$5:$H$5)) -> #DIV/0! | E21: =(E5-MIN($D$5:$H$5))/(MAX($D$5:$H$5)-MIN($D$5:$H$5)) -> #DIV/0! | F21: =(F5-MIN($D$5:$H$5))/(MAX($D$5:$H$5)-MIN($D$5:$H$5)) -> #DIV/0! | G21: =(G5-MIN($D$5:$H$5))/(MAX($D$5:$H$5)-MIN($D$5:$H$5)) -> #DIV/0! | H21: =(H5-MIN($D$5:$H$5))/(MAX($D$5:$H$5)-MIN($D$5:$H$5)) -> #DIV/0!
B22: =CONCATENATE("Normalized"," ",B6) -> Normalized Absolute YTD Savings ($) | C22: 0.05 | D22: =(D6-MIN($D$6:$H$6))/(MAX($D$6:$H$6)-MIN($D$6:$H$6)) -> 1 | E22: =(E6-MIN($D$6:$H$6))/(MAX($D$6:$H$6)-MIN($D$6:$H$6)) -> 0 | F22: =(F6-MIN($D$6:$H$6))/(MAX($D$6:$H$6)-MIN($D$6:$H$6)) -> 0 | G22: =(G6-MIN($D$6:$H$6))/(MAX($D$6:$H$6)-MIN($D$6:$H$6)) -> 0 | H22: =(H6-MIN($D$6:$H$6))/(MAX($D$6:$H$6)-MIN($D$6:$H$6)) -> 0
B23: =CONCATENATE("Normalized"," ",B7) -> Normalized TAT for PR Approval (Days) | C23: 0.1 | D23: =(MAX($D$7:$H$7)-D7)/(MAX($D$7:$H$7)-MIN($D$7:$H$7)) -> #DIV/0! | E23: =(MAX($D$7:$H$7)-E7)/(MAX($D$7:$H$7)-MIN($D$7:$H$7)) -> #DIV/0! | F23: =(MAX($D$7:$H$7)-F7)/(MAX($D$7:$H$7)-MIN($D$7:$H$7)) -> #DIV/0! | G23: =(MAX($D$7:$H$7)-G7)/(MAX($D$7:$H$7)-MIN($D$7:$H$7)) -> #DIV/0! | H23: =(MAX($D$7:$H$7)-H7)/(MAX($D$7:$H$7)-MIN($D$7:$H$7)) -> #DIV/0!
B24: =CONCATENATE("Normalized"," ",B8) -> Normalized TAT for PR Approval vs. SLA Compliance (%) | C24: 0.1 | D24: =(D8-MIN($D$8:$H$8))/(MAX($D$8:$H$8)-MIN($D$8:$H$8)) -> #DIV/0! | E24: =(E8-MIN($D$8:$H$8))/(MAX($D$8:$H$8)-MIN($D$8:$H$8)) -> #DIV/0! | F24: =(F8-MIN($D$8:$H$8))/(MAX($D$8:$H$8)-MIN($D$8:$H$8)) -> #DIV/0! | G24: =(G8-MIN($D$8:$H$8))/(MAX($D$8:$H$8)-MIN($D$8:$H$8)) -> #DIV/0! | H24: =(H8-MIN($D$8:$H$8))/(MAX($D$8:$H$8)-MIN($D$8:$H$8)) -> #DIV/0!
B25: =CONCATENATE("Normalized"," ",B9) -> Normalized TAT for PR to PO SLA Conversion (Days) | C25: 0.1 | D25: =(MAX($D$9:$H$9)-D9)/(MAX($D$9:$H$9)-MIN($D$9:$H$9)) -> #DIV/0! | E25: =(MAX($D$9:$H$9)-E9)/(MAX($D$9:$H$9)-MIN($D$9:$H$9)) -> #DIV/0! | F25: =(MAX($D$9:$H$9)-F9)/(MAX($D$9:$H$9)-MIN($D$9:$H$9)) -> #DIV/0! | G25: =(MAX($D$9:$H$9)-G9)/(MAX($D$9:$H$9)-MIN($D$9:$H$9)) -> #DIV/0! | H25: =(MAX($D$9:$H$9)-H9)/(MAX($D$9:$H$9)-MIN($D$9:$H$9)) -> #DIV/0!
B26: Normalized TAT for PO Approval vs. SLA Compliance (%) | C26: 0.05 | D26: =(D10-MIN($D$10:$H$10))/(MAX($D$10:$H$10)-MIN($D$10:$H$10)) -> #DIV/0! | E26: =(E10-MIN($D$10:$H$10))/(MAX($D$10:$H$10)-MIN($D$10:$H$10)) -> #DIV/0! | F26: =(F10-MIN($D$10:$H$10))/(MAX($D$10:$H$10)-MIN($D$10:$H$10)) -> #DIV/0! | G26: =(G10-MIN($D$10:$H$10))/(MAX($D$10:$H$10)-MIN($D$10:$H$10)) -> #DIV/0! | H26: =(H10-MIN($D$10:$H$10))/(MAX($D$10:$H$10)-MIN($D$10:$H$10)) -> #DIV/0!
B27: =CONCATENATE("Normalized"," ",B11) -> Normalized TAT for custom clearance (AIR): SLA compliance (Days) | C27: 0.05 | D27: =(MAX($D$11:$H$11)-D11)/(MAX($D$11:$H$11)-MIN($D$11:$H$11)) -> 0 | E27: =(MAX($D$11:$H$11)-E11)/(MAX($D$11:$H$11)-MIN($D$11:$H$11)) -> 1 | F27: =(MAX($D$11:$H$11)-F11)/(MAX($D$11:$H$11)-MIN($D$11:$H$11)) -> 1 | G27: =(MAX($D$11:$H$11)-G11)/(MAX($D$11:$H$11)-MIN($D$11:$H$11)) -> 1 | H27: =(MAX($D$11:$H$11)-H11)/(MAX($D$11:$H$11)-MIN($D$11:$H$11)) -> 1
B28: =CONCATENATE("Normalized"," ",B12) -> Normalized TAT for custom clearance (SEA): SLA compliance (Days) | C28: 0.05 | D28: =(MAX($D$12:$H$12)-D12)/(MAX($D$12:$H$12)-MIN($D$12:$H$12)) -> 0 | E28: =(MAX($D$12:$H$12)-E12)/(MAX($D$12:$H$12)-MIN($D$12:$H$12)) -> 1 | F28: =(MAX($D$12:$H$12)-F12)/(MAX($D$12:$H$12)-MIN($D$12:$H$12)) -> 1 | G28: =(MAX($D$12:$H$12)-G12)/(MAX($D$12:$H$12)-MIN($D$12:$H$12)) -> 1 | H28: =(MAX($D$12:$H$12)-H12)/(MAX($D$12:$H$12)-MIN($D$12:$H$12)) -> 1
B29: =CONCATENATE("Normalized"," ",B13) -> Normalized % Purchase on Contracts (Count) | C29: 0.2 | D29: =(D13-MIN($D$13:$H$13))/(MAX($D$13:$H$13)-MIN($D$13:$H$13)) -> #DIV/0! | E29: =(E13-MIN($D$13:$H$13))/(MAX($D$13:$H$13)-MIN($D$13:$H$13)) -> #DIV/0! | F29: =(F13-MIN($D$13:$H$13))/(MAX($D$13:$H$13)-MIN($D$13:$H$13)) -> #DIV/0! | G29: =(G13-MIN($D$13:$H$13))/(MAX($D$13:$H$13)-MIN($D$13:$H$13)) -> #DIV/0! | H29: =(H13-MIN($D$13:$H$13))/(MAX($D$13:$H$13)-MIN($D$13:$H$13)) -> #DIV/0!
B30: =CONCATENATE("Normalized"," ",B15) -> Normalized PPOT (% Due invoices paid) | C30: 0.15 | D30: =(D15-MIN($D$15:$H$15))/(MAX($D$15:$H$15)-MIN($D$15:$H$15)) -> 1 | E30: =(E15-MIN($D$15:$H$15))/(MAX($D$15:$H$15)-MIN($D$15:$H$15)) -> 0 | F30: =(F15-MIN($D$15:$H$15))/(MAX($D$15:$H$15)-MIN($D$15:$H$15)) -> 0 | G30: =(G15-MIN($D$15:$H$15))/(MAX($D$15:$H$15)-MIN($D$15:$H$15)) -> 0 | H30: =(H15-MIN($D$15:$H$15))/(MAX($D$15:$H$15)-MIN($D$15:$H$15)) -> 0
B31: Global Weighted Score | D31: =D21*$C$21+D22*$C$22+D23*$C$23+D24*$C$24+D25*$C$25+D26*$C$26+D27*$C$27+D28*$C$28+D29*$C$29+D30*$C$30 -> #DIV/0! | E31: =E21*$C$21+E22*$C$22+E23*$C$23+E24*$C$24+E25*$C$25+E26*$C$26+E27*$C$27+E28*$C$28+E29*$C$29+E30*$C$30 -> #DIV/0! | F31: =F21*$C$21+F22*$C$22+F23*$C$23+F24*$C$24+F25*$C$25+F26*$C$26+F27*$C$27+F28*$C$28+F29*$C$29+F30*$C$30 -> #DIV/0! | G31: =G21*$C$21+G22*$C$22+G23*$C$23+G24*$C$24+G25*$C$25+G26*$C$26+G27*$C$27+G28*$C$28+G29*$C$29+G30*$C$30 -> #DIV/0! | H31: =H21*$C$21+H22*$C$22+H23*$C$23+H24*$C$24+H25*$C$25+H26*$C$26+H27*$C$27+H28*$C$28+H29*$C$29+H30*$C$30 -> #DIV/0!
A32: Month Over Month Progress | C32: OPCOs | D32: MADAGASCAR | E32: COMOROS | F32: SENEGAL | G32: TANZANIA | H32: TOGO
C33: Target YTD
A35: Section | B35: KPI
A36: Savings | B36: % of Saving after Negotiations (bps) | C36: 0.1 | D36: =(D5-'M-1 YTD performance'!D5)*10000 -> 802.66307 | E36: =(E5-'M-1 YTD performance'!E5)*10000 -> #DIV/0! | F36: =(F5-'M-1 YTD performance'!F5)*10000 -> #DIV/0! | G36: =(G5-'M-1 YTD performance'!G5)*10000 -> #DIV/0! | H36: =(H5-'M-1 YTD performance'!H5)*10000 -> #DIV/0!
B37: Absolute YTD Savings ($) | D37: =D6-'M-1 YTD performance'!D6 -> -134165.16 | E37: =E6-'M-1 YTD performance'!E6 -> -1405117.3 | F37: =F6-'M-1 YTD performance'!F6 -> -2944643 | G37: =G6-'M-1 YTD performance'!G6 -> -5911843.3 | H37: =H6-'M-1 YTD performance'!H6 -> -4057811.9
A38: Purchase Request - Purchase Order | B38: TAT for PR Approval (Days) | C38: 4 | D38: =D7-'M-1 YTD performance'!D7 -> 0.81897838 | E38: =E7-'M-1 YTD performance'!E7 -> #DIV/0! | F38: =F7-'M-1 YTD performance'!F7 -> #DIV/0! | G38: =G7-'M-1 YTD performance'!G7 -> #DIV/0! | H38: =H7-'M-1 YTD performance'!H7 -> #DIV/0!
B39: TAT for PR Approval vs. SLA Compliance (bps) | C39: 0.9 | D39: =(D8-'M-1 YTD performance'!D8)*10000 -> -45.588243 | E39: =(E8-'M-1 YTD performance'!E8)*10000 -> #DIV/0! | F39: =(F8-'M-1 YTD performance'!F8)*10000 -> #DIV/0! | G39: =(G8-'M-1 YTD performance'!G8)*10000 -> #DIV/0! | H39: =(H8-'M-1 YTD performance'!H8)*10000 -> #DIV/0!
B40: TAT for PR to PO SLA Conversion (Days) | C40: 4 | D40: =D9-'M-1 YTD performance'!D9 -> -1.653142 | E40: =E9-'M-1 YTD performance'!E9 -> #DIV/0! | F40: =F9-'M-1 YTD performance'!F9 -> #DIV/0! | G40: =G9-'M-1 YTD performance'!G9 -> #DIV/0! | H40: =H9-'M-1 YTD performance'!H9 -> #DIV/0!
B41: TAT for PO Approval vs. SLA Compliance (bps) | C41: 0.9 | D41: =(D10-'M-1 YTD performance'!D10)*10000 -> 152.51476 | E41: =(E10-'M-1 YTD performance'!E10)*10000 -> #DIV/0! | F41: =(F10-'M-1 YTD performance'!F10)*10000 -> #DIV/0! | G41: =(G10-'M-1 YTD performance'!G10)*10000 -> #DIV/0! | H41: =(H10-'M-1 YTD performance'!H10)*10000 -> #DIV/0!
A42: Custom Clearance | B42: TAT for custom clearance (AIR): SLA compliance (Days) | C42: 5 | D42: =D11-'M-1 YTD performance'!D11 -> -0.68434343 | E42: =E11-'M-1 YTD performance'!E11 -> -8.75 | F42: =F11-'M-1 YTD performance'!F11 -> -5.7115385 | G42: =G11-'M-1 YTD performance'!G11 -> -5.9318182 | H42: =H11-'M-1 YTD performance'!H11 -> -8.7857143
B43: TAT for custom clearance (SEA): SLA compliance (Days) | C43: 10 | D43: =D12-'M-1 YTD performance'!D12 -> 0.84313725 | E43: =E12-'M-1 YTD performance'!E12 -> -12 | F43: =F12-'M-1 YTD performance'!F12 -> -6.9333333 | G43: =G12-'M-1 YTD performance'!G12 -> -17.166667 | H43: =H12-'M-1 YTD performance'!H12 -> -11.384615
A44: Contracts Compliance | B44: % Purchase on Contracts (Count - bps) | C44: 0.7 | D44: =(D13-'M-1 YTD performance'!D13)*10000 -> 2440.586 | E44: =(E13-'M-1 YTD performance'!E13)*10000 -> #DIV/0! | F44: =(F13-'M-1 YTD performance'!F13)*10000 -> #DIV/0! | G44: =(G13-'M-1 YTD performance'!G13)*10000 -> #DIV/0! | H44: =(H13-'M-1 YTD performance'!H13)*10000 -> #DIV/0!
B45: % Purchase on Contracts (Value-bps) | C45: 0.7 | D45: =(D14-'M-1 YTD performance'!D14)*10000 -> 1103.6744 | E45: =(E14-'M-1 YTD performance'!E14)*10000 -> -6847.5342 | F45: =(F14-'M-1 YTD performance'!F14)*10000 -> -3424.4347 | G45: =(G14-'M-1 YTD performance'!G14)*10000 -> -8653.3852 | H45: =(H14-'M-1 YTD performance'!H14)*10000 -> -6383.2356
A46: Payment | B46: PPOT -% Due invoices paid (bps) | C46: 0.7 | D46: =(D15-'M-1 YTD performance'!D15)*10000 -> 353.06051 | E46: =(E15-'M-1 YTD performance'!E15)*10000 -> -8704.4146 | F46: =(F15-'M-1 YTD performance'!F15)*10000 -> 0 | G46: =(G15-'M-1 YTD performance'!G15)*10000 -> -4575.3968 | H46: =(H15-'M-1 YTD performance'!H15)*10000 -> -7741.9355

Sheet PR-PO SLA & Contract%
B1: OPCOS MONTHLY DETAILS TRACKER
C2: same OpCo spelling as in the Dashboard | F2: =LEFT('[1]PR-PO SLA & Contract%'!G5,10) -> 30/01/2026 | G2: Date in MM/DD/YYYY format | H2: Date in MM/DD/YYYY format | I2: Automatic Formula | J2: Date in MM/DD/YYYY format | K2: Automatic Formula | L2: Date in MM/DD/YYYY format | M2: Automatic Formula | P2: exchange to USD | S2: Automatic Formula | T2: indicate the saving from OpCo nego effort (USD) | U2: indicate the saving from Group nego effort (USD) | W2: Automatic Formula
F3: =RIGHT(LEFT('[1]PR-PO SLA & Contract%'!G5,8),4) -> 1/20
B4: N° | C4: OPCO | D4: PO reference | E4: Under contract (Yes or No) | F4: PR Number | G4: PR Created Date | H4: PR Approved Date | I4: PR Approval TAT | J4: PO Created Date | K4: Approved PR - PO TAT | L4: PO Approved Date | M4: PO Approval TAT | N4: Designation | O4: Partner | P4: Currency usd | Q4: Amount before Negotiation | R4: Amount after Negotiation | S4: Saving | T4: OpCo saving | U4: Group saving | V4: Target Savings | W4: % Savings
B5: 1 | C5: Madagascar | D5: 136497 | E5: Yes | F5: 138888 | G5: 46211 | H5: 2026-07-13 | I5: =IF(OR(H5="", G5=""), "", NETWORKDAYS(G5, H5)) -> 4 | J5: 46229 | K5: =IF(OR(H5="", J5=""), "", NETWORKDAYS(H5, J5)) -> 10 | L5: 46230 | M5: =IF(OR(J5="", L5=""), "", NETWORKDAYS(J5, L5)) -> 1 | N5: Badge sans puce | O5: TECHNOALARME | P5: USD | Q5: 391.30435 | R5: 391.30435 | S5: =Q5-R5 -> 0 | V5: =IF(Q5="", "", Q5*10%) -> 39.130435 | W5: =IF(OR(Q5="", R5=""), "", (Q5- R5)/Q5) -> 0
B6: 2 | C6: Madagascar | D6: 136157 | E6: Yes | F6: 138949 | G6: 46231 | H6: 2026-07-31 | I6: =IF(OR(H6="", G6=""), "", NETWORKDAYS(G6, H6)) -> 4 | J6: 46237 | K6: =IF(OR(H6="", J6=""), "", NETWORKDAYS(H6, J6)) -> 2 | L6: 2026-08-03 | M6: =IF(OR(J6="", L6=""), "", NETWORKDAYS(J6, L6)) -> 1 | N6: Prestation intérimaire: PERDIEM Suivi routier - Eudes, Aldo, Tolotra mars au juillet 26# FACTURE PROFORMA N°335-A/FP/TELMA/2026 DU 10/07/2026 | O6: LCS CONSULTING | P6: USD | Q6: 2419.8913 | R6: 2419.8913 | S6: =Q6-R6 -> 0 | V6: =IF(Q6="", "", Q6*10%) -> 241.98913 | W6: =IF(OR(Q6="", R6=""), "", (Q6- R6)/Q6) -> 0
B7: 3 | C7: Madagascar | D7: 136158 | E7: Yes | F7: 138947 | G7: 46231 | H7: 2026-07-31 | I7: =IF(OR(H7="", G7=""), "", NETWORKDAYS(G7, H7)) -> 4 | J7: 46237 | K7: =IF(OR(H7="", J7=""), "", NETWORKDAYS(H7, J7)) -> 2 | L7: 2026-08-03 | M7: =IF(OR(J7="", L7=""), "", NETWORKDAYS(J7, L7)) -> 1 | N7: Prestation intérimaire: PERDIEM Suivi routier - Eric juillet 26# FACTURE PROFORMA N°333-A/FP/TELMA/2026 DU 10/07/2026 | O7: LCS CONSULTING | P7: USD | Q7: 341.95652 | R7: 341.95652 | S7: =Q7-R7 -> 0 | V7: =IF(Q7="", "", Q7*10%) -> 34.195652 | W7: =IF(OR(Q7="", R7=""), "", (Q7- R7)/Q7) -> 0
B8: 4 | C8: Madagascar | D8: 136159 | E8: Yes | F8: 138931 | G8: 46231 | H8: 2026-07-31 | I8: =IF(OR(H8="", G8=""), "", NETWORKDAYS(G8, H8)) -> 4 | J8: 46237 | K8: =IF(OR(H8="", J8=""), "", NETWORKDAYS(H8, J8)) -> 2 | L8: 2026-08-03 | M8: =IF(OR(J8="", L8=""), "", NETWORKDAYS(J8, L8)) -> 1 | N8: Prestation intérimaire: PERDIEM mission - 01 Formateur Commercial du 130726 au 040826# FACTURE PROFORMA N°332-A/FP/TELMA/2026 DU 09/07/2026 | O8: LCS CONSULTING | P8: USD | Q8: 336.95652 | R8: 336.95652 | S8: =Q8-R8 -> 0 | V8: =IF(Q8="", "", Q8*10%) -> 33.695652 | W8: =IF(OR(Q8="", R8=""), "", (Q8- R8)/Q8) -> 0
B9: 5 | C9: Madagascar | D9: 136160 | E9: Yes | F9: 138945 | G9: 46231 | H9: 2026-07-31 | I9: =IF(OR(H9="", G9=""), "", NETWORKDAYS(G9, H9)) -> 4 | J9: 46237 | K9: =IF(OR(H9="", J9=""), "", NETWORKDAYS(H9, J9)) -> 2 | L9: 2026-08-03 | M9: =IF(OR(J9="", L9=""), "", NETWORKDAYS(J9, L9)) -> 1 | N9: Prestation intérimaire: PERDIEM Mission - Moïbe, Bernard, Haja, Hilaire,Chistien avril au juillet 26# FACTURE PROFORMA N°334-A/FP/TELMA/2026 DU 10/07/2026 | O9: LCS CONSULTING | P9: USD | Q9: 674.13043 | R9: 674.13043 | S9: =Q9-R9 -> 0 | V9: =IF(Q9="", "", Q9*10%) -> 67.413043 | W9: =IF(OR(Q9="", R9=""), "", (Q9- R9)/Q9) -> 0
B10: 6 | C10: Madagascar | D10: 136156 | E10: Yes | F10: 139005 | G10: 46221 | H10: 2026-07-31 | I10: =IF(OR(H10="", G10=""), "", NETWORKDAYS(G10, H10)) -> 10 | J10: 46237 | K10: =IF(OR(H10="", J10=""), "", NETWORKDAYS(H10, J10)) -> 2 | L10: 2026-08-03 | M10: =IF(OR(J10="", L10=""), "", NETWORKDAYS(J10, L10)) -> 1 | N10: Prestation intérimaire: PERDIEM Suivi routier - Tsiry, Niriana, Thierry, Tahiry mai au juillet 26# FACTURE PROFORMA N°336-A/FP/TELMA/2026 DU 13/07/2026 | O10: LCS CONSULTING | P10: USD | Q10: 2769.087 | R10: 2769.087 | S10: =Q10-R10 -> 0 | V10: =IF(Q10="", "", Q10*10%) -> 276.9087 | W10: =IF(OR(Q10="", R10=""), "", (Q10- R10)/Q10) -> 0
B11: 7 | C11: Madagascar | D11: 136155 | E11: Yes | F11: 139038 | G11: 46219 | H11: 2026-07-31 | I11: =IF(OR(H11="", G11=""), "", NETWORKDAYS(G11, H11)) -> 12 | J11: 46237 | K11: =IF(OR(H11="", J11=""), "", NETWORKDAYS(H11, J11)) -> 2 | L11: 2026-08-03 | M11: =IF(OR(J11="", L11=""), "", NETWORKDAYS(J11, L11)) -> 1 | N11: Transport bagages SAMBATRA suite rapatriement# DEVIS N° 058 DU 13/06/2026 | O11: RAHANTAMALALA FANJANIRINA SYLVIENE | P11: USD | Q11: 326.08696 | R11: 326.08696 | S11: =Q11-R11 -> 0 | V11: =IF(Q11="", "", Q11*10%) -> 32.608696 | W11: =IF(OR(Q11="", R11=""), "", (Q11- R11)/Q11) -> 0
B12: 8 | C12: Madagascar | D12: 136154 | E12: Yes | F12: 139090 | G12: 46220 | H12: 2026-07-31 | I12: =IF(OR(H12="", G12=""), "", NETWORKDAYS(G12, H12)) -> 11 | J12: 46237 | K12: =IF(OR(H12="", J12=""), "", NETWORKDAYS(H12, J12)) -> 2 | L12: 2026-08-03 | M12: =IF(OR(J12="", L12=""), "", NETWORKDAYS(J12, L12)) -> 1 | N12: RSE - Page RSE Yas dans le magazine EcoAustral | O12: EDITIONS AUSTRALES INTERNATIONALES LTD | P12: USD | Q12: 1408.6957 | R12: 1408.6957 | S12: =Q12-R12 -> 0 | V12: =IF(Q12="", "", Q12*10%) -> 140.86957 | W12: =IF(OR(Q12="", R12=""), "", (Q12- R12)/Q12) -> 0
B13: 9 | C13: Madagascar | D13: 136202 | E13: Yes | F13: 139078 | G13: 46221 | H13: 2026-08-05 | I13: =IF(OR(H13="", G13=""), "", NETWORKDAYS(G13, H13)) -> 13 | J13: 46240 | K13: =IF(OR(H13="", J13=""), "", NETWORKDAYS(H13, J13)) -> 2 | L13: 2026-08-06 | M13: =IF(OR(J13="", L13=""), "", NETWORKDAYS(J13, L13)) -> 1 | N13: DAET 13748 | O13: EASY NETCOM | P13: USD | Q13: 2591.3043 | R13: 2591.3043 | S13: =Q13-R13 -> 0 | V13: =IF(Q13="", "", Q13*10%) -> 259.13043 | W13: =IF(OR(Q13="", R13=""), "", (Q13- R13)/Q13) -> 0
B14: 10 | C14: Madagascar | D14: 136211 | E14: Yes | F14: 139076 | G14: 46234 | H14: 2026-08-05 | I14: =IF(OR(H14="", G14=""), "", NETWORKDAYS(G14, H14)) -> 4 | J14: 46240 | K14: =IF(OR(H14="", J14=""), "", NETWORKDAYS(H14, J14)) -> 2 | L14: 2026-08-06 | M14: =IF(OR(J14="", L14=""), "", NETWORKDAYS(J14, L14)) -> 1 | N14: DAET 13731/13730/13746/13751/13802/13747/13752/13803 | O14: EASY NETCOM | P14: USD | Q14: 2893.4783 | R14: 2893.4783 | S14: =Q14-R14 -> 0 | V14: =IF(Q14="", "", Q14*10%) -> 289.34783 | W14: =IF(OR(Q14="", R14=""), "", (Q14- R14)/Q14) -> 0
B15: 11 | C15: Madagascar | D15: 136212 | E15: Yes | F15: 139077 | G15: 46234 | H15: 2026-08-05 | I15: =IF(OR(H15="", G15=""), "", NETWORKDAYS(G15, H15)) -> 4 | J15: 46240 | K15: =IF(OR(H15="", J15=""), "", NETWORKDAYS(H15, J15)) -> 2 | L15: 2026-08-06 | M15: =IF(OR(J15="", L15=""), "", NETWORKDAYS(J15, L15)) -> 1 | N15: DAET 13732 | O15: EASY NETCOM | P15: USD | Q15: 1629.4783 | R15: 1629.4783 | S15: =Q15-R15 -> 0 | V15: =IF(Q15="", "", Q15*10%) -> 162.94783 | W15: =IF(OR(Q15="", R15=""), "", (Q15- R15)/Q15) -> 0
B16: 12 | C16: Madagascar | D16: 136213 | E16: Yes | F16: 139081 | G16: 46234 | H16: 2026-08-05 | I16: =IF(OR(H16="", G16=""), "", NETWORKDAYS(G16, H16)) -> 4 | J16: 46240 | K16: =IF(OR(H16="", J16=""), "", NETWORKDAYS(H16, J16)) -> 2 | L16: 2026-08-06 | M16: =IF(OR(J16="", L16=""), "", NETWORKDAYS(J16, L16)) -> 1 | N16: DAET 13749/13750/13754 | O16: EASY NETCOM | P16: USD | Q16: 1748.6957 | R16: 1748.6957 | S16: =Q16-R16 -> 0 | V16: =IF(Q16="", "", Q16*10%) -> 174.86957 | W16: =IF(OR(Q16="", R16=""), "", (Q16- R16)/Q16) -> 0
B17: 13 | C17: Madagascar | D17: 136214 | E17: Yes | F17: 139079 | G17: 46234 | H17: 2026-08-05 | I17: =IF(OR(H17="", G17=""), "", NETWORKDAYS(G17, H17)) -> 4 | J17: 46240 | K17: =IF(OR(H17="", J17=""), "", NETWORKDAYS(H17, J17)) -> 2 | L17: 2026-08-06 | M17: =IF(OR(J17="", L17=""), "", NETWORKDAYS(J17, L17)) -> 1 | N17: DAET 13731/13730/13746/13751/13802/13747/13752/13803 | O17: EASY NETCOM | P17: USD | Q17: 2802.587 | R17: 2802.587 | S17: =Q17-R17 -> 0 | V17: =IF(Q17="", "", Q17*10%) -> 280.2587 | W17: =IF(OR(Q17="", R17=""), "", (Q17- R17)/Q17) -> 0
... B20: 16 | C20: Madagascar | D20: 136221 | E20: No | F20: 139102 | G20: 46234 | H20: 2026-08-05 | I20: =IF(OR(H20="", G20=""), "", NETWORKDAYS(G20, H20)) -> 4 | J20: 46241 | K20: =IF(OR(H20="", J20=""), "", NETWORKDAYS(H20, J20)) -> 3 | L20: 2026-08-07 | M20: =IF(OR(J20="", L20=""), "", NETWORKDAYS(J20, L20)) -> 1 | N20: DAET 13738/13757 | O20: PRIMA CE SARLU | P20: USD | Q20: 1928.1304 | R20: 1928.1304 | S20: =Q20-R20 -> 0 | V20: =IF(Q20="", "", Q20*10%) -> 192.81304 | W20: =IF(OR(Q20="", R20=""), "", (Q20- R20)/Q20) -> 0
B21: 17 | C21: Madagascar | D21: 136508 | E21: Yes | F21: 139093 | G21: 46220 | H21: 2026-07-20 | I21: =IF(OR(H21="", G21=""), "", NETWORKDAYS(G21, H21)) -> 2 | J21: 46230 | K21: =IF(OR(H21="", J21=""), "", NETWORKDAYS(H21, J21)) -> 6 | L21: 46234 | M21: =IF(OR(J21="", L21=""), "", NETWORKDAYS(J21, L21)) -> 5 | N21: Gant de manutention | O21: ALL TRADE SARLU | P21: USD | Q21: 91.304348 | R21: 91.304348 | S21: =Q21-R21 -> 0 | V21: =IF(Q21="", "", Q21*10%) -> 9.1304348 | W21: =IF(OR(Q21="", R21=""), "", (Q21- R21)/Q21) -> 0
B22: 18 | C22: Madagascar | D22: 136284 | E22: Yes | F22: 139125 | G22: 46234 | H22: 2026-08-13 | I22: =IF(OR(H22="", G22=""), "", NETWORKDAYS(G22, H22)) -> 10 | J22: 46247 | K22: =IF(OR(H22="", J22=""), "", NETWORKDAYS(H22, J22)) -> 1 | L22: 2026-08-13 | M22: =IF(OR(J22="", L22=""), "", NETWORKDAYS(J22, L22)) -> 1 | N22: RSE - Vérification technique avant travaux MDN Antsirabe | O22: SOCOTEC MADAGASCAR | P22: USD | Q22: 2510.8696 | R22: 2510.8696 | S22: =Q22-R22 -> 0 | V22: =IF(Q22="", "", Q22*10%) -> 251.08696 | W22: =IF(OR(Q22="", R22=""), "", (Q22- R22)/Q22) -> 0
B23: 19 | C23: Madagascar | D23: 136131 | E23: Yes | F23: 139161 | G23: 46224 | H23: 2026-07-30 | I23: =IF(OR(H23="", G23=""), "", NETWORKDAYS(G23, H23)) -> 8 | J23: 46237 | K23: =IF(OR(H23="", J23=""), "", NETWORKDAYS(H23, J23)) -> 3 | L23: 2026-08-03 | M23: =IF(OR(J23="", L23=""), "", NETWORKDAYS(J23, L23)) -> 1 | N23: Agents Intérimaires KYC | O23: LCS CONSULTING | P23: USD | Q23: 2287.0435 | R23: 2287.0435 | S23: =Q23-R23 -> 0 | V23: =IF(Q23="", "", Q23*10%) -> 228.70435 | W23: =IF(OR(Q23="", R23=""), "", (Q23- R23)/Q23) -> 0
B24: 20 | C24: Madagascar | D24: 136153 | E24: Yes | F24: 139145 | G24: 46224 | H24: 2026-07-31 | I24: =IF(OR(H24="", G24=""), "", NETWORKDAYS(G24, H24)) -> 9 | J24: 46237 | K24: =IF(OR(H24="", J24=""), "", NETWORKDAYS(H24, J24)) -> 2 | L24: 2026-08-03 | M24: =IF(OR(J24="", L24=""), "", NETWORKDAYS(J24, L24)) -> 1 | N24: Prestation intérimaire: 01 NOC Spécialist HC pour 4 mois (annulation BC n°135794)# DEVIS N°2873 | O24: MADAJOB | P24: USD | Q24: 573.28261 | R24: 573.28261 | S24: =Q24-R24 -> 0 | V24: =IF(Q24="", "", Q24*10%) -> 57.328261 | W24: =IF(OR(Q24="", R24=""), "", (Q24- R24)/Q24) -> 0
B25: 21 | C25: Madagascar | D25: 136506 | E25: Yes | F25: 139143 | G25: 46224 | H25: 2026-07-21 | I25: =IF(OR(H25="", G25=""), "", NETWORKDAYS(G25, H25)) -> 1 | J25: 46230 | K25: =IF(OR(H25="", J25=""), "", NETWORKDAYS(H25, J25)) -> 5 | L25: 46230 | M25: =IF(OR(J25="", L25=""), "", NETWORKDAYS(J25, L25)) -> 1 | N25: Calibration équipements de mesure HSE | O25: BCL (BUREAU DE CONTROLE LABOTECH) | P25: USD | Q25: 2760.8696 | R25: 2760.8696 | S25: =Q25-R25 -> 0 | V25: =IF(Q25="", "", Q25*10%) -> 276.08696 | W25: =IF(OR(Q25="", R25=""), "", (Q25- R25)/Q25) -> 0
B26: 22 | C26: Madagascar | D26: 136258 | E26: Yes | F26: 139202 | G26: 46225 | H26: 2026-07-23 | I26: =IF(OR(H26="", G26=""), "", NETWORKDAYS(G26, H26)) -> 2 | J26: 46241 | K26: =IF(OR(H26="", J26=""), "", NETWORKDAYS(H26, J26)) -> 12 | L26: 2026-08-10 | M26: =IF(OR(J26="", L26=""), "", NETWORKDAYS(J26, L26)) -> 2 | N26: Accompagnement 5S des dépôt AGL et ADV | O26: SUSTAINABLE MANAGEMENT SYSTEMS CONSULTING | P26: USD | Q26: 3710.9301 | R26: 3695.6522 | S26: =Q26-R26 -> 15.277899 | V26: =IF(Q26="", "", Q26*10%) -> 371.09301 | W26: =IF(OR(Q26="", R26=""), "", (Q26- R26)/Q26) -> 0.004117
B27: 23 | C27: Madagascar | D27: 136081 | E27: Yes | F27: 139174 | G27: 46225 | H27: 2026-07-31 | I27: =IF(OR(H27="", G27=""), "", NETWORKDAYS(G27, H27)) -> 8 | J27: 46237 | K27: =IF(OR(H27="", J27=""), "", NETWORKDAYS(H27, J27)) -> 2 | L27: 2026-08-03 | M27: =IF(OR(J27="", L27=""), "", NETWORKDAYS(J27, L27)) -> 1 | N27: Prestation intérimaire: 582 AR Terrain en Axe Régions pour 2 mois# FACTURE PROFORMA N°356-A/FP/TELMA /2026 DU 17/07/2026 | O27: LCS CONSULTING | P27: USD | Q27: 102153.65 | R27: 102153.65 | S27: =Q27-R27 -> 0 | V27: =IF(Q27="", "", Q27*10%) -> 10215.365 | W27: =IF(OR(Q27="", R27=""), "", (Q27- R27)/Q27) -> 0
B28: 24 | C28: Madagascar | D28: 136082 | E28: No | F28: 139206 | G28: 46225 | H28: 2026-07-30 | I28: =IF(OR(H28="", G28=""), "", NETWORKDAYS(G28, H28)) -> 7 | J28: 46237 | K28: =IF(OR(H28="", J28=""), "", NETWORKDAYS(H28, J28)) -> 3 | L28: 2026-08-03 | M28: =IF(OR(J28="", L28=""), "", NETWORKDAYS(J28, L28)) -> 1 | N28: REMBOURSEMENT IM AR & FRAIS COLIS & IM ADV | O28: LCS CONSULTING | P28: USD | Q28: 2027.2989 | R28: 2027.2989 | S28: =Q28-R28 -> 0 | V28: =IF(Q28="", "", Q28*10%) -> 202.72989 | W28: =IF(OR(Q28="", R28=""), "", (Q28- R28)/Q28) -> 0
B29: 25 | C29: Madagascar | D29: 136083 | E29: Yes | F29: 139190 | G29: 46225 | H29: 2026-07-31 | I29: =IF(OR(H29="", G29=""), "", NETWORKDAYS(G29, H29)) -> 8 | J29: 46237 | K29: =IF(OR(H29="", J29=""), "", NETWORKDAYS(H29, J29)) -> 2 | L29: 2026-08-03 | M29: =IF(OR(J29="", L29=""), "", NETWORKDAYS(J29, L29)) -> 1 | N29: Prestation intérimaire: 01 Analyste Fonctionnel VE pour 2 mois# FACTURE PROFORMA N°366-A/FP/TELMA/2026 DU 17/07/2026 | O29: LCS CONSULTING | P29: USD | Q29: 488.65217 | R29: 488.65217 | S29: =Q29-R29 -> 0 | V29: =IF(Q29="", "", Q29*10%) -> 48.865217 | W29: =IF(OR(Q29="", R29=""), "", (Q29- R29)/Q29) -> 0
B30: 26 | C30: Madagascar | D30: 136084 | E30: Yes | F30: 139173 | G30: 46225 | H30: 2026-07-31 | I30: =IF(OR(H30="", G30=""), "", NETWORKDAYS(G30, H30)) -> 8 | J30: 46237 | K30: =IF(OR(H30="", J30=""), "", NETWORKDAYS(H30, J30)) -> 2 | L30: 2026-08-03 | M30: =IF(OR(J30="", L30=""), "", NETWORKDAYS(J30, L30)) -> 1 | N30: Prestation intérimaire: 75 AR Roadshow pour 2 mois# FACTURE PROFORMA N°355-A/FP/TELMA /2026 DU 17/07/2026 | O30: LCS CONSULTING | P30: USD | Q30: 13164.13 | R30: 13164.13 | S30: =Q30-R30 -> 0 | V30: =IF(Q30="", "", Q30*10%) -> 1316.413 | W30: =IF(OR(Q30="", R30=""), "", (Q30- R30)/Q30) -> 0
B31: 27 | C31: Madagascar | D31: 136085 | E31: No | F31: 139200 | G31: 46225 | H31: 2026-07-28 | I31: =IF(OR(H31="", G31=""), "", NETWORKDAYS(G31, H31)) -> 5 | J31: 46237 | K31: =IF(OR(H31="", J31=""), "", NETWORKDAYS(H31, J31)) -> 5 | L31: 2026-08-03 | M31: =IF(OR(J31="", L31=""), "", NETWORKDAYS(J31, L31)) -> 1 | N31: COLLATION LE 24/07/2026 | O31: SOCIETE DE GESTION ET EXPLOITATION DE M/CAR | P31: USD | Q31: 26.086957 | R31: 26.086957 | S31: =Q31-R31 -> 0 | V31: =IF(Q31="", "", Q31*10%) -> 2.6086957 | W31: =IF(OR(Q31="", R31=""), "", (Q31- R31)/Q31) -> 0
B32: 28 | C32: Madagascar | D32: 136132 | E32: Yes | F32: 139194 | G32: 46231 | H32: 2026-07-31 | I32: =IF(OR(H32="", G32=""), "", NETWORKDAYS(G32, H32)) -> 4 | J32: 46237 | K32: =IF(OR(H32="", J32=""), "", NETWORKDAYS(H32, J32)) -> 2 | L32: 2026-08-03 | M32: =IF(OR(J32="", L32=""), "", NETWORKDAYS(J32, L32)) -> 1 | N32: Prestation intérimaire: IM 66 AR Terrain en Siège pour 2 mois# FACTURE PROFORMA N° 376-A/FP/TELMA /2026 du 17/07/2026 | O32: LCS CONSULTING | P32: USD | Q32: 5229.7826 | R32: 5229.7826 | S32: =Q32-R32 -> 0 | V32: =IF(Q32="", "", Q32*10%) -> 522.97826 | W32: =IF(OR(Q32="", R32=""), "", (Q32- R32)/Q32) -> 0
B33: 29 | C33: Madagascar | D33: 136133 | E33: Yes | F33: 139193 | G33: 46231 | H33: 2026-07-31 | I33: =IF(OR(H33="", G33=""), "", NETWORKDAYS(G33, H33)) -> 4 | J33: 46237 | K33: =IF(OR(H33="", J33=""), "", NETWORKDAYS(H33, J33)) -> 2 | L33: 2026-08-03 | M33: =IF(OR(J33="", L33=""), "", NETWORKDAYS(J33, L33)) -> 1 | N33: Prestation intérimaire: IM 37 CT Tanà et Régions pour 2 mois# FACTURE PROFORMA N° 375-A/FP/TELMA /2026 DU 17/07/2026 | O33: LCS CONSULTING | P33: USD | Q33: 7721.7391 | R33: 7721.7391 | S33: =Q33-R33 -> 0 | V33: =IF(Q33="", "", Q33*10%) -> 772.17391 | W33: =IF(OR(Q33="", R33=""), "", (Q33- R33)/Q33) -> 0
B34: 30 | C34: Madagascar | D34: 136134 | E34: Yes | F34: 139192 | G34: 46231 | H34: 2026-07-31 | I34: =IF(OR(H34="", G34=""), "", NETWORKDAYS(G34, H34)) -> 4 | J34: 46237 | K34: =IF(OR(H34="", J34=""), "", NETWORKDAYS(H34, J34)) -> 2 | L34: 2026-08-03 | M34: =IF(OR(J34="", L34=""), "", NETWORKDAYS(J34, L34)) -> 1 | N34: Prestation intérimaire: IM 75 AR Roadshow Régions pour 2 mois# FACTURE PROFORMA N°374-A/FP/TELMA/2026 DU 17/07/2026 | O34: LCS CONSULTING | P34: USD | Q34: 11885.87 | R34: 11885.87 | S34: =Q34-R34 -> 0 | V34: =IF(Q34="", "", Q34*10%) -> 1188.587 | W34: =IF(OR(Q34="", R34=""), "", (Q34- R34)/Q34) -> 0
B35: 31 | C35: Madagascar | D35: 136135 | E35: Yes | F35: 139191 | G35: 46231 | H35: 2026-07-31 | I35: =IF(OR(H35="", G35=""), "", NETWORKDAYS(G35, H35)) -> 4 | J35: 46237 | K35: =IF(OR(H35="", J35=""), "", NETWORKDAYS(H35, J35)) -> 2 | L35: 2026-08-03 | M35: =IF(OR(J35="", L35=""), "", NETWORKDAYS(J35, L35)) -> 1 | N35: Prestation intérimaire: IM 05 AR Micro Régions pour 2 mois# FACTURE PROFORMA N°373-A/FP/TELMA /2026 DU 17/07/2026 | O35: LCS CONSULTING | P35: USD | Q35: 792.3913 | R35: 792.3913 | S35: =Q35-R35 -> 0 | V35: =IF(Q35="", "", Q35*10%) -> 79.23913 | W35: =IF(OR(Q35="", R35=""), "", (Q35- R35)/Q35) -> 0
B36: 32 | C36: Madagascar | D36: 136136 | E36: Yes | F36: 139189 | G36: 46231 | H36: 2026-07-31 | I36: =IF(OR(H36="", G36=""), "", NETWORKDAYS(G36, H36)) -> 4 | J36: 46237 | K36: =IF(OR(H36="", J36=""), "", NETWORKDAYS(H36, J36)) -> 2 | L36: 2026-08-03 | M36: =IF(OR(J36="", L36=""), "", NETWORKDAYS(J36, L36)) -> 1 | N36: Prestation intérimaire: Logement 22 Tech Pol pour 2 mois# FACTURE PROFORMA N°372-A/FP/TELMA/2026 DU 17/07/2026 | O36: LCS CONSULTING | P36: USD | Q36: 827 | R36: 827 | S36: =Q36-R36 -> 0 | V36: =IF(Q36="", "", Q36*10%) -> 82.7 | W36: =IF(OR(Q36="", R36=""), "", (Q36- R36)/Q36) -> 0
B37: 33 | C37: Madagascar | D37: 136137 | E37: Yes | F37: 139188 | G37: 46231 | H37: 2026-07-31 | I37: =IF(OR(H37="", G37=""), "", NETWORKDAYS(G37, H37)) -> 4 | J37: 46237 | K37: =IF(OR(H37="", J37=""), "", NETWORKDAYS(H37, J37)) -> 2 | L37: 2026-08-03 | M37: =IF(OR(J37="", L37=""), "", NETWORKDAYS(J37, L37)) -> 1 | N37: Prestation intérimaire: 23 Tech Pol pour 2 mois# FACTURE PROFORMA N°371-A/FP/TELMA/2026 du 17/07/2026 | O37: LCS CONSULTING | P37: USD | Q37: 10944 | R37: 10944 | S37: =Q37-R37 -> 0 | V37: =IF(Q37="", "", Q37*10%) -> 1094.4 | W37: =IF(OR(Q37="", R37=""), "", (Q37- R37)/Q37) -> 0
... B132: 130 | C132: Madagascar | D132: 136271 | E132: Yes | F132: 139327 | G132: 46233 | H132: 2026-08-05 | I132: =IF(OR(H132="", G132=""), "", NETWORKDAYS(G132, H132)) -> 5 | J132: 46245 | K132: =IF(OR(H132="", J132=""), "", NETWORKDAYS(H132, J132)) -> 5 | L132: 2026-08-11 | M132: =IF(OR(J132="", L132=""), "", NETWORKDAYS(J132, L132)) -> 1 | N132: Transport et Manut 50 Poteaux ANTALAHA vers SAMBAVA | O132: LUCKKY COMPANY | P132: USD | Q132: 652.17391 | R132: 652.17391 | S132: =Q132-R132 -> 0 | V132: =IF(Q132="", "", Q132*10%) -> 65.217391 | W132: =IF(OR(Q132="", R132=""), "", (Q132- R132)/Q132) -> 0
B133: 131 | C133: Madagascar | D133: 136545 | E133: Yes | F133: 139332 | G133: 46233 | H133: 2026-08-05 | I133: =IF(OR(H133="", G133=""), "", NETWORKDAYS(G133, H133)) -> 5 | J133: 46242 | K133: =IF(OR(H133="", J133=""), "", NETWORKDAYS(H133, J133)) -> 3 | L133: 46244 | M133: =IF(OR(J133="", L133=""), "", NETWORKDAYS(J133, L133)) -> 1 | N133: BLACK BOX COMPLEMENTAIRE BC135734 | O133: BLACK BOX | P133: USD | Q133: 1743.3 | R133: 1743.3 | S133: =Q133-R133 -> 0 | V133: =IF(Q133="", "", Q133*10%) -> 174.33 | W133: =IF(OR(Q133="", R133=""), "", (Q133- R133)/Q133) -> 0
B134: 132 | C134: Madagascar | D134: 136078 | E134: Yes | F134: 139362 | G134: 46234 | H134: 2026-08-03 | I134: =IF(OR(H134="", G134=""), "", NETWORKDAYS(G134, H134)) -> 2 | J134: 46237 | K134: =IF(OR(H134="", J134=""), "", NETWORKDAYS(H134, J134)) -> 1 | L134: 2026-08-03 | M134: =IF(OR(J134="", L134=""), "", NETWORKDAYS(J134, L134)) -> 1 | N134: Location LCD-Mission Tafita à Mahanoro 05 au 12 Août 2026 | O134: LOXEA MADAGASCAR | P134: USD | Q134: 573.91304 | R134: 552.17391 | S134: =Q134-R134 -> 21.73913 | V134: =IF(Q134="", "", Q134*10%) -> 57.391304 | W134: =IF(OR(Q134="", R134=""), "", (Q134- R134)/Q134) -> 0.037878788
B135: 133 | C135: Madagascar | D135: 136079 | E135: Yes | F135: 139295 | G135: 46234 | H135: 2026-08-03 | I135: =IF(OR(H135="", G135=""), "", NETWORKDAYS(G135, H135)) -> 2 | J135: 46237 | K135: =IF(OR(H135="", J135=""), "", NETWORKDAYS(H135, J135)) -> 1 | L135: 2026-08-03 | M135: =IF(OR(J135="", L135=""), "", NETWORKDAYS(J135, L135)) -> 1 | N135: Achat 15000 Enveloppes GM En tête pour facturation | O135: MEGAPRINT | P135: USD | Q135: 465.34526 | R135: 398.97698 | S135: =Q135-R135 -> 66.368283 | V135: =IF(Q135="", "", Q135*10%) -> 46.534526 | W135: =IF(OR(Q135="", R135=""), "", (Q135- R135)/Q135) -> 0.14262159
B136: 134 | C136: Madagascar | D136: 136089 | E136: No | F136: 139357 | G136: 46234 | H136: 2026-07-31 | I136: =IF(OR(H136="", G136=""), "", NETWORKDAYS(G136, H136)) -> 1 | J136: 46237 | K136: =IF(OR(H136="", J136=""), "", NETWORKDAYS(H136, J136)) -> 2 | L136: 2026-08-03 | M136: =IF(OR(J136="", L136=""), "", NETWORKDAYS(J136, L136)) -> 1 | N136: HOUSSE CHAPITEAU | O136: MORA MARKET | P136: USD | Q136: 1762.5 | R136: 1762.5 | S136: =Q136-R136 -> 0 | V136: =IF(Q136="", "", Q136*10%) -> 176.25 | W136: =IF(OR(Q136="", R136=""), "", (Q136- R136)/Q136) -> 0
B137: 135 | C137: Madagascar | D137: 136087 | E137: Yes | F137: 139363 | G137: 46234 | H137: 2026-07-31 | I137: =IF(OR(H137="", G137=""), "", NETWORKDAYS(G137, H137)) -> 1 | J137: 46237 | K137: =IF(OR(H137="", J137=""), "", NETWORKDAYS(H137, J137)) -> 2 | L137: 2026-08-03 | M137: =IF(OR(J137="", L137=""), "", NETWORKDAYS(J137, L137)) -> 1 | N137: FESTIVAL SOROGNO 2026 | O137: ONG SOROGNO | P137: USD | Q137: 8695.6522 | R137: 8695.6522 | S137: =Q137-R137 -> 0 | V137: =IF(Q137="", "", Q137*10%) -> 869.56522 | W137: =IF(OR(Q137="", R137=""), "", (Q137- R137)/Q137) -> 0
B138: 136 | C138: Madagascar | D138: 136094 | E138: Yes | F138: 139356 | G138: 46234 | H138: 2026-07-31 | I138: =IF(OR(H138="", G138=""), "", NETWORKDAYS(G138, H138)) -> 1 | J138: 46237 | K138: =IF(OR(H138="", J138=""), "", NETWORKDAYS(H138, J138)) -> 2 | L138: 2026-08-03 | M138: =IF(OR(J138="", L138=""), "", NETWORKDAYS(J138, L138)) -> 1 | N138: ACHAT MOTO | O138: MADAGASCAR AUTOMOBILE | P138: USD | Q138: 1543.4783 | R138: 1543.4783 | S138: =Q138-R138 -> 0 | V138: =IF(Q138="", "", Q138*10%) -> 154.34783 | W138: =IF(OR(Q138="", R138=""), "", (Q138- R138)/Q138) -> 0
B139: 137 | C139: Madagascar | D139: 136095 | E139: Yes | F139: 139355 | G139: 46234 | H139: 2026-07-31 | I139: =IF(OR(H139="", G139=""), "", NETWORKDAYS(G139, H139)) -> 1 | J139: 46237 | K139: =IF(OR(H139="", J139=""), "", NETWORKDAYS(H139, J139)) -> 2 | L139: 2026-08-03 | M139: =IF(OR(J139="", L139=""), "", NETWORKDAYS(J139, L139)) -> 1 | N139: ACHAT MOTO | O139: MADAGASCAR AUTOMOBILE | P139: USD | Q139: 2630.4348 | R139: 2630.4348 | S139: =Q139-R139 -> 0 | V139: =IF(Q139="", "", Q139*10%) -> 263.04348 | W139: =IF(OR(Q139="", R139=""), "", (Q139- R139)/Q139) -> 0
B140: 138 | C140: Madagascar | D140: 136169 | E140: Yes | F140: 139367 | G140: 46234 | H140: 2026-08-03 | I140: =IF(OR(H140="", G140=""), "", NETWORKDAYS(G140, H140)) -> 2 | J140: 46238 | K140: =IF(OR(H140="", J140=""), "", NETWORKDAYS(H140, J140)) -> 2 | L140: 2026-08-06 | M140: =IF(OR(J140="", L140=""), "", NETWORKDAYS(J140, L140)) -> 3 | N140: COFI 2026 - VOITURE GRS GASI PRO | O140: CFAO MOBILITY MADAGASCAR | P140: USD | Q140: 24456.522 | R140: 24456.522 | S140: =Q140-R140 -> 0 | V140: =IF(Q140="", "", Q140*10%) -> 2445.6522 | W140: =IF(OR(Q140="", R140=""), "", (Q140- R140)/Q140) -> 0
B141: 139 | C141: Madagascar | D141: 136171 | E141: Yes | F141: 139366 | G141: 46234 | H141: 2026-08-03 | I141: =IF(OR(H141="", G141=""), "", NETWORKDAYS(G141, H141)) -> 2 | J141: 46238 | K141: =IF(OR(H141="", J141=""), "", NETWORKDAYS(H141, J141)) -> 2 | L141: 2026-08-04 | M141: =IF(OR(J141="", L141=""), "", NETWORKDAYS(J141, L141)) -> 1 | N141: ENTRETIEN MOTO - FORT DAUPHIN | O141: RANDRIAMBAO Vola(MADA SCOOT RACING | P141: USD | Q141: 259.78261 | R141: 259.78261 | S141: =Q141-R141 -> 0 | V141: =IF(Q141="", "", Q141*10%) -> 25.978261 | W141: =IF(OR(Q141="", R141=""), "", (Q141- R141)/Q141) -> 0
B142: 140 | C142: Madagascar | D142: 136183 | E142: Yes | F142: 139354 | G142: 46234 | H142: 2026-08-04 | I142: =IF(OR(H142="", G142=""), "", NETWORKDAYS(G142, H142)) -> 3 | J142: 46239 | K142: =IF(OR(H142="", J142=""), "", NETWORKDAYS(H142, J142)) -> 2 | L142: 2026-08-05 | M142: =IF(OR(J142="", L142=""), "", NETWORKDAYS(J142, L142)) -> 1 | N142: ACHAT MOTO | O142: MADAGASCAR AUTOMOBILE | P142: USD | Q142: 24695.652 | R142: 24695.652 | S142: =Q142-R142 -> 0 | V142: =IF(Q142="", "", Q142*10%) -> 2469.5652 | W142: =IF(OR(Q142="", R142=""), "", (Q142- R142)/Q142) -> 0
B143: 141 | C143: Madagascar | D143: 136210 | E143: Yes | F143: 139364 | G143: 46234 | H143: 2026-08-04 | I143: =IF(OR(H143="", G143=""), "", NETWORKDAYS(G143, H143)) -> 3 | J143: 46240 | K143: =IF(OR(H143="", J143=""), "", NETWORKDAYS(H143, J143)) -> 3 | L143: 2026-08-06 | M143: =IF(OR(J143="", L143=""), "", NETWORKDAYS(J143, L143)) -> 1 | N143: ENVOI CHAUFFEURS POUR SOMAROHO | O143: OCEAN TRADE CO | P143: USD | Q143: 478.26087 | R143: 478.26087 | S143: =Q143-R143 -> 0 | V143: =IF(Q143="", "", Q143*10%) -> 47.826087 | W143: =IF(OR(Q143="", R143=""), "", (Q143- R143)/Q143) -> 0
B144: 142 | C144: Madagascar | D144: 136224 | E144: Yes | F144: 139359 | G144: 46234 | H144: 2026-08-05 | I144: =IF(OR(H144="", G144=""), "", NETWORKDAYS(G144, H144)) -> 4 | J144: 46241 | K144: =IF(OR(H144="", J144=""), "", NETWORKDAYS(H144, J144)) -> 3 | L144: 2026-08-07 | M144: =IF(OR(J144="", L144=""), "", NETWORKDAYS(J144, L144)) -> 1 | N144: Transport et manut 200 poteaux TANA vers MAHAJANGA | O144: MADAGASCAR LOGISTICS ET SERVICES | P144: USD | Q144: 2913.0435 | R144: 2913.0435 | S144: =Q144-R144 -> 0 | V144: =IF(Q144="", "", Q144*10%) -> 291.30435 | W144: =IF(OR(Q144="", R144=""), "", (Q144- R144)/Q144) -> 0
B145: 143 | C145: Madagascar | D145: 136243 | E145: Yes | F145: 139358 | G145: 46234 | H145: 2026-08-05 | I145: =IF(OR(H145="", G145=""), "", NETWORKDAYS(G145, H145)) -> 4 | J145: 46244 | K145: =IF(OR(H145="", J145=""), "", NETWORKDAYS(H145, J145)) -> 4 | L145: 2026-08-10 | M145: =IF(OR(J145="", L145=""), "", NETWORKDAYS(J145, L145)) -> 1 | N145: Transport et manut 200 poteaux TANA vers AMBANJ | O145: LUCKKY COMPANY | P145: USD | Q145: 3043.4783 | R145: 3043.4783 | S145: =Q145-R145 -> 0 | V145: =IF(Q145="", "", Q145*10%) -> 304.34783 | W145: =IF(OR(Q145="", R145=""), "", (Q145- R145)/Q145) -> 0
... B162: 160 | C162: Madagascar | D162: 136188 | E162: Yes | F162: 139392 | G162: 46237 | H162: 2026-08-04 | I162: =IF(OR(H162="", G162=""), "", NETWORKDAYS(G162, H162)) -> 2 | J162: 46239 | K162: =IF(OR(H162="", J162=""), "", NETWORKDAYS(H162, J162)) -> 2 | L162: 2026-08-05 | M162: =IF(OR(J162="", L162=""), "", NETWORKDAYS(J162, L162)) -> 1 | N162: Réparation moto 18892WWT(nettoyage carburateur...) | O162: Funbike Sarl | P162: USD | Q162: 28.396739 | R162: 28.396739 | S162: =Q162-R162 -> 0 | V162: =IF(Q162="", "", Q162*10%) -> 2.8396739 | W162: =IF(OR(Q162="", R162=""), "", (Q162- R162)/Q162) -> 0
B163: 161 | C163: Madagascar | D163: 136189 | E163: Yes | F163: 139388 | G163: 46237 | H163: 2026-08-04 | I163: =IF(OR(H163="", G163=""), "", NETWORKDAYS(G163, H163)) -> 2 | J163: 46239 | K163: =IF(OR(H163="", J163=""), "", NETWORKDAYS(H163, J163)) -> 2 | L163: 2026-08-05 | M163: =IF(OR(J163="", L163=""), "", NETWORKDAYS(J163, L163)) -> 1 | N163: Réparation moto 38477WWT | O163: Funbike Sarl | P163: USD | Q163: 28.75 | R163: 28.75 | S163: 109.06935 | V163: =IF(Q163="", "", Q163*10%) -> 2.875 | W163: =IF(OR(Q163="", R163=""), "", (Q163- R163)/Q163) -> 0
B164: 162 | C164: Madagascar | D164: 136287 | E164: Yes | F164: 139389 | G164: 46237 | H164: 2026-08-12 | I164: =IF(OR(H164="", G164=""), "", NETWORKDAYS(G164, H164)) -> 8 | J164: 46247 | K164: =IF(OR(H164="", J164=""), "", NETWORKDAYS(H164, J164)) -> 2 | L164: 2026-08-13 | M164: =IF(OR(J164="", L164=""), "", NETWORKDAYS(J164, L164)) -> 1 | N164: FESTIVAL DES BALEINES 2026 | O164: FESTIV | P164: USD | Q164: 1739.1304 | R164: 1739.1304 | S164: 144.04268 | V164: =IF(Q164="", "", Q164*10%) -> 173.91304 | W164: =IF(OR(Q164="", R164=""), "", (Q164- R164)/Q164) -> 0
B165: 163 | C165: Madagascar | D165: 136288 | E165: Yes | F165: 139371 | G165: 46237 | H165: 2026-08-12 | I165: =IF(OR(H165="", G165=""), "", NETWORKDAYS(G165, H165)) -> 8 | J165: 46247 | K165: =IF(OR(H165="", J165=""), "", NETWORKDAYS(H165, J165)) -> 2 | L165: 2026-08-13 | M165: =IF(OR(J165="", L165=""), "", NETWORKDAYS(J165, L165)) -> 1 | N165: TRANSPORT PLV YAS | O165: LUCKKY COMPANY | P165: USD | Q165: 173.91304 | R165: 173.91304 | S165: 0 | V165: =IF(Q165="", "", Q165*10%) -> 17.391304 | W165: =IF(OR(Q165="", R165=""), "", (Q165- R165)/Q165) -> 0
B166: 164 | C166: Madagascar | D166: 136289 | E166: Yes | F166: 139370 | G166: 46237 | H166: 2026-08-12 | I166: =IF(OR(H166="", G166=""), "", NETWORKDAYS(G166, H166)) -> 8 | J166: 46247 | K166: =IF(OR(H166="", J166=""), "", NETWORKDAYS(H166, J166)) -> 2 | L166: 2026-08-13 | M166: =IF(OR(J166="", L166=""), "", NETWORKDAYS(J166, L166)) -> 1 | N166: SPONSORING | O166: ROTARY | P166: USD | Q166: 1086.9565 | R166: 1086.9565 | S166: 0 | V166: =IF(Q166="", "", Q166*10%) -> 108.69565 | W166: =IF(OR(Q166="", R166=""), "", (Q166- R166)/Q166) -> 0
B167: 165 | C167: Madagascar | D167: 136292 | E167: Yes | F167: 139369 | G167: 46237 | H167: 2026-08-12 | I167: =IF(OR(H167="", G167=""), "", NETWORKDAYS(G167, H167)) -> 8 | J167: 46247 | K167: =IF(OR(H167="", J167=""), "", NETWORKDAYS(H167, J167)) -> 2 | L167: 2026-08-13 | M167: =IF(OR(J167="", L167=""), "", NETWORKDAYS(J167, L167)) -> 1 | N167: FESTIVAL DES BALEINES 2026 | O167: FLORA BEAUTY | P167: USD | Q167: 1304.3478 | R167: 1304.3478 | S167: 156859.24 | V167: =IF(Q167="", "", Q167*10%) -> 130.43478 | W167: =IF(OR(Q167="", R167=""), "", (Q167- R167)/Q167) -> 0
B168: 166 | C168: Madagascar | D168: 136365 | E168: Yes | F168: 139372 | G168: 46237 | H168: 2026-08-18 | I168: =IF(OR(H168="", G168=""), "", NETWORKDAYS(G168, H168)) -> 12 | J168: 46252 | K168: =IF(OR(H168="", J168=""), "", NETWORKDAYS(H168, J168)) -> 1 | L168: 2026-08-18 | M168: =IF(OR(J168="", L168=""), "", NETWORKDAYS(J168, L168)) -> 1 | N168: Transport bagages RAPHAEL suite affectation# N° Proforma : FP-2026-063 du 30/06/2026 | O168: RANDRIAMANARIVO NICOLAS | P168: USD | Q168: 413.04348 | R168: 413.04348 | S168: 0 | V168: =IF(Q168="", "", Q168*10%) -> 41.304348 | W168: =IF(OR(Q168="", R168=""), "", (Q168- R168)/Q168) -> 0
B169: 167 | C169: Madagascar | D169: 136195 | E169: Yes | F169: 139399 | G169: 46238 | H169: 2026-08-05 | I169: =IF(OR(H169="", G169=""), "", NETWORKDAYS(G169, H169)) -> 2 | J169: 46240 | K169: =IF(OR(H169="", J169=""), "", NETWORKDAYS(H169, J169)) -> 2 | L169: 2026-08-06 | M169: =IF(OR(J169="", L169=""), "", NETWORKDAYS(J169, L169)) -> 1 | N169: Maintenance et Consommables MP-LOT3 | O169: SMART TECHNOLOGIES ET ENGINEERING | P169: USD | Q169: 149937.08 | R169: 136306.44 | S169: 0 | V169: =IF(Q169="", "", Q169*10%) -> 14993.708 | W169: =IF(OR(Q169="", R169=""), "", (Q169- R169)/Q169) -> 0.090909091
B170: 168 | C170: Madagascar | D170: 136185 | E170: Yes | F170: 139410 | G170: 46238 | H170: 2026-08-04 | I170: =IF(OR(H170="", G170=""), "", NETWORKDAYS(G170, H170)) -> 1 | J170: 46239 | K170: =IF(OR(H170="", J170=""), "", NETWORKDAYS(H170, J170)) -> 2 | L170: 2026-08-05 | M170: =IF(OR(J170="", L170=""), "", NETWORKDAYS(J170, L170)) -> 1 | N170: Achat 200 Enveloppe GM blanche pour facturation | O170: MEGAPRINT | P170: USD | Q170: 75.882352 | R170: 65.984654 | S170: 0 | V170: =IF(Q170="", "", Q170*10%) -> 7.5882352 | W170: =IF(OR(Q170="", R170=""), "", (Q170- R170)/Q170) -> 0.13043478
B171: 169 | C171: Madagascar | D171: 136225 | E171: Yes | F171: 139420 | G171: 46238 | H171: 2026-08-05 | I171: =IF(OR(H171="", G171=""), "", NETWORKDAYS(G171, H171)) -> 2 | J171: 46241 | K171: =IF(OR(H171="", J171=""), "", NETWORKDAYS(H171, J171)) -> 3 | L171: 2026-08-10 | M171: =IF(OR(J171="", L171=""), "", NETWORKDAYS(J171, L171)) -> 2 | N171: 4G Capacity Expansion Q2-Q4 2026-TANA(Software) | O171: HUAWEI TECHNOLOGIES CO., LTD | P171: USD | Q171: 772629.37 | R171: 472289.69 | S171: 0 | V171: =IF(Q171="", "", Q171*10%) -> 77262.937 | W171: =IF(OR(Q171="", R171=""), "", (Q171- R171)/Q171) -> 0.38872413
B172: 170 | C172: Madagascar | D172: 136291 | E172: Yes | F172: 139393 | G172: 46238 | H172: 2026-08-12 | I172: =IF(OR(H172="", G172=""), "", NETWORKDAYS(G172, H172)) -> 7 | J172: 46247 | K172: =IF(OR(H172="", J172=""), "", NETWORKDAYS(H172, J172)) -> 2 | L172: 2026-08-13 | M172: =IF(OR(J172="", L172=""), "", NETWORKDAYS(J172, L172)) -> 1 | N172: SOMAROHO 2026 | O172: TSGV | P172: USD | Q172: 1712.6087 | R172: 1712.6087 | S172: 0 | V172: =IF(Q172="", "", Q172*10%) -> 171.26087 | W172: =IF(OR(Q172="", R172=""), "", (Q172- R172)/Q172) -> 0
B173: 171 | C173: Madagascar | D173: 136184 | E173: Yes | F173: 139419 | G173: 46238 | H173: 2026-08-04 | I173: =IF(OR(H173="", G173=""), "", NETWORKDAYS(G173, H173)) -> 1 | J173: 46239 | K173: =IF(OR(H173="", J173=""), "", NETWORKDAYS(H173, J173)) -> 2 | L173: 2026-08-05 | M173: =IF(OR(J173="", L173=""), "", NETWORKDAYS(J173, L173)) -> 1 | N173: Refacturation Modification et Frais Aerien Ahmad Famille | O173: VOYAGEXPERT | P173: USD | Q173: 2965.0725 | R173: 2965.0725 | S173: 0 | V173: =IF(Q173="", "", Q173*10%) -> 296.50725 | W173: =IF(OR(Q173="", R173=""), "", (Q173- R173)/Q173) -> 0
B174: 172 | C174: Madagascar | D174: 136194 | E174: Yes | F174: 139394 | G174: 46238 | H174: 2026-08-05 | I174: =IF(OR(H174="", G174=""), "", NETWORKDAYS(G174, H174)) -> 2 | J174: 46240 | K174: =IF(OR(H174="", J174=""), "", NETWORKDAYS(H174, J174)) -> 2 | L174: 2026-08-06 | M174: =IF(OR(J174="", L174=""), "", NETWORKDAYS(J174, L174)) -> 1 | N174: Maintenance et Consommables MP-LOT2 | O174: NEXTHOPE | P174: USD | Q174: 114437.95 | R174: 114437.95 | S174: 0 | V174: =IF(Q174="", "", Q174*10%) -> 11443.795 | W174: =IF(OR(Q174="", R174=""), "", (Q174- R174)/Q174) -> 0
... B183: 181 | C183: Madagascar | D183: 136233 | E183: Yes | F183: 139406 | G183: 46238 | H183: 2026-08-05 | I183: =IF(OR(H183="", G183=""), "", NETWORKDAYS(G183, H183)) -> 2 | J183: 46241 | K183: =IF(OR(H183="", J183=""), "", NETWORKDAYS(H183, J183)) -> 3 | L183: 2026-08-07 | M183: =IF(OR(J183="", L183=""), "", NETWORKDAYS(J183, L183)) -> 1 | N183: Maintenance Préventive LOT6(251 sites) | O183: NETWORK GENERAL SERVICE | P183: USD | Q183: 93321.582 | R183: 93321.582 | S183: 2494.3687 | V183: =IF(Q183="", "", Q183*10%) -> 9332.1582 | W183: =IF(OR(Q183="", R183=""), "", (Q183- R183)/Q183) -> 0
B184: 182 | C184: Madagascar | D184: 136237 | E184: Yes | F184: 139411 | G184: 46238 | H184: 2026-08-05 | I184: =IF(OR(H184="", G184=""), "", NETWORKDAYS(G184, H184)) -> 2 | J184: 46244 | K184: =IF(OR(H184="", J184=""), "", NETWORKDAYS(H184, J184)) -> 4 | L184: 2026-08-10 | M184: =IF(OR(J184="", L184=""), "", NETWORKDAYS(J184, L184)) -> 1 | N184: Transport des mobiliers -DOM Brickaville | O184: LUCKKY COMPANY | P184: USD | Q184: 271.73913 | R184: 271.73913 | S184: =Q184-R184 -> 0 | V184: =IF(Q184="", "", Q184*10%) -> 27.173913 | W184: =IF(OR(Q184="", R184=""), "", (Q184- R184)/Q184) -> 0
B185: 183 | C185: Madagascar | D185: 136238 | E185: Yes | F185: 139408 | G185: 46238 | H185: 2026-08-05 | I185: =IF(OR(H185="", G185=""), "", NETWORKDAYS(G185, H185)) -> 2 | J185: 46244 | K185: =IF(OR(H185="", J185=""), "", NETWORKDAYS(H185, J185)) -> 4 | L185: 2026-08-10 | M185: =IF(OR(J185="", L185=""), "", NETWORKDAYS(J185, L185)) -> 1 | N185: Maintenance et Consommables MP-LOT 05 | O185: H-TELI DRC SUCCURSALE MADAGASCAR | P185: USD | Q185: 38478.261 | R185: 38478.261 | S185: =Q185-R185 -> 0 | V185: =IF(Q185="", "", Q185*10%) -> 3847.8261 | W185: =IF(OR(Q185="", R185=""), "", (Q185- R185)/Q185) -> 0
B186: 184 | C186: Madagascar | D186: 136290 | E186: Yes | F186: 139395 | G186: 46238 | H186: 2026-08-12 | I186: =IF(OR(H186="", G186=""), "", NETWORKDAYS(G186, H186)) -> 7 | J186: 46247 | K186: =IF(OR(H186="", J186=""), "", NETWORKDAYS(H186, J186)) -> 2 | L186: 2026-08-13 | M186: =IF(OR(J186="", L186=""), "", NETWORKDAYS(J186, L186)) -> 1 | N186: Ambassadeur - MAMAN'I TSOLOLO | O186: MAMAN'I TSÔLÔLÔ | P186: USD | Q186: 2173.913 | R186: 2173.913 | S186: =Q186-R186 -> 0 | V186: =IF(Q186="", "", Q186*10%) -> 217.3913 | W186: =IF(OR(Q186="", R186=""), "", (Q186- R186)/Q186) -> 0
B187: 185 | C187: Madagascar | D187: 136302 | E187: Yes | F187: 139417 | G187: 46238 | H187: 2026-08-12 | I187: =IF(OR(H187="", G187=""), "", NETWORKDAYS(G187, H187)) -> 7 | J187: 46247 | K187: =IF(OR(H187="", J187=""), "", NETWORKDAYS(H187, J187)) -> 2 | L187: 2026-08-13 | M187: =IF(OR(J187="", L187=""), "", NETWORKDAYS(J187, L187)) -> 1 | N187: INFLUENCEUR - JE CROIS PAS | O187: IMPERIAL BEAUTE (Je crois pas) | P187: USD | Q187: 869.56522 | R187: 869.56522 | S187: =Q187-R187 -> 0 | V187: =IF(Q187="", "", Q187*10%) -> 86.956522 | W187: =IF(OR(Q187="", R187=""), "", (Q187- R187)/Q187) -> 0
B188: 186 | C188: Madagascar | D188: 136303 | E188: Yes | F188: 139415 | G188: 46238 | H188: 2026-08-12 | I188: =IF(OR(H188="", G188=""), "", NETWORKDAYS(G188, H188)) -> 7 | J188: 46247 | K188: =IF(OR(H188="", J188=""), "", NETWORKDAYS(H188, J188)) -> 2 | L188: 2026-08-13 | M188: =IF(OR(J188="", L188=""), "", NETWORKDAYS(J188, L188)) -> 1 | N188: SPONSORING | O188: ALLIANCE FRANCAISE D ANTANANARIVO | P188: USD | Q188: 5434.7826 | R188: 5434.7826 | S188: =Q188-R188 -> 0 | V188: =IF(Q188="", "", Q188*10%) -> 543.47826 | W188: =IF(OR(Q188="", R188=""), "", (Q188- R188)/Q188) -> 0
B189: 187 | C189: Madagascar | D189: 136315 | E189: Yes | F189: 139401 | G189: 46238 | H189: 2026-08-13 | I189: =IF(OR(H189="", G189=""), "", NETWORKDAYS(G189, H189)) -> 8 | J189: 46247 | K189: =IF(OR(H189="", J189=""), "", NETWORKDAYS(H189, J189)) -> 1 | L189: 2026-08-13 | M189: =IF(OR(J189="", L189=""), "", NETWORKDAYS(J189, L189)) -> 1 | N189: COMMANDE DVI 2026 | O189: GRANDE DISTRIBUTION SERVICE | P189: USD | Q189: 175000 | R189: 175000 | S189: =Q189-R189 -> 0 | V189: =IF(Q189="", "", Q189*10%) -> 17500 | W189: =IF(OR(Q189="", R189=""), "", (Q189- R189)/Q189) -> 0
B190: 188 | C190: Madagascar | D190: 136318 | E190: Yes | F190: 139407 | G190: 46238 | H190: 2026-08-04 | I190: =IF(OR(H190="", G190=""), "", NETWORKDAYS(G190, H190)) -> 1 | J190: 46247 | K190: =IF(OR(H190="", J190=""), "", NETWORKDAYS(H190, J190)) -> 8 | L190: 2026-08-13 | M190: =IF(OR(J190="", L190=""), "", NETWORKDAYS(J190, L190)) -> 1 | N190: Anémomètre portable | O190: GEKA TELECOM | P190: USD | Q190: 3217.5 | R190: 3217.5 | S190: =Q190-R190 -> 0 | V190: =IF(Q190="", "", Q190*10%) -> 321.75 | W190: =IF(OR(Q190="", R190=""), "", (Q190- R190)/Q190) -> 0
B191: 189 | C191: Madagascar | D191: 136366 | E191: Yes | F191: 139405 | G191: 46238 | H191: 2026-08-18 | I191: =IF(OR(H191="", G191=""), "", NETWORKDAYS(G191, H191)) -> 11 | J191: 46252 | K191: =IF(OR(H191="", J191=""), "", NETWORKDAYS(H191, J191)) -> 1 | L191: 2026-08-18 | M191: =IF(OR(J191="", L191=""), "", NETWORKDAYS(J191, L191)) -> 1 | N191: Transport bagages FRANCISCO suite affectation# DEVIS N° AR2607DIE0866982 DU 13/07/2026 | O191: COLIS EXPRESS | P191: USD | Q191: 184.17609 | R191: 184.17609 | S191: =Q191-R191 -> 0 | V191: =IF(Q191="", "", Q191*10%) -> 18.417609 | W191: =IF(OR(Q191="", R191=""), "", (Q191- R191)/Q191) -> 0
B192: 190 | C192: Madagascar | D192: 136199 | E192: Yes | F192: 139429 | G192: 46239 | H192: 2026-08-05 | I192: =IF(OR(H192="", G192=""), "", NETWORKDAYS(G192, H192)) -> 1 | J192: 46240 | K192: =IF(OR(H192="", J192=""), "", NETWORKDAYS(H192, J192)) -> 2 | L192: 2026-08-06 | M192: =IF(OR(J192="", L192=""), "", NETWORKDAYS(J192, L192)) -> 1 | N192: Régul factures JUIN2026 -équipe DTG | O192: VOYAGEXPERT | P192: USD | Q192: 10395.193 | R192: 10240.753 | S192: =Q192-R192 -> 154.44 | V192: =IF(Q192="", "", Q192*10%) -> 1039.5193 | W192: =IF(OR(Q192="", R192=""), "", (Q192- R192)/Q192) -> 0.014856868
B193: 191 | C193: Madagascar | D193: 136310 | E193: No | F193: 139424 | G193: 46239 | H193: 2026-08-11 | I193: =IF(OR(H193="", G193=""), "", NETWORKDAYS(G193, H193)) -> 5 | J193: 46247 | K193: =IF(OR(H193="", J193=""), "", NETWORKDAYS(H193, J193)) -> 3 | L193: 2026-08-13 | M193: =IF(OR(J193="", L193=""), "", NETWORKDAYS(J193, L193)) -> 1 | N193: TX GC FO sur AAT067 FENOAMBANY | O193: PRIMA CE SARLU | P193: USD | Q193: 4487.0217 | R193: 4193.4783 | S193: =Q193-R193 -> 293.54348 | V193: =IF(Q193="", "", Q193*10%) -> 448.70217 | W193: =IF(OR(Q193="", R193=""), "", (Q193- R193)/Q193) -> 0.065420561
B194: 192 | C194: Madagascar | D194: 136314 | E194: Yes | F194: 139442 | G194: 46239 | H194: 2026-08-11 | I194: =IF(OR(H194="", G194=""), "", NETWORKDAYS(G194, H194)) -> 5 | J194: 46247 | K194: =IF(OR(H194="", J194=""), "", NETWORKDAYS(H194, J194)) -> 3 | L194: 2026-08-14 | M194: =IF(OR(J194="", L194=""), "", NETWORKDAYS(J194, L194)) -> 2 | N194: TX GC FO sur SOF228 BEKORATSAKA | O194: EASY NETCOM | P194: USD | Q194: 4696.9876 | R194: 4269.9887 | S194: =Q194-R194 -> 426.99891 | V194: =IF(Q194="", "", Q194*10%) -> 469.69876 | W194: =IF(OR(Q194="", R194=""), "", (Q194- R194)/Q194) -> 0.090909099
B195: 193 | C195: Madagascar | D195: 136251 | E195: Yes | F195: 139427 | G195: 46239 | H195: 2026-08-07 | I195: =IF(OR(H195="", G195=""), "", NETWORKDAYS(G195, H195)) -> 3 | J195: 46244 | K195: =IF(OR(H195="", J195=""), "", NETWORKDAYS(H195, J195)) -> 2 | L195: 2026-08-10 | M195: =IF(OR(J195="", L195=""), "", NETWORKDAYS(J195, L195)) -> 1 | N195: Maintenance et Consommables MP-LOT1(197 sites) | O195: AFRO EGYPT | P195: USD | Q195: 130392.89 | R195: 115865.68 | S195: =Q195-R195 -> 14527.208 | V195: =IF(Q195="", "", Q195*10%) -> 13039.289 | W195: =IF(OR(Q195="", R195=""), "", (Q195- R195)/Q195) -> 0.11141105
... B477: 476 | C477: Madagascar | D477: 136544 | E477: Yes | F477: 139835 | G477: 46262 | H477: 2026-08-28 | I477: =IF(OR(H477="", G477=""), "", NETWORKDAYS(G477, H477)) -> 1 | J477: 46262 | K477: =IF(OR(H477="", J477=""), "", NETWORKDAYS(H477, J477)) -> 1 | L477: 2026-08-28 | M477: =IF(OR(J477="", L477=""), "", NETWORKDAYS(J477, L477)) -> 1 | N477: HABILLAGE VITRE PORTE-annule et remplace BC136040 | O477: ECO FUSION | P477: USD | Q477: 247.28261 | R477: 247.28261 | S477: =Q477-R477 -> 0 | V477: =IF(Q477="", "", Q477*10%) -> 24.728261 | W477: =IF(OR(Q477="", R477=""), "", (Q477- R477)/Q477) -> 0

Sheet Customs_Clearance
B1: OPCOS MONTHLY CUSTOMS CLEARANCE TRACKER
C2: use same OpCo spelling as in the Dashboard | I2: SEA/AIR fromat only | J2: Date in MM/DD/YYYY format | K2: Date in MM/DD/YYYY format | L2: Automatic Formula
B4: N° | C4: OPCO | D4: PO reference | E4: Designation | F4: Vendor | G4: Incoterm | H4: Custom Clearance Partner | I4: SEA/AIR | J4: Date of Arrival in Country | K4: Date of Warehouse Delivery | L4: GRN (TAT) | M4: Agreed SLA days
B5: 1 | C5: Madagascar | D5: 134118 | E5: 128 K LTE SIM | F5: VALID | I5: SEA | J5: 46241 | K5: 46254 | L5: =IF(OR(J5="", K5=""), "", NETWORKDAYS(J5,K5)) -> 10 | M5: =IF(I5="SEA", 10, IF(I5="AIR", 5, "")) -> 10
B6: 2 | C6: Madagascar | D6: 134287 | E6: FIRE EMERGENCY LIGHT | F6: TRIDENT | I6: AIR | J6: 46233 | K6: 46238 | L6: =IF(OR(J6="", K6=""), "", NETWORKDAYS(J6,K6)) -> 4 | M6: =IF(I6="SEA", 10, IF(I6="AIR", 5, "")) -> 5
B7: 3 | C7: Madagascar | D7: 1333222 | E7: DIRECTIONAL ANTENNA | F7: PROJET PHOENIX HUAWEI | I7: SEA | J7: 46248 | K7: 46260 | L7: =IF(OR(J7="", K7=""), "", NETWORKDAYS(J7,K7)) -> 9 | M7: =IF(I7="SEA", 10, IF(I7="AIR", 5, "")) -> 10
B8: 4 | C8: Madagascar | D8: 134142 | E8: POINT ACCES ROCKET | F8: NF TECH | I8: AIR | J8: 46245 | K8: 46251 | L8: =IF(OR(J8="", K8=""), "", NETWORKDAYS(J8,K8)) -> 5 | M8: =IF(I8="SEA", 10, IF(I8="AIR", 5, "")) -> 5
B9: 5 | C9: Madagascar | D9: 134610 | E9: OPTICAL TRANSCEIVER | F9: HUAWEI | I9: AIR | J9: 46245 | K9: 46248 | L9: =IF(OR(J9="", K9=""), "", NETWORKDAYS(J9,K9)) -> 4 | M9: =IF(I9="SEA", 10, IF(I9="AIR", 5, "")) -> 5
B10: 7 | C10: Madagascar | D10: 134379 | E10: KIT DROP CABLE | F10: GEKA | I10: AIR | J10: 46245 | K10: 46248 | L10: =IF(OR(J10="", K10=""), "", NETWORKDAYS(J10,K10)) -> 4 | M10: =IF(I10="SEA", 10, IF(I10="AIR", 5, "")) -> 5
B11: 8 | C11: Madagascar | D11: 135045 | E11: DECLENCHEUR GODOX | F11: OBJECTIF BASTILLE | I11: AIR | J11: 46248 | K11: 46252 | L11: =IF(OR(J11="", K11=""), "", NETWORKDAYS(J11,K11)) -> 3 | M11: =IF(I11="SEA", 10, IF(I11="AIR", 5, "")) -> 5
B12: 9 | C12: Madagascar | D12: 136002 | E12: ETIQUETEUSE | F12: GEKA | I12: AIR | J12: 46248 | K12: 46254 | L12: =IF(OR(J12="", K12=""), "", NETWORKDAYS(J12,K12)) -> 5 | M12: =IF(I12="SEA", 10, IF(I12="AIR", 5, "")) -> 5
B13: 12 | C13: Madagascar | D13: 135080 | E13: LASER TRANCEIVER | F13: HUAWEI | I13: AIR | J13: 46258 | K13: 46262 | L13: =IF(OR(J13="", K13=""), "", NETWORKDAYS(J13,K13)) -> 5 | M13: =IF(I13="SEA", 10, IF(I13="AIR", 5, "")) -> 5
B14: 13 | C14: Madagascar | D14: 135180 | E14: PEHD 27/32 + 34/40 | F14: SAGEMCOM | I14: SEA | J14: 46258 | K14: 46270 | L14: =IF(OR(J14="", K14=""), "", NETWORKDAYS(J14,K14)) -> 10 | M14: =IF(I14="SEA", 10, IF(I14="AIR", 5, "")) -> 10
B15: 14 | C15: Madagascar | D15: 134378 | E15: PBO T2 PRECO | F15: GEKA | I15: AIR | J15: 46256 | K15: 46259 | L15: =IF(OR(J15="", K15=""), "", NETWORKDAYS(J15,K15)) -> 2 | M15: =IF(I15="SEA", 10, IF(I15="AIR", 5, "")) -> 5
B16: 15 | C16: Madagascar | D16: 136318 | E16: VEVOR ANEMOMETRE | F16: GEKA | I16: AIR | J16: 46259 | K16: 46265 | L16: =IF(OR(J16="", K16=""), "", NETWORKDAYS(J16,K16)) -> 5 | M16: =IF(I16="SEA", 10, IF(I16="AIR", 5, "")) -> 5
B17: 17 | L17: =IF(OR(J17="", K17=""), "", NETWORKDAYS(J17,K17)) | M17: =IF(I17="SEA", 10, IF(I17="AIR", 5, ""))
B18: 18 | L18: =IF(OR(J18="", K18=""), "", NETWORKDAYS(J18,K18)) | M18: =IF(I18="SEA", 10, IF(I18="AIR", 5, ""))
B19: 19 | L19: =IF(OR(J19="", K19=""), "", NETWORKDAYS(J19,K19)) | M19: =IF(I19="SEA", 10, IF(I19="AIR", 5, ""))
B20: 20 | L20: =IF(OR(J20="", K20=""), "", NETWORKDAYS(J20,K20)) | M20: =IF(I20="SEA", 10, IF(I20="AIR", 5, ""))
B21: 21 | L21: =IF(OR(J21="", K21=""), "", NETWORKDAYS(J21,K21)) | M21: =IF(I21="SEA", 10, IF(I21="AIR", 5, ""))
B22: 22 | L22: =IF(OR(J22="", K22=""), "", NETWORKDAYS(J22,K22)) | M22: =IF(I22="SEA", 10, IF(I22="AIR", 5, ""))
B23: 23 | L23: =IF(OR(J23="", K23=""), "", NETWORKDAYS(J23,K23)) | M23: =IF(I23="SEA", 10, IF(I23="AIR", 5, ""))
B24: 24 | L24: =IF(OR(J24="", K24=""), "", NETWORKDAYS(J24,K24)) | M24: =IF(I24="SEA", 10, IF(I24="AIR", 5, ""))
B25: 25 | L25: =IF(OR(J25="", K25=""), "", NETWORKDAYS(J25,K25)) | M25: =IF(I25="SEA", 10, IF(I25="AIR", 5, ""))
B26: 26 | L26: =IF(OR(J26="", K26=""), "", NETWORKDAYS(J26,K26)) | M26: =IF(I26="SEA", 10, IF(I26="AIR", 5, ""))
B27: 27 | L27: =IF(OR(J27="", K27=""), "", NETWORKDAYS(J27,K27)) | M27: =IF(I27="SEA", 10, IF(I27="AIR", 5, ""))
B28: 28 | L28: =IF(OR(J28="", K28=""), "", NETWORKDAYS(J28,K28)) | M28: =IF(I28="SEA", 10, IF(I28="AIR", 5, ""))
... B702: 704 | L702: =IF(OR(J702="", K702=""), "", NETWORKDAYS(J702,K702)) | M702: =IF(I702="SEA", 10, IF(I702="AIR", 5, ""))

Sheet Open Projects
A1: Entity Initiator | B1: OpCo | C1: Category | D1: Project | E1: Overall Status | F1: Project description | G1: Business Owner | H1: Number of suppliers contacted | I1: RFP Received | J1: RFP Issuance | K1: RFP Offer date | L1: Status | M1: Action Owner | N1: Selected supplier | O1: Initial price | P1: Final price | Q1: SAVING | R1: Contract start date | S1: Contract signature target date | T1: Actual Contract signature date | U1: Tender target closing date | V1: Buyer | W1: Supplier 1 | X1: Supplier 2 | Y1: Supplier 3 | Z1: Supplier 4 | AA1: Supplier 5 | AB1: Supplier 6 | AC1: Supplier 7 | AD1: Supplier 8 | AE1: Supplier 9 | AF1: Supplier 10 | AG1: Supplier 11
A2: Yas Comores | B2: COMOROS | C2: TELECOM | D2: Civil engineering works and installation of 5GE on sites | E2: OFFER | F2: Civil engineering works and installation of 5GE on sites. | G2: Ando | H2: 6 | I2: 45988 | J2: 45989 | K2: 45994 | L2: Purchase request submitted today, 19/02/2026. | M2: Chimba Nghemning Henri | N2: Entreprise OBT | O2: 119833.84 | P2: 103057.1 | Q2: =O2-P2 -> 16776.74 | V2: Issoufi Djamal-Edine | W2: Entreprise OBT | X2: ELM construction | Y2: Societé Nahouza | Z2: STE Beta | AA2: Bundo construct | AB2: Sec Daniel
A3: Yas Comores | B3: COMOROS | C3: TELECOM | D3: Fiber-optic connection works for El Maarouf Hospital | E3: OFFER | F3: Fiber-optic connection works for El Maarouf Hospital. | G3: Sidi Aman Ahmed | H3: 4 | I3: 46020 | J3: 46021 | K3: 46027 | L3: Work in Progress | M3: Sidi Aman Ahmed | N3: ELM construction | O3: 30516.44 | P3: 28018.52 | Q3: =O3-P3 -> 2497.92 | R3: 46049 | S3: No contrat | T3: No contrat | U3: 46027 | V3: Issoufi Djamal-Edine | W3: ELM construction | X3: Entreprise OBT | Y3: STE Beta | Z3: Bundo construct
A4: Yas Comores | B4: COMOROS | C4: TELECOM | D4: MPox prevention (hydroalcoholic gels) | E4: CLOSED | F4: Hydroalcoholic gels for Mpox prevention. | G4: Raymane Ali Matoir | H4: 2 | I4: 46041 | J4: 46043 | K4: 46046 | L4: Closed. | N4: Ocopharma | O4: 4749 | P4: 4749 | Q4: =O4-P4 -> 0 | R4: 46058 | S4: No contrat | T4: No contrat | U4: 46046 | V4: Issoufi Djamal-Edine | W4: Ocopharma | X4: Ligapharma
A5: Yas Comores | B5: COMOROS | C5: TELECOM | D5: Laptop acquisition | E5: EVALUATION | F5: The project consists of assigning laptops based on actual needs: standard models are intended for roles with simple tasks, while high-end laptops are reserved for employees using tools or software requiring higher performance. | G5: Ahmed Mohamed | H5: 4 | I5: 46028 | J5: 46042 | K5: 46050 | L5: Waiting for validation of the 2026 Facilities IT budget to confirm, together with Olivier (financial controller), the extent to which purchases can be committed. This validation is essential to determine the exact acquisition volume based on supplier prices. | M5: Nazlye/ Olivier | Q5: =O5-P5 -> 0 | V5: Issoufi Djamal-Edine | W5: Fan pro services | X5: Hakimi multimedia | Y5: Pateterie des Comores | Z5: Mak technoligie
A6: Yas Comores | B6: COMOROS | C6: TELECOM | D6: FTTX equipment acquisition | E6: RFI | F6: Equipment for FTTX installations. | G6: Karim Attoumani Mohamed | H6: 6 | I6: 46035 | J6: 46036 | K6: 46048 | L6: A supplier consultation was launched locally for the acquisition of this equipment. However, since it is not available in the country, it must be ordered from abroad, with a delivery lead time of 15–20 days. We are currently awaiting technical offers; once received and a supplier is selected, we will issue the purchase order. | M6: Irchad Radjabou | Q6: =O6-P6 -> 0 | V6: Issoufi Djamal-Edine | W6: Comores multiservices | X6: Hakimi multimedia | Y6: Fan pro services | Z6: Magasin said Hassane Fils | AA6: Rehamani SARL | AB6: Photo soleil
A7: Yas Comores | B7: COMOROS | C7: TELECOM | D7: Ubiquiti equipment purchase | E7: OFFER | F7: Ubiquiti stock order | G7: Karim Attoumani Mohamed | H7: 4 | I7: 46035 | J7: 46037 | K7: 46042 | L7: The purchase order has been sent to the supplier. Part of the goods has been received, and we are awaiting the remaining items. | M7: Supplier | N7: Fan pro services/ Hakimi multimedia/ Comores multiservices | O7: =26213.93+71213.34+92722.3 -> 190149.57 | P7: =28835.33+64056.74+83058.29 -> 175950.36 | Q7: =O7-P7 -> 14199.21 | R7: 46056 | S7: No contrat for supplier 1&3. in Progress for 2 | T7: No contrat for supplier 1&3. in Progress for 2 | V7: Issoufi Djamal-Edine | W7: Fan pro services | X7: Hakimi multimedia | Y7: Comores multiservices | Z7: Pateterie des Comores
A8: Yas Comores | B8: COMOROS | C8: TELECOM | D8: store Djivani concrete floor renovation works | E8: OFFER | F8: This project concerns concrete floor refurbishment works around the Djivani Store. | G8: Chenaz Abdallah | H8: 3 | I8: 46037 | J8: 46059 | K8: 46071 | L8: PO under processing by Procurement | M8: Bachir Houamadi | N8: NLN | O8: 14246.7 | P8: 14246.7 | Q8: =O8-P8 -> 0 | V8: Issoufi Djamal-Edine | W8: NLN | X8: STC
A9: Yas Comores | B9: COMOROS | C9: TELECOM | D9: Purchase of 12 KVA generator | E9: CLOSED | F9: 12 KVA generator for the Mitsamihouli shop due to frequent power outages, which risk slowing down or interrupting commercial activities. | G9: Chimba Nghemning Henri | H9: 1 | I9: 46066 | J9: 46066 | K9: 46068 | L9: Closed. | N9: Electro foid | O9: 5876.76 | P9: 5283.15 | Q9: =O9-P9 -> 593.61 | R9: 46058 | S9: No contrat | T9: No contrat | U9: 46052 | V9: Issoufi Djamal-Edine | W9: Electro froid

Sheet Open Projects Pivot
A1: Overall Status | B1: (Multiple Items)
A3: Count of Project | B3: Column Labels
A4: Row Labels | B4: COMOROS | C4: Grand Total
A5: TELECOM | B5: 6 | C5: 6
A6: Grand Total | B6: 6 | C6: 6
A9: Category | B9: (All)
A11: Count of Project | B11: Column Labels
A12: Row Labels | B12: COMOROS | C12: Grand Total
A13: CLOSED | B13: 2 | C13: 2
A14: EVALUATION | B14: 1 | C14: 1
A15: OFFER | B15: 4 | C15: 4
A16: RFI | B16: 1 | C16: 1
A17: Grand Total | B17: 8 | C17: 8
A18: Overall Status | B18: (Multiple Items)
A20: Sum of SAVING | B20: Column Labels
A21: Row Labels | B21: COMOROS | C21: Grand Total
A22: TELECOM | B22: 33473.87 | C22: 33473.87
A23: Grand Total | B23: 33473.87 | C23: 33473.87

Sheet List
A1: Category | C1: Global Status
A2: Commercial D&S | C2: CANCELLED
A3: Communication | C3: CLOSED
A4: CONSULTING | C4: COMINVEST
A5: DEVICE | C5: CONTRACT
A6: GROUP | C6: EVALUATION
A7: HR | C7: NEEDS
A8: IT | C8: NEGO
A9: OTHERS | C9: OFFER
A10: OTHERS / SERVICES CONSULTANCY | C10: RFI
A11: SIM | C11: RFP
A12: TELECOM | C12: STAND BY
A13: VEHICLE | C13: (vide)

Sheet PPOT
B1: OPCOS MONTHLY PPOT TRACKER
C2: use same OpCo spelling as in the Dashboard | J2: 421.75 | K2: Date in MM/DD/YYYY format | L2: agreed paypment term with Supplier | M2: Date in MM/DD/YYYY format | N2: Automatic Formula | O2: Automatic Formula
B4: N° | C4: OPCO | D4: Invoice Ref | E4: PO Ref | F4: Designation | G4: Partner | I4: Invoice Amount | J4: Currency usd | K4: Invoice Receipt Date | L4: Agreed Payment Days/Jours (Terms) | M4: Invoice Payment Date | N4: Invoice Payment (TAT) | O4: PPOT (Yes/No)
B5: 1 | C5: Madagascar | D5: INV/2026/00032 | E5: 134706 | F5: Titre de Sponsor Gold | G5: OKALOU EVENT | I5: 2125 | J5: USD | K5: 46220 | L5: 30 | M5: 46247 | N5: =IF(OR(M5="", K5=""),"", M5- K5) -> 27 | O5: =IF(OR(M5="", K5="", L5=""), "", IF((M5 - K5) > L5, "No", "Yes")) -> Yes
B6: 2 | C6: Madagascar | D6: LN/00159/26 | E6: 133475 | F6: LES NOUVELLES/Publicité JNAV 2026 | G6: ULTIMA MEDIA | I6: 1704.886 | J6: USD | K6: 46210 | L6: 30 | M6: 46235 | N6: =IF(OR(M6="", K6=""),"", M6- K6) -> 25 | O6: =IF(OR(M6="", K6="", L6=""), "", IF((M6 - K6) > L6, "No", "Yes")) -> Yes
B7: 3 | C7: Madagascar | D7: TR/00098/26 | E7: 133475 | F7: TARATRA MARS 2026 | G7: ULTIMA MEDIA | I7: 1788.1095 | J7: USD | K7: 46210 | L7: 30 | M7: 46246 | N7: =IF(OR(M7="", K7=""),"", M7- K7) -> 36 | O7: =IF(OR(M7="", K7="", L7=""), "", IF((M7 - K7) > L7, "No", "Yes")) -> No
B8: 4 | C8: Madagascar | D8: LN/00494/26 | E8: 133475 | F8: LES NOUVELLES/Publicité mois de mars 2026 | G8: ULTIMA MEDIA | I8: 1788.1095 | J8: USD | K8: 46210 | L8: 30 | M8: 46247 | N8: =IF(OR(M8="", K8=""),"", M8- K8) -> 37 | O8: =IF(OR(M8="", K8="", L8=""), "", IF((M8 - K8) > L8, "No", "Yes")) -> No
B9: 5 | C9: Madagascar | D9: 226/2026 | E9: 134858 | F9: JTVM MARS 2026 | G9: KOLO TV (SMPC) | I9: 1100 | J9: USD | K9: 46177 | L9: 30 | M9: 46206 | N9: =IF(OR(M9="", K9=""),"", M9- K9) -> 29 | O9: =IF(OR(M9="", K9="", L9=""), "", IF((M9 - K9) > L9, "No", "Yes")) -> Yes
B10: 6 | C10: Madagascar | D10: 414/2026 | E10: 134858 | F10: JVTM MOIS DE MAI 2026 | G10: KOLO TV (SMPC) | I10: 1100 | J10: USD | K10: 46177 | L10: 30 | M10: 46205 | N10: =IF(OR(M10="", K10=""),"", M10- K10) -> 28 | O10: =IF(OR(M10="", K10="", L10=""), "", IF((M10 - K10) > L10, "No", "Yes")) -> Yes
B11: 7 | C11: Madagascar | D11: 330/2026 | E11: 134858 | F11: PACK PARRAINAGE AVRIL 2026 | G11: KOLO TV (SMPC) | I11: 1100 | J11: USD | K11: 46177 | L11: 30 | M11: 46213 | N11: =IF(OR(M11="", K11=""),"", M11- K11) -> 36 | O11: =IF(OR(M11="", K11="", L11=""), "", IF((M11 - K11) > L11, "No", "Yes")) -> No
B12: 8 | C12: Madagascar | D12: FAC/OT/2026/8511 | E12: 134643 | F12: RALLONGE D'UTILISATION NEW DUSTER 53044WWT - | G12: OCEAN TRADE CO | I12: 1717.5 | J12: USD | K12: 46177 | L12: 30 | M12: 46212 | N12: =IF(OR(M12="", K12=""),"", M12- K12) -> 35 | O12: =IF(OR(M12="", K12="", L12=""), "", IF((M12 - K12) > L12, "No", "Yes")) -> No
B13: 9 | C13: Madagascar | D13: FAC/OT/2026/8512 | E13: 134638 | F13: REPARATION AVEC PIECES DE RECHANGES | G13: OCEAN TRADE CO | I13: 1804.18 | J13: USD | K13: 46177 | L13: 30 | M13: 46205 | N13: =IF(OR(M13="", K13=""),"", M13- K13) -> 28 | O13: =IF(OR(M13="", K13="", L13=""), "", IF((M13 - K13) > L13, "No", "Yes")) -> Yes
B14: 10 | C14: Madagascar | D14: FAC/OT/2026/8514 | E14: 133870 | F14: RALLONGE D'UTILISATION - 56887WWT | G14: OCEAN TRADE CO | I14: 1495 | J14: USD | K14: 46177 | L14: 30 | M14: 46202 | N14: =IF(OR(M14="", K14=""),"", M14- K14) -> 25 | O14: =IF(OR(M14="", K14="", L14=""), "", IF((M14 - K14) > L14, "No", "Yes")) -> Yes
B15: 11 | C15: Madagascar | D15: FAC/OT/2026/9287 | E15: 134956 | F15: RALLONGE D'UTILISATION | G15: OCEAN TRADE CO | I15: 496.16665 | J15: USD | K15: 46190 | L15: 30 | M15: 46216 | N15: =IF(OR(M15="", K15=""),"", M15- K15) -> 26 | O15: =IF(OR(M15="", K15="", L15=""), "", IF((M15 - K15) > L15, "No", "Yes")) -> Yes
B16: 12 | C16: Madagascar | D16: 0215/MOTO/2026 | E16: 135154 | F16: COFI 2026 - MOTO GRS IMPROVE EVOLUTION | G16: MADAGASCAR AUTOMOBILE | I16: 6414.5837 | J16: USD | K16: 46197 | L16: 30 | M16: 46222 | N16: =IF(OR(M16="", K16=""),"", M16- K16) -> 25 | O16: =IF(OR(M16="", K16="", L16=""), "", IF((M16 - K16) > L16, "No", "Yes")) -> Yes
... B18: 14 | C18: Madagascar | D18: 0217/MOTO/2026 | E18: 135331 | F18: COFI 2026 - MOTO GRS ADR MOBILE | G18: MADAGASCAR AUTOMOBILE | I18: 1135.4168 | J18: USD | K18: 46198 | L18: 30 | M18: 46235 | N18: =IF(OR(M18="", K18=""),"", M18- K18) -> 37 | O18: =IF(OR(M18="", K18="", L18=""), "", IF((M18 - K18) > L18, "No", "Yes")) -> No
B19: 15 | C19: Madagascar | D19: 134962 | E19: 134962 | F19: Séminaire RAS 2026 - Ambanja | G19: BAR HERMES | I19: 496.875 | J19: USD | K19: 46196 | L19: 30 | M19: 46227 | N19: =IF(OR(M19="", K19=""),"", M19- K19) -> 31 | O19: =IF(OR(M19="", K19="", L19=""), "", IF((M19 - K19) > L19, "No", "Yes")) -> No
B20: 16 | C20: Madagascar | D20: 001/06/2026 | E20: 135446 | F20: Sponsoring Body Perfect 2026 | G20: FEDERATION MALAGASY DE BODYBUILDING | I20: 1041.6667 | J20: USD | K20: 46204 | L20: 30 | M20: 46236 | N20: =IF(OR(M20="", K20=""),"", M20- K20) -> 32 | O20: =IF(OR(M20="", K20="", L20=""), "", IF((M20 - K20) > L20, "No", "Yes")) -> No
B21: 17 | C21: Madagascar | D21: 22/2026/F | E21: 135531 | F21: Séminaire RAS_RC Bongolava | G21: RAFARASOA SUZANNE (HORIZON) | I21: 381.25 | J21: USD | K21: 46259 | L21: 30 | M21: 46262 | N21: =IF(OR(M21="", K21=""),"", M21- K21) -> 3 | O21: =IF(OR(M21="", K21="", L21=""), "", IF((M21 - K21) > L21, "No", "Yes")) -> Yes
B22: 18 | C22: Madagascar | D22: sn | E22: 135805 | F22: SFM1_135805_135805_Partenariat Commune Moramanga | G22: Association SFM | I22: 2604.1667 | J22: USD | K22: 46216 | L22: 30 | M22: 46239 | N22: =IF(OR(M22="", K22=""),"", M22- K22) -> 23 | O22: =IF(OR(M22="", K22="", L22=""), "", IF((M22 - K22) > L22, "No", "Yes")) -> Yes
B23: 19 | C23: Madagascar | D23: CN-00863 | E23: 135260 | F23: MADAJOB1_AVOIR Frais de transport JUIN 2026_FA N°CN-00863_BC 135260 | G23: MADAJOB | I23: -71.875 | J23: USD | K23: 46209 | L23: 30 | M23: 46238 | N23: =IF(OR(M23="", K23=""),"", M23- K23) -> 29 | O23: =IF(OR(M23="", K23="", L23=""), "", IF((M23 - K23) > L23, "No", "Yes")) -> Yes
B24: 20 | C24: Madagascar | D24: SN | E24: 136051 | F24: LESDELICES1_Location salle de réunion à Manakara du 27-07-26 au 31-07-26_BC 136051 | G24: LES DELICES MANAKARA | I24: 156.25 | J24: USD | K24: 46237 | L24: 30 | M24: 46238 | N24: =IF(OR(M24="", K24=""),"", M24- K24) -> 1 | O24: =IF(OR(M24="", K24="", L24=""), "", IF((M24 - K24) > L24, "No", "Yes")) -> Yes
B25: 21 | C25: Madagascar | D25: 006/TELMA/FMBB/2026 | E25: 135894 | F25: FMBB1_Consommation Internet et Flotte Mois de Juin 2026 _006/TELMA/FMBB/2026_135894 | G25: FEDERATION MALAGASY DE BASKET BALL | I25: 1085.2522 | J25: USD | K25: 46188 | L25: 30 | M25: 46223 | N25: =IF(OR(M25="", K25=""),"", M25- K25) -> 35 | O25: =IF(OR(M25="", K25="", L25=""), "", IF((M25 - K25) > L25, "No", "Yes")) -> No
B26: 22 | C26: Madagascar | D26: sn | E26: 135885 | F26: Paiement Jeton de présence Avantages Asdministrateur YAS Mr Tahiry Trimosoa RABENANAHARY pour l'année 2026 | G26: RABENANAHARY Tahiry Trimosoa | I26: 1250 | J26: USD | K26: 46216 | L26: 30 | M26: 46240 | N26: =IF(OR(M26="", K26=""),"", M26- K26) -> 24 | O26: =IF(OR(M26="", K26="", L26=""), "", IF((M26 - K26) > L26, "No", "Yes")) -> Yes
B27: 23 | C27: Madagascar | D27: 18072025/BC129775/NSB | E27: 129775 | F27: Transport et implantation poteau en bois-Client Nosy BE-9è vague | G27: ASSOMANY ASSANY | I27: 729.16667 | J27: USD | K27: 46180 | L27: 30 | M27: 46215 | N27: =IF(OR(M27="", K27=""),"", M27- K27) -> 35 | O27: =IF(OR(M27="", K27="", L27=""), "", IF((M27 - K27) > L27, "No", "Yes")) -> No
B28: 24 | C28: Madagascar | D28: 025/502/ENC-HR/Fact/TEL | E28: 123187 | F28: Installation FO-Extension INFRA GPON Ambohimanambola | G28: EASY NETCOM | I28: 387.5 | J28: USD | K28: 46205 | L28: 30 | M28: 46241 | N28: =IF(OR(M28="", K28=""),"", M28- K28) -> 36 | O28: =IF(OR(M28="", K28="", L28=""), "", IF((M28 - K28) > L28, "No", "Yes")) -> No
B29: 25 | C29: Madagascar | D29: 026/508/ENC-HR/Fact/TEL | E29: 133746 | F29: Travaux de maintenance filaire- Ivato | G29: EASY NETCOM | I29: 330 | J29: USD | K29: 46205 | L29: 30 | M29: 46241 | N29: =IF(OR(M29="", K29=""),"", M29- K29) -> 36 | O29: =IF(OR(M29="", K29="", L29=""), "", IF((M29 - K29) > L29, "No", "Yes")) -> No
B30: 26 | C30: Madagascar | D30: 026/507/ENC-HR/Fact/TEL | E30: 133716 | F30: Travaux de maintenance filaire-Extension Analamahitsy | G30: EASY NETCOM | I30: 412.5 | J30: USD | K30: 46205 | L30: 30 | M30: 46240 | N30: =IF(OR(M30="", K30=""),"", M30- K30) -> 35 | O30: =IF(OR(M30="", K30="", L30=""), "", IF((M30 - K30) > L30, "No", "Yes")) -> No
B31: 27 | C31: Madagascar | D31: 026/501/ENC-HR/Fact/TEL | E31: 133746 | F31: Travaux de maintenance -GC Sabotsy Namehana | G31: EASY NETCOM | I31: 18.75 | J31: USD | K31: 46205 | L31: 30 | M31: 46234 | N31: =IF(OR(M31="", K31=""),"", M31- K31) -> 29 | O31: =IF(OR(M31="", K31="", L31=""), "", IF((M31 - K31) > L31, "No", "Yes")) -> Yes
... B60: 56 | C60: Madagascar | D60: INVOICE-061/2025/HM | E60: 131912 | F60: Travaux d'implantation 50 poteaux sur Fort Dauphin | G60: HERTS MADAGASCAR SARLU | I60: 1375 | J60: USD | K60: 46205 | L60: 30 | M60: 46230 | N60: =IF(OR(M60="", K60=""),"", M60- K60) -> 25 | O60: =IF(OR(M60="", K60="", L60=""), "", IF((M60 - K60) > L60, "No", "Yes")) -> Yes
B61: 57 | C61: Madagascar | D61: 2605621 | E61: 135989 | F61: Acompte Plateau pour rack | G61: ICHTUS SERVICE | I61: 13900.425 | J61: USD | K61: 46231 | L61: 30 | M61: 46251 | N61: =IF(OR(M61="", K61=""),"", M61- K61) -> 20 | O61: =IF(OR(M61="", K61="", L61=""), "", IF((M61 - K61) > L61, "No", "Yes")) -> Yes
B62: 58 | C62: Madagascar | D62: ING.M/2026/0040 | E62: 134293 | F62: régie janvier 2026 | G62: INGENOSYA | I62: 1662.5 | J62: USD | K62: 46170 | L62: 30 | M62: 46206 | N62: =IF(OR(M62="", K62=""),"", M62- K62) -> 36 | O62: =IF(OR(M62="", K62="", L62=""), "", IF((M62 - K62) > L62, "No", "Yes")) -> No
B63: 59 | C63: Madagascar | D63: ING.M/2026/0039 | E63: 134293 | F63: REGIE JANVIER 2026 | G63: INGENOSYA | I63: 3368.75 | J63: USD | K63: 46170 | L63: 30 | M63: 46207 | N63: =IF(OR(M63="", K63=""),"", M63- K63) -> 37 | O63: =IF(OR(M63="", K63="", L63=""), "", IF((M63 - K63) > L63, "No", "Yes")) -> No
B64: 60 | C64: Madagascar | D64: ING.M/2026/0038 | E64: 134293 | F64: REGIE JANVIER 2026 | G64: INGENOSYA | I64: 1711.7625 | J64: USD | K64: 46170 | L64: 30 | M64: 46199 | N64: =IF(OR(M64="", K64=""),"", M64- K64) -> 29 | O64: =IF(OR(M64="", K64="", L64=""), "", IF((M64 - K64) > L64, "No", "Yes")) -> Yes
B65: 61 | C65: Madagascar | D65: ING.M/2026/0037 | E65: 134293 | F65: DEV ET TESTS JANVIER 2026 | G65: INGENOSYA | I65: 1050 | J65: USD | K65: 46170 | L65: 30 | M65: 46205 | N65: =IF(OR(M65="", K65=""),"", M65- K65) -> 35 | O65: =IF(OR(M65="", K65="", L65=""), "", IF((M65 - K65) > L65, "No", "Yes")) -> No
B66: 62 | C66: Madagascar | D66: ING.M/2026/0036 | E66: 134293 | F66: REGIE JANVIER | G66: INGENOSYA | I66: 1618.75 | J66: USD | K66: 46170 | L66: 30 | M66: 46200 | N66: =IF(OR(M66="", K66=""),"", M66- K66) -> 30 | O66: =IF(OR(M66="", K66="", L66=""), "", IF((M66 - K66) > L66, "No", "Yes")) -> Yes
B67: 63 | C67: Madagascar | D67: ING.M/2026/0035 | E67: 134293 | F67: PILOTAGE JAN 2026 | G67: INGENOSYA | I67: 960 | J67: USD | K67: 46170 | L67: 30 | M67: 46200 | N67: =IF(OR(M67="", K67=""),"", M67- K67) -> 30 | O67: =IF(OR(M67="", K67="", L67=""), "", IF((M67 - K67) > L67, "No", "Yes")) -> Yes
B68: 64 | C68: Madagascar | D68: ING.M/2026/0034 | E68: 134293 | F68: TEST JANV 2026 | G68: INGENOSYA | I68: 3062.5 | J68: USD | K68: 46170 | L68: 30 | M68: 46196 | N68: =IF(OR(M68="", K68=""),"", M68- K68) -> 26 | O68: =IF(OR(M68="", K68="", L68=""), "", IF((M68 - K68) > L68, "No", "Yes")) -> Yes
B69: 65 | C69: Madagascar | D69: 061/26 | E69: 134573 | F69: Transport 30PT 8m de Tana vers Morondava | G69: MADAGASCAR LOGISTICS ET SERVICES | I69: 1072.9167 | J69: USD | K69: 46168 | L69: 30 | M69: 46195 | N69: =IF(OR(M69="", K69=""),"", M69- K69) -> 27 | O69: =IF(OR(M69="", K69="", L69=""), "", IF((M69 - K69) > L69, "No", "Yes")) -> Yes
B70: 66 | C70: Madagascar | D70: 4057247 | E70: 132063 | F70: Mise à disposition équipes pour installation FO juin2026 | G70: MATERIEL ET MAINTENANCE INFORMATIQUE(2MI) | I70: 4000 | J70: USD | K70: 46220 | L70: 30 | M70: 46248 | N70: =IF(OR(M70="", K70=""),"", M70- K70) -> 28 | O70: =IF(OR(M70="", K70="", L70=""), "", IF((M70 - K70) > L70, "No", "Yes")) -> Yes
B71: 67 | C71: Madagascar | D71: PRIMA-FACT-0326-0788 | E71: 133504 | F71: ACOMPTE SUR TRAVAUX GC ET TIRAGE FOAMBOHIBARY | G71: PRIMA CE SARLU | I71: 3339.8625 | J71: USD | K71: 46220 | L71: 30 | M71: 46248 | N71: =IF(OR(M71="", K71=""),"", M71- K71) -> 28 | O71: =IF(OR(M71="", K71="", L71=""), "", IF((M71 - K71) > L71, "No", "Yes")) -> Yes
B72: 68 | C72: Madagascar | D72: PRIMA-FACT-0626-0905 | E72: 135234 | F72: TRAVAUX LASTMILE FTTX TAMATAVE AXE CENTRE DE LA VILLE | G72: PRIMA CE SARLU | I72: 6075 | J72: USD | K72: 46202 | L72: 30 | M72: 46239 | N72: =IF(OR(M72="", K72=""),"", M72- K72) -> 37 | O72: =IF(OR(M72="", K72="", L72=""), "", IF((M72 - K72) > L72, "No", "Yes")) -> No
B73: 69 | C73: Madagascar | D73: PRIMA-FACT-0626-0906 | E73: 135232 | F73: TRAVAUX LASTMILE FTTX TAMATAVE AXE SUD DE LA VILLE | G73: PRIMA CE SARLU | I73: 10125 | J73: USD | K73: 46202 | L73: 30 | M73: 46238 | N73: =IF(OR(M73="", K73=""),"", M73- K73) -> 36 | O73: =IF(OR(M73="", K73="", L73=""), "", IF((M73 - K73) > L73, "No", "Yes")) -> No
B74: 70 | C74: Madagascar | D74: PRIMA-FACT-0626-0904 | E74: 135231 | F74: TRAVAUX LASTMILLE FTTX TAMATAVE AXE NORD | G74: PRIMA CE SARLU | I74: 8100 | J74: USD | K74: 46202 | L74: 30 | M74: 46229 | N74: =IF(OR(M74="", K74=""),"", M74- K74) -> 27 | O74: =IF(OR(M74="", K74="", L74=""), "", IF((M74 - K74) > L74, "No", "Yes")) -> Yes
B75: 71 | C75: Madagascar | D75: PRIMA-FACT-0626-0903 | E75: 134724 | F75: INSPECTION ET TRAITEMENT POTEAUX BOIS | G75: PRIMA CE SARLU | I75: 3400 | J75: USD | K75: 46198 | L75: 30 | M75: 46235 | N75: =IF(OR(M75="", K75=""),"", M75- K75) -> 37 | O75: =IF(OR(M75="", K75="", L75=""), "", IF((M75 - K75) > L75, "No", "Yes")) -> No
B76: 72 | C76: Madagascar | D76: 008/26 | E76: 135375 | F76: TRAVAUX GC | G76: RANDRIANANTENAINA PATRICIA (ENTREPRISE MANDA) | I76: 523.95833 | J76: USD | K76: 46217 | L76: 30 | M76: 46249 | N76: =IF(OR(M76="", K76=""),"", M76- K76) -> 32 | O76: =IF(OR(M76="", K76="", L76=""), "", IF((M76 - K76) > L76, "No", "Yes")) -> No
B77: 73 | C77: Madagascar | D77: 007/26 | E77: 134878 | F77: TRAVAUX GC | G77: RANDRIANANTENAINA PATRICIA (ENTREPRISE MANDA) | I77: 406.25 | J77: USD | K77: 46217 | L77: 30 | M77: 46246 | N77: =IF(OR(M77="", K77=""),"", M77- K77) -> 29 | O77: =IF(OR(M77="", K77="", L77=""), "", IF((M77 - K77) > L77, "No", "Yes")) -> Yes
B78: 74 | C78: Madagascar | D78: FAC/2026/02351 | E78: 135572 | F78: Chaise Visiteur SM-138 | G78: SOCIETE QUBETA IMPORT-EXPORT SARLU | I78: 1066.5 | J78: USD | K78: 46224 | L78: 30 | M78: 46251 | N78: =IF(OR(M78="", K78=""),"", M78- K78) -> 27 | O78: =IF(OR(M78="", K78="", L78=""), "", IF((M78 - K78) > L78, "No", "Yes")) -> Yes
B79: 75 | C79: Madagascar | D79: 157/AR/26 | E79: 135462 | F79: Diffusion TRAIL D'IBITY 2026 | G79: ACEEM RADIO | I79: 24 | J79: USD | K79: 46212 | L79: 30 | M79: 46243 | N79: =IF(OR(M79="", K79=""),"", M79- K79) -> 31 | O79: =IF(OR(M79="", K79="", L79=""), "", IF((M79 - K79) > L79, "No", "Yes")) -> No
B80: 76 | C80: Madagascar | D80: 156/AR/26 | E80: 135588 | F80: Spot radio - Tournoi Inter Universitaire | G80: ACEEM RADIO | I80: 10 | J80: USD | K80: 46212 | L80: 30 | M80: 46244 | N80: =IF(OR(M80="", K80=""),"", M80- K80) -> 32 | O80: =IF(OR(M80="", K80="", L80=""), "", IF((M80 - K80) > L80, "No", "Yes")) -> No
B81: 77 | C81: Madagascar | D81: TNR-143/2026 | E81: 135717 | F81: Solvant périmés | G81: ADONIS ENVIRONNEMENT | I81: 79.939846 | J81: USD | K81: 46204 | L81: 30 | M81: 46239 | N81: =IF(OR(M81="", K81=""),"", M81- K81) -> 35 | O81: =IF(OR(M81="", K81="", L81=""), "", IF((M81 - K81) > L81, "No", "Yes")) -> No
B82: 78 | C82: Madagascar | D82: FA000268 | E82: 135849 | F82: COUPE DU MONDE 2026 | G82: AEROPUB | I82: 3125 | J82: USD | K82: 46224 | L82: 30 | M82: 46244 | N82: =IF(OR(M82="", K82=""),"", M82- K82) -> 20 | O82: =IF(OR(M82="", K82="", L82=""), "", IF((M82 - K82) > L82, "No", "Yes")) -> Yes
... B85: 81 | C85: Madagascar | D85: YAS/WL/2026/00010 | E85: 135711 | F85: Tx VSAT sur 04 sites | G85: AFRO EGYPT | I85: 7372 | J85: USD | K85: 46232 | L85: 30 | M85: 46253 | N85: =IF(OR(M85="", K85=""),"", M85- K85) -> 21 | O85: =IF(OR(M85="", K85="", L85=""), "", IF((M85 - K85) > L85, "No", "Yes")) -> Yes
B86: 82 | C86: Madagascar | D86: 134923 | E86: 134923 | F86: SPONSORING ALLIANCE FRANCAISE AMBILOBE | G86: ALLIANCE FRANCAISE AMBILOBE | I86: 520.83333 | J86: USD | K86: 46180 | L86: 30 | M86: 46216 | N86: =IF(OR(M86="", K86=""),"", M86- K86) -> 36 | O86: =IF(OR(M86="", K86="", L86=""), "", IF((M86 - K86) > L86, "No", "Yes")) -> No
B87: 83 | C87: Madagascar | D87: FA-2026-0601 | E87: 135111 | F87: Méditation&Tai chi | G87: ANDRIAMBELO HOLIARISOA HASINA (HHENIKA ) | I87: 958.33333 | J87: USD | K87: 46188 | L87: 30 | M87: 46224 | N87: =IF(OR(M87="", K87=""),"", M87- K87) -> 36 | O87: =IF(OR(M87="", K87="", L87=""), "", IF((M87 - K87) > L87, "No", "Yes")) -> No
B88: 84 | C88: Madagascar | D88: FA-2026-0601-R2 | E88: 135813 | F88: Atelier massage | G88: ANDRIAMBELO HOLIARISOA HASINA (HHENIKA ) | I88: 1502.0833 | J88: USD | K88: 46220 | L88: 30 | M88: 46255 | N88: =IF(OR(M88="", K88=""),"", M88- K88) -> 35 | O88: =IF(OR(M88="", K88="", L88=""), "", IF((M88 - K88) > L88, "No", "Yes")) -> No
B89: 85 | C89: Madagascar | D89: 4260623033 | E89: 135215 | F89: Distribution PPN 2026 | G89: ANDRIAMBOLOLONARISOA HAINGO(4 TIA) | I89: 4293.6285 | J89: USD | K89: 46202 | L89: 30 | M89: 46237 | N89: =IF(OR(M89="", K89=""),"", M89- K89) -> 35 | O89: =IF(OR(M89="", K89="", L89=""), "", IF((M89 - K89) > L89, "No", "Yes")) -> No
B90: 86 | C90: Madagascar | D90: 4260622030 | E90: 135781 | F90: TRANSPORT Location camion | G90: ANDRIAMBOLOLONARISOA HAINGO(4 TIA) | I90: 83.333333 | J90: USD | K90: 46230 | L90: 30 | M90: 46248 | N90: =IF(OR(M90="", K90=""),"", M90- K90) -> 18 | O90: =IF(OR(M90="", K90="", L90=""), "", IF((M90 - K90) > L90, "No", "Yes")) -> Yes
B91: 87 | C91: Madagascar | D91: 4260624035 | E91: 135779 | F91: RIZ HUILE | G91: ANDRIAMBOLOLONARISOA HAINGO(4 TIA) | I91: 266.685 | J91: USD | K91: 46230 | L91: 30 | M91: 46248 | N91: =IF(OR(M91="", K91=""),"", M91- K91) -> 18 | O91: =IF(OR(M91="", K91="", L91=""), "", IF((M91 - K91) > L91, "No", "Yes")) -> Yes
B92: 88 | C92: Madagascar | D92: 4260624036 | E92: 135816 | F92: TSIHY 150x80cm | G92: ANDRIAMBOLOLONARISOA HAINGO(4 TIA) | I92: 390.62813 | J92: USD | K92: 46219 | L92: 30 | M92: 46248 | N92: =IF(OR(M92="", K92=""),"", M92- K92) -> 29 | O92: =IF(OR(M92="", K92="", L92=""), "", IF((M92 - K92) > L92, "No", "Yes")) -> Yes
B93: 89 | C93: Madagascar | D93: TANA/05/26 | E93: 135870 | F93: DISTRIBUTION PAR UNITE DE FACTURE TANA MOIS DE MAI 2026 | G93: SOCIETE ANDRY | I93: 18.208333 | J93: USD | K93: 46185 | L93: 30 | M93: 46222 | N93: =IF(OR(M93="", K93=""),"", M93- K93) -> 37 | O93: =IF(OR(M93="", K93="", L93=""), "", IF((M93 - K93) > L93, "No", "Yes")) -> No
B94: 90 | C94: Madagascar | D94: PROV/05/26 | E94: 135870 | F94: Distribution des factures en Province - Mai 2026 | G94: SOCIETE ANDRY | I94: 260.41667 | J94: USD | K94: 46185 | L94: 30 | M94: 46212 | N94: =IF(OR(M94="", K94=""),"", M94- K94) -> 27 | O94: =IF(OR(M94="", K94="", L94=""), "", IF((M94 - K94) > L94, "No", "Yes")) -> Yes
B95: 91 | C95: Madagascar | D95: 2 | E95: 135852 | F95: Influenceur Antonis | G95: ANTONIS | I95: 479.16667 | J95: USD | K95: 46226 | L95: 30 | M95: 46241 | N95: =IF(OR(M95="", K95=""),"", M95- K95) -> 15 | O95: =IF(OR(M95="", K95="", L95=""), "", IF((M95 - K95) > L95, "No", "Yes")) -> Yes
B96: 92 | C96: Madagascar | D96: 001/2026 | E96: 135565 | F96: SPONSORING | G96: ASSOCIATION KITSANA | I96: 831 | J96: USD | K96: 46212 | L96: 30 | M96: 46243 | N96: =IF(OR(M96="", K96=""),"", M96- K96) -> 31 | O96: =IF(OR(M96="", K96="", L96=""), "", IF((M96 - K96) > L96, "No", "Yes")) -> No
B97: 93 | C97: Madagascar | D97: 019/06/BS/2026 | E97: 135679 | F97: Manutentionnaire - Foire de la la fibre Tuléar | G97: BAKAO SERVICES | I97: 104.16667 | J97: USD | K97: 46218 | L97: 30 | M97: 46244 | N97: =IF(OR(M97="", K97=""),"", M97- K97) -> 26 | O97: =IF(OR(M97="", K97="", L97=""), "", IF((M97 - K97) > L97, "No", "Yes")) -> Yes
B98: 94 | C98: Madagascar | D98: 0015/06/BS/2026 | E98: 135439 | F98: SOLDE PRESTATION EVENT JUILLET 2026 TOLIARA | G98: BAKAO SERVICES | I98: 239.58333 | J98: USD | K98: 46211 | L98: 30 | M98: 46241 | N98: =IF(OR(M98="", K98=""),"", M98- K98) -> 30 | O98: =IF(OR(M98="", K98="", L98=""), "", IF((M98 - K98) > L98, "No", "Yes")) -> Yes
B99: 95 | C99: Madagascar | D99: 20261668 | E99: 135134 | F99: Hébergement Baobab Tree | G99: BAOBAB TREE HOTEL | I99: 333.72646 | J99: USD | K99: 46216 | L99: 30 | M99: 46244 | N99: =IF(OR(M99="", K99=""),"", M99- K99) -> 28 | O99: =IF(OR(M99="", K99="", L99=""), "", IF((M99 - K99) > L99, "No", "Yes")) -> Yes
B100: 96 | C100: Madagascar | D100: 20261666 | E100: 135134 | F100: Hébergement Baobab Tree | G100: BAOBAB TREE HOTEL | I100: 342.99646 | J100: USD | K100: 46216 | L100: 30 | M100: 46244 | N100: =IF(OR(M100="", K100=""),"", M100- K100) -> 28 | O100: =IF(OR(M100="", K100="", L100=""), "", IF((M100 - K100) > L100, "No", "Yes")) -> Yes
B101: 97 | C101: Madagascar | D101: FA11071 | E101: 135395 | F101: GANT JETABLE | G101: BATIMAX | I101: 95.832917 | J101: USD | K101: 46202 | L101: 30 | M101: 46228 | N101: =IF(OR(M101="", K101=""),"", M101- K101) -> 26 | O101: =IF(OR(M101="", K101="", L101=""), "", IF((M101 - K101) > L101, "No", "Yes")) -> Yes
B102: 98 | C102: Madagascar | D102: M260000499 | E102: 134865 | F102: CAMPAGNE JUIN 2026 | G102: CANAL PLUS ADVERTISING MADAGASCAR | I102: 1171.3383 | J102: USD | K102: 46209 | L102: 30 | M102: 46244 | N102: =IF(OR(M102="", K102=""),"", M102- K102) -> 35 | O102: =IF(OR(M102="", K102="", L102=""), "", IF((M102 - K102) > L102, "No", "Yes")) -> No
B103: 99 | C103: Madagascar | D103: M260000498 | E103: 134865 | F103: CAMPAGNE JUIN 2026 | G103: CANAL PLUS ADVERTISING MADAGASCAR | I103: 1171.3383 | J103: USD | K103: 46209 | L103: 30 | M103: 46237 | N103: =IF(OR(M103="", K103=""),"", M103- K103) -> 28 | O103: =IF(OR(M103="", K103="", L103=""), "", IF((M103 - K103) > L103, "No", "Yes")) -> Yes
B104: 100 | C104: Madagascar | D104: M260000500 | E104: 134557 | F104: CAMPAGNE MOIS DE JUIN 2026 | G104: CANAL PLUS ADVERTISING MADAGASCAR | I104: 825 | J104: USD | K104: 46161 | L104: 30 | M104: 46189 | N104: =IF(OR(M104="", K104=""),"", M104- K104) -> 28 | O104: =IF(OR(M104="", K104="", L104=""), "", IF((M104 - K104) > L104, "No", "Yes")) -> Yes
B105: 101 | C105: Madagascar | D105: M260000501 | E105: 134557 | F105: CAMPAGNE JUIN 2026 | G105: CANAL PLUS ADVERTISING MADAGASCAR | I105: 675 | J105: USD | K105: 46161 | L105: 30 | M105: 46188 | N105: =IF(OR(M105="", K105=""),"", M105- K105) -> 27 | O105: =IF(OR(M105="", K105="", L105=""), "", IF((M105 - K105) > L105, "No", "Yes")) -> Yes
B106: 102 | C106: Madagascar | D106: M260000502 | E106: 134557 | F106: CAMPAGNE JUIN 2026 | G106: CANAL PLUS ADVERTISING MADAGASCAR | I106: 618.75 | J106: USD | K106: 46161 | L106: 30 | M106: 46196 | N106: =IF(OR(M106="", K106=""),"", M106- K106) -> 35 | O106: =IF(OR(M106="", K106="", L106=""), "", IF((M106 - K106) > L106, "No", "Yes")) -> No
B107: 103 | C107: Madagascar | D107: M260000504 | E107: 134557 | F107: CAMPAGNE JUIN 2026 | G107: CANAL PLUS ADVERTISING MADAGASCAR | I107: 1856.25 | J107: USD | K107: 46161 | L107: 30 | M107: 46191 | N107: =IF(OR(M107="", K107=""),"", M107- K107) -> 30 | O107: =IF(OR(M107="", K107="", L107=""), "", IF((M107 - K107) > L107, "No", "Yes")) -> Yes
B108: 104 | C108: Madagascar | D108: M260000503 | E108: 135003 | F108: DIFF MOIS DE JUIN 2026 | G108: CANAL PLUS ADVERTISING MADAGASCAR | I108: 6178.72 | J108: USD | K108: 46190 | L108: 30 | M108: 46225 | N108: =IF(OR(M108="", K108=""),"", M108- K108) -> 35 | O108: =IF(OR(M108="", K108="", L108=""), "", IF((M108 - K108) > L108, "No", "Yes")) -> No
B109: 105 | C109: Madagascar | D109: 135754 | E109: 135754 | F109: Sponsoring Course du Lac Anosy | G109: COLLEGES DE FRANCE ET DU MONDE | I109: 520.83333 | J109: USD | K109: 46224 | L109: 30 | M109: 46244 | N109: =IF(OR(M109="", K109=""),"", M109- K109) -> 20 | O109: =IF(OR(M109="", K109="", L109=""), "", IF((M109 - K109) > L109, "No", "Yes")) -> Yes
B110: 106 | C110: Madagascar | D110: FAC/CA/2026/1926 | E110: 134231 | F110: PNEU 235/85R16: PNEU BOTO RADIAL 235/85R16 D/XTERBA80+10PR | G110: CONTINENTAL AUTO | I110: 275 | J110: USD | K110: 46189 | L110: 30 | M110: 46217 | N110: =IF(OR(M110="", K110=""),"", M110- K110) -> 28 | O110: =IF(OR(M110="", K110="", L110=""), "", IF((M110 - K110) > L110, "No", "Yes")) -> Yes
B111: 107 | C111: Madagascar | D111: 6 422 / FA | E111: 134866 | F111: SPOT PUB ENTRETIEN JANV 2026 | G111: DREAM ON RADIO SARL | I111: 374.4 | J111: USD | K111: 46177 | L111: 30 | M111: 46205 | N111: =IF(OR(M111="", K111=""),"", M111- K111) -> 28 | O111: =IF(OR(M111="", K111="", L111=""), "", IF((M111 - K111) > L111, "No", "Yes")) -> Yes
B112: 108 | C112: Madagascar | D112: 6 443 / FA | E112: 134866 | F112: SPOT PUB ENTRETIEN JANV 2026 | G112: DREAM ON RADIO SARL | I112: 374.4 | J112: USD | K112: 46177 | L112: 30 | M112: 46202 | N112: =IF(OR(M112="", K112=""),"", M112- K112) -> 25 | O112: =IF(OR(M112="", K112="", L112=""), "", IF((M112 - K112) > L112, "No", "Yes")) -> Yes
B113: 109 | C113: Madagascar | D113: 6 444 / FA | E113: 134866 | F113: SPOT PUB JAN 2026 | G113: DREAM ON RADIO SARL | I113: 374.4 | J113: USD | K113: 46177 | L113: 30 | M113: 46214 | N113: =IF(OR(M113="", K113=""),"", M113- K113) -> 37 | O113: =IF(OR(M113="", K113="", L113=""), "", IF((M113 - K113) > L113, "No", "Yes")) -> No
B114: 110 | C114: Madagascar | D114: 6 445 / FA | E114: 134866 | F114: SPOT PUB JANV 2026 | G114: DREAM ON RADIO SARL | I114: 748.8 | J114: USD | K114: 46177 | L114: 30 | M114: 46213 | N114: =IF(OR(M114="", K114=""),"", M114- K114) -> 36 | O114: =IF(OR(M114="", K114="", L114=""), "", IF((M114 - K114) > L114, "No", "Yes")) -> No
B115: 111 | C115: Madagascar | D115: 6 446 / FA | E115: 134866 | F115: SPOT PUB FEV 2026 | G115: DREAM ON RADIO SARL | I115: 1056 | J115: USD | K115: 46177 | L115: 30 | M115: 46212 | N115: =IF(OR(M115="", K115=""),"", M115- K115) -> 35 | O115: =IF(OR(M115="", K115="", L115=""), "", IF((M115 - K115) > L115, "No", "Yes")) -> No
B116: 112 | C116: Madagascar | D116: 6 431 / FA | E116: 134866 | F116: SPOT PUB JUIN 2026 | G116: DREAM ON RADIO SARL | I116: 297.91667 | J116: USD | K116: 46177 | L116: 30 | M116: 46212 | N116: =IF(OR(M116="", K116=""),"", M116- K116) -> 35 | O116: =IF(OR(M116="", K116="", L116=""), "", IF((M116 - K116) > L116, "No", "Yes")) -> No
B117: 113 | C117: Madagascar | D117: 6 439 / FA | E117: 134866 | F117: SPOT PUB MOIS DE JUIN 2026 | G117: DREAM ON RADIO SARL | I117: 297.91667 | J117: USD | K117: 46177 | L117: 30 | M117: 46206 | N117: =IF(OR(M117="", K117=""),"", M117- K117) -> 29 | O117: =IF(OR(M117="", K117="", L117=""), "", IF((M117 - K117) > L117, "No", "Yes")) -> Yes
B118: 114 | C118: Madagascar | D118: 6 438 / FA | E118: 134866 | F118: SPOT PUB JUIN 2026 | G118: DREAM ON RADIO SARL | I118: 297.91667 | J118: USD | K118: 46177 | L118: 30 | M118: 46204 | N118: =IF(OR(M118="", K118=""),"", M118- K118) -> 27 | O118: =IF(OR(M118="", K118="", L118=""), "", IF((M118 - K118) > L118, "No", "Yes")) -> Yes
B119: 115 | C119: Madagascar | D119: 6 437 / FA | E119: 134866 | F119: SPOT PUB JUIN 2026 | G119: DREAM ON RADIO SARL | I119: 338.75 | J119: USD | K119: 46177 | L119: 30 | M119: 46206 | N119: =IF(OR(M119="", K119=""),"", M119- K119) -> 29 | O119: =IF(OR(M119="", K119="", L119=""), "", IF((M119 - K119) > L119, "No", "Yes")) -> Yes
B120: 116 | C120: Madagascar | D120: 6 370 / FA | E120: 134866 | F120: SPOT PUB FEV 2026 | G120: DREAM ON RADIO SARL | I120: 13.541667 | J120: USD | K120: 46177 | L120: 30 | M120: 46205 | N120: =IF(OR(M120="", K120=""),"", M120- K120) -> 28 | O120: =IF(OR(M120="", K120="", L120=""), "", IF((M120 - K120) > L120, "No", "Yes")) -> Yes
B121: 117 | C121: Madagascar | D121: 6 373 / FA | E121: 134866 | F121: SPOT PUB MARS 2026 | G121: DREAM ON RADIO SARL | I121: 27.083333 | J121: USD | K121: 46177 | L121: 30 | M121: 46213 | N121: =IF(OR(M121="", K121=""),"", M121- K121) -> 36 | O121: =IF(OR(M121="", K121="", L121=""), "", IF((M121 - K121) > L121, "No", "Yes")) -> No
... B136: 132 | C136: Madagascar | D136: 6 430 / FA | E136: 134581 | F136: SPONSORING EMISSION JITE juillet 2026 | G136: DREAM ON RADIO SARL | I136: 833.33333 | J136: USD | K136: 46157 | L136: 30 | M136: 46185 | N136: =IF(OR(M136="", K136=""),"", M136- K136) -> 28 | O136: =IF(OR(M136="", K136="", L136=""), "", IF((M136 - K136) > L136, "No", "Yes")) -> Yes
B137: 133 | C137: Madagascar | D137: 2 | E137: 134522 | F137: PUB FEV 2026 | G137: ECAR ARCHIDIOCESE (Radio Faniry) | I137: 312.5 | J137: USD | K137: 46180 | L137: 30 | M137: 46208 | N137: =IF(OR(M137="", K137=""),"", M137- K137) -> 28 | O137: =IF(OR(M137="", K137="", L137=""), "", IF((M137 - K137) > L137, "No", "Yes")) -> Yes
B138: 134 | C138: Madagascar | D138: 4 | E138: 134522 | F138: PUB ET ANNONCES AVRIL 2026 | G138: ECAR ARCHIDIOCESE (Radio Faniry) | I138: 312.5 | J138: USD | K138: 46180 | L138: 30 | M138: 46217 | N138: =IF(OR(M138="", K138=""),"", M138- K138) -> 37 | O138: =IF(OR(M138="", K138="", L138=""), "", IF((M138 - K138) > L138, "No", "Yes")) -> No
B139: 135 | C139: Madagascar | D139: 3 | E139: 134522 | F139: PUB ANNONCES MARS 2026 | G139: ECAR ARCHIDIOCESE (Radio Faniry) | I139: 312.5 | J139: USD | K139: 46180 | L139: 30 | M139: 46207 | N139: =IF(OR(M139="", K139=""),"", M139- K139) -> 27 | O139: =IF(OR(M139="", K139="", L139=""), "", IF((M139 - K139) > L139, "No", "Yes")) -> Yes
B140: 136 | C140: Madagascar | D140: 016-2026 | E140: 134479 | F140: Location de véhicule(s ) avec carburant | G140: EXCEL TRANSPORT et TRAVEL | I140: 101 | J140: USD | K140: 46147 | L140: 30 | M140: 46172 | N140: =IF(OR(M140="", K140=""),"", M140- K140) -> 25 | O140: =IF(OR(M140="", K140="", L140=""), "", IF((M140 - K140) > L140, "No", "Yes")) -> Yes
B141: 137 | C141: Madagascar | D141: 0002/2026-FMF/SG/DAF/26 | E141: 135684 | F141: Subvention des équipes finalistes - Yas Coupe de Madagascar - Facture N°0001/2026-FMF/SG/DAF/26 | G141: FEDERATION MALAGASY DE FOOT BALL | I141: 1666.6667 | J141: USD | K141: 46218 | L141: 30 | M141: 46244 | N141: =IF(OR(M141="", K141=""),"", M141- K141) -> 26 | O141: =IF(OR(M141="", K141="", L141=""), "", IF((M141 - K141) > L141, "No", "Yes")) -> Yes
B142: 138 | C142: Madagascar | D142: 0001/2026-FMF/SG/DAF/26 | E142: 135684 | F142: Primes Yas Coupe de Madagascar - Facture N°0001/2026-FMF/SG/DAF/26 | G142: FEDERATION MALAGASY DE FOOT BALL | I142: 3125 | J142: USD | K142: 46218 | L142: 30 | M142: 46244 | N142: =IF(OR(M142="", K142=""),"", M142- K142) -> 26 | O142: =IF(OR(M142="", K142="", L142=""), "", IF((M142 - K142) > L142, "No", "Yes")) -> Yes
B143: 139 | C143: Madagascar | D143: 004-05-26/FSBM | E143: 135018 | F143: Participation YAS aux tournois nationaux | G143: FEDERATION SPORT BOULES MALAGASY | I143: 1250 | J143: USD | K143: 46182 | L143: 30 | M143: 46211 | N143: =IF(OR(M143="", K143=""),"", M143- K143) -> 29 | O143: =IF(OR(M143="", K143="", L143=""), "", IF((M143 - K143) > L143, "No", "Yes")) -> Yes
B144: 140 | C144: Madagascar | D144: 098/2025 | E144: 134311 | F144: REMPLACEMENT TOTEM TOAMASINA | G144: FRANCE PUB | I144: 10625 | J144: USD | K144: 46217 | L144: 30 | M144: 46244 | N144: =IF(OR(M144="", K144=""),"", M144- K144) -> 27 | O144: =IF(OR(M144="", K144="", L144=""), "", IF((M144 - K144) > L144, "No", "Yes")) -> Yes
B145: 141 | C145: Madagascar | D145: FAC178/072026 | E145: 135765 | F145: Location Pagode - YAS HOOPFEST | G145: GASY BLESSED EVENT | I145: 570.83333 | J145: USD | K145: 46224 | L145: 30 | M145: 46248 | N145: =IF(OR(M145="", K145=""),"", M145- K145) -> 24 | O145: =IF(OR(M145="", K145="", L145=""), "", IF((M145 - K145) > L145, "No", "Yes")) -> Yes
B146: 142 | C146: Madagascar | D146: F2613502 | E146: 134788 | F146: CARTE DE VISTE AU NOM ZO MIHANTA | G146: GRAPH EXPRESS IMPRIMERIE | I146: 33.75 | J146: USD | K146: 46185 | L146: 30 | M146: 46221 | N146: =IF(OR(M146="", K146=""),"", M146- K146) -> 36 | O146: =IF(OR(M146="", K146="", L146=""), "", IF((M146 - K146) > L146, "No", "Yes")) -> No
...

Sheet M-1 YTD performance
C1: OPCOs | D1: MADAGASCAR | E1: COMOROS | F1: SENEGAL | G1: TANZANIA | H1: TOGO
C2: Target YTD
B5: Savings: % of Saving after Negotiations | C5: 0.1 | D5: 0.048171294 | E5: 0.16677991 | F5: 0.033134847 | G5: 0.02527433 | H5: 0.084332494
B6: Savings: Absolute Value ($) | D6: 2313581 | E6: 1405117.3 | F6: 2944643 | G6: 5911843.3 | H6: 4057811.9
B7: TAT for PR Approval (Days) | C7: 4 | D7: 2.6799645 | E7: 2.2793522 | F7: 2.5273523 | G7: 4.4675716 | H7: 10.03
B8: TAT for PR Approval vs. SLA Compliance (%) | C8: 0.9 | D8: 0.82062648 | E8: 0.92307692 | F8: 0.89934354 | G8: 0.6746988 | H8: 0.37090909
B9: TAT for PO:PO SLA Conversion (Days) | C9: 4 | D9: 3.9787234 | E9: 5.0769231 | F9: 4.9474836 | G9: 5.4630468 | H9: 10.289091
B10: TAT for PO Approval vs. SLA Compliance (%) | C10: 0.9 | D10: 0.96572104 | E10: 0.93117409 | F10: 0.57330416 | G10: 1 | H10: 0.64181818
B11: TAT for custom clearance (AIR): SLA compliance (Days) | C11: 5 | D11: 4.7954545 | E11: 8.75 | F11: 5.7115385 | G11: 5.9318182 | H11: 8.7857143
B12: TAT for custom clearance (SEA): SLA compliance (Days) | C12: 10 | D12: 8.8235294 | E12: 12 | F12: 6.9333333 | G12: 17.166667 | H12: 11.384615
B13: Contracts Compliance (% Purchase on Contracts) | C13: 0.7 | D13: 0.63120567 | E13: 0.34008097 | F13: 0.42669584 | G13: 0.67168675 | H13: 0.69272727
B14: contracts conpliance in value | D14: 0.86749214 | E14: 0.68475342 | F14: 0.34244347 | G14: 0.86533852 | H14: 0.63832356
B15: PPOT (% Due invoices paid) | C15: 0.7 | D15: 0.69405175 | E15: 0.87044146 | F15: 0 | G15: 0.45753968 | H15: 0.77419355

Sheet Submissions
B3: OpCo | C3: Submission Status
B4: MADAGASCAR
B5: COMOROS
B6: SENEGAL
B7: TANZANIA
B8: TOGO
B12: Timelines | C12: Activity | D12: Current month cut off dates | E12: Status
B13: Week 1 | C13: Process kick-off | D13: Sep 3rd | E13: Completed
B14: Week 2 | C14: OpCos reports submission | D14: Sep 14th | E14: In Progress
B15: Week 3 | C15: Analysis & insights collection | D15: Sep 21st
B16: Week 4 | C16: Dashboard circulation | D16: Sep 28th
